Workbook
Name JC_MA: 'PARÁMETROS'!$K$21:$K$26
Name FV_OP: 'PARÁMETROS'!$BV$3:$BV$11
Name FR_G: 'PARÁMETROS'!$BJ$3:$BJ$30
Name CC_G: 'PARÁMETROS'!$L$47:$N$47
Name FR_L: 'PARÁMETROS'!$AT$3:$AT$30
Name FA_MA: 'PARÁMETROS'!$Z$3:$Z$46
Name FC_DS: 'PARÁMETROS'!$BD$3:$BD$26
Name FR_FI: 'PARÁMETROS'!$BZ$3:$BZ$30
Name FP_op: 'PARÁMETROS'!$BP$3:$BP$10
Name Op_Sev: 'PARÁMETROS'!$C$12:$C$16
Name CC_MA: 'PARÁMETROS'!$L$20:$N$20
Name CC_OP: 'PARÁMETROS'!$L$56:$N$56
Name FV_FI: 'PARÁMETROS'!$CD$3:$CD$30
Name FC_SA: 'PARÁMETROS'!$AN$3:$AN$30
Name FI_MA: 'PARÁMETROS'!$AB$3:$AB$29
Name p_o: 'PARÁMETROS'!$C$18:$C$22
Name FR_DS: 'PARÁMETROS'!$BB$3:$BB$16
Name FP_SE: 'PARÁMETROS'!$P$3:$P$45
Name FC_MA: 'PARÁMETROS'!$AD$3:$AD$35
Name Oportunidad: 'PARÁMETROS'!$D$12:$H$16
Name FC_SE: 'PARÁMETROS'!$T$3:$T$19
Name FC_OP: 'PARÁMETROS'!$BT$3:$BT$11
Name JC_DS: 'PARÁMETROS'!$K$12:$K$17
Name FP_SA: 'PARÁMETROS'!$AJ$3:$AJ$30
Name JC_G: 'PARÁMETROS'!$K$48:$K$53
Name OP_prob: 'PARÁMETROS'!$D$11:$H$11
Name FV_SE: 'PARÁMETROS'!$V$3:$V$8
Name FC_G: 'PARÁMETROS'!$BL$3:$BL$30
Name FP_DS: 'PARÁMETROS'!$AZ$3:$AZ$24
Name FV_G: 'PARÁMETROS'!$BN$3:$BN$30
Name FC_FI: 'PARÁMETROS'!$CB$3:$CB$30
Name CC_FI: 'PARÁMETROS'!$L$65:$N$65
Name FC_L: 'PARÁMETROS'!$AV$3:$AV$30
Name FP_L: 'PARÁMETROS'!$AR$3:$AR$30
Name FP_FI: 'PARÁMETROS'!$BX$3:$BX$30
Name VS: 'PARÁMETROS'!$X$3:$X$22
Name FV_MA: 'PARÁMETROS'!$AF$3:$AF$12
Name FR_SA: 'PARÁMETROS'!$AL$3:$AL$30
Name JC_L: 'PARÁMETROS'!$K$39:$K$44
Name CC_L: 'PARÁMETROS'!$L$38:$N$38
Name JC_SE: 'PARÁMETROS'!$K$3:$K$8
Name FR_OP: 'PARÁMETROS'!$BR$3:$BR$11
Name JC_SA: 'PARÁMETROS'!$K$30:$K$35
Name FV_DS: 'PARÁMETROS'!$BF$3:$BF$7
Name CC_DS: 'PARÁMETROS'!$L$11:$N$11
Name FR_SE: 'PARÁMETROS'!$R$3:$R$46
Name FV_SA: 'PARÁMETROS'!$AP$3:$AP$30
Name JC_OP: 'PARÁMETROS'!$K$57:$K$62
Name FP_G: 'PARÁMETROS'!$BH$3:$BH$30
Name JC_FI: 'PARÁMETROS'!$K$66:$K$71
Name CC_SA: 'PARÁMETROS'!$L$29:$N$29
Name FV_L: 'PARÁMETROS'!$AX$3:$AX$30
Name CC_SE: 'PARÁMETROS'!$L$2:$N$2
Name VM: 'PARÁMETROS'!$AH$3:$AH$12

Sheet MATRIZ DE RIESGOS
D1: IDENTIFICACIÓN, EVALUACIÓN DE RIESGOS | W1: 1.02.P06.F01
W2: Revisión. 7
W3: INTERNA
A5: Gerencia: | H5: Elaborado por: | T5: Revisado y Aprobado por:
A6: Superintendencia:
A7: Área/Departamento: | H7: Fecha: | T7: Fecha:
A9: N° | B9: Área / Proceso / Alcance | C9: Actividad / Tarea / Grupo de Interés | D9: Condición Normal, Anormal, Emergencia o Factor | E9: Seguridad, Salud, Medio Ambiente, Legal, Responsabilidad Social, Otro | F9: Familia Peligro/ Aspecto / Evento | G9: Descripción Peligro / Aspecto / Evento | H9: Familia Riesgo / Impacto / Consecuencia | I9: Descripción Riesgo / Impacto / Coonsecuencia | J9: RIESGO / IMPACTO | P9: Familia de Controles | Q9: Medidas de Prevención, Control y Mitigación | R9: Familia de Verificadores | S9: Verificadores | T9: Calidad del Control | U9: Jerarquía de Control | V9: Eficacia del Control / Acción | W9: Nivel de Riesgo / Impacto Actual | X9: Incidentes Ocurridos | Y9: Trazabilidad / Historial / Observaciones Actual
J10: Exposición | K10: Posibilidad | L10: Probabilidad (R/I) | M10: Severidad | N10: Resultado de Evaluación Riesgo / Iimpacto | O10: Nivel de Riesgo / Iimpacto Inicial Puro
D11: Normal | E11: Seguridad | L11: =IF(OR(J11<>"",K11<>""),OFFSET('PARÁMETROS'!$B$2,K11,J11),"") | N11: =IFERROR(L11*M11,"") -> 0 | O11: =IF(N11="","",IFERROR(IF(N11<=2,"ACEPTABLE",IF(N11<=6,"BAJA",IF(N11<=10,"ACEPTABLE CON REVISIÓN",IF(N11<=15,"SUSTANCIAL","INACEPTABLE")))),"")) -> ACEPTABLE | V11: =IFERROR(IF(AA11="SEGURIDAD",OFFSET('PARÁMETROS'!$K$2,MATCH(U11,JC_SE,0),MATCH(T11,CC_SE,0)), IF(OR(AA11="DSRC/Estratégico",AA11="DSRC/Operativo"),OFFSET('PARÁMETROS'!$K$11,MATCH(U11,JC_DS,0),MATCH(T11,CC_DS,0)), IF(AA11="SALUD",OFFSET('PARÁMETROS'!$K$29,MATCH(U11,JC_SA,0),MATCH(T11,CC_SA,0)), IF(AA11="MEDIO AMBIENTE",OFFSET('PARÁMETROS'!$K$20,MATCH(U11,JC_MA,0),MATCH(T11,CC_MA,0)), IF(AA11="Rel. Gubernamentales",OFFSET('PARÁMETROS'!$K$48,MATCH(U11,JC_G,0),MATCH(T11,CC_G,0)), IF(AA11="OPERACIONAL",OFFSET('PARÁMETROS'!$K$56,MATCH(U11,JC_OP,0),MATCH(T11,CC_OP,0)), IF(AA11="FINANCIERO",OFFSET('PARÁMETROS'!$K$56,MATCH(U11,JC_FI,0),MATCH(T11,CC_FI,0)), OFFSET('PARÁMETROS'!$K$38,MATCH(U11,JC_L,0),MATCH(T11,CC_L,0))))))))),"") | W11: =IF(E11="","", IF(COUNTA(V11:V26)-COUNTBLANK(V11:V26)=1, IF(O11="INACEPTABLE",IF(COUNTIF(V11:V26,"Control/Acción Eficaz")>=1,"SUSTANCIAL","INACEPTABLE"), IF(O11="SUSTANCIAL",IF(COUNTIF(V11:V26,"Control/Acción Eficaz")>=1,"ACEPTABLE CON REVISIÓN","SUSTANCIAL"), IF(O11="ACEPTABLE CON REVISIÓN",IF(COUNTIF(V11:V26,"Control/Acción Eficaz")>=1,"BAJA","ACEPTABLE CON REVISIÓN"), IF(O11="BAJA",IF(COUNTIF(V11:V26,"Control/Acción Eficaz")>=1,"ACEPTABLE","BAJA"),)))), IF(COUNTA(V11:V26)-COUNTBLANK(V11:V26)=2, IF(O11="INACEPTABLE",IF(COUNTIF(V11:V26,"Control/Acción Eficaz")=2,"ACEPTABLE CON REVISIÓN", IF(OR(AND(COUNTIF(V11:V26,"Control/Acción Eficaz")=1,COUNTIF(V11:V26,"Control/Acción Satisfactorio")=1), AND(COUNTIF(V11:V26,"Control/Acción Eficaz")=1,COUNTIF(V11:V26,"Control/Acción No Eficaz")=1)),"SUSTANCIAL","INACEPTABLE")), IF(O11="SUSTANCIAL",IF(COUNTIF(V11:V26,"Control/Acción Eficaz")=2,"BAJA", IF(OR(AND(COUNTIF(V11:V26,"Control/Acción Eficaz")=1,COUNTIF(V11:V26,"Control/Acción Satisfactorio")=1), AND(COUNTIF(V11:V26,"Control/Acción Eficaz")=1,COUNTIF(V11:V26,"Control/Acción No Eficaz")=1)),"ACEPTABLE CON REVISIÓN ","SUSTANCIAL")), IF(O11="ACEPTABLE CON REVISIÓN",IF(COUNTIF(V11:V26,"Control/Acción Eficaz")=2,"ACEPTABLE", IF(OR(AND(COUNTIF(V11:V26,"Control/Acción Eficaz")=1,COUNTIF(V11:V26,"Control/Acción Satisfactorio")=1), AND(COUNTIF(V11:V26,"Control/Acción Eficaz")=1,COUNTIF(V11:V26,"Control/Acción No Eficaz")=1)),"BAJA","ACEPTABLE CON REVISIÓN")), IF(O11="BAJA",IF(COUNTIF(V11:V26,"Control/Acción Eficaz")>=2,"ACEPTABLE","BAJA"),)))), IF(COUNTA(V11:V26)-COUNTBLANK(V11:V26)>=3, IF(O11="INACEPTABLE", IF(COUNTBLANK(V11:V26)=COUNTA(V11:V26),"", IF(COUNTIF(V11:V26,"Control/Acción No Eficaz")>=2,"INACEPTABLE", IF(AND(COUNTIF(V11:V26,"Control/Acción No Eficaz")=0,COUNTIF(V11:V26,"Control/Acción Eficaz")>=2),"ACEPTABLE CON REVISIÓN ","SUSTANCIAL"))), IF(O11="SUSTANCIAL", IF(COUNTBLANK(V11:V26)=COUNTA(V11:V26),"", IF(COUNTIF(V11:V26,"Control/Acción No Eficaz")>=2,"SUSTANCIAL", IF(AND(COUNTIF(V11:V26,"Control/Acción No Eficaz")=0,COUNTIF(V11:V26,"Control/Acción Eficaz")>=2),"BAJA","ACEPTABLE CON REVISIÓN"))), IF(O11="ACEPTABLE CON REVISIÓN", IF(COUNTBLANK(V11:V26)=COUNTA(V11:V26),"", IF(COUNTIF(V11:V26,"Control/Acción No Eficaz")>=2,"ACEPTABLE CON REVISIÓN", IF(AND(COUNTIF(V11:V26,"Control/Acción No Eficaz")=0,COUNTIF(V11:V26,"Control/Acción Eficaz")>=2),"ACEPTABLE","BAJA"))), IF(O11="BAJA", IF(COUNTBLANK(V11:V26)=COUNTA(V11:V26),"", IF(AND(COUNTBLANK(V11:V26)<1,COUNTA(V11:V26)=1), IF(COUNTIF(V11:V26,"Control/Acción No Eficaz")>=2,"BAJA", IF(AND(COUNTIF(V11:V26,"Control/Acción No Eficaz")=0,COUNTIF(V11:V26,"Control/Acción Eficaz")>=2),"ACEPTABLE","BAJA")), IF(COUNTIF(V11:V26,"Control/Acción No Eficaz")>=2,"BAJA", IF(AND(COUNTIF(V11:V26,"Control/Acción No Eficaz")=0,COUNTIF(V11:V26,"Control/Acción Eficaz")>=2),"ACEPTABLE","BAJA")))), IF(COUNTIF(V11:V26,"")>=5,"",O11))))), "")))) | AA11: =E11 -> Seguridad
V12: =IFERROR(IF(AA12="SEGURIDAD",OFFSET('PARÁMETROS'!$K$2,MATCH(U12,JC_SE,0),MATCH(T12,CC_SE,0)), IF(OR(AA12="DSRC/Estratégico",AA12="DSRC/Operativo"),OFFSET('PARÁMETROS'!$K$11,MATCH(U12,JC_DS,0),MATCH(T12,CC_DS,0)), IF(AA12="SALUD",OFFSET('PARÁMETROS'!$K$29,MATCH(U12,JC_SA,0),MATCH(T12,CC_SA,0)), IF(AA12="MEDIO AMBIENTE",OFFSET('PARÁMETROS'!$K$20,MATCH(U12,JC_MA,0),MATCH(T12,CC_MA,0)), IF(AA12="Rel. Gubernamentales",OFFSET('PARÁMETROS'!$K$48,MATCH(U12,JC_G,0),MATCH(T12,CC_G,0)), IF(AA12="OPERACIONAL",OFFSET('PARÁMETROS'!$K$56,MATCH(U12,JC_OP,0),MATCH(T12,CC_OP,0)), IF(AA12="FINANCIERO",OFFSET('PARÁMETROS'!$K$56,MATCH(U12,JC_FI,0),MATCH(T12,CC_FI,0)), OFFSET('PARÁMETROS'!$K$38,MATCH(U12,JC_L,0),MATCH(T12,CC_L,0))))))))),"") | AA12: =E11 -> Seguridad
V13: =IFERROR(IF(AA13="SEGURIDAD",OFFSET('PARÁMETROS'!$K$2,MATCH(U13,JC_SE,0),MATCH(T13,CC_SE,0)), IF(OR(AA13="DSRC/Estratégico",AA13="DSRC/Operativo"),OFFSET('PARÁMETROS'!$K$11,MATCH(U13,JC_DS,0),MATCH(T13,CC_DS,0)), IF(AA13="SALUD",OFFSET('PARÁMETROS'!$K$29,MATCH(U13,JC_SA,0),MATCH(T13,CC_SA,0)), IF(AA13="MEDIO AMBIENTE",OFFSET('PARÁMETROS'!$K$20,MATCH(U13,JC_MA,0),MATCH(T13,CC_MA,0)), IF(AA13="Rel. Gubernamentales",OFFSET('PARÁMETROS'!$K$48,MATCH(U13,JC_G,0),MATCH(T13,CC_G,0)), IF(AA13="OPERACIONAL",OFFSET('PARÁMETROS'!$K$56,MATCH(U13,JC_OP,0),MATCH(T13,CC_OP,0)), IF(AA13="FINANCIERO",OFFSET('PARÁMETROS'!$K$56,MATCH(U13,JC_FI,0),MATCH(T13,CC_FI,0)), OFFSET('PARÁMETROS'!$K$38,MATCH(U13,JC_L,0),MATCH(T13,CC_L,0))))))))),"") | AA13: =E11 -> Seguridad
V14: =IFERROR(IF(AA14="SEGURIDAD",OFFSET('PARÁMETROS'!$K$2,MATCH(U14,JC_SE,0),MATCH(T14,CC_SE,0)), IF(OR(AA14="DSRC/Estratégico",AA14="DSRC/Operativo"),OFFSET('PARÁMETROS'!$K$11,MATCH(U14,JC_DS,0),MATCH(T14,CC_DS,0)), IF(AA14="SALUD",OFFSET('PARÁMETROS'!$K$29,MATCH(U14,JC_SA,0),MATCH(T14,CC_SA,0)), IF(AA14="MEDIO AMBIENTE",OFFSET('PARÁMETROS'!$K$20,MATCH(U14,JC_MA,0),MATCH(T14,CC_MA,0)), IF(AA14="Rel. Gubernamentales",OFFSET('PARÁMETROS'!$K$48,MATCH(U14,JC_G,0),MATCH(T14,CC_G,0)), IF(AA14="OPERACIONAL",OFFSET('PARÁMETROS'!$K$56,MATCH(U14,JC_OP,0),MATCH(T14,CC_OP,0)), IF(AA14="FINANCIERO",OFFSET('PARÁMETROS'!$K$56,MATCH(U14,JC_FI,0),MATCH(T14,CC_FI,0)), OFFSET('PARÁMETROS'!$K$38,MATCH(U14,JC_L,0),MATCH(T14,CC_L,0))))))))),"") | AA14: =E11 -> Seguridad
V15: =IFERROR(IF(AA15="SEGURIDAD",OFFSET('PARÁMETROS'!$K$2,MATCH(U15,JC_SE,0),MATCH(T15,CC_SE,0)), IF(OR(AA15="DSRC/Estratégico",AA15="DSRC/Operativo"),OFFSET('PARÁMETROS'!$K$11,MATCH(U15,JC_DS,0),MATCH(T15,CC_DS,0)), IF(AA15="SALUD",OFFSET('PARÁMETROS'!$K$29,MATCH(U15,JC_SA,0),MATCH(T15,CC_SA,0)), IF(AA15="MEDIO AMBIENTE",OFFSET('PARÁMETROS'!$K$20,MATCH(U15,JC_MA,0),MATCH(T15,CC_MA,0)), IF(AA15="Rel. Gubernamentales",OFFSET('PARÁMETROS'!$K$48,MATCH(U15,JC_G,0),MATCH(T15,CC_G,0)), IF(AA15="OPERACIONAL",OFFSET('PARÁMETROS'!$K$56,MATCH(U15,JC_OP,0),MATCH(T15,CC_OP,0)), IF(AA15="FINANCIERO",OFFSET('PARÁMETROS'!$K$56,MATCH(U15,JC_FI,0),MATCH(T15,CC_FI,0)), OFFSET('PARÁMETROS'!$K$38,MATCH(U15,JC_L,0),MATCH(T15,CC_L,0))))))))),"") | AA15: =E11 -> Seguridad
V16: =IFERROR(IF(AA16="SEGURIDAD",OFFSET('PARÁMETROS'!$K$2,MATCH(U16,JC_SE,0),MATCH(T16,CC_SE,0)), IF(OR(AA16="DSRC/Estratégico",AA16="DSRC/Operativo"),OFFSET('PARÁMETROS'!$K$11,MATCH(U16,JC_DS,0),MATCH(T16,CC_DS,0)), IF(AA16="SALUD",OFFSET('PARÁMETROS'!$K$29,MATCH(U16,JC_SA,0),MATCH(T16,CC_SA,0)), IF(AA16="MEDIO AMBIENTE",OFFSET('PARÁMETROS'!$K$20,MATCH(U16,JC_MA,0),MATCH(T16,CC_MA,0)), IF(AA16="Rel. Gubernamentales",OFFSET('PARÁMETROS'!$K$48,MATCH(U16,JC_G,0),MATCH(T16,CC_G,0)), IF(AA16="OPERACIONAL",OFFSET('PARÁMETROS'!$K$56,MATCH(U16,JC_OP,0),MATCH(T16,CC_OP,0)), IF(AA16="FINANCIERO",OFFSET('PARÁMETROS'!$K$56,MATCH(U16,JC_FI,0),MATCH(T16,CC_FI,0)), OFFSET('PARÁMETROS'!$K$38,MATCH(U16,JC_L,0),MATCH(T16,CC_L,0))))))))),"") | AA16: =E11 -> Seguridad
V17: =IFERROR(IF(AA17="SEGURIDAD",OFFSET('PARÁMETROS'!$K$2,MATCH(U17,JC_SE,0),MATCH(T17,CC_SE,0)), IF(OR(AA17="DSRC/Estratégico",AA17="DSRC/Operativo"),OFFSET('PARÁMETROS'!$K$11,MATCH(U17,JC_DS,0),MATCH(T17,CC_DS,0)), IF(AA17="SALUD",OFFSET('PARÁMETROS'!$K$29,MATCH(U17,JC_SA,0),MATCH(T17,CC_SA,0)), IF(AA17="MEDIO AMBIENTE",OFFSET('PARÁMETROS'!$K$20,MATCH(U17,JC_MA,0),MATCH(T17,CC_MA,0)), IF(AA17="Rel. Gubernamentales",OFFSET('PARÁMETROS'!$K$48,MATCH(U17,JC_G,0),MATCH(T17,CC_G,0)), IF(AA17="OPERACIONAL",OFFSET('PARÁMETROS'!$K$56,MATCH(U17,JC_OP,0),MATCH(T17,CC_OP,0)), IF(AA17="FINANCIERO",OFFSET('PARÁMETROS'!$K$56,MATCH(U17,JC_FI,0),MATCH(T17,CC_FI,0)), OFFSET('PARÁMETROS'!$K$38,MATCH(U17,JC_L,0),MATCH(T17,CC_L,0))))))))),"") | AA17: =E11 -> Seguridad
V18: =IFERROR(IF(AA18="SEGURIDAD",OFFSET('PARÁMETROS'!$K$2,MATCH(U18,JC_SE,0),MATCH(T18,CC_SE,0)), IF(OR(AA18="DSRC/Estratégico",AA18="DSRC/Operativo"),OFFSET('PARÁMETROS'!$K$11,MATCH(U18,JC_DS,0),MATCH(T18,CC_DS,0)), IF(AA18="SALUD",OFFSET('PARÁMETROS'!$K$29,MATCH(U18,JC_SA,0),MATCH(T18,CC_SA,0)), IF(AA18="MEDIO AMBIENTE",OFFSET('PARÁMETROS'!$K$20,MATCH(U18,JC_MA,0),MATCH(T18,CC_MA,0)), IF(AA18="Rel. Gubernamentales",OFFSET('PARÁMETROS'!$K$48,MATCH(U18,JC_G,0),MATCH(T18,CC_G,0)), IF(AA18="OPERACIONAL",OFFSET('PARÁMETROS'!$K$56,MATCH(U18,JC_OP,0),MATCH(T18,CC_OP,0)), IF(AA18="FINANCIERO",OFFSET('PARÁMETROS'!$K$56,MATCH(U18,JC_FI,0),MATCH(T18,CC_FI,0)), OFFSET('PARÁMETROS'!$K$38,MATCH(U18,JC_L,0),MATCH(T18,CC_L,0))))))))),"") | AA18: =E11 -> Seguridad
V19: =IFERROR(IF(AA19="SEGURIDAD",OFFSET('PARÁMETROS'!$K$2,MATCH(U19,JC_SE,0),MATCH(T19,CC_SE,0)), IF(OR(AA19="DSRC/Estratégico",AA19="DSRC/Operativo"),OFFSET('PARÁMETROS'!$K$11,MATCH(U19,JC_DS,0),MATCH(T19,CC_DS,0)), IF(AA19="SALUD",OFFSET('PARÁMETROS'!$K$29,MATCH(U19,JC_SA,0),MATCH(T19,CC_SA,0)), IF(AA19="MEDIO AMBIENTE",OFFSET('PARÁMETROS'!$K$20,MATCH(U19,JC_MA,0),MATCH(T19,CC_MA,0)), IF(AA19="Rel. Gubernamentales",OFFSET('PARÁMETROS'!$K$48,MATCH(U19,JC_G,0),MATCH(T19,CC_G,0)), IF(AA19="OPERACIONAL",OFFSET('PARÁMETROS'!$K$56,MATCH(U19,JC_OP,0),MATCH(T19,CC_OP,0)), IF(AA19="FINANCIERO",OFFSET('PARÁMETROS'!$K$56,MATCH(U19,JC_FI,0),MATCH(T19,CC_FI,0)), OFFSET('PARÁMETROS'!$K$38,MATCH(U19,JC_L,0),MATCH(T19,CC_L,0))))))))),"") | AA19: =E11 -> Seguridad
V20: =IFERROR(IF(AA20="SEGURIDAD",OFFSET('PARÁMETROS'!$K$2,MATCH(U20,JC_SE,0),MATCH(T20,CC_SE,0)), IF(OR(AA20="DSRC/Estratégico",AA20="DSRC/Operativo"),OFFSET('PARÁMETROS'!$K$11,MATCH(U20,JC_DS,0),MATCH(T20,CC_DS,0)), IF(AA20="SALUD",OFFSET('PARÁMETROS'!$K$29,MATCH(U20,JC_SA,0),MATCH(T20,CC_SA,0)), IF(AA20="MEDIO AMBIENTE",OFFSET('PARÁMETROS'!$K$20,MATCH(U20,JC_MA,0),MATCH(T20,CC_MA,0)), IF(AA20="Rel. Gubernamentales",OFFSET('PARÁMETROS'!$K$48,MATCH(U20,JC_G,0),MATCH(T20,CC_G,0)), IF(AA20="OPERACIONAL",OFFSET('PARÁMETROS'!$K$56,MATCH(U20,JC_OP,0),MATCH(T20,CC_OP,0)), IF(AA20="FINANCIERO",OFFSET('PARÁMETROS'!$K$56,MATCH(U20,JC_FI,0),MATCH(T20,CC_FI,0)), OFFSET('PARÁMETROS'!$K$38,MATCH(U20,JC_L,0),MATCH(T20,CC_L,0))))))))),"") | AA20: =E11 -> Seguridad
V21: =IFERROR(IF(AA21="SEGURIDAD",OFFSET('PARÁMETROS'!$K$2,MATCH(U21,JC_SE,0),MATCH(T21,CC_SE,0)), IF(OR(AA21="DSRC/Estratégico",AA21="DSRC/Operativo"),OFFSET('PARÁMETROS'!$K$11,MATCH(U21,JC_DS,0),MATCH(T21,CC_DS,0)), IF(AA21="SALUD",OFFSET('PARÁMETROS'!$K$29,MATCH(U21,JC_SA,0),MATCH(T21,CC_SA,0)), IF(AA21="MEDIO AMBIENTE",OFFSET('PARÁMETROS'!$K$20,MATCH(U21,JC_MA,0),MATCH(T21,CC_MA,0)), IF(AA21="Rel. Gubernamentales",OFFSET('PARÁMETROS'!$K$48,MATCH(U21,JC_G,0),MATCH(T21,CC_G,0)), IF(AA21="OPERACIONAL",OFFSET('PARÁMETROS'!$K$56,MATCH(U21,JC_OP,0),MATCH(T21,CC_OP,0)), IF(AA21="FINANCIERO",OFFSET('PARÁMETROS'!$K$56,MATCH(U21,JC_FI,0),MATCH(T21,CC_FI,0)), OFFSET('PARÁMETROS'!$K$38,MATCH(U21,JC_L,0),MATCH(T21,CC_L,0))))))))),"") | AA21: =E11 -> Seguridad
V22: =IFERROR(IF(AA22="SEGURIDAD",OFFSET('PARÁMETROS'!$K$2,MATCH(U22,JC_SE,0),MATCH(T22,CC_SE,0)), IF(OR(AA22="DSRC/Estratégico",AA22="DSRC/Operativo"),OFFSET('PARÁMETROS'!$K$11,MATCH(U22,JC_DS,0),MATCH(T22,CC_DS,0)), IF(AA22="SALUD",OFFSET('PARÁMETROS'!$K$29,MATCH(U22,JC_SA,0),MATCH(T22,CC_SA,0)), IF(AA22="MEDIO AMBIENTE",OFFSET('PARÁMETROS'!$K$20,MATCH(U22,JC_MA,0),MATCH(T22,CC_MA,0)), IF(AA22="Rel. Gubernamentales",OFFSET('PARÁMETROS'!$K$48,MATCH(U22,JC_G,0),MATCH(T22,CC_G,0)), IF(AA22="OPERACIONAL",OFFSET('PARÁMETROS'!$K$56,MATCH(U22,JC_OP,0),MATCH(T22,CC_OP,0)), IF(AA22="FINANCIERO",OFFSET('PARÁMETROS'!$K$56,MATCH(U22,JC_FI,0),MATCH(T22,CC_FI,0)), OFFSET('PARÁMETROS'!$K$38,MATCH(U22,JC_L,0),MATCH(T22,CC_L,0))))))))),"") | AA22: =E11 -> Seguridad
V23: =IFERROR(IF(AA23="SEGURIDAD",OFFSET('PARÁMETROS'!$K$2,MATCH(U23,JC_SE,0),MATCH(T23,CC_SE,0)), IF(OR(AA23="DSRC/Estratégico",AA23="DSRC/Operativo"),OFFSET('PARÁMETROS'!$K$11,MATCH(U23,JC_DS,0),MATCH(T23,CC_DS,0)), IF(AA23="SALUD",OFFSET('PARÁMETROS'!$K$29,MATCH(U23,JC_SA,0),MATCH(T23,CC_SA,0)), IF(AA23="MEDIO AMBIENTE",OFFSET('PARÁMETROS'!$K$20,MATCH(U23,JC_MA,0),MATCH(T23,CC_MA,0)), IF(AA23="Rel. Gubernamentales",OFFSET('PARÁMETROS'!$K$48,MATCH(U23,JC_G,0),MATCH(T23,CC_G,0)), IF(AA23="OPERACIONAL",OFFSET('PARÁMETROS'!$K$56,MATCH(U23,JC_OP,0),MATCH(T23,CC_OP,0)), IF(AA23="FINANCIERO",OFFSET('PARÁMETROS'!$K$56,MATCH(U23,JC_FI,0),MATCH(T23,CC_FI,0)), OFFSET('PARÁMETROS'!$K$38,MATCH(U23,JC_L,0),MATCH(T23,CC_L,0))))))))),"") | AA23: =E11 -> Seguridad
V24: =IFERROR(IF(AA24="SEGURIDAD",OFFSET('PARÁMETROS'!$K$2,MATCH(U24,JC_SE,0),MATCH(T24,CC_SE,0)), IF(OR(AA24="DSRC/Estratégico",AA24="DSRC/Operativo"),OFFSET('PARÁMETROS'!$K$11,MATCH(U24,JC_DS,0),MATCH(T24,CC_DS,0)), IF(AA24="SALUD",OFFSET('PARÁMETROS'!$K$29,MATCH(U24,JC_SA,0),MATCH(T24,CC_SA,0)), IF(AA24="MEDIO AMBIENTE",OFFSET('PARÁMETROS'!$K$20,MATCH(U24,JC_MA,0),MATCH(T24,CC_MA,0)), IF(AA24="Rel. Gubernamentales",OFFSET('PARÁMETROS'!$K$48,MATCH(U24,JC_G,0),MATCH(T24,CC_G,0)), IF(AA24="OPERACIONAL",OFFSET('PARÁMETROS'!$K$56,MATCH(U24,JC_OP,0),MATCH(T24,CC_OP,0)), IF(AA24="FINANCIERO",OFFSET('PARÁMETROS'!$K$56,MATCH(U24,JC_FI,0),MATCH(T24,CC_FI,0)), OFFSET('PARÁMETROS'!$K$38,MATCH(U24,JC_L,0),MATCH(T24,CC_L,0))))))))),"") | AA24: =E11 -> Seguridad
V25: =IFERROR(IF(AA25="SEGURIDAD",OFFSET('PARÁMETROS'!$K$2,MATCH(U25,JC_SE,0),MATCH(T25,CC_SE,0)), IF(OR(AA25="DSRC/Estratégico",AA25="DSRC/Operativo"),OFFSET('PARÁMETROS'!$K$11,MATCH(U25,JC_DS,0),MATCH(T25,CC_DS,0)), IF(AA25="SALUD",OFFSET('PARÁMETROS'!$K$29,MATCH(U25,JC_SA,0),MATCH(T25,CC_SA,0)), IF(AA25="MEDIO AMBIENTE",OFFSET('PARÁMETROS'!$K$20,MATCH(U25,JC_MA,0),MATCH(T25,CC_MA,0)), IF(AA25="Rel. Gubernamentales",OFFSET('PARÁMETROS'!$K$48,MATCH(U25,JC_G,0),MATCH(T25,CC_G,0)), IF(AA25="OPERACIONAL",OFFSET('PARÁMETROS'!$K$56,MATCH(U25,JC_OP,0),MATCH(T25,CC_OP,0)), IF(AA25="FINANCIERO",OFFSET('PARÁMETROS'!$K$56,MATCH(U25,JC_FI,0),MATCH(T25,CC_FI,0)), OFFSET('PARÁMETROS'!$K$38,MATCH(U25,JC_L,0),MATCH(T25,CC_L,0))))))))),"") | AA25: =E11 -> Seguridad
V26: =IFERROR(IF(AA26="SEGURIDAD",OFFSET('PARÁMETROS'!$K$2,MATCH(U26,JC_SE,0),MATCH(T26,CC_SE,0)), IF(OR(AA26="DSRC/Estratégico",AA26="DSRC/Operativo"),OFFSET('PARÁMETROS'!$K$11,MATCH(U26,JC_DS,0),MATCH(T26,CC_DS,0)), IF(AA26="SALUD",OFFSET('PARÁMETROS'!$K$29,MATCH(U26,JC_SA,0),MATCH(T26,CC_SA,0)), IF(AA26="MEDIO AMBIENTE",OFFSET('PARÁMETROS'!$K$20,MATCH(U26,JC_MA,0),MATCH(T26,CC_MA,0)), IF(AA26="Rel. Gubernamentales",OFFSET('PARÁMETROS'!$K$48,MATCH(U26,JC_G,0),MATCH(T26,CC_G,0)), IF(AA26="OPERACIONAL",OFFSET('PARÁMETROS'!$K$56,MATCH(U26,JC_OP,0),MATCH(T26,CC_OP,0)), IF(AA26="FINANCIERO",OFFSET('PARÁMETROS'!$K$56,MATCH(U26,JC_FI,0),MATCH(T26,CC_FI,0)), OFFSET('PARÁMETROS'!$K$38,MATCH(U26,JC_L,0),MATCH(T26,CC_L,0))))))))),"") | AA26: =E11 -> Seguridad
L27: =IF(OR(J27<>"",K27<>""),OFFSET('PARÁMETROS'!$B$2,K27,J27),"") | N27: =IFERROR(L27*M27,"") -> 0 | O27: =IF(N27="","",IFERROR(IF(N27<=2,"ACEPTABLE",IF(N27<=6,"BAJA",IF(N27<=10,"ACEPTABLE CON REVISIÓN",IF(N27<=15,"SUSTANCIAL","INACEPTABLE")))),"")) -> ACEPTABLE | V27: =IFERROR(IF(AA27="SEGURIDAD",OFFSET('PARÁMETROS'!$K$2,MATCH(U27,JC_SE,0),MATCH(T27,CC_SE,0)), IF(OR(AA27="DSRC/Estratégico",AA27="DSRC/Operativo"),OFFSET('PARÁMETROS'!$K$11,MATCH(U27,JC_DS,0),MATCH(T27,CC_DS,0)), IF(AA27="SALUD",OFFSET('PARÁMETROS'!$K$29,MATCH(U27,JC_SA,0),MATCH(T27,CC_SA,0)), IF(AA27="MEDIO AMBIENTE",OFFSET('PARÁMETROS'!$K$20,MATCH(U27,JC_MA,0),MATCH(T27,CC_MA,0)), IF(AA27="Rel. Gubernamentales",OFFSET('PARÁMETROS'!$K$48,MATCH(U27,JC_G,0),MATCH(T27,CC_G,0)), IF(AA27="OPERACIONAL",OFFSET('PARÁMETROS'!$K$56,MATCH(U27,JC_OP,0),MATCH(T27,CC_OP,0)), IF(AA27="FINANCIERO",OFFSET('PARÁMETROS'!$K$56,MATCH(U27,JC_FI,0),MATCH(T27,CC_FI,0)), OFFSET('PARÁMETROS'!$K$38,MATCH(U27,JC_L,0),MATCH(T27,CC_L,0))))))))),"") | W27: =IF(E27="","", IF(COUNTA(V27:V42)-COUNTBLANK(V27:V42)=1, IF(O27="INACEPTABLE",IF(COUNTIF(V27:V42,"Control/Acción Eficaz")>=1,"SUSTANCIAL","INACEPTABLE"), IF(O27="SUSTANCIAL",IF(COUNTIF(V27:V42,"Control/Acción Eficaz")>=1,"ACEPTABLE CON REVISIÓN","SUSTANCIAL"), IF(O27="ACEPTABLE CON REVISIÓN",IF(COUNTIF(V27:V42,"Control/Acción Eficaz")>=1,"BAJA","ACEPTABLE CON REVISIÓN"), IF(O27="BAJA",IF(COUNTIF(V27:V42,"Control/Acción Eficaz")>=1,"ACEPTABLE","BAJA"),)))), IF(COUNTA(V27:V42)-COUNTBLANK(V27:V42)=2, IF(O27="INACEPTABLE",IF(COUNTIF(V27:V42,"Control/Acción Eficaz")=2,"ACEPTABLE CON REVISIÓN", IF(OR(AND(COUNTIF(V27:V42,"Control/Acción Eficaz")=1,COUNTIF(V27:V42,"Control/Acción Satisfactorio")=1), AND(COUNTIF(V27:V42,"Control/Acción Eficaz")=1,COUNTIF(V27:V42,"Control/Acción No Eficaz")=1)),"SUSTANCIAL","INACEPTABLE")), IF(O27="SUSTANCIAL",IF(COUNTIF(V27:V42,"Control/Acción Eficaz")=2,"BAJA", IF(OR(AND(COUNTIF(V27:V42,"Control/Acción Eficaz")=1,COUNTIF(V27:V42,"Control/Acción Satisfactorio")=1), AND(COUNTIF(V27:V42,"Control/Acción Eficaz")=1,COUNTIF(V27:V42,"Control/Acción No Eficaz")=1)),"ACEPTABLE CON REVISIÓN ","SUSTANCIAL")), IF(O27="ACEPTABLE CON REVISIÓN",IF(COUNTIF(V27:V42,"Control/Acción Eficaz")=2,"ACEPTABLE", IF(OR(AND(COUNTIF(V27:V42,"Control/Acción Eficaz")=1,COUNTIF(V27:V42,"Control/Acción Satisfactorio")=1), AND(COUNTIF(V27:V42,"Control/Acción Eficaz")=1,COUNTIF(V27:V42,"Control/Acción No Eficaz")=1)),"BAJA","ACEPTABLE CON REVISIÓN")), IF(O27="BAJA",IF(COUNTIF(V27:V42,"Control/Acción Eficaz")>=2,"ACEPTABLE","BAJA"),)))), IF(COUNTA(V27:V42)-COUNTBLANK(V27:V42)>=3, IF(O27="INACEPTABLE", IF(COUNTBLANK(V27:V42)=COUNTA(V27:V42),"", IF(COUNTIF(V27:V42,"Control/Acción No Eficaz")>=2,"INACEPTABLE", IF(AND(COUNTIF(V27:V42,"Control/Acción No Eficaz")=0,COUNTIF(V27:V42,"Control/Acción Eficaz")>=2),"ACEPTABLE CON REVISIÓN ","SUSTANCIAL"))), IF(O27="SUSTANCIAL", IF(COUNTBLANK(V27:V42)=COUNTA(V27:V42),"", IF(COUNTIF(V27:V42,"Control/Acción No Eficaz")>=2,"SUSTANCIAL", IF(AND(COUNTIF(V27:V42,"Control/Acción No Eficaz")=0,COUNTIF(V27:V42,"Control/Acción Eficaz")>=2),"BAJA","ACEPTABLE CON REVISIÓN"))), IF(O27="ACEPTABLE CON REVISIÓN", IF(COUNTBLANK(V27:V42)=COUNTA(V27:V42),"", IF(COUNTIF(V27:V42,"Control/Acción No Eficaz")>=2,"ACEPTABLE CON REVISIÓN", IF(AND(COUNTIF(V27:V42,"Control/Acción No Eficaz")=0,COUNTIF(V27:V42,"Control/Acción Eficaz")>=2),"ACEPTABLE","BAJA"))), IF(O27="BAJA", IF(COUNTBLANK(V27:V42)=COUNTA(V27:V42),"", IF(AND(COUNTBLANK(V27:V42)<1,COUNTA(V27:V42)=1), IF(COUNTIF(V27:V42,"Control/Acción No Eficaz")>=2,"BAJA", IF(AND(COUNTIF(V27:V42,"Control/Acción No Eficaz")=0,COUNTIF(V27:V42,"Control/Acción Eficaz")>=2),"ACEPTABLE","BAJA")), IF(COUNTIF(V27:V42,"Control/Acción No Eficaz")>=2,"BAJA", IF(AND(COUNTIF(V27:V42,"Control/Acción No Eficaz")=0,COUNTIF(V27:V42,"Control/Acción Eficaz")>=2),"ACEPTABLE","BAJA")))), IF(COUNTIF(V27:V42,"")>=5,"",O27))))), "")))) | AA27: =E27
V28: =IFERROR(IF(AA28="SEGURIDAD",OFFSET('PARÁMETROS'!$K$2,MATCH(U28,JC_SE,0),MATCH(T28,CC_SE,0)), IF(OR(AA28="DSRC/Estratégico",AA28="DSRC/Operativo"),OFFSET('PARÁMETROS'!$K$11,MATCH(U28,JC_DS,0),MATCH(T28,CC_DS,0)), IF(AA28="SALUD",OFFSET('PARÁMETROS'!$K$29,MATCH(U28,JC_SA,0),MATCH(T28,CC_SA,0)), IF(AA28="MEDIO AMBIENTE",OFFSET('PARÁMETROS'!$K$20,MATCH(U28,JC_MA,0),MATCH(T28,CC_MA,0)), IF(AA28="Rel. Gubernamentales",OFFSET('PARÁMETROS'!$K$48,MATCH(U28,JC_G,0),MATCH(T28,CC_G,0)), IF(AA28="OPERACIONAL",OFFSET('PARÁMETROS'!$K$56,MATCH(U28,JC_OP,0),MATCH(T28,CC_OP,0)), IF(AA28="FINANCIERO",OFFSET('PARÁMETROS'!$K$56,MATCH(U28,JC_FI,0),MATCH(T28,CC_FI,0)), OFFSET('PARÁMETROS'!$K$38,MATCH(U28,JC_L,0),MATCH(T28,CC_L,0))))))))),"") | AA28: =E27
V29: =IFERROR(IF(AA29="SEGURIDAD",OFFSET('PARÁMETROS'!$K$2,MATCH(U29,JC_SE,0),MATCH(T29,CC_SE,0)), IF(OR(AA29="DSRC/Estratégico",AA29="DSRC/Operativo"),OFFSET('PARÁMETROS'!$K$11,MATCH(U29,JC_DS,0),MATCH(T29,CC_DS,0)), IF(AA29="SALUD",OFFSET('PARÁMETROS'!$K$29,MATCH(U29,JC_SA,0),MATCH(T29,CC_SA,0)), IF(AA29="MEDIO AMBIENTE",OFFSET('PARÁMETROS'!$K$20,MATCH(U29,JC_MA,0),MATCH(T29,CC_MA,0)), IF(AA29="Rel. Gubernamentales",OFFSET('PARÁMETROS'!$K$48,MATCH(U29,JC_G,0),MATCH(T29,CC_G,0)), IF(AA29="OPERACIONAL",OFFSET('PARÁMETROS'!$K$56,MATCH(U29,JC_OP,0),MATCH(T29,CC_OP,0)), IF(AA29="FINANCIERO",OFFSET('PARÁMETROS'!$K$56,MATCH(U29,JC_FI,0),MATCH(T29,CC_FI,0)), OFFSET('PARÁMETROS'!$K$38,MATCH(U29,JC_L,0),MATCH(T29,CC_L,0))))))))),"") | AA29: =E27
V30: =IFERROR(IF(AA30="SEGURIDAD",OFFSET('PARÁMETROS'!$K$2,MATCH(U30,JC_SE,0),MATCH(T30,CC_SE,0)), IF(OR(AA30="DSRC/Estratégico",AA30="DSRC/Operativo"),OFFSET('PARÁMETROS'!$K$11,MATCH(U30,JC_DS,0),MATCH(T30,CC_DS,0)), IF(AA30="SALUD",OFFSET('PARÁMETROS'!$K$29,MATCH(U30,JC_SA,0),MATCH(T30,CC_SA,0)), IF(AA30="MEDIO AMBIENTE",OFFSET('PARÁMETROS'!$K$20,MATCH(U30,JC_MA,0),MATCH(T30,CC_MA,0)), IF(AA30="Rel. Gubernamentales",OFFSET('PARÁMETROS'!$K$48,MATCH(U30,JC_G,0),MATCH(T30,CC_G,0)), IF(AA30="OPERACIONAL",OFFSET('PARÁMETROS'!$K$56,MATCH(U30,JC_OP,0),MATCH(T30,CC_OP,0)), IF(AA30="FINANCIERO",OFFSET('PARÁMETROS'!$K$56,MATCH(U30,JC_FI,0),MATCH(T30,CC_FI,0)), OFFSET('PARÁMETROS'!$K$38,MATCH(U30,JC_L,0),MATCH(T30,CC_L,0))))))))),"") | AA30: =E27
V31: =IFERROR(IF(AA31="SEGURIDAD",OFFSET('PARÁMETROS'!$K$2,MATCH(U31,JC_SE,0),MATCH(T31,CC_SE,0)), IF(OR(AA31="DSRC/Estratégico",AA31="DSRC/Operativo"),OFFSET('PARÁMETROS'!$K$11,MATCH(U31,JC_DS,0),MATCH(T31,CC_DS,0)), IF(AA31="SALUD",OFFSET('PARÁMETROS'!$K$29,MATCH(U31,JC_SA,0),MATCH(T31,CC_SA,0)), IF(AA31="MEDIO AMBIENTE",OFFSET('PARÁMETROS'!$K$20,MATCH(U31,JC_MA,0),MATCH(T31,CC_MA,0)), IF(AA31="Rel. Gubernamentales",OFFSET('PARÁMETROS'!$K$48,MATCH(U31,JC_G,0),MATCH(T31,CC_G,0)), IF(AA31="OPERACIONAL",OFFSET('PARÁMETROS'!$K$56,MATCH(U31,JC_OP,0),MATCH(T31,CC_OP,0)), IF(AA31="FINANCIERO",OFFSET('PARÁMETROS'!$K$56,MATCH(U31,JC_FI,0),MATCH(T31,CC_FI,0)), OFFSET('PARÁMETROS'!$K$38,MATCH(U31,JC_L,0),MATCH(T31,CC_L,0))))))))),"") | AA31: =E27
V32: =IFERROR(IF(AA32="SEGURIDAD",OFFSET('PARÁMETROS'!$K$2,MATCH(U32,JC_SE,0),MATCH(T32,CC_SE,0)), IF(OR(AA32="DSRC/Estratégico",AA32="DSRC/Operativo"),OFFSET('PARÁMETROS'!$K$11,MATCH(U32,JC_DS,0),MATCH(T32,CC_DS,0)), IF(AA32="SALUD",OFFSET('PARÁMETROS'!$K$29,MATCH(U32,JC_SA,0),MATCH(T32,CC_SA,0)), IF(AA32="MEDIO AMBIENTE",OFFSET('PARÁMETROS'!$K$20,MATCH(U32,JC_MA,0),MATCH(T32,CC_MA,0)), IF(AA32="Rel. Gubernamentales",OFFSET('PARÁMETROS'!$K$48,MATCH(U32,JC_G,0),MATCH(T32,CC_G,0)), IF(AA32="OPERACIONAL",OFFSET('PARÁMETROS'!$K$56,MATCH(U32,JC_OP,0),MATCH(T32,CC_OP,0)), IF(AA32="FINANCIERO",OFFSET('PARÁMETROS'!$K$56,MATCH(U32,JC_FI,0),MATCH(T32,CC_FI,0)), OFFSET('PARÁMETROS'!$K$38,MATCH(U32,JC_L,0),MATCH(T32,CC_L,0))))))))),"") | AA32: =E27
V33: =IFERROR(IF(AA33="SEGURIDAD",OFFSET('PARÁMETROS'!$K$2,MATCH(U33,JC_SE,0),MATCH(T33,CC_SE,0)), IF(OR(AA33="DSRC/Estratégico",AA33="DSRC/Operativo"),OFFSET('PARÁMETROS'!$K$11,MATCH(U33,JC_DS,0),MATCH(T33,CC_DS,0)), IF(AA33="SALUD",OFFSET('PARÁMETROS'!$K$29,MATCH(U33,JC_SA,0),MATCH(T33,CC_SA,0)), IF(AA33="MEDIO AMBIENTE",OFFSET('PARÁMETROS'!$K$20,MATCH(U33,JC_MA,0),MATCH(T33,CC_MA,0)), IF(AA33="Rel. Gubernamentales",OFFSET('PARÁMETROS'!$K$48,MATCH(U33,JC_G,0),MATCH(T33,CC_G,0)), IF(AA33="OPERACIONAL",OFFSET('PARÁMETROS'!$K$56,MATCH(U33,JC_OP,0),MATCH(T33,CC_OP,0)), IF(AA33="FINANCIERO",OFFSET('PARÁMETROS'!$K$56,MATCH(U33,JC_FI,0),MATCH(T33,CC_FI,0)), OFFSET('PARÁMETROS'!$K$38,MATCH(U33,JC_L,0),MATCH(T33,CC_L,0))))))))),"") | AA33: =E27
V34: =IFERROR(IF(AA34="SEGURIDAD",OFFSET('PARÁMETROS'!$K$2,MATCH(U34,JC_SE,0),MATCH(T34,CC_SE,0)), IF(OR(AA34="DSRC/Estratégico",AA34="DSRC/Operativo"),OFFSET('PARÁMETROS'!$K$11,MATCH(U34,JC_DS,0),MATCH(T34,CC_DS,0)), IF(AA34="SALUD",OFFSET('PARÁMETROS'!$K$29,MATCH(U34,JC_SA,0),MATCH(T34,CC_SA,0)), IF(AA34="MEDIO AMBIENTE",OFFSET('PARÁMETROS'!$K$20,MATCH(U34,JC_MA,0),MATCH(T34,CC_MA,0)), IF(AA34="Rel. Gubernamentales",OFFSET('PARÁMETROS'!$K$48,MATCH(U34,JC_G,0),MATCH(T34,CC_G,0)), IF(AA34="OPERACIONAL",OFFSET('PARÁMETROS'!$K$56,MATCH(U34,JC_OP,0),MATCH(T34,CC_OP,0)), IF(AA34="FINANCIERO",OFFSET('PARÁMETROS'!$K$56,MATCH(U34,JC_FI,0),MATCH(T34,CC_FI,0)), OFFSET('PARÁMETROS'!$K$38,MATCH(U34,JC_L,0),MATCH(T34,CC_L,0))))))))),"") | AA34: =E27
V35: =IFERROR(IF(AA35="SEGURIDAD",OFFSET('PARÁMETROS'!$K$2,MATCH(U35,JC_SE,0),MATCH(T35,CC_SE,0)), IF(OR(AA35="DSRC/Estratégico",AA35="DSRC/Operativo"),OFFSET('PARÁMETROS'!$K$11,MATCH(U35,JC_DS,0),MATCH(T35,CC_DS,0)), IF(AA35="SALUD",OFFSET('PARÁMETROS'!$K$29,MATCH(U35,JC_SA,0),MATCH(T35,CC_SA,0)), IF(AA35="MEDIO AMBIENTE",OFFSET('PARÁMETROS'!$K$20,MATCH(U35,JC_MA,0),MATCH(T35,CC_MA,0)), IF(AA35="Rel. Gubernamentales",OFFSET('PARÁMETROS'!$K$48,MATCH(U35,JC_G,0),MATCH(T35,CC_G,0)), IF(AA35="OPERACIONAL",OFFSET('PARÁMETROS'!$K$56,MATCH(U35,JC_OP,0),MATCH(T35,CC_OP,0)), IF(AA35="FINANCIERO",OFFSET('PARÁMETROS'!$K$56,MATCH(U35,JC_FI,0),MATCH(T35,CC_FI,0)), OFFSET('PARÁMETROS'!$K$38,MATCH(U35,JC_L,0),MATCH(T35,CC_L,0))))))))),"") | AA35: =E27
V36: =IFERROR(IF(AA36="SEGURIDAD",OFFSET('PARÁMETROS'!$K$2,MATCH(U36,JC_SE,0),MATCH(T36,CC_SE,0)), IF(OR(AA36="DSRC/Estratégico",AA36="DSRC/Operativo"),OFFSET('PARÁMETROS'!$K$11,MATCH(U36,JC_DS,0),MATCH(T36,CC_DS,0)), IF(AA36="SALUD",OFFSET('PARÁMETROS'!$K$29,MATCH(U36,JC_SA,0),MATCH(T36,CC_SA,0)), IF(AA36="MEDIO AMBIENTE",OFFSET('PARÁMETROS'!$K$20,MATCH(U36,JC_MA,0),MATCH(T36,CC_MA,0)), IF(AA36="Rel. Gubernamentales",OFFSET('PARÁMETROS'!$K$48,MATCH(U36,JC_G,0),MATCH(T36,CC_G,0)), IF(AA36="OPERACIONAL",OFFSET('PARÁMETROS'!$K$56,MATCH(U36,JC_OP,0),MATCH(T36,CC_OP,0)), IF(AA36="FINANCIERO",OFFSET('PARÁMETROS'!$K$56,MATCH(U36,JC_FI,0),MATCH(T36,CC_FI,0)), OFFSET('PARÁMETROS'!$K$38,MATCH(U36,JC_L,0),MATCH(T36,CC_L,0))))))))),"") | AA36: =E27
V37: =IFERROR(IF(AA37="SEGURIDAD",OFFSET('PARÁMETROS'!$K$2,MATCH(U37,JC_SE,0),MATCH(T37,CC_SE,0)), IF(OR(AA37="DSRC/Estratégico",AA37="DSRC/Operativo"),OFFSET('PARÁMETROS'!$K$11,MATCH(U37,JC_DS,0),MATCH(T37,CC_DS,0)), IF(AA37="SALUD",OFFSET('PARÁMETROS'!$K$29,MATCH(U37,JC_SA,0),MATCH(T37,CC_SA,0)), IF(AA37="MEDIO AMBIENTE",OFFSET('PARÁMETROS'!$K$20,MATCH(U37,JC_MA,0),MATCH(T37,CC_MA,0)), IF(AA37="Rel. Gubernamentales",OFFSET('PARÁMETROS'!$K$48,MATCH(U37,JC_G,0),MATCH(T37,CC_G,0)), IF(AA37="OPERACIONAL",OFFSET('PARÁMETROS'!$K$56,MATCH(U37,JC_OP,0),MATCH(T37,CC_OP,0)), IF(AA37="FINANCIERO",OFFSET('PARÁMETROS'!$K$56,MATCH(U37,JC_FI,0),MATCH(T37,CC_FI,0)), OFFSET('PARÁMETROS'!$K$38,MATCH(U37,JC_L,0),MATCH(T37,CC_L,0))))))))),"") | AA37: =E27
V38: =IFERROR(IF(AA38="SEGURIDAD",OFFSET('PARÁMETROS'!$K$2,MATCH(U38,JC_SE,0),MATCH(T38,CC_SE,0)), IF(OR(AA38="DSRC/Estratégico",AA38="DSRC/Operativo"),OFFSET('PARÁMETROS'!$K$11,MATCH(U38,JC_DS,0),MATCH(T38,CC_DS,0)), IF(AA38="SALUD",OFFSET('PARÁMETROS'!$K$29,MATCH(U38,JC_SA,0),MATCH(T38,CC_SA,0)), IF(AA38="MEDIO AMBIENTE",OFFSET('PARÁMETROS'!$K$20,MATCH(U38,JC_MA,0),MATCH(T38,CC_MA,0)), IF(AA38="Rel. Gubernamentales",OFFSET('PARÁMETROS'!$K$48,MATCH(U38,JC_G,0),MATCH(T38,CC_G,0)), IF(AA38="OPERACIONAL",OFFSET('PARÁMETROS'!$K$56,MATCH(U38,JC_OP,0),MATCH(T38,CC_OP,0)), IF(AA38="FINANCIERO",OFFSET('PARÁMETROS'!$K$56,MATCH(U38,JC_FI,0),MATCH(T38,CC_FI,0)), OFFSET('PARÁMETROS'!$K$38,MATCH(U38,JC_L,0),MATCH(T38,CC_L,0))))))))),"") | AA38: =E27
V39: =IFERROR(IF(AA39="SEGURIDAD",OFFSET('PARÁMETROS'!$K$2,MATCH(U39,JC_SE,0),MATCH(T39,CC_SE,0)), IF(OR(AA39="DSRC/Estratégico",AA39="DSRC/Operativo"),OFFSET('PARÁMETROS'!$K$11,MATCH(U39,JC_DS,0),MATCH(T39,CC_DS,0)), IF(AA39="SALUD",OFFSET('PARÁMETROS'!$K$29,MATCH(U39,JC_SA,0),MATCH(T39,CC_SA,0)), IF(AA39="MEDIO AMBIENTE",OFFSET('PARÁMETROS'!$K$20,MATCH(U39,JC_MA,0),MATCH(T39,CC_MA,0)), IF(AA39="Rel. Gubernamentales",OFFSET('PARÁMETROS'!$K$48,MATCH(U39,JC_G,0),MATCH(T39,CC_G,0)), IF(AA39="OPERACIONAL",OFFSET('PARÁMETROS'!$K$56,MATCH(U39,JC_OP,0),MATCH(T39,CC_OP,0)), IF(AA39="FINANCIERO",OFFSET('PARÁMETROS'!$K$56,MATCH(U39,JC_FI,0),MATCH(T39,CC_FI,0)), OFFSET('PARÁMETROS'!$K$38,MATCH(U39,JC_L,0),MATCH(T39,CC_L,0))))))))),"") | AA39: =E27
V40: =IFERROR(IF(AA40="SEGURIDAD",OFFSET('PARÁMETROS'!$K$2,MATCH(U40,JC_SE,0),MATCH(T40,CC_SE,0)), IF(OR(AA40="DSRC/Estratégico",AA40="DSRC/Operativo"),OFFSET('PARÁMETROS'!$K$11,MATCH(U40,JC_DS,0),MATCH(T40,CC_DS,0)), IF(AA40="SALUD",OFFSET('PARÁMETROS'!$K$29,MATCH(U40,JC_SA,0),MATCH(T40,CC_SA,0)), IF(AA40="MEDIO AMBIENTE",OFFSET('PARÁMETROS'!$K$20,MATCH(U40,JC_MA,0),MATCH(T40,CC_MA,0)), IF(AA40="Rel. Gubernamentales",OFFSET('PARÁMETROS'!$K$48,MATCH(U40,JC_G,0),MATCH(T40,CC_G,0)), IF(AA40="OPERACIONAL",OFFSET('PARÁMETROS'!$K$56,MATCH(U40,JC_OP,0),MATCH(T40,CC_OP,0)), IF(AA40="FINANCIERO",OFFSET('PARÁMETROS'!$K$56,MATCH(U40,JC_FI,0),MATCH(T40,CC_FI,0)), OFFSET('PARÁMETROS'!$K$38,MATCH(U40,JC_L,0),MATCH(T40,CC_L,0))))))))),"") | AA40: =E27
V41: =IFERROR(IF(AA41="SEGURIDAD",OFFSET('PARÁMETROS'!$K$2,MATCH(U41,JC_SE,0),MATCH(T41,CC_SE,0)), IF(OR(AA41="DSRC/Estratégico",AA41="DSRC/Operativo"),OFFSET('PARÁMETROS'!$K$11,MATCH(U41,JC_DS,0),MATCH(T41,CC_DS,0)), IF(AA41="SALUD",OFFSET('PARÁMETROS'!$K$29,MATCH(U41,JC_SA,0),MATCH(T41,CC_SA,0)), IF(AA41="MEDIO AMBIENTE",OFFSET('PARÁMETROS'!$K$20,MATCH(U41,JC_MA,0),MATCH(T41,CC_MA,0)), IF(AA41="Rel. Gubernamentales",OFFSET('PARÁMETROS'!$K$48,MATCH(U41,JC_G,0),MATCH(T41,CC_G,0)), IF(AA41="OPERACIONAL",OFFSET('PARÁMETROS'!$K$56,MATCH(U41,JC_OP,0),MATCH(T41,CC_OP,0)), IF(AA41="FINANCIERO",OFFSET('PARÁMETROS'!$K$56,MATCH(U41,JC_FI,0),MATCH(T41,CC_FI,0)), OFFSET('PARÁMETROS'!$K$38,MATCH(U41,JC_L,0),MATCH(T41,CC_L,0))))))))),"") | AA41: =E27
V42: =IFERROR(IF(AA42="SEGURIDAD",OFFSET('PARÁMETROS'!$K$2,MATCH(U42,JC_SE,0),MATCH(T42,CC_SE,0)), IF(OR(AA42="DSRC/Estratégico",AA42="DSRC/Operativo"),OFFSET('PARÁMETROS'!$K$11,MATCH(U42,JC_DS,0),MATCH(T42,CC_DS,0)), IF(AA42="SALUD",OFFSET('PARÁMETROS'!$K$29,MATCH(U42,JC_SA,0),MATCH(T42,CC_SA,0)), IF(AA42="MEDIO AMBIENTE",OFFSET('PARÁMETROS'!$K$20,MATCH(U42,JC_MA,0),MATCH(T42,CC_MA,0)), IF(AA42="Rel. Gubernamentales",OFFSET('PARÁMETROS'!$K$48,MATCH(U42,JC_G,0),MATCH(T42,CC_G,0)), IF(AA42="OPERACIONAL",OFFSET('PARÁMETROS'!$K$56,MATCH(U42,JC_OP,0),MATCH(T42,CC_OP,0)), IF(AA42="FINANCIERO",OFFSET('PARÁMETROS'!$K$56,MATCH(U42,JC_FI,0),MATCH(T42,CC_FI,0)), OFFSET('PARÁMETROS'!$K$38,MATCH(U42,JC_L,0),MATCH(T42,CC_L,0))))))))),"") | AA42: =E27
L43: =IF(OR(J43<>"",K43<>""),OFFSET('PARÁMETROS'!$B$2,K43,J43),"") | N43: =IFERROR(L43*M43,"") -> 0 | O43: =IF(N43="","",IFERROR(IF(N43<=2,"ACEPTABLE",IF(N43<=6,"BAJA",IF(N43<=10,"ACEPTABLE CON REVISIÓN",IF(N43<=15,"SUSTANCIAL","INACEPTABLE")))),"")) -> ACEPTABLE | V43: =IFERROR(IF(AA43="SEGURIDAD",OFFSET('PARÁMETROS'!$K$2,MATCH(U43,JC_SE,0),MATCH(T43,CC_SE,0)), IF(OR(AA43="DSRC/Estratégico",AA43="DSRC/Operativo"),OFFSET('PARÁMETROS'!$K$11,MATCH(U43,JC_DS,0),MATCH(T43,CC_DS,0)), IF(AA43="SALUD",OFFSET('PARÁMETROS'!$K$29,MATCH(U43,JC_SA,0),MATCH(T43,CC_SA,0)), IF(AA43="MEDIO AMBIENTE",OFFSET('PARÁMETROS'!$K$20,MATCH(U43,JC_MA,0),MATCH(T43,CC_MA,0)), IF(AA43="Rel. Gubernamentales",OFFSET('PARÁMETROS'!$K$48,MATCH(U43,JC_G,0),MATCH(T43,CC_G,0)), IF(AA43="OPERACIONAL",OFFSET('PARÁMETROS'!$K$56,MATCH(U43,JC_OP,0),MATCH(T43,CC_OP,0)), IF(AA43="FINANCIERO",OFFSET('PARÁMETROS'!$K$56,MATCH(U43,JC_FI,0),MATCH(T43,CC_FI,0)), OFFSET('PARÁMETROS'!$K$38,MATCH(U43,JC_L,0),MATCH(T43,CC_L,0))))))))),"") | W43: =IF(E43="","", IF(COUNTA(V43:V58)-COUNTBLANK(V43:V58)=1, IF(O43="INACEPTABLE",IF(COUNTIF(V43:V58,"Control/Acción Eficaz")>=1,"SUSTANCIAL","INACEPTABLE"), IF(O43="SUSTANCIAL",IF(COUNTIF(V43:V58,"Control/Acción Eficaz")>=1,"ACEPTABLE CON REVISIÓN","SUSTANCIAL"), IF(O43="ACEPTABLE CON REVISIÓN",IF(COUNTIF(V43:V58,"Control/Acción Eficaz")>=1,"BAJA","ACEPTABLE CON REVISIÓN"), IF(O43="BAJA",IF(COUNTIF(V43:V58,"Control/Acción Eficaz")>=1,"ACEPTABLE","BAJA"),)))), IF(COUNTA(V43:V58)-COUNTBLANK(V43:V58)=2, IF(O43="INACEPTABLE",IF(COUNTIF(V43:V58,"Control/Acción Eficaz")=2,"ACEPTABLE CON REVISIÓN", IF(OR(AND(COUNTIF(V43:V58,"Control/Acción Eficaz")=1,COUNTIF(V43:V58,"Control/Acción Satisfactorio")=1), AND(COUNTIF(V43:V58,"Control/Acción Eficaz")=1,COUNTIF(V43:V58,"Control/Acción No Eficaz")=1)),"SUSTANCIAL","INACEPTABLE")), IF(O43="SUSTANCIAL",IF(COUNTIF(V43:V58,"Control/Acción Eficaz")=2,"BAJA", IF(OR(AND(COUNTIF(V43:V58,"Control/Acción Eficaz")=1,COUNTIF(V43:V58,"Control/Acción Satisfactorio")=1), AND(COUNTIF(V43:V58,"Control/Acción Eficaz")=1,COUNTIF(V43:V58,"Control/Acción No Eficaz")=1)),"ACEPTABLE CON REVISIÓN ","SUSTANCIAL")), IF(O43="ACEPTABLE CON REVISIÓN",IF(COUNTIF(V43:V58,"Control/Acción Eficaz")=2,"ACEPTABLE", IF(OR(AND(COUNTIF(V43:V58,"Control/Acción Eficaz")=1,COUNTIF(V43:V58,"Control/Acción Satisfactorio")=1), AND(COUNTIF(V43:V58,"Control/Acción Eficaz")=1,COUNTIF(V43:V58,"Control/Acción No Eficaz")=1)),"BAJA","ACEPTABLE CON REVISIÓN")), IF(O43="BAJA",IF(COUNTIF(V43:V58,"Control/Acción Eficaz")>=2,"ACEPTABLE","BAJA"),)))), IF(COUNTA(V43:V58)-COUNTBLANK(V43:V58)>=3, IF(O43="INACEPTABLE", IF(COUNTBLANK(V43:V58)=COUNTA(V43:V58),"", IF(COUNTIF(V43:V58,"Control/Acción No Eficaz")>=2,"INACEPTABLE", IF(AND(COUNTIF(V43:V58,"Control/Acción No Eficaz")=0,COUNTIF(V43:V58,"Control/Acción Eficaz")>=2),"ACEPTABLE CON REVISIÓN ","SUSTANCIAL"))), IF(O43="SUSTANCIAL", IF(COUNTBLANK(V43:V58)=COUNTA(V43:V58),"", IF(COUNTIF(V43:V58,"Control/Acción No Eficaz")>=2,"SUSTANCIAL", IF(AND(COUNTIF(V43:V58,"Control/Acción No Eficaz")=0,COUNTIF(V43:V58,"Control/Acción Eficaz")>=2),"BAJA","ACEPTABLE CON REVISIÓN"))), IF(O43="ACEPTABLE CON REVISIÓN", IF(COUNTBLANK(V43:V58)=COUNTA(V43:V58),"", IF(COUNTIF(V43:V58,"Control/Acción No Eficaz")>=2,"ACEPTABLE CON REVISIÓN", IF(AND(COUNTIF(V43:V58,"Control/Acción No Eficaz")=0,COUNTIF(V43:V58,"Control/Acción Eficaz")>=2),"ACEPTABLE","BAJA"))), IF(O43="BAJA", IF(COUNTBLANK(V43:V58)=COUNTA(V43:V58),"", IF(AND(COUNTBLANK(V43:V58)<1,COUNTA(V43:V58)=1), IF(COUNTIF(V43:V58,"Control/Acción No Eficaz")>=2,"BAJA", IF(AND(COUNTIF(V43:V58,"Control/Acción No Eficaz")=0,COUNTIF(V43:V58,"Control/Acción Eficaz")>=2),"ACEPTABLE","BAJA")), IF(COUNTIF(V43:V58,"Control/Acción No Eficaz")>=2,"BAJA", IF(AND(COUNTIF(V43:V58,"Control/Acción No Eficaz")=0,COUNTIF(V43:V58,"Control/Acción Eficaz")>=2),"ACEPTABLE","BAJA")))), IF(COUNTIF(V43:V58,"")>=5,"",O43))))), "")))) | AA43: =E43
V44: =IFERROR(IF(AA44="SEGURIDAD",OFFSET('PARÁMETROS'!$K$2,MATCH(U44,JC_SE,0),MATCH(T44,CC_SE,0)), IF(OR(AA44="DSRC/Estratégico",AA44="DSRC/Operativo"),OFFSET('PARÁMETROS'!$K$11,MATCH(U44,JC_DS,0),MATCH(T44,CC_DS,0)), IF(AA44="SALUD",OFFSET('PARÁMETROS'!$K$29,MATCH(U44,JC_SA,0),MATCH(T44,CC_SA,0)), IF(AA44="MEDIO AMBIENTE",OFFSET('PARÁMETROS'!$K$20,MATCH(U44,JC_MA,0),MATCH(T44,CC_MA,0)), IF(AA44="Rel. Gubernamentales",OFFSET('PARÁMETROS'!$K$48,MATCH(U44,JC_G,0),MATCH(T44,CC_G,0)), IF(AA44="OPERACIONAL",OFFSET('PARÁMETROS'!$K$56,MATCH(U44,JC_OP,0),MATCH(T44,CC_OP,0)), IF(AA44="FINANCIERO",OFFSET('PARÁMETROS'!$K$56,MATCH(U44,JC_FI,0),MATCH(T44,CC_FI,0)), OFFSET('PARÁMETROS'!$K$38,MATCH(U44,JC_L,0),MATCH(T44,CC_L,0))))))))),"") | AA44: =E43
V45: =IFERROR(IF(AA45="SEGURIDAD",OFFSET('PARÁMETROS'!$K$2,MATCH(U45,JC_SE,0),MATCH(T45,CC_SE,0)), IF(OR(AA45="DSRC/Estratégico",AA45="DSRC/Operativo"),OFFSET('PARÁMETROS'!$K$11,MATCH(U45,JC_DS,0),MATCH(T45,CC_DS,0)), IF(AA45="SALUD",OFFSET('PARÁMETROS'!$K$29,MATCH(U45,JC_SA,0),MATCH(T45,CC_SA,0)), IF(AA45="MEDIO AMBIENTE",OFFSET('PARÁMETROS'!$K$20,MATCH(U45,JC_MA,0),MATCH(T45,CC_MA,0)), IF(AA45="Rel. Gubernamentales",OFFSET('PARÁMETROS'!$K$48,MATCH(U45,JC_G,0),MATCH(T45,CC_G,0)), IF(AA45="OPERACIONAL",OFFSET('PARÁMETROS'!$K$56,MATCH(U45,JC_OP,0),MATCH(T45,CC_OP,0)), IF(AA45="FINANCIERO",OFFSET('PARÁMETROS'!$K$56,MATCH(U45,JC_FI,0),MATCH(T45,CC_FI,0)), OFFSET('PARÁMETROS'!$K$38,MATCH(U45,JC_L,0),MATCH(T45,CC_L,0))))))))),"") | AA45: =E43
V46: =IFERROR(IF(AA46="SEGURIDAD",OFFSET('PARÁMETROS'!$K$2,MATCH(U46,JC_SE,0),MATCH(T46,CC_SE,0)), IF(OR(AA46="DSRC/Estratégico",AA46="DSRC/Operativo"),OFFSET('PARÁMETROS'!$K$11,MATCH(U46,JC_DS,0),MATCH(T46,CC_DS,0)), IF(AA46="SALUD",OFFSET('PARÁMETROS'!$K$29,MATCH(U46,JC_SA,0),MATCH(T46,CC_SA,0)), IF(AA46="MEDIO AMBIENTE",OFFSET('PARÁMETROS'!$K$20,MATCH(U46,JC_MA,0),MATCH(T46,CC_MA,0)), IF(AA46="Rel. Gubernamentales",OFFSET('PARÁMETROS'!$K$48,MATCH(U46,JC_G,0),MATCH(T46,CC_G,0)), IF(AA46="OPERACIONAL",OFFSET('PARÁMETROS'!$K$56,MATCH(U46,JC_OP,0),MATCH(T46,CC_OP,0)), IF(AA46="FINANCIERO",OFFSET('PARÁMETROS'!$K$56,MATCH(U46,JC_FI,0),MATCH(T46,CC_FI,0)), OFFSET('PARÁMETROS'!$K$38,MATCH(U46,JC_L,0),MATCH(T46,CC_L,0))))))))),"") | AA46: =E43
V47: =IFERROR(IF(AA47="SEGURIDAD",OFFSET('PARÁMETROS'!$K$2,MATCH(U47,JC_SE,0),MATCH(T47,CC_SE,0)), IF(OR(AA47="DSRC/Estratégico",AA47="DSRC/Operativo"),OFFSET('PARÁMETROS'!$K$11,MATCH(U47,JC_DS,0),MATCH(T47,CC_DS,0)), IF(AA47="SALUD",OFFSET('PARÁMETROS'!$K$29,MATCH(U47,JC_SA,0),MATCH(T47,CC_SA,0)), IF(AA47="MEDIO AMBIENTE",OFFSET('PARÁMETROS'!$K$20,MATCH(U47,JC_MA,0),MATCH(T47,CC_MA,0)), IF(AA47="Rel. Gubernamentales",OFFSET('PARÁMETROS'!$K$48,MATCH(U47,JC_G,0),MATCH(T47,CC_G,0)), IF(AA47="OPERACIONAL",OFFSET('PARÁMETROS'!$K$56,MATCH(U47,JC_OP,0),MATCH(T47,CC_OP,0)), IF(AA47="FINANCIERO",OFFSET('PARÁMETROS'!$K$56,MATCH(U47,JC_FI,0),MATCH(T47,CC_FI,0)), OFFSET('PARÁMETROS'!$K$38,MATCH(U47,JC_L,0),MATCH(T47,CC_L,0))))))))),"") | AA47: =E43
V48: =IFERROR(IF(AA48="SEGURIDAD",OFFSET('PARÁMETROS'!$K$2,MATCH(U48,JC_SE,0),MATCH(T48,CC_SE,0)), IF(OR(AA48="DSRC/Estratégico",AA48="DSRC/Operativo"),OFFSET('PARÁMETROS'!$K$11,MATCH(U48,JC_DS,0),MATCH(T48,CC_DS,0)), IF(AA48="SALUD",OFFSET('PARÁMETROS'!$K$29,MATCH(U48,JC_SA,0),MATCH(T48,CC_SA,0)), IF(AA48="MEDIO AMBIENTE",OFFSET('PARÁMETROS'!$K$20,MATCH(U48,JC_MA,0),MATCH(T48,CC_MA,0)), IF(AA48="Rel. Gubernamentales",OFFSET('PARÁMETROS'!$K$48,MATCH(U48,JC_G,0),MATCH(T48,CC_G,0)), IF(AA48="OPERACIONAL",OFFSET('PARÁMETROS'!$K$56,MATCH(U48,JC_OP,0),MATCH(T48,CC_OP,0)), IF(AA48="FINANCIERO",OFFSET('PARÁMETROS'!$K$56,MATCH(U48,JC_FI,0),MATCH(T48,CC_FI,0)), OFFSET('PARÁMETROS'!$K$38,MATCH(U48,JC_L,0),MATCH(T48,CC_L,0))))))))),"") | AA48: =E43
V49: =IFERROR(IF(AA49="SEGURIDAD",OFFSET('PARÁMETROS'!$K$2,MATCH(U49,JC_SE,0),MATCH(T49,CC_SE,0)), IF(OR(AA49="DSRC/Estratégico",AA49="DSRC/Operativo"),OFFSET('PARÁMETROS'!$K$11,MATCH(U49,JC_DS,0),MATCH(T49,CC_DS,0)), IF(AA49="SALUD",OFFSET('PARÁMETROS'!$K$29,MATCH(U49,JC_SA,0),MATCH(T49,CC_SA,0)), IF(AA49="MEDIO AMBIENTE",OFFSET('PARÁMETROS'!$K$20,MATCH(U49,JC_MA,0),MATCH(T49,CC_MA,0)), IF(AA49="Rel. Gubernamentales",OFFSET('PARÁMETROS'!$K$48,MATCH(U49,JC_G,0),MATCH(T49,CC_G,0)), IF(AA49="OPERACIONAL",OFFSET('PARÁMETROS'!$K$56,MATCH(U49,JC_OP,0),MATCH(T49,CC_OP,0)), IF(AA49="FINANCIERO",OFFSET('PARÁMETROS'!$K$56,MATCH(U49,JC_FI,0),MATCH(T49,CC_FI,0)), OFFSET('PARÁMETROS'!$K$38,MATCH(U49,JC_L,0),MATCH(T49,CC_L,0))))))))),"") | AA49: =E43
V50: =IFERROR(IF(AA50="SEGURIDAD",OFFSET('PARÁMETROS'!$K$2,MATCH(U50,JC_SE,0),MATCH(T50,CC_SE,0)), IF(OR(AA50="DSRC/Estratégico",AA50="DSRC/Operativo"),OFFSET('PARÁMETROS'!$K$11,MATCH(U50,JC_DS,0),MATCH(T50,CC_DS,0)), IF(AA50="SALUD",OFFSET('PARÁMETROS'!$K$29,MATCH(U50,JC_SA,0),MATCH(T50,CC_SA,0)), IF(AA50="MEDIO AMBIENTE",OFFSET('PARÁMETROS'!$K$20,MATCH(U50,JC_MA,0),MATCH(T50,CC_MA,0)), IF(AA50="Rel. Gubernamentales",OFFSET('PARÁMETROS'!$K$48,MATCH(U50,JC_G,0),MATCH(T50,CC_G,0)), IF(AA50="OPERACIONAL",OFFSET('PARÁMETROS'!$K$56,MATCH(U50,JC_OP,0),MATCH(T50,CC_OP,0)), IF(AA50="FINANCIERO",OFFSET('PARÁMETROS'!$K$56,MATCH(U50,JC_FI,0),MATCH(T50,CC_FI,0)), OFFSET('PARÁMETROS'!$K$38,MATCH(U50,JC_L,0),MATCH(T50,CC_L,0))))))))),"") | AA50: =E43
V51: =IFERROR(IF(AA51="SEGURIDAD",OFFSET('PARÁMETROS'!$K$2,MATCH(U51,JC_SE,0),MATCH(T51,CC_SE,0)), IF(OR(AA51="DSRC/Estratégico",AA51="DSRC/Operativo"),OFFSET('PARÁMETROS'!$K$11,MATCH(U51,JC_DS,0),MATCH(T51,CC_DS,0)), IF(AA51="SALUD",OFFSET('PARÁMETROS'!$K$29,MATCH(U51,JC_SA,0),MATCH(T51,CC_SA,0)), IF(AA51="MEDIO AMBIENTE",OFFSET('PARÁMETROS'!$K$20,MATCH(U51,JC_MA,0),MATCH(T51,CC_MA,0)), IF(AA51="Rel. Gubernamentales",OFFSET('PARÁMETROS'!$K$48,MATCH(U51,JC_G,0),MATCH(T51,CC_G,0)), IF(AA51="OPERACIONAL",OFFSET('PARÁMETROS'!$K$56,MATCH(U51,JC_OP,0),MATCH(T51,CC_OP,0)), IF(AA51="FINANCIERO",OFFSET('PARÁMETROS'!$K$56,MATCH(U51,JC_FI,0),MATCH(T51,CC_FI,0)), OFFSET('PARÁMETROS'!$K$38,MATCH(U51,JC_L,0),MATCH(T51,CC_L,0))))))))),"") | AA51: =E43
V52: =IFERROR(IF(AA52="SEGURIDAD",OFFSET('PARÁMETROS'!$K$2,MATCH(U52,JC_SE,0),MATCH(T52,CC_SE,0)), IF(OR(AA52="DSRC/Estratégico",AA52="DSRC/Operativo"),OFFSET('PARÁMETROS'!$K$11,MATCH(U52,JC_DS,0),MATCH(T52,CC_DS,0)), IF(AA52="SALUD",OFFSET('PARÁMETROS'!$K$29,MATCH(U52,JC_SA,0),MATCH(T52,CC_SA,0)), IF(AA52="MEDIO AMBIENTE",OFFSET('PARÁMETROS'!$K$20,MATCH(U52,JC_MA,0),MATCH(T52,CC_MA,0)), IF(AA52="Rel. Gubernamentales",OFFSET('PARÁMETROS'!$K$48,MATCH(U52,JC_G,0),MATCH(T52,CC_G,0)), IF(AA52="OPERACIONAL",OFFSET('PARÁMETROS'!$K$56,MATCH(U52,JC_OP,0),MATCH(T52,CC_OP,0)), IF(AA52="FINANCIERO",OFFSET('PARÁMETROS'!$K$56,MATCH(U52,JC_FI,0),MATCH(T52,CC_FI,0)), OFFSET('PARÁMETROS'!$K$38,MATCH(U52,JC_L,0),MATCH(T52,CC_L,0))))))))),"") | AA52: =E43
V53: =IFERROR(IF(AA53="SEGURIDAD",OFFSET('PARÁMETROS'!$K$2,MATCH(U53,JC_SE,0),MATCH(T53,CC_SE,0)), IF(OR(AA53="DSRC/Estratégico",AA53="DSRC/Operativo"),OFFSET('PARÁMETROS'!$K$11,MATCH(U53,JC_DS,0),MATCH(T53,CC_DS,0)), IF(AA53="SALUD",OFFSET('PARÁMETROS'!$K$29,MATCH(U53,JC_SA,0),MATCH(T53,CC_SA,0)), IF(AA53="MEDIO AMBIENTE",OFFSET('PARÁMETROS'!$K$20,MATCH(U53,JC_MA,0),MATCH(T53,CC_MA,0)), IF(AA53="Rel. Gubernamentales",OFFSET('PARÁMETROS'!$K$48,MATCH(U53,JC_G,0),MATCH(T53,CC_G,0)), IF(AA53="OPERACIONAL",OFFSET('PARÁMETROS'!$K$56,MATCH(U53,JC_OP,0),MATCH(T53,CC_OP,0)), IF(AA53="FINANCIERO",OFFSET('PARÁMETROS'!$K$56,MATCH(U53,JC_FI,0),MATCH(T53,CC_FI,0)), OFFSET('PARÁMETROS'!$K$38,MATCH(U53,JC_L,0),MATCH(T53,CC_L,0))))))))),"") | AA53: =E43
V54: =IFERROR(IF(AA54="SEGURIDAD",OFFSET('PARÁMETROS'!$K$2,MATCH(U54,JC_SE,0),MATCH(T54,CC_SE,0)), IF(OR(AA54="DSRC/Estratégico",AA54="DSRC/Operativo"),OFFSET('PARÁMETROS'!$K$11,MATCH(U54,JC_DS,0),MATCH(T54,CC_DS,0)), IF(AA54="SALUD",OFFSET('PARÁMETROS'!$K$29,MATCH(U54,JC_SA,0),MATCH(T54,CC_SA,0)), IF(AA54="MEDIO AMBIENTE",OFFSET('PARÁMETROS'!$K$20,MATCH(U54,JC_MA,0),MATCH(T54,CC_MA,0)), IF(AA54="Rel. Gubernamentales",OFFSET('PARÁMETROS'!$K$48,MATCH(U54,JC_G,0),MATCH(T54,CC_G,0)), IF(AA54="OPERACIONAL",OFFSET('PARÁMETROS'!$K$56,MATCH(U54,JC_OP,0),MATCH(T54,CC_OP,0)), IF(AA54="FINANCIERO",OFFSET('PARÁMETROS'!$K$56,MATCH(U54,JC_FI,0),MATCH(T54,CC_FI,0)), OFFSET('PARÁMETROS'!$K$38,MATCH(U54,JC_L,0),MATCH(T54,CC_L,0))))))))),"") | AA54: =E43
V55: =IFERROR(IF(AA55="SEGURIDAD",OFFSET('PARÁMETROS'!$K$2,MATCH(U55,JC_SE,0),MATCH(T55,CC_SE,0)), IF(OR(AA55="DSRC/Estratégico",AA55="DSRC/Operativo"),OFFSET('PARÁMETROS'!$K$11,MATCH(U55,JC_DS,0),MATCH(T55,CC_DS,0)), IF(AA55="SALUD",OFFSET('PARÁMETROS'!$K$29,MATCH(U55,JC_SA,0),MATCH(T55,CC_SA,0)), IF(AA55="MEDIO AMBIENTE",OFFSET('PARÁMETROS'!$K$20,MATCH(U55,JC_MA,0),MATCH(T55,CC_MA,0)), IF(AA55="Rel. Gubernamentales",OFFSET('PARÁMETROS'!$K$48,MATCH(U55,JC_G,0),MATCH(T55,CC_G,0)), IF(AA55="OPERACIONAL",OFFSET('PARÁMETROS'!$K$56,MATCH(U55,JC_OP,0),MATCH(T55,CC_OP,0)), IF(AA55="FINANCIERO",OFFSET('PARÁMETROS'!$K$56,MATCH(U55,JC_FI,0),MATCH(T55,CC_FI,0)), OFFSET('PARÁMETROS'!$K$38,MATCH(U55,JC_L,0),MATCH(T55,CC_L,0))))))))),"") | AA55: =E43
V56: =IFERROR(IF(AA56="SEGURIDAD",OFFSET('PARÁMETROS'!$K$2,MATCH(U56,JC_SE,0),MATCH(T56,CC_SE,0)), IF(OR(AA56="DSRC/Estratégico",AA56="DSRC/Operativo"),OFFSET('PARÁMETROS'!$K$11,MATCH(U56,JC_DS,0),MATCH(T56,CC_DS,0)), IF(AA56="SALUD",OFFSET('PARÁMETROS'!$K$29,MATCH(U56,JC_SA,0),MATCH(T56,CC_SA,0)), IF(AA56="MEDIO AMBIENTE",OFFSET('PARÁMETROS'!$K$20,MATCH(U56,JC_MA,0),MATCH(T56,CC_MA,0)), IF(AA56="Rel. Gubernamentales",OFFSET('PARÁMETROS'!$K$48,MATCH(U56,JC_G,0),MATCH(T56,CC_G,0)), IF(AA56="OPERACIONAL",OFFSET('PARÁMETROS'!$K$56,MATCH(U56,JC_OP,0),MATCH(T56,CC_OP,0)), IF(AA56="FINANCIERO",OFFSET('PARÁMETROS'!$K$56,MATCH(U56,JC_FI,0),MATCH(T56,CC_FI,0)), OFFSET('PARÁMETROS'!$K$38,MATCH(U56,JC_L,0),MATCH(T56,CC_L,0))))))))),"") | AA56: =E43
V57: =IFERROR(IF(AA57="SEGURIDAD",OFFSET('PARÁMETROS'!$K$2,MATCH(U57,JC_SE,0),MATCH(T57,CC_SE,0)), IF(OR(AA57="DSRC/Estratégico",AA57="DSRC/Operativo"),OFFSET('PARÁMETROS'!$K$11,MATCH(U57,JC_DS,0),MATCH(T57,CC_DS,0)), IF(AA57="SALUD",OFFSET('PARÁMETROS'!$K$29,MATCH(U57,JC_SA,0),MATCH(T57,CC_SA,0)), IF(AA57="MEDIO AMBIENTE",OFFSET('PARÁMETROS'!$K$20,MATCH(U57,JC_MA,0),MATCH(T57,CC_MA,0)), IF(AA57="Rel. Gubernamentales",OFFSET('PARÁMETROS'!$K$48,MATCH(U57,JC_G,0),MATCH(T57,CC_G,0)), IF(AA57="OPERACIONAL",OFFSET('PARÁMETROS'!$K$56,MATCH(U57,JC_OP,0),MATCH(T57,CC_OP,0)), IF(AA57="FINANCIERO",OFFSET('PARÁMETROS'!$K$56,MATCH(U57,JC_FI,0),MATCH(T57,CC_FI,0)), OFFSET('PARÁMETROS'!$K$38,MATCH(U57,JC_L,0),MATCH(T57,CC_L,0))))))))),"") | AA57: =E43
V58: =IFERROR(IF(AA58="SEGURIDAD",OFFSET('PARÁMETROS'!$K$2,MATCH(U58,JC_SE,0),MATCH(T58,CC_SE,0)), IF(OR(AA58="DSRC/Estratégico",AA58="DSRC/Operativo"),OFFSET('PARÁMETROS'!$K$11,MATCH(U58,JC_DS,0),MATCH(T58,CC_DS,0)), IF(AA58="SALUD",OFFSET('PARÁMETROS'!$K$29,MATCH(U58,JC_SA,0),MATCH(T58,CC_SA,0)), IF(AA58="MEDIO AMBIENTE",OFFSET('PARÁMETROS'!$K$20,MATCH(U58,JC_MA,0),MATCH(T58,CC_MA,0)), IF(AA58="Rel. Gubernamentales",OFFSET('PARÁMETROS'!$K$48,MATCH(U58,JC_G,0),MATCH(T58,CC_G,0)), IF(AA58="OPERACIONAL",OFFSET('PARÁMETROS'!$K$56,MATCH(U58,JC_OP,0),MATCH(T58,CC_OP,0)), IF(AA58="FINANCIERO",OFFSET('PARÁMETROS'!$K$56,MATCH(U58,JC_FI,0),MATCH(T58,CC_FI,0)), OFFSET('PARÁMETROS'!$K$38,MATCH(U58,JC_L,0),MATCH(T58,CC_L,0))))))))),"") | AA58: =E43
L59: =IF(OR(J59<>"",K59<>""),OFFSET('PARÁMETROS'!$B$2,K59,J59),"") | N59: =IFERROR(L59*M59,"") -> 0 | O59: =IF(N59="","",IFERROR(IF(N59<=2,"ACEPTABLE",IF(N59<=6,"BAJA",IF(N59<=10,"ACEPTABLE CON REVISIÓN",IF(N59<=15,"SUSTANCIAL","INACEPTABLE")))),"")) -> ACEPTABLE | V59: =IFERROR(IF(AA59="SEGURIDAD",OFFSET('PARÁMETROS'!$K$2,MATCH(U59,JC_SE,0),MATCH(T59,CC_SE,0)), IF(OR(AA59="DSRC/Estratégico",AA59="DSRC/Operativo"),OFFSET('PARÁMETROS'!$K$11,MATCH(U59,JC_DS,0),MATCH(T59,CC_DS,0)), IF(AA59="SALUD",OFFSET('PARÁMETROS'!$K$29,MATCH(U59,JC_SA,0),MATCH(T59,CC_SA,0)), IF(AA59="MEDIO AMBIENTE",OFFSET('PARÁMETROS'!$K$20,MATCH(U59,JC_MA,0),MATCH(T59,CC_MA,0)), IF(AA59="Rel. Gubernamentales",OFFSET('PARÁMETROS'!$K$48,MATCH(U59,JC_G,0),MATCH(T59,CC_G,0)), IF(AA59="OPERACIONAL",OFFSET('PARÁMETROS'!$K$56,MATCH(U59,JC_OP,0),MATCH(T59,CC_OP,0)), IF(AA59="FINANCIERO",OFFSET('PARÁMETROS'!$K$56,MATCH(U59,JC_FI,0),MATCH(T59,CC_FI,0)), OFFSET('PARÁMETROS'!$K$38,MATCH(U59,JC_L,0),MATCH(T59,CC_L,0))))))))),"") | W59: =IF(E59="","", IF(COUNTA(V59:V74)-COUNTBLANK(V59:V74)=1, IF(O59="INACEPTABLE",IF(COUNTIF(V59:V74,"Control/Acción Eficaz")>=1,"SUSTANCIAL","INACEPTABLE"), IF(O59="SUSTANCIAL",IF(COUNTIF(V59:V74,"Control/Acción Eficaz")>=1,"ACEPTABLE CON REVISIÓN","SUSTANCIAL"), IF(O59="ACEPTABLE CON REVISIÓN",IF(COUNTIF(V59:V74,"Control/Acción Eficaz")>=1,"BAJA","ACEPTABLE CON REVISIÓN"), IF(O59="BAJA",IF(COUNTIF(V59:V74,"Control/Acción Eficaz")>=1,"ACEPTABLE","BAJA"),)))), IF(COUNTA(V59:V74)-COUNTBLANK(V59:V74)=2, IF(O59="INACEPTABLE",IF(COUNTIF(V59:V74,"Control/Acción Eficaz")=2,"ACEPTABLE CON REVISIÓN", IF(OR(AND(COUNTIF(V59:V74,"Control/Acción Eficaz")=1,COUNTIF(V59:V74,"Control/Acción Satisfactorio")=1), AND(COUNTIF(V59:V74,"Control/Acción Eficaz")=1,COUNTIF(V59:V74,"Control/Acción No Eficaz")=1)),"SUSTANCIAL","INACEPTABLE")), IF(O59="SUSTANCIAL",IF(COUNTIF(V59:V74,"Control/Acción Eficaz")=2,"BAJA", IF(OR(AND(COUNTIF(V59:V74,"Control/Acción Eficaz")=1,COUNTIF(V59:V74,"Control/Acción Satisfactorio")=1), AND(COUNTIF(V59:V74,"Control/Acción Eficaz")=1,COUNTIF(V59:V74,"Control/Acción No Eficaz")=1)),"ACEPTABLE CON REVISIÓN ","SUSTANCIAL")), IF(O59="ACEPTABLE CON REVISIÓN",IF(COUNTIF(V59:V74,"Control/Acción Eficaz")=2,"ACEPTABLE", IF(OR(AND(COUNTIF(V59:V74,"Control/Acción Eficaz")=1,COUNTIF(V59:V74,"Control/Acción Satisfactorio")=1), AND(COUNTIF(V59:V74,"Control/Acción Eficaz")=1,COUNTIF(V59:V74,"Control/Acción No Eficaz")=1)),"BAJA","ACEPTABLE CON REVISIÓN")), IF(O59="BAJA",IF(COUNTIF(V59:V74,"Control/Acción Eficaz")>=2,"ACEPTABLE","BAJA"),)))), IF(COUNTA(V59:V74)-COUNTBLANK(V59:V74)>=3, IF(O59="INACEPTABLE", IF(COUNTBLANK(V59:V74)=COUNTA(V59:V74),"", IF(COUNTIF(V59:V74,"Control/Acción No Eficaz")>=2,"INACEPTABLE", IF(AND(COUNTIF(V59:V74,"Control/Acción No Eficaz")=0,COUNTIF(V59:V74,"Control/Acción Eficaz")>=2),"ACEPTABLE CON REVISIÓN ","SUSTANCIAL"))), IF(O59="SUSTANCIAL", IF(COUNTBLANK(V59:V74)=COUNTA(V59:V74),"", IF(COUNTIF(V59:V74,"Control/Acción No Eficaz")>=2,"SUSTANCIAL", IF(AND(COUNTIF(V59:V74,"Control/Acción No Eficaz")=0,COUNTIF(V59:V74,"Control/Acción Eficaz")>=2),"BAJA","ACEPTABLE CON REVISIÓN"))), IF(O59="ACEPTABLE CON REVISIÓN", IF(COUNTBLANK(V59:V74)=COUNTA(V59:V74),"", IF(COUNTIF(V59:V74,"Control/Acción No Eficaz")>=2,"ACEPTABLE CON REVISIÓN", IF(AND(COUNTIF(V59:V74,"Control/Acción No Eficaz")=0,COUNTIF(V59:V74,"Control/Acción Eficaz")>=2),"ACEPTABLE","BAJA"))), IF(O59="BAJA", IF(COUNTBLANK(V59:V74)=COUNTA(V59:V74),"", IF(AND(COUNTBLANK(V59:V74)<1,COUNTA(V59:V74)=1), IF(COUNTIF(V59:V74,"Control/Acción No Eficaz")>=2,"BAJA", IF(AND(COUNTIF(V59:V74,"Control/Acción No Eficaz")=0,COUNTIF(V59:V74,"Control/Acción Eficaz")>=2),"ACEPTABLE","BAJA")), IF(COUNTIF(V59:V74,"Control/Acción No Eficaz")>=2,"BAJA", IF(AND(COUNTIF(V59:V74,"Control/Acción No Eficaz")=0,COUNTIF(V59:V74,"Control/Acción Eficaz")>=2),"ACEPTABLE","BAJA")))), IF(COUNTIF(V59:V74,"")>=5,"",O59))))), "")))) | AA59: =E59
V60: =IFERROR(IF(AA60="SEGURIDAD",OFFSET('PARÁMETROS'!$K$2,MATCH(U60,JC_SE,0),MATCH(T60,CC_SE,0)), IF(OR(AA60="DSRC/Estratégico",AA60="DSRC/Operativo"),OFFSET('PARÁMETROS'!$K$11,MATCH(U60,JC_DS,0),MATCH(T60,CC_DS,0)), IF(AA60="SALUD",OFFSET('PARÁMETROS'!$K$29,MATCH(U60,JC_SA,0),MATCH(T60,CC_SA,0)), IF(AA60="MEDIO AMBIENTE",OFFSET('PARÁMETROS'!$K$20,MATCH(U60,JC_MA,0),MATCH(T60,CC_MA,0)), IF(AA60="Rel. Gubernamentales",OFFSET('PARÁMETROS'!$K$48,MATCH(U60,JC_G,0),MATCH(T60,CC_G,0)), IF(AA60="OPERACIONAL",OFFSET('PARÁMETROS'!$K$56,MATCH(U60,JC_OP,0),MATCH(T60,CC_OP,0)), IF(AA60="FINANCIERO",OFFSET('PARÁMETROS'!$K$56,MATCH(U60,JC_FI,0),MATCH(T60,CC_FI,0)), OFFSET('PARÁMETROS'!$K$38,MATCH(U60,JC_L,0),MATCH(T60,CC_L,0))))))))),"") | AA60: =E59
V61: =IFERROR(IF(AA61="SEGURIDAD",OFFSET('PARÁMETROS'!$K$2,MATCH(U61,JC_SE,0),MATCH(T61,CC_SE,0)), IF(OR(AA61="DSRC/Estratégico",AA61="DSRC/Operativo"),OFFSET('PARÁMETROS'!$K$11,MATCH(U61,JC_DS,0),MATCH(T61,CC_DS,0)), IF(AA61="SALUD",OFFSET('PARÁMETROS'!$K$29,MATCH(U61,JC_SA,0),MATCH(T61,CC_SA,0)), IF(AA61="MEDIO AMBIENTE",OFFSET('PARÁMETROS'!$K$20,MATCH(U61,JC_MA,0),MATCH(T61,CC_MA,0)), IF(AA61="Rel. Gubernamentales",OFFSET('PARÁMETROS'!$K$48,MATCH(U61,JC_G,0),MATCH(T61,CC_G,0)), IF(AA61="OPERACIONAL",OFFSET('PARÁMETROS'!$K$56,MATCH(U61,JC_OP,0),MATCH(T61,CC_OP,0)), IF(AA61="FINANCIERO",OFFSET('PARÁMETROS'!$K$56,MATCH(U61,JC_FI,0),MATCH(T61,CC_FI,0)), OFFSET('PARÁMETROS'!$K$38,MATCH(U61,JC_L,0),MATCH(T61,CC_L,0))))))))),"") | AA61: =E59
V62: =IFERROR(IF(AA62="SEGURIDAD",OFFSET('PARÁMETROS'!$K$2,MATCH(U62,JC_SE,0),MATCH(T62,CC_SE,0)), IF(OR(AA62="DSRC/Estratégico",AA62="DSRC/Operativo"),OFFSET('PARÁMETROS'!$K$11,MATCH(U62,JC_DS,0),MATCH(T62,CC_DS,0)), IF(AA62="SALUD",OFFSET('PARÁMETROS'!$K$29,MATCH(U62,JC_SA,0),MATCH(T62,CC_SA,0)), IF(AA62="MEDIO AMBIENTE",OFFSET('PARÁMETROS'!$K$20,MATCH(U62,JC_MA,0),MATCH(T62,CC_MA,0)), IF(AA62="Rel. Gubernamentales",OFFSET('PARÁMETROS'!$K$48,MATCH(U62,JC_G,0),MATCH(T62,CC_G,0)), IF(AA62="OPERACIONAL",OFFSET('PARÁMETROS'!$K$56,MATCH(U62,JC_OP,0),MATCH(T62,CC_OP,0)), IF(AA62="FINANCIERO",OFFSET('PARÁMETROS'!$K$56,MATCH(U62,JC_FI,0),MATCH(T62,CC_FI,0)), OFFSET('PARÁMETROS'!$K$38,MATCH(U62,JC_L,0),MATCH(T62,CC_L,0))))))))),"") | AA62: =E59
V63: =IFERROR(IF(AA63="SEGURIDAD",OFFSET('PARÁMETROS'!$K$2,MATCH(U63,JC_SE,0),MATCH(T63,CC_SE,0)), IF(OR(AA63="DSRC/Estratégico",AA63="DSRC/Operativo"),OFFSET('PARÁMETROS'!$K$11,MATCH(U63,JC_DS,0),MATCH(T63,CC_DS,0)), IF(AA63="SALUD",OFFSET('PARÁMETROS'!$K$29,MATCH(U63,JC_SA,0),MATCH(T63,CC_SA,0)), IF(AA63="MEDIO AMBIENTE",OFFSET('PARÁMETROS'!$K$20,MATCH(U63,JC_MA,0),MATCH(T63,CC_MA,0)), IF(AA63="Rel. Gubernamentales",OFFSET('PARÁMETROS'!$K$48,MATCH(U63,JC_G,0),MATCH(T63,CC_G,0)), IF(AA63="OPERACIONAL",OFFSET('PARÁMETROS'!$K$56,MATCH(U63,JC_OP,0),MATCH(T63,CC_OP,0)), IF(AA63="FINANCIERO",OFFSET('PARÁMETROS'!$K$56,MATCH(U63,JC_FI,0),MATCH(T63,CC_FI,0)), OFFSET('PARÁMETROS'!$K$38,MATCH(U63,JC_L,0),MATCH(T63,CC_L,0))))))))),"") | AA63: =E59
V64: =IFERROR(IF(AA64="SEGURIDAD",OFFSET('PARÁMETROS'!$K$2,MATCH(U64,JC_SE,0),MATCH(T64,CC_SE,0)), IF(OR(AA64="DSRC/Estratégico",AA64="DSRC/Operativo"),OFFSET('PARÁMETROS'!$K$11,MATCH(U64,JC_DS,0),MATCH(T64,CC_DS,0)), IF(AA64="SALUD",OFFSET('PARÁMETROS'!$K$29,MATCH(U64,JC_SA,0),MATCH(T64,CC_SA,0)), IF(AA64="MEDIO AMBIENTE",OFFSET('PARÁMETROS'!$K$20,MATCH(U64,JC_MA,0),MATCH(T64,CC_MA,0)), IF(AA64="Rel. Gubernamentales",OFFSET('PARÁMETROS'!$K$48,MATCH(U64,JC_G,0),MATCH(T64,CC_G,0)), IF(AA64="OPERACIONAL",OFFSET('PARÁMETROS'!$K$56,MATCH(U64,JC_OP,0),MATCH(T64,CC_OP,0)), IF(AA64="FINANCIERO",OFFSET('PARÁMETROS'!$K$56,MATCH(U64,JC_FI,0),MATCH(T64,CC_FI,0)), OFFSET('PARÁMETROS'!$K$38,MATCH(U64,JC_L,0),MATCH(T64,CC_L,0))))))))),"") | AA64: =E59
V65: =IFERROR(IF(AA65="SEGURIDAD",OFFSET('PARÁMETROS'!$K$2,MATCH(U65,JC_SE,0),MATCH(T65,CC_SE,0)), IF(OR(AA65="DSRC/Estratégico",AA65="DSRC/Operativo"),OFFSET('PARÁMETROS'!$K$11,MATCH(U65,JC_DS,0),MATCH(T65,CC_DS,0)), IF(AA65="SALUD",OFFSET('PARÁMETROS'!$K$29,MATCH(U65,JC_SA,0),MATCH(T65,CC_SA,0)), IF(AA65="MEDIO AMBIENTE",OFFSET('PARÁMETROS'!$K$20,MATCH(U65,JC_MA,0),MATCH(T65,CC_MA,0)), IF(AA65="Rel. Gubernamentales",OFFSET('PARÁMETROS'!$K$48,MATCH(U65,JC_G,0),MATCH(T65,CC_G,0)), IF(AA65="OPERACIONAL",OFFSET('PARÁMETROS'!$K$56,MATCH(U65,JC_OP,0),MATCH(T65,CC_OP,0)), IF(AA65="FINANCIERO",OFFSET('PARÁMETROS'!$K$56,MATCH(U65,JC_FI,0),MATCH(T65,CC_FI,0)), OFFSET('PARÁMETROS'!$K$38,MATCH(U65,JC_L,0),MATCH(T65,CC_L,0))))))))),"") | AA65: =E59
V66: =IFERROR(IF(AA66="SEGURIDAD",OFFSET('PARÁMETROS'!$K$2,MATCH(U66,JC_SE,0),MATCH(T66,CC_SE,0)), IF(OR(AA66="DSRC/Estratégico",AA66="DSRC/Operativo"),OFFSET('PARÁMETROS'!$K$11,MATCH(U66,JC_DS,0),MATCH(T66,CC_DS,0)), IF(AA66="SALUD",OFFSET('PARÁMETROS'!$K$29,MATCH(U66,JC_SA,0),MATCH(T66,CC_SA,0)), IF(AA66="MEDIO AMBIENTE",OFFSET('PARÁMETROS'!$K$20,MATCH(U66,JC_MA,0),MATCH(T66,CC_MA,0)), IF(AA66="Rel. Gubernamentales",OFFSET('PARÁMETROS'!$K$48,MATCH(U66,JC_G,0),MATCH(T66,CC_G,0)), IF(AA66="OPERACIONAL",OFFSET('PARÁMETROS'!$K$56,MATCH(U66,JC_OP,0),MATCH(T66,CC_OP,0)), IF(AA66="FINANCIERO",OFFSET('PARÁMETROS'!$K$56,MATCH(U66,JC_FI,0),MATCH(T66,CC_FI,0)), OFFSET('PARÁMETROS'!$K$38,MATCH(U66,JC_L,0),MATCH(T66,CC_L,0))))))))),"") | AA66: =E59
V67: =IFERROR(IF(AA67="SEGURIDAD",OFFSET('PARÁMETROS'!$K$2,MATCH(U67,JC_SE,0),MATCH(T67,CC_SE,0)), IF(OR(AA67="DSRC/Estratégico",AA67="DSRC/Operativo"),OFFSET('PARÁMETROS'!$K$11,MATCH(U67,JC_DS,0),MATCH(T67,CC_DS,0)), IF(AA67="SALUD",OFFSET('PARÁMETROS'!$K$29,MATCH(U67,JC_SA,0),MATCH(T67,CC_SA,0)), IF(AA67="MEDIO AMBIENTE",OFFSET('PARÁMETROS'!$K$20,MATCH(U67,JC_MA,0),MATCH(T67,CC_MA,0)), IF(AA67="Rel. Gubernamentales",OFFSET('PARÁMETROS'!$K$48,MATCH(U67,JC_G,0),MATCH(T67,CC_G,0)), IF(AA67="OPERACIONAL",OFFSET('PARÁMETROS'!$K$56,MATCH(U67,JC_OP,0),MATCH(T67,CC_OP,0)), IF(AA67="FINANCIERO",OFFSET('PARÁMETROS'!$K$56,MATCH(U67,JC_FI,0),MATCH(T67,CC_FI,0)), OFFSET('PARÁMETROS'!$K$38,MATCH(U67,JC_L,0),MATCH(T67,CC_L,0))))))))),"") | AA67: =E59
V68: =IFERROR(IF(AA68="SEGURIDAD",OFFSET('PARÁMETROS'!$K$2,MATCH(U68,JC_SE,0),MATCH(T68,CC_SE,0)), IF(OR(AA68="DSRC/Estratégico",AA68="DSRC/Operativo"),OFFSET('PARÁMETROS'!$K$11,MATCH(U68,JC_DS,0),MATCH(T68,CC_DS,0)), IF(AA68="SALUD",OFFSET('PARÁMETROS'!$K$29,MATCH(U68,JC_SA,0),MATCH(T68,CC_SA,0)), IF(AA68="MEDIO AMBIENTE",OFFSET('PARÁMETROS'!$K$20,MATCH(U68,JC_MA,0),MATCH(T68,CC_MA,0)), IF(AA68="Rel. Gubernamentales",OFFSET('PARÁMETROS'!$K$48,MATCH(U68,JC_G,0),MATCH(T68,CC_G,0)), IF(AA68="OPERACIONAL",OFFSET('PARÁMETROS'!$K$56,MATCH(U68,JC_OP,0),MATCH(T68,CC_OP,0)), IF(AA68="FINANCIERO",OFFSET('PARÁMETROS'!$K$56,MATCH(U68,JC_FI,0),MATCH(T68,CC_FI,0)), OFFSET('PARÁMETROS'!$K$38,MATCH(U68,JC_L,0),MATCH(T68,CC_L,0))))))))),"") | AA68: =E59
V69: =IFERROR(IF(AA69="SEGURIDAD",OFFSET('PARÁMETROS'!$K$2,MATCH(U69,JC_SE,0),MATCH(T69,CC_SE,0)), IF(OR(AA69="DSRC/Estratégico",AA69="DSRC/Operativo"),OFFSET('PARÁMETROS'!$K$11,MATCH(U69,JC_DS,0),MATCH(T69,CC_DS,0)), IF(AA69="SALUD",OFFSET('PARÁMETROS'!$K$29,MATCH(U69,JC_SA,0),MATCH(T69,CC_SA,0)), IF(AA69="MEDIO AMBIENTE",OFFSET('PARÁMETROS'!$K$20,MATCH(U69,JC_MA,0),MATCH(T69,CC_MA,0)), IF(AA69="Rel. Gubernamentales",OFFSET('PARÁMETROS'!$K$48,MATCH(U69,JC_G,0),MATCH(T69,CC_G,0)), IF(AA69="OPERACIONAL",OFFSET('PARÁMETROS'!$K$56,MATCH(U69,JC_OP,0),MATCH(T69,CC_OP,0)), IF(AA69="FINANCIERO",OFFSET('PARÁMETROS'!$K$56,MATCH(U69,JC_FI,0),MATCH(T69,CC_FI,0)), OFFSET('PARÁMETROS'!$K$38,MATCH(U69,JC_L,0),MATCH(T69,CC_L,0))))))))),"") | AA69: =E59
V70: =IFERROR(IF(AA70="SEGURIDAD",OFFSET('PARÁMETROS'!$K$2,MATCH(U70,JC_SE,0),MATCH(T70,CC_SE,0)), IF(OR(AA70="DSRC/Estratégico",AA70="DSRC/Operativo"),OFFSET('PARÁMETROS'!$K$11,MATCH(U70,JC_DS,0),MATCH(T70,CC_DS,0)), IF(AA70="SALUD",OFFSET('PARÁMETROS'!$K$29,MATCH(U70,JC_SA,0),MATCH(T70,CC_SA,0)), IF(AA70="MEDIO AMBIENTE",OFFSET('PARÁMETROS'!$K$20,MATCH(U70,JC_MA,0),MATCH(T70,CC_MA,0)), IF(AA70="Rel. Gubernamentales",OFFSET('PARÁMETROS'!$K$48,MATCH(U70,JC_G,0),MATCH(T70,CC_G,0)), IF(AA70="OPERACIONAL",OFFSET('PARÁMETROS'!$K$56,MATCH(U70,JC_OP,0),MATCH(T70,CC_OP,0)), IF(AA70="FINANCIERO",OFFSET('PARÁMETROS'!$K$56,MATCH(U70,JC_FI,0),MATCH(T70,CC_FI,0)), OFFSET('PARÁMETROS'!$K$38,MATCH(U70,JC_L,0),MATCH(T70,CC_L,0))))))))),"") | AA70: =E59
V71: =IFERROR(IF(AA71="SEGURIDAD",OFFSET('PARÁMETROS'!$K$2,MATCH(U71,JC_SE,0),MATCH(T71,CC_SE,0)), IF(OR(AA71="DSRC/Estratégico",AA71="DSRC/Operativo"),OFFSET('PARÁMETROS'!$K$11,MATCH(U71,JC_DS,0),MATCH(T71,CC_DS,0)), IF(AA71="SALUD",OFFSET('PARÁMETROS'!$K$29,MATCH(U71,JC_SA,0),MATCH(T71,CC_SA,0)), IF(AA71="MEDIO AMBIENTE",OFFSET('PARÁMETROS'!$K$20,MATCH(U71,JC_MA,0),MATCH(T71,CC_MA,0)), IF(AA71="Rel. Gubernamentales",OFFSET('PARÁMETROS'!$K$48,MATCH(U71,JC_G,0),MATCH(T71,CC_G,0)), IF(AA71="OPERACIONAL",OFFSET('PARÁMETROS'!$K$56,MATCH(U71,JC_OP,0),MATCH(T71,CC_OP,0)), IF(AA71="FINANCIERO",OFFSET('PARÁMETROS'!$K$56,MATCH(U71,JC_FI,0),MATCH(T71,CC_FI,0)), OFFSET('PARÁMETROS'!$K$38,MATCH(U71,JC_L,0),MATCH(T71,CC_L,0))))))))),"") | AA71: =E59
V72: =IFERROR(IF(AA72="SEGURIDAD",OFFSET('PARÁMETROS'!$K$2,MATCH(U72,JC_SE,0),MATCH(T72,CC_SE,0)), IF(OR(AA72="DSRC/Estratégico",AA72="DSRC/Operativo"),OFFSET('PARÁMETROS'!$K$11,MATCH(U72,JC_DS,0),MATCH(T72,CC_DS,0)), IF(AA72="SALUD",OFFSET('PARÁMETROS'!$K$29,MATCH(U72,JC_SA,0),MATCH(T72,CC_SA,0)), IF(AA72="MEDIO AMBIENTE",OFFSET('PARÁMETROS'!$K$20,MATCH(U72,JC_MA,0),MATCH(T72,CC_MA,0)), IF(AA72="Rel. Gubernamentales",OFFSET('PARÁMETROS'!$K$48,MATCH(U72,JC_G,0),MATCH(T72,CC_G,0)), IF(AA72="OPERACIONAL",OFFSET('PARÁMETROS'!$K$56,MATCH(U72,JC_OP,0),MATCH(T72,CC_OP,0)), IF(AA72="FINANCIERO",OFFSET('PARÁMETROS'!$K$56,MATCH(U72,JC_FI,0),MATCH(T72,CC_FI,0)), OFFSET('PARÁMETROS'!$K$38,MATCH(U72,JC_L,0),MATCH(T72,CC_L,0))))))))),"") | AA72: =E59
V73: =IFERROR(IF(AA73="SEGURIDAD",OFFSET('PARÁMETROS'!$K$2,MATCH(U73,JC_SE,0),MATCH(T73,CC_SE,0)), IF(OR(AA73="DSRC/Estratégico",AA73="DSRC/Operativo"),OFFSET('PARÁMETROS'!$K$11,MATCH(U73,JC_DS,0),MATCH(T73,CC_DS,0)), IF(AA73="SALUD",OFFSET('PARÁMETROS'!$K$29,MATCH(U73,JC_SA,0),MATCH(T73,CC_SA,0)), IF(AA73="MEDIO AMBIENTE",OFFSET('PARÁMETROS'!$K$20,MATCH(U73,JC_MA,0),MATCH(T73,CC_MA,0)), IF(AA73="Rel. Gubernamentales",OFFSET('PARÁMETROS'!$K$48,MATCH(U73,JC_G,0),MATCH(T73,CC_G,0)), IF(AA73="OPERACIONAL",OFFSET('PARÁMETROS'!$K$56,MATCH(U73,JC_OP,0),MATCH(T73,CC_OP,0)), IF(AA73="FINANCIERO",OFFSET('PARÁMETROS'!$K$56,MATCH(U73,JC_FI,0),MATCH(T73,CC_FI,0)), OFFSET('PARÁMETROS'!$K$38,MATCH(U73,JC_L,0),MATCH(T73,CC_L,0))))))))),"") | AA73: =E59
V74: =IFERROR(IF(AA74="SEGURIDAD",OFFSET('PARÁMETROS'!$K$2,MATCH(U74,JC_SE,0),MATCH(T74,CC_SE,0)), IF(OR(AA74="DSRC/Estratégico",AA74="DSRC/Operativo"),OFFSET('PARÁMETROS'!$K$11,MATCH(U74,JC_DS,0),MATCH(T74,CC_DS,0)), IF(AA74="SALUD",OFFSET('PARÁMETROS'!$K$29,MATCH(U74,JC_SA,0),MATCH(T74,CC_SA,0)), IF(AA74="MEDIO AMBIENTE",OFFSET('PARÁMETROS'!$K$20,MATCH(U74,JC_MA,0),MATCH(T74,CC_MA,0)), IF(AA74="Rel. Gubernamentales",OFFSET('PARÁMETROS'!$K$48,MATCH(U74,JC_G,0),MATCH(T74,CC_G,0)), IF(AA74="OPERACIONAL",OFFSET('PARÁMETROS'!$K$56,MATCH(U74,JC_OP,0),MATCH(T74,CC_OP,0)), IF(AA74="FINANCIERO",OFFSET('PARÁMETROS'!$K$56,MATCH(U74,JC_FI,0),MATCH(T74,CC_FI,0)), OFFSET('PARÁMETROS'!$K$38,MATCH(U74,JC_L,0),MATCH(T74,CC_L,0))))))))),"") | AA74: =E59
L75: =IF(OR(J75<>"",K75<>""),OFFSET('PARÁMETROS'!$B$2,K75,J75),"") | N75: =IFERROR(L75*M75,"") -> 0 | O75: =IF(N75="","",IFERROR(IF(N75<=2,"ACEPTABLE",IF(N75<=6,"BAJA",IF(N75<=10,"ACEPTABLE CON REVISIÓN",IF(N75<=15,"SUSTANCIAL","INACEPTABLE")))),"")) -> ACEPTABLE | V75: =IFERROR(IF(AA75="SEGURIDAD",OFFSET('PARÁMETROS'!$K$2,MATCH(U75,JC_SE,0),MATCH(T75,CC_SE,0)), IF(OR(AA75="DSRC/Estratégico",AA75="DSRC/Operativo"),OFFSET('PARÁMETROS'!$K$11,MATCH(U75,JC_DS,0),MATCH(T75,CC_DS,0)), IF(AA75="SALUD",OFFSET('PARÁMETROS'!$K$29,MATCH(U75,JC_SA,0),MATCH(T75,CC_SA,0)), IF(AA75="MEDIO AMBIENTE",OFFSET('PARÁMETROS'!$K$20,MATCH(U75,JC_MA,0),MATCH(T75,CC_MA,0)), IF(AA75="Rel. Gubernamentales",OFFSET('PARÁMETROS'!$K$48,MATCH(U75,JC_G,0),MATCH(T75,CC_G,0)), IF(AA75="OPERACIONAL",OFFSET('PARÁMETROS'!$K$56,MATCH(U75,JC_OP,0),MATCH(T75,CC_OP,0)), IF(AA75="FINANCIERO",OFFSET('PARÁMETROS'!$K$56,MATCH(U75,JC_FI,0),MATCH(T75,CC_FI,0)), OFFSET('PARÁMETROS'!$K$38,MATCH(U75,JC_L,0),MATCH(T75,CC_L,0))))))))),"") | W75: =IF(E75="","", IF(COUNTA(V75:V90)-COUNTBLANK(V75:V90)=1, IF(O75="INACEPTABLE",IF(COUNTIF(V75:V90,"Control/Acción Eficaz")>=1,"SUSTANCIAL","INACEPTABLE"), IF(O75="SUSTANCIAL",IF(COUNTIF(V75:V90,"Control/Acción Eficaz")>=1,"ACEPTABLE CON REVISIÓN","SUSTANCIAL"), IF(O75="ACEPTABLE CON REVISIÓN",IF(COUNTIF(V75:V90,"Control/Acción Eficaz")>=1,"BAJA","ACEPTABLE CON REVISIÓN"), IF(O75="BAJA",IF(COUNTIF(V75:V90,"Control/Acción Eficaz")>=1,"ACEPTABLE","BAJA"),)))), IF(COUNTA(V75:V90)-COUNTBLANK(V75:V90)=2, IF(O75="INACEPTABLE",IF(COUNTIF(V75:V90,"Control/Acción Eficaz")=2,"ACEPTABLE CON REVISIÓN", IF(OR(AND(COUNTIF(V75:V90,"Control/Acción Eficaz")=1,COUNTIF(V75:V90,"Control/Acción Satisfactorio")=1), AND(COUNTIF(V75:V90,"Control/Acción Eficaz")=1,COUNTIF(V75:V90,"Control/Acción No Eficaz")=1)),"SUSTANCIAL","INACEPTABLE")), IF(O75="SUSTANCIAL",IF(COUNTIF(V75:V90,"Control/Acción Eficaz")=2,"BAJA", IF(OR(AND(COUNTIF(V75:V90,"Control/Acción Eficaz")=1,COUNTIF(V75:V90,"Control/Acción Satisfactorio")=1), AND(COUNTIF(V75:V90,"Control/Acción Eficaz")=1,COUNTIF(V75:V90,"Control/Acción No Eficaz")=1)),"ACEPTABLE CON REVISIÓN ","SUSTANCIAL")), IF(O75="ACEPTABLE CON REVISIÓN",IF(COUNTIF(V75:V90,"Control/Acción Eficaz")=2,"ACEPTABLE", IF(OR(AND(COUNTIF(V75:V90,"Control/Acción Eficaz")=1,COUNTIF(V75:V90,"Control/Acción Satisfactorio")=1), AND(COUNTIF(V75:V90,"Control/Acción Eficaz")=1,COUNTIF(V75:V90,"Control/Acción No Eficaz")=1)),"BAJA","ACEPTABLE CON REVISIÓN")), IF(O75="BAJA",IF(COUNTIF(V75:V90,"Control/Acción Eficaz")>=2,"ACEPTABLE","BAJA"),)))), IF(COUNTA(V75:V90)-COUNTBLANK(V75:V90)>=3, IF(O75="INACEPTABLE", IF(COUNTBLANK(V75:V90)=COUNTA(V75:V90),"", IF(COUNTIF(V75:V90,"Control/Acción No Eficaz")>=2,"INACEPTABLE", IF(AND(COUNTIF(V75:V90,"Control/Acción No Eficaz")=0,COUNTIF(V75:V90,"Control/Acción Eficaz")>=2),"ACEPTABLE CON REVISIÓN ","SUSTANCIAL"))), IF(O75="SUSTANCIAL", IF(COUNTBLANK(V75:V90)=COUNTA(V75:V90),"", IF(COUNTIF(V75:V90,"Control/Acción No Eficaz")>=2,"SUSTANCIAL", IF(AND(COUNTIF(V75:V90,"Control/Acción No Eficaz")=0,COUNTIF(V75:V90,"Control/Acción Eficaz")>=2),"BAJA","ACEPTABLE CON REVISIÓN"))), IF(O75="ACEPTABLE CON REVISIÓN", IF(COUNTBLANK(V75:V90)=COUNTA(V75:V90),"", IF(COUNTIF(V75:V90,"Control/Acción No Eficaz")>=2,"ACEPTABLE CON REVISIÓN", IF(AND(COUNTIF(V75:V90,"Control/Acción No Eficaz")=0,COUNTIF(V75:V90,"Control/Acción Eficaz")>=2),"ACEPTABLE","BAJA"))), IF(O75="BAJA", IF(COUNTBLANK(V75:V90)=COUNTA(V75:V90),"", IF(AND(COUNTBLANK(V75:V90)<1,COUNTA(V75:V90)=1), IF(COUNTIF(V75:V90,"Control/Acción No Eficaz")>=2,"BAJA", IF(AND(COUNTIF(V75:V90,"Control/Acción No Eficaz")=0,COUNTIF(V75:V90,"Control/Acción Eficaz")>=2),"ACEPTABLE","BAJA")), IF(COUNTIF(V75:V90,"Control/Acción No Eficaz")>=2,"BAJA", IF(AND(COUNTIF(V75:V90,"Control/Acción No Eficaz")=0,COUNTIF(V75:V90,"Control/Acción Eficaz")>=2),"ACEPTABLE","BAJA")))), IF(COUNTIF(V75:V90,"")>=5,"",O75))))), "")))) | AA75: =E75
V76: =IFERROR(IF(AA76="SEGURIDAD",OFFSET('PARÁMETROS'!$K$2,MATCH(U76,JC_SE,0),MATCH(T76,CC_SE,0)), IF(OR(AA76="DSRC/Estratégico",AA76="DSRC/Operativo"),OFFSET('PARÁMETROS'!$K$11,MATCH(U76,JC_DS,0),MATCH(T76,CC_DS,0)), IF(AA76="SALUD",OFFSET('PARÁMETROS'!$K$29,MATCH(U76,JC_SA,0),MATCH(T76,CC_SA,0)), IF(AA76="MEDIO AMBIENTE",OFFSET('PARÁMETROS'!$K$20,MATCH(U76,JC_MA,0),MATCH(T76,CC_MA,0)), IF(AA76="Rel. Gubernamentales",OFFSET('PARÁMETROS'!$K$48,MATCH(U76,JC_G,0),MATCH(T76,CC_G,0)), IF(AA76="OPERACIONAL",OFFSET('PARÁMETROS'!$K$56,MATCH(U76,JC_OP,0),MATCH(T76,CC_OP,0)), IF(AA76="FINANCIERO",OFFSET('PARÁMETROS'!$K$56,MATCH(U76,JC_FI,0),MATCH(T76,CC_FI,0)), OFFSET('PARÁMETROS'!$K$38,MATCH(U76,JC_L,0),MATCH(T76,CC_L,0))))))))),"") | AA76: =E75
V77: =IFERROR(IF(AA77="SEGURIDAD",OFFSET('PARÁMETROS'!$K$2,MATCH(U77,JC_SE,0),MATCH(T77,CC_SE,0)), IF(OR(AA77="DSRC/Estratégico",AA77="DSRC/Operativo"),OFFSET('PARÁMETROS'!$K$11,MATCH(U77,JC_DS,0),MATCH(T77,CC_DS,0)), IF(AA77="SALUD",OFFSET('PARÁMETROS'!$K$29,MATCH(U77,JC_SA,0),MATCH(T77,CC_SA,0)), IF(AA77="MEDIO AMBIENTE",OFFSET('PARÁMETROS'!$K$20,MATCH(U77,JC_MA,0),MATCH(T77,CC_MA,0)), IF(AA77="Rel. Gubernamentales",OFFSET('PARÁMETROS'!$K$48,MATCH(U77,JC_G,0),MATCH(T77,CC_G,0)), IF(AA77="OPERACIONAL",OFFSET('PARÁMETROS'!$K$56,MATCH(U77,JC_OP,0),MATCH(T77,CC_OP,0)), IF(AA77="FINANCIERO",OFFSET('PARÁMETROS'!$K$56,MATCH(U77,JC_FI,0),MATCH(T77,CC_FI,0)), OFFSET('PARÁMETROS'!$K$38,MATCH(U77,JC_L,0),MATCH(T77,CC_L,0))))))))),"") | AA77: =E75
V78: =IFERROR(IF(AA78="SEGURIDAD",OFFSET('PARÁMETROS'!$K$2,MATCH(U78,JC_SE,0),MATCH(T78,CC_SE,0)), IF(OR(AA78="DSRC/Estratégico",AA78="DSRC/Operativo"),OFFSET('PARÁMETROS'!$K$11,MATCH(U78,JC_DS,0),MATCH(T78,CC_DS,0)), IF(AA78="SALUD",OFFSET('PARÁMETROS'!$K$29,MATCH(U78,JC_SA,0),MATCH(T78,CC_SA,0)), IF(AA78="MEDIO AMBIENTE",OFFSET('PARÁMETROS'!$K$20,MATCH(U78,JC_MA,0),MATCH(T78,CC_MA,0)), IF(AA78="Rel. Gubernamentales",OFFSET('PARÁMETROS'!$K$48,MATCH(U78,JC_G,0),MATCH(T78,CC_G,0)), IF(AA78="OPERACIONAL",OFFSET('PARÁMETROS'!$K$56,MATCH(U78,JC_OP,0),MATCH(T78,CC_OP,0)), IF(AA78="FINANCIERO",OFFSET('PARÁMETROS'!$K$56,MATCH(U78,JC_FI,0),MATCH(T78,CC_FI,0)), OFFSET('PARÁMETROS'!$K$38,MATCH(U78,JC_L,0),MATCH(T78,CC_L,0))))))))),"") | AA78: =E75
V79: =IFERROR(IF(AA79="SEGURIDAD",OFFSET('PARÁMETROS'!$K$2,MATCH(U79,JC_SE,0),MATCH(T79,CC_SE,0)), IF(OR(AA79="DSRC/Estratégico",AA79="DSRC/Operativo"),OFFSET('PARÁMETROS'!$K$11,MATCH(U79,JC_DS,0),MATCH(T79,CC_DS,0)), IF(AA79="SALUD",OFFSET('PARÁMETROS'!$K$29,MATCH(U79,JC_SA,0),MATCH(T79,CC_SA,0)), IF(AA79="MEDIO AMBIENTE",OFFSET('PARÁMETROS'!$K$20,MATCH(U79,JC_MA,0),MATCH(T79,CC_MA,0)), IF(AA79="Rel. Gubernamentales",OFFSET('PARÁMETROS'!$K$48,MATCH(U79,JC_G,0),MATCH(T79,CC_G,0)), IF(AA79="OPERACIONAL",OFFSET('PARÁMETROS'!$K$56,MATCH(U79,JC_OP,0),MATCH(T79,CC_OP,0)), IF(AA79="FINANCIERO",OFFSET('PARÁMETROS'!$K$56,MATCH(U79,JC_FI,0),MATCH(T79,CC_FI,0)), OFFSET('PARÁMETROS'!$K$38,MATCH(U79,JC_L,0),MATCH(T79,CC_L,0))))))))),"") | AA79: =E75
V80: =IFERROR(IF(AA80="SEGURIDAD",OFFSET('PARÁMETROS'!$K$2,MATCH(U80,JC_SE,0),MATCH(T80,CC_SE,0)), IF(OR(AA80="DSRC/Estratégico",AA80="DSRC/Operativo"),OFFSET('PARÁMETROS'!$K$11,MATCH(U80,JC_DS,0),MATCH(T80,CC_DS,0)), IF(AA80="SALUD",OFFSET('PARÁMETROS'!$K$29,MATCH(U80,JC_SA,0),MATCH(T80,CC_SA,0)), IF(AA80="MEDIO AMBIENTE",OFFSET('PARÁMETROS'!$K$20,MATCH(U80,JC_MA,0),MATCH(T80,CC_MA,0)), IF(AA80="Rel. Gubernamentales",OFFSET('PARÁMETROS'!$K$48,MATCH(U80,JC_G,0),MATCH(T80,CC_G,0)), IF(AA80="OPERACIONAL",OFFSET('PARÁMETROS'!$K$56,MATCH(U80,JC_OP,0),MATCH(T80,CC_OP,0)), IF(AA80="FINANCIERO",OFFSET('PARÁMETROS'!$K$56,MATCH(U80,JC_FI,0),MATCH(T80,CC_FI,0)), OFFSET('PARÁMETROS'!$K$38,MATCH(U80,JC_L,0),MATCH(T80,CC_L,0))))))))),"") | AA80: =E75
V81: =IFERROR(IF(AA81="SEGURIDAD",OFFSET('PARÁMETROS'!$K$2,MATCH(U81,JC_SE,0),MATCH(T81,CC_SE,0)), IF(OR(AA81="DSRC/Estratégico",AA81="DSRC/Operativo"),OFFSET('PARÁMETROS'!$K$11,MATCH(U81,JC_DS,0),MATCH(T81,CC_DS,0)), IF(AA81="SALUD",OFFSET('PARÁMETROS'!$K$29,MATCH(U81,JC_SA,0),MATCH(T81,CC_SA,0)), IF(AA81="MEDIO AMBIENTE",OFFSET('PARÁMETROS'!$K$20,MATCH(U81,JC_MA,0),MATCH(T81,CC_MA,0)), IF(AA81="Rel. Gubernamentales",OFFSET('PARÁMETROS'!$K$48,MATCH(U81,JC_G,0),MATCH(T81,CC_G,0)), IF(AA81="OPERACIONAL",OFFSET('PARÁMETROS'!$K$56,MATCH(U81,JC_OP,0),MATCH(T81,CC_OP,0)), IF(AA81="FINANCIERO",OFFSET('PARÁMETROS'!$K$56,MATCH(U81,JC_FI,0),MATCH(T81,CC_FI,0)), OFFSET('PARÁMETROS'!$K$38,MATCH(U81,JC_L,0),MATCH(T81,CC_L,0))))))))),"") | AA81: =E75
V82: =IFERROR(IF(AA82="SEGURIDAD",OFFSET('PARÁMETROS'!$K$2,MATCH(U82,JC_SE,0),MATCH(T82,CC_SE,0)), IF(OR(AA82="DSRC/Estratégico",AA82="DSRC/Operativo"),OFFSET('PARÁMETROS'!$K$11,MATCH(U82,JC_DS,0),MATCH(T82,CC_DS,0)), IF(AA82="SALUD",OFFSET('PARÁMETROS'!$K$29,MATCH(U82,JC_SA,0),MATCH(T82,CC_SA,0)), IF(AA82="MEDIO AMBIENTE",OFFSET('PARÁMETROS'!$K$20,MATCH(U82,JC_MA,0),MATCH(T82,CC_MA,0)), IF(AA82="Rel. Gubernamentales",OFFSET('PARÁMETROS'!$K$48,MATCH(U82,JC_G,0),MATCH(T82,CC_G,0)), IF(AA82="OPERACIONAL",OFFSET('PARÁMETROS'!$K$56,MATCH(U82,JC_OP,0),MATCH(T82,CC_OP,0)), IF(AA82="FINANCIERO",OFFSET('PARÁMETROS'!$K$56,MATCH(U82,JC_FI,0),MATCH(T82,CC_FI,0)), OFFSET('PARÁMETROS'!$K$38,MATCH(U82,JC_L,0),MATCH(T82,CC_L,0))))))))),"") | AA82: =E75
V83: =IFERROR(IF(AA83="SEGURIDAD",OFFSET('PARÁMETROS'!$K$2,MATCH(U83,JC_SE,0),MATCH(T83,CC_SE,0)), IF(OR(AA83="DSRC/Estratégico",AA83="DSRC/Operativo"),OFFSET('PARÁMETROS'!$K$11,MATCH(U83,JC_DS,0),MATCH(T83,CC_DS,0)), IF(AA83="SALUD",OFFSET('PARÁMETROS'!$K$29,MATCH(U83,JC_SA,0),MATCH(T83,CC_SA,0)), IF(AA83="MEDIO AMBIENTE",OFFSET('PARÁMETROS'!$K$20,MATCH(U83,JC_MA,0),MATCH(T83,CC_MA,0)), IF(AA83="Rel. Gubernamentales",OFFSET('PARÁMETROS'!$K$48,MATCH(U83,JC_G,0),MATCH(T83,CC_G,0)), IF(AA83="OPERACIONAL",OFFSET('PARÁMETROS'!$K$56,MATCH(U83,JC_OP,0),MATCH(T83,CC_OP,0)), IF(AA83="FINANCIERO",OFFSET('PARÁMETROS'!$K$56,MATCH(U83,JC_FI,0),MATCH(T83,CC_FI,0)), OFFSET('PARÁMETROS'!$K$38,MATCH(U83,JC_L,0),MATCH(T83,CC_L,0))))))))),"") | AA83: =E75
V84: =IFERROR(IF(AA84="SEGURIDAD",OFFSET('PARÁMETROS'!$K$2,MATCH(U84,JC_SE,0),MATCH(T84,CC_SE,0)), IF(OR(AA84="DSRC/Estratégico",AA84="DSRC/Operativo"),OFFSET('PARÁMETROS'!$K$11,MATCH(U84,JC_DS,0),MATCH(T84,CC_DS,0)), IF(AA84="SALUD",OFFSET('PARÁMETROS'!$K$29,MATCH(U84,JC_SA,0),MATCH(T84,CC_SA,0)), IF(AA84="MEDIO AMBIENTE",OFFSET('PARÁMETROS'!$K$20,MATCH(U84,JC_MA,0),MATCH(T84,CC_MA,0)), IF(AA84="Rel. Gubernamentales",OFFSET('PARÁMETROS'!$K$48,MATCH(U84,JC_G,0),MATCH(T84,CC_G,0)), IF(AA84="OPERACIONAL",OFFSET('PARÁMETROS'!$K$56,MATCH(U84,JC_OP,0),MATCH(T84,CC_OP,0)), IF(AA84="FINANCIERO",OFFSET('PARÁMETROS'!$K$56,MATCH(U84,JC_FI,0),MATCH(T84,CC_FI,0)), OFFSET('PARÁMETROS'!$K$38,MATCH(U84,JC_L,0),MATCH(T84,CC_L,0))))))))),"") | AA84: =E75
V85: =IFERROR(IF(AA85="SEGURIDAD",OFFSET('PARÁMETROS'!$K$2,MATCH(U85,JC_SE,0),MATCH(T85,CC_SE,0)), IF(OR(AA85="DSRC/Estratégico",AA85="DSRC/Operativo"),OFFSET('PARÁMETROS'!$K$11,MATCH(U85,JC_DS,0),MATCH(T85,CC_DS,0)), IF(AA85="SALUD",OFFSET('PARÁMETROS'!$K$29,MATCH(U85,JC_SA,0),MATCH(T85,CC_SA,0)), IF(AA85="MEDIO AMBIENTE",OFFSET('PARÁMETROS'!$K$20,MATCH(U85,JC_MA,0),MATCH(T85,CC_MA,0)), IF(AA85="Rel. Gubernamentales",OFFSET('PARÁMETROS'!$K$48,MATCH(U85,JC_G,0),MATCH(T85,CC_G,0)), IF(AA85="OPERACIONAL",OFFSET('PARÁMETROS'!$K$56,MATCH(U85,JC_OP,0),MATCH(T85,CC_OP,0)), IF(AA85="FINANCIERO",OFFSET('PARÁMETROS'!$K$56,MATCH(U85,JC_FI,0),MATCH(T85,CC_FI,0)), OFFSET('PARÁMETROS'!$K$38,MATCH(U85,JC_L,0),MATCH(T85,CC_L,0))))))))),"") | AA85: =E75
V86: =IFERROR(IF(AA86="SEGURIDAD",OFFSET('PARÁMETROS'!$K$2,MATCH(U86,JC_SE,0),MATCH(T86,CC_SE,0)), IF(OR(AA86="DSRC/Estratégico",AA86="DSRC/Operativo"),OFFSET('PARÁMETROS'!$K$11,MATCH(U86,JC_DS,0),MATCH(T86,CC_DS,0)), IF(AA86="SALUD",OFFSET('PARÁMETROS'!$K$29,MATCH(U86,JC_SA,0),MATCH(T86,CC_SA,0)), IF(AA86="MEDIO AMBIENTE",OFFSET('PARÁMETROS'!$K$20,MATCH(U86,JC_MA,0),MATCH(T86,CC_MA,0)), IF(AA86="Rel. Gubernamentales",OFFSET('PARÁMETROS'!$K$48,MATCH(U86,JC_G,0),MATCH(T86,CC_G,0)), IF(AA86="OPERACIONAL",OFFSET('PARÁMETROS'!$K$56,MATCH(U86,JC_OP,0),MATCH(T86,CC_OP,0)), IF(AA86="FINANCIERO",OFFSET('PARÁMETROS'!$K$56,MATCH(U86,JC_FI,0),MATCH(T86,CC_FI,0)), OFFSET('PARÁMETROS'!$K$38,MATCH(U86,JC_L,0),MATCH(T86,CC_L,0))))))))),"") | AA86: =E75
V87: =IFERROR(IF(AA87="SEGURIDAD",OFFSET('PARÁMETROS'!$K$2,MATCH(U87,JC_SE,0),MATCH(T87,CC_SE,0)), IF(OR(AA87="DSRC/Estratégico",AA87="DSRC/Operativo"),OFFSET('PARÁMETROS'!$K$11,MATCH(U87,JC_DS,0),MATCH(T87,CC_DS,0)), IF(AA87="SALUD",OFFSET('PARÁMETROS'!$K$29,MATCH(U87,JC_SA,0),MATCH(T87,CC_SA,0)), IF(AA87="MEDIO AMBIENTE",OFFSET('PARÁMETROS'!$K$20,MATCH(U87,JC_MA,0),MATCH(T87,CC_MA,0)), IF(AA87="Rel. Gubernamentales",OFFSET('PARÁMETROS'!$K$48,MATCH(U87,JC_G,0),MATCH(T87,CC_G,0)), IF(AA87="OPERACIONAL",OFFSET('PARÁMETROS'!$K$56,MATCH(U87,JC_OP,0),MATCH(T87,CC_OP,0)), IF(AA87="FINANCIERO",OFFSET('PARÁMETROS'!$K$56,MATCH(U87,JC_FI,0),MATCH(T87,CC_FI,0)), OFFSET('PARÁMETROS'!$K$38,MATCH(U87,JC_L,0),MATCH(T87,CC_L,0))))))))),"") | AA87: =E75
V88: =IFERROR(IF(AA88="SEGURIDAD",OFFSET('PARÁMETROS'!$K$2,MATCH(U88,JC_SE,0),MATCH(T88,CC_SE,0)), IF(OR(AA88="DSRC/Estratégico",AA88="DSRC/Operativo"),OFFSET('PARÁMETROS'!$K$11,MATCH(U88,JC_DS,0),MATCH(T88,CC_DS,0)), IF(AA88="SALUD",OFFSET('PARÁMETROS'!$K$29,MATCH(U88,JC_SA,0),MATCH(T88,CC_SA,0)), IF(AA88="MEDIO AMBIENTE",OFFSET('PARÁMETROS'!$K$20,MATCH(U88,JC_MA,0),MATCH(T88,CC_MA,0)), IF(AA88="Rel. Gubernamentales",OFFSET('PARÁMETROS'!$K$48,MATCH(U88,JC_G,0),MATCH(T88,CC_G,0)), IF(AA88="OPERACIONAL",OFFSET('PARÁMETROS'!$K$56,MATCH(U88,JC_OP,0),MATCH(T88,CC_OP,0)), IF(AA88="FINANCIERO",OFFSET('PARÁMETROS'!$K$56,MATCH(U88,JC_FI,0),MATCH(T88,CC_FI,0)), OFFSET('PARÁMETROS'!$K$38,MATCH(U88,JC_L,0),MATCH(T88,CC_L,0))))))))),"") | AA88: =E75
V89: =IFERROR(IF(AA89="SEGURIDAD",OFFSET('PARÁMETROS'!$K$2,MATCH(U89,JC_SE,0),MATCH(T89,CC_SE,0)), IF(OR(AA89="DSRC/Estratégico",AA89="DSRC/Operativo"),OFFSET('PARÁMETROS'!$K$11,MATCH(U89,JC_DS,0),MATCH(T89,CC_DS,0)), IF(AA89="SALUD",OFFSET('PARÁMETROS'!$K$29,MATCH(U89,JC_SA,0),MATCH(T89,CC_SA,0)), IF(AA89="MEDIO AMBIENTE",OFFSET('PARÁMETROS'!$K$20,MATCH(U89,JC_MA,0),MATCH(T89,CC_MA,0)), IF(AA89="Rel. Gubernamentales",OFFSET('PARÁMETROS'!$K$48,MATCH(U89,JC_G,0),MATCH(T89,CC_G,0)), IF(AA89="OPERACIONAL",OFFSET('PARÁMETROS'!$K$56,MATCH(U89,JC_OP,0),MATCH(T89,CC_OP,0)), IF(AA89="FINANCIERO",OFFSET('PARÁMETROS'!$K$56,MATCH(U89,JC_FI,0),MATCH(T89,CC_FI,0)), OFFSET('PARÁMETROS'!$K$38,MATCH(U89,JC_L,0),MATCH(T89,CC_L,0))))))))),"") | AA89: =E75
V90: =IFERROR(IF(AA90="SEGURIDAD",OFFSET('PARÁMETROS'!$K$2,MATCH(U90,JC_SE,0),MATCH(T90,CC_SE,0)), IF(OR(AA90="DSRC/Estratégico",AA90="DSRC/Operativo"),OFFSET('PARÁMETROS'!$K$11,MATCH(U90,JC_DS,0),MATCH(T90,CC_DS,0)), IF(AA90="SALUD",OFFSET('PARÁMETROS'!$K$29,MATCH(U90,JC_SA,0),MATCH(T90,CC_SA,0)), IF(AA90="MEDIO AMBIENTE",OFFSET('PARÁMETROS'!$K$20,MATCH(U90,JC_MA,0),MATCH(T90,CC_MA,0)), IF(AA90="Rel. Gubernamentales",OFFSET('PARÁMETROS'!$K$48,MATCH(U90,JC_G,0),MATCH(T90,CC_G,0)), IF(AA90="OPERACIONAL",OFFSET('PARÁMETROS'!$K$56,MATCH(U90,JC_OP,0),MATCH(T90,CC_OP,0)), IF(AA90="FINANCIERO",OFFSET('PARÁMETROS'!$K$56,MATCH(U90,JC_FI,0),MATCH(T90,CC_FI,0)), OFFSET('PARÁMETROS'!$K$38,MATCH(U90,JC_L,0),MATCH(T90,CC_L,0))))))))),"") | AA90: =E75
L91: =IF(OR(J91<>"",K91<>""),OFFSET('PARÁMETROS'!$B$2,K91,J91),"") | N91: =IFERROR(L91*M91,"") -> 0 | O91: =IF(N91="","",IFERROR(IF(N91<=2,"ACEPTABLE",IF(N91<=6,"BAJA",IF(N91<=10,"ACEPTABLE CON REVISIÓN",IF(N91<=15,"SUSTANCIAL","INACEPTABLE")))),"")) -> ACEPTABLE | V91: =IFERROR(IF(AA91="SEGURIDAD",OFFSET('PARÁMETROS'!$K$2,MATCH(U91,JC_SE,0),MATCH(T91,CC_SE,0)), IF(OR(AA91="DSRC/Estratégico",AA91="DSRC/Operativo"),OFFSET('PARÁMETROS'!$K$11,MATCH(U91,JC_DS,0),MATCH(T91,CC_DS,0)), IF(AA91="SALUD",OFFSET('PARÁMETROS'!$K$29,MATCH(U91,JC_SA,0),MATCH(T91,CC_SA,0)), IF(AA91="MEDIO AMBIENTE",OFFSET('PARÁMETROS'!$K$20,MATCH(U91,JC_MA,0),MATCH(T91,CC_MA,0)), IF(AA91="Rel. Gubernamentales",OFFSET('PARÁMETROS'!$K$48,MATCH(U91,JC_G,0),MATCH(T91,CC_G,0)), IF(AA91="OPERACIONAL",OFFSET('PARÁMETROS'!$K$56,MATCH(U91,JC_OP,0),MATCH(T91,CC_OP,0)), IF(AA91="FINANCIERO",OFFSET('PARÁMETROS'!$K$56,MATCH(U91,JC_FI,0),MATCH(T91,CC_FI,0)), OFFSET('PARÁMETROS'!$K$38,MATCH(U91,JC_L,0),MATCH(T91,CC_L,0))))))))),"") | W91: =IF(E91="","", IF(COUNTA(V91:V106)-COUNTBLANK(V91:V106)=1, IF(O91="INACEPTABLE",IF(COUNTIF(V91:V106,"Control/Acción Eficaz")>=1,"SUSTANCIAL","INACEPTABLE"), IF(O91="SUSTANCIAL",IF(COUNTIF(V91:V106,"Control/Acción Eficaz")>=1,"ACEPTABLE CON REVISIÓN","SUSTANCIAL"), IF(O91="ACEPTABLE CON REVISIÓN",IF(COUNTIF(V91:V106,"Control/Acción Eficaz")>=1,"BAJA","ACEPTABLE CON REVISIÓN"), IF(O91="BAJA",IF(COUNTIF(V91:V106,"Control/Acción Eficaz")>=1,"ACEPTABLE","BAJA"),)))), IF(COUNTA(V91:V106)-COUNTBLANK(V91:V106)=2, IF(O91="INACEPTABLE",IF(COUNTIF(V91:V106,"Control/Acción Eficaz")=2,"ACEPTABLE CON REVISIÓN", IF(OR(AND(COUNTIF(V91:V106,"Control/Acción Eficaz")=1,COUNTIF(V91:V106,"Control/Acción Satisfactorio")=1), AND(COUNTIF(V91:V106,"Control/Acción Eficaz")=1,COUNTIF(V91:V106,"Control/Acción No Eficaz")=1)),"SUSTANCIAL","INACEPTABLE")), IF(O91="SUSTANCIAL",IF(COUNTIF(V91:V106,"Control/Acción Eficaz")=2,"BAJA", IF(OR(AND(COUNTIF(V91:V106,"Control/Acción Eficaz")=1,COUNTIF(V91:V106,"Control/Acción Satisfactorio")=1), AND(COUNTIF(V91:V106,"Control/Acción Eficaz")=1,COUNTIF(V91:V106,"Control/Acción No Eficaz")=1)),"ACEPTABLE CON REVISIÓN ","SUSTANCIAL")), IF(O91="ACEPTABLE CON REVISIÓN",IF(COUNTIF(V91:V106,"Control/Acción Eficaz")=2,"ACEPTABLE", IF(OR(AND(COUNTIF(V91:V106,"Control/Acción Eficaz")=1,COUNTIF(V91:V106,"Control/Acción Satisfactorio")=1), AND(COUNTIF(V91:V106,"Control/Acción Eficaz")=1,COUNTIF(V91:V106,"Control/Acción No Eficaz")=1)),"BAJA","ACEPTABLE CON REVISIÓN")), IF(O91="BAJA",IF(COUNTIF(V91:V106,"Control/Acción Eficaz")>=2,"ACEPTABLE","BAJA"),)))), IF(COUNTA(V91:V106)-COUNTBLANK(V91:V106)>=3, IF(O91="INACEPTABLE", IF(COUNTBLANK(V91:V106)=COUNTA(V91:V106),"", IF(COUNTIF(V91:V106,"Control/Acción No Eficaz")>=2,"INACEPTABLE", IF(AND(COUNTIF(V91:V106,"Control/Acción No Eficaz")=0,COUNTIF(V91:V106,"Control/Acción Eficaz")>=2),"ACEPTABLE CON REVISIÓN ","SUSTANCIAL"))), IF(O91="SUSTANCIAL", IF(COUNTBLANK(V91:V106)=COUNTA(V91:V106),"", IF(COUNTIF(V91:V106,"Control/Acción No Eficaz")>=2,"SUSTANCIAL", IF(AND(COUNTIF(V91:V106,"Control/Acción No Eficaz")=0,COUNTIF(V91:V106,"Control/Acción Eficaz")>=2),"BAJA","ACEPTABLE CON REVISIÓN"))), IF(O91="ACEPTABLE CON REVISIÓN", IF(COUNTBLANK(V91:V106)=COUNTA(V91:V106),"", IF(COUNTIF(V91:V106,"Control/Acción No Eficaz")>=2,"ACEPTABLE CON REVISIÓN", IF(AND(COUNTIF(V91:V106,"Control/Acción No Eficaz")=0,COUNTIF(V91:V106,"Control/Acción Eficaz")>=2),"ACEPTABLE","BAJA"))), IF(O91="BAJA", IF(COUNTBLANK(V91:V106)=COUNTA(V91:V106),"", IF(AND(COUNTBLANK(V91:V106)<1,COUNTA(V91:V106)=1), IF(COUNTIF(V91:V106,"Control/Acción No Eficaz")>=2,"BAJA", IF(AND(COUNTIF(V91:V106,"Control/Acción No Eficaz")=0,COUNTIF(V91:V106,"Control/Acción Eficaz")>=2),"ACEPTABLE","BAJA")), IF(COUNTIF(V91:V106,"Control/Acción No Eficaz")>=2,"BAJA", IF(AND(COUNTIF(V91:V106,"Control/Acción No Eficaz")=0,COUNTIF(V91:V106,"Control/Acción Eficaz")>=2),"ACEPTABLE","BAJA")))), IF(COUNTIF(V91:V106,"")>=5,"",O91))))), "")))) | AA91: =E91
V92: =IFERROR(IF(AA92="SEGURIDAD",OFFSET('PARÁMETROS'!$K$2,MATCH(U92,JC_SE,0),MATCH(T92,CC_SE,0)), IF(OR(AA92="DSRC/Estratégico",AA92="DSRC/Operativo"),OFFSET('PARÁMETROS'!$K$11,MATCH(U92,JC_DS,0),MATCH(T92,CC_DS,0)), IF(AA92="SALUD",OFFSET('PARÁMETROS'!$K$29,MATCH(U92,JC_SA,0),MATCH(T92,CC_SA,0)), IF(AA92="MEDIO AMBIENTE",OFFSET('PARÁMETROS'!$K$20,MATCH(U92,JC_MA,0),MATCH(T92,CC_MA,0)), IF(AA92="Rel. Gubernamentales",OFFSET('PARÁMETROS'!$K$48,MATCH(U92,JC_G,0),MATCH(T92,CC_G,0)), IF(AA92="OPERACIONAL",OFFSET('PARÁMETROS'!$K$56,MATCH(U92,JC_OP,0),MATCH(T92,CC_OP,0)), IF(AA92="FINANCIERO",OFFSET('PARÁMETROS'!$K$56,MATCH(U92,JC_FI,0),MATCH(T92,CC_FI,0)), OFFSET('PARÁMETROS'!$K$38,MATCH(U92,JC_L,0),MATCH(T92,CC_L,0))))))))),"") | AA92: =E91
V93: =IFERROR(IF(AA93="SEGURIDAD",OFFSET('PARÁMETROS'!$K$2,MATCH(U93,JC_SE,0),MATCH(T93,CC_SE,0)), IF(OR(AA93="DSRC/Estratégico",AA93="DSRC/Operativo"),OFFSET('PARÁMETROS'!$K$11,MATCH(U93,JC_DS,0),MATCH(T93,CC_DS,0)), IF(AA93="SALUD",OFFSET('PARÁMETROS'!$K$29,MATCH(U93,JC_SA,0),MATCH(T93,CC_SA,0)), IF(AA93="MEDIO AMBIENTE",OFFSET('PARÁMETROS'!$K$20,MATCH(U93,JC_MA,0),MATCH(T93,CC_MA,0)), IF(AA93="Rel. Gubernamentales",OFFSET('PARÁMETROS'!$K$48,MATCH(U93,JC_G,0),MATCH(T93,CC_G,0)), IF(AA93="OPERACIONAL",OFFSET('PARÁMETROS'!$K$56,MATCH(U93,JC_OP,0),MATCH(T93,CC_OP,0)), IF(AA93="FINANCIERO",OFFSET('PARÁMETROS'!$K$56,MATCH(U93,JC_FI,0),MATCH(T93,CC_FI,0)), OFFSET('PARÁMETROS'!$K$38,MATCH(U93,JC_L,0),MATCH(T93,CC_L,0))))))))),"") | AA93: =E91
V94: =IFERROR(IF(AA94="SEGURIDAD",OFFSET('PARÁMETROS'!$K$2,MATCH(U94,JC_SE,0),MATCH(T94,CC_SE,0)), IF(OR(AA94="DSRC/Estratégico",AA94="DSRC/Operativo"),OFFSET('PARÁMETROS'!$K$11,MATCH(U94,JC_DS,0),MATCH(T94,CC_DS,0)), IF(AA94="SALUD",OFFSET('PARÁMETROS'!$K$29,MATCH(U94,JC_SA,0),MATCH(T94,CC_SA,0)), IF(AA94="MEDIO AMBIENTE",OFFSET('PARÁMETROS'!$K$20,MATCH(U94,JC_MA,0),MATCH(T94,CC_MA,0)), IF(AA94="Rel. Gubernamentales",OFFSET('PARÁMETROS'!$K$48,MATCH(U94,JC_G,0),MATCH(T94,CC_G,0)), IF(AA94="OPERACIONAL",OFFSET('PARÁMETROS'!$K$56,MATCH(U94,JC_OP,0),MATCH(T94,CC_OP,0)), IF(AA94="FINANCIERO",OFFSET('PARÁMETROS'!$K$56,MATCH(U94,JC_FI,0),MATCH(T94,CC_FI,0)), OFFSET('PARÁMETROS'!$K$38,MATCH(U94,JC_L,0),MATCH(T94,CC_L,0))))))))),"") | AA94: =E91
V95: =IFERROR(IF(AA95="SEGURIDAD",OFFSET('PARÁMETROS'!$K$2,MATCH(U95,JC_SE,0),MATCH(T95,CC_SE,0)), IF(OR(AA95="DSRC/Estratégico",AA95="DSRC/Operativo"),OFFSET('PARÁMETROS'!$K$11,MATCH(U95,JC_DS,0),MATCH(T95,CC_DS,0)), IF(AA95="SALUD",OFFSET('PARÁMETROS'!$K$29,MATCH(U95,JC_SA,0),MATCH(T95,CC_SA,0)), IF(AA95="MEDIO AMBIENTE",OFFSET('PARÁMETROS'!$K$20,MATCH(U95,JC_MA,0),MATCH(T95,CC_MA,0)), IF(AA95="Rel. Gubernamentales",OFFSET('PARÁMETROS'!$K$48,MATCH(U95,JC_G,0),MATCH(T95,CC_G,0)), IF(AA95="OPERACIONAL",OFFSET('PARÁMETROS'!$K$56,MATCH(U95,JC_OP,0),MATCH(T95,CC_OP,0)), IF(AA95="FINANCIERO",OFFSET('PARÁMETROS'!$K$56,MATCH(U95,JC_FI,0),MATCH(T95,CC_FI,0)), OFFSET('PARÁMETROS'!$K$38,MATCH(U95,JC_L,0),MATCH(T95,CC_L,0))))))))),"") | AA95: =E91
V96: =IFERROR(IF(AA96="SEGURIDAD",OFFSET('PARÁMETROS'!$K$2,MATCH(U96,JC_SE,0),MATCH(T96,CC_SE,0)), IF(OR(AA96="DSRC/Estratégico",AA96="DSRC/Operativo"),OFFSET('PARÁMETROS'!$K$11,MATCH(U96,JC_DS,0),MATCH(T96,CC_DS,0)), IF(AA96="SALUD",OFFSET('PARÁMETROS'!$K$29,MATCH(U96,JC_SA,0),MATCH(T96,CC_SA,0)), IF(AA96="MEDIO AMBIENTE",OFFSET('PARÁMETROS'!$K$20,MATCH(U96,JC_MA,0),MATCH(T96,CC_MA,0)), IF(AA96="Rel. Gubernamentales",OFFSET('PARÁMETROS'!$K$48,MATCH(U96,JC_G,0),MATCH(T96,CC_G,0)), IF(AA96="OPERACIONAL",OFFSET('PARÁMETROS'!$K$56,MATCH(U96,JC_OP,0),MATCH(T96,CC_OP,0)), IF(AA96="FINANCIERO",OFFSET('PARÁMETROS'!$K$56,MATCH(U96,JC_FI,0),MATCH(T96,CC_FI,0)), OFFSET('PARÁMETROS'!$K$38,MATCH(U96,JC_L,0),MATCH(T96,CC_L,0))))))))),"") | AA96: =E91
V97: =IFERROR(IF(AA97="SEGURIDAD",OFFSET('PARÁMETROS'!$K$2,MATCH(U97,JC_SE,0),MATCH(T97,CC_SE,0)), IF(OR(AA97="DSRC/Estratégico",AA97="DSRC/Operativo"),OFFSET('PARÁMETROS'!$K$11,MATCH(U97,JC_DS,0),MATCH(T97,CC_DS,0)), IF(AA97="SALUD",OFFSET('PARÁMETROS'!$K$29,MATCH(U97,JC_SA,0),MATCH(T97,CC_SA,0)), IF(AA97="MEDIO AMBIENTE",OFFSET('PARÁMETROS'!$K$20,MATCH(U97,JC_MA,0),MATCH(T97,CC_MA,0)), IF(AA97="Rel. Gubernamentales",OFFSET('PARÁMETROS'!$K$48,MATCH(U97,JC_G,0),MATCH(T97,CC_G,0)), IF(AA97="OPERACIONAL",OFFSET('PARÁMETROS'!$K$56,MATCH(U97,JC_OP,0),MATCH(T97,CC_OP,0)), IF(AA97="FINANCIERO",OFFSET('PARÁMETROS'!$K$56,MATCH(U97,JC_FI,0),MATCH(T97,CC_FI,0)), OFFSET('PARÁMETROS'!$K$38,MATCH(U97,JC_L,0),MATCH(T97,CC_L,0))))))))),"") | AA97: =E91
V98: =IFERROR(IF(AA98="SEGURIDAD",OFFSET('PARÁMETROS'!$K$2,MATCH(U98,JC_SE,0),MATCH(T98,CC_SE,0)), IF(OR(AA98="DSRC/Estratégico",AA98="DSRC/Operativo"),OFFSET('PARÁMETROS'!$K$11,MATCH(U98,JC_DS,0),MATCH(T98,CC_DS,0)), IF(AA98="SALUD",OFFSET('PARÁMETROS'!$K$29,MATCH(U98,JC_SA,0),MATCH(T98,CC_SA,0)), IF(AA98="MEDIO AMBIENTE",OFFSET('PARÁMETROS'!$K$20,MATCH(U98,JC_MA,0),MATCH(T98,CC_MA,0)), IF(AA98="Rel. Gubernamentales",OFFSET('PARÁMETROS'!$K$48,MATCH(U98,JC_G,0),MATCH(T98,CC_G,0)), IF(AA98="OPERACIONAL",OFFSET('PARÁMETROS'!$K$56,MATCH(U98,JC_OP,0),MATCH(T98,CC_OP,0)), IF(AA98="FINANCIERO",OFFSET('PARÁMETROS'!$K$56,MATCH(U98,JC_FI,0),MATCH(T98,CC_FI,0)), OFFSET('PARÁMETROS'!$K$38,MATCH(U98,JC_L,0),MATCH(T98,CC_L,0))))))))),"") | AA98: =E91
V99: =IFERROR(IF(AA99="SEGURIDAD",OFFSET('PARÁMETROS'!$K$2,MATCH(U99,JC_SE,0),MATCH(T99,CC_SE,0)), IF(OR(AA99="DSRC/Estratégico",AA99="DSRC/Operativo"),OFFSET('PARÁMETROS'!$K$11,MATCH(U99,JC_DS,0),MATCH(T99,CC_DS,0)), IF(AA99="SALUD",OFFSET('PARÁMETROS'!$K$29,MATCH(U99,JC_SA,0),MATCH(T99,CC_SA,0)), IF(AA99="MEDIO AMBIENTE",OFFSET('PARÁMETROS'!$K$20,MATCH(U99,JC_MA,0),MATCH(T99,CC_MA,0)), IF(AA99="Rel. Gubernamentales",OFFSET('PARÁMETROS'!$K$48,MATCH(U99,JC_G,0),MATCH(T99,CC_G,0)), IF(AA99="OPERACIONAL",OFFSET('PARÁMETROS'!$K$56,MATCH(U99,JC_OP,0),MATCH(T99,CC_OP,0)), IF(AA99="FINANCIERO",OFFSET('PARÁMETROS'!$K$56,MATCH(U99,JC_FI,0),MATCH(T99,CC_FI,0)), OFFSET('PARÁMETROS'!$K$38,MATCH(U99,JC_L,0),MATCH(T99,CC_L,0))))))))),"") | AA99: =E91
V100: =IFERROR(IF(AA100="SEGURIDAD",OFFSET('PARÁMETROS'!$K$2,MATCH(U100,JC_SE,0),MATCH(T100,CC_SE,0)), IF(OR(AA100="DSRC/Estratégico",AA100="DSRC/Operativo"),OFFSET('PARÁMETROS'!$K$11,MATCH(U100,JC_DS,0),MATCH(T100,CC_DS,0)), IF(AA100="SALUD",OFFSET('PARÁMETROS'!$K$29,MATCH(U100,JC_SA,0),MATCH(T100,CC_SA,0)), IF(AA100="MEDIO AMBIENTE",OFFSET('PARÁMETROS'!$K$20,MATCH(U100,JC_MA,0),MATCH(T100,CC_MA,0)), IF(AA100="Rel. Gubernamentales",OFFSET('PARÁMETROS'!$K$48,MATCH(U100,JC_G,0),MATCH(T100,CC_G,0)), IF(AA100="OPERACIONAL",OFFSET('PARÁMETROS'!$K$56,MATCH(U100,JC_OP,0),MATCH(T100,CC_OP,0)), IF(AA100="FINANCIERO",OFFSET('PARÁMETROS'!$K$56,MATCH(U100,JC_FI,0),MATCH(T100,CC_FI,0)), OFFSET('PARÁMETROS'!$K$38,MATCH(U100,JC_L,0),MATCH(T100,CC_L,0))))))))),"") | AA100: =E91
V101: =IFERROR(IF(AA101="SEGURIDAD",OFFSET('PARÁMETROS'!$K$2,MATCH(U101,JC_SE,0),MATCH(T101,CC_SE,0)), IF(OR(AA101="DSRC/Estratégico",AA101="DSRC/Operativo"),OFFSET('PARÁMETROS'!$K$11,MATCH(U101,JC_DS,0),MATCH(T101,CC_DS,0)), IF(AA101="SALUD",OFFSET('PARÁMETROS'!$K$29,MATCH(U101,JC_SA,0),MATCH(T101,CC_SA,0)), IF(AA101="MEDIO AMBIENTE",OFFSET('PARÁMETROS'!$K$20,MATCH(U101,JC_MA,0),MATCH(T101,CC_MA,0)), IF(AA101="Rel. Gubernamentales",OFFSET('PARÁMETROS'!$K$48,MATCH(U101,JC_G,0),MATCH(T101,CC_G,0)), IF(AA101="OPERACIONAL",OFFSET('PARÁMETROS'!$K$56,MATCH(U101,JC_OP,0),MATCH(T101,CC_OP,0)), IF(AA101="FINANCIERO",OFFSET('PARÁMETROS'!$K$56,MATCH(U101,JC_FI,0),MATCH(T101,CC_FI,0)), OFFSET('PARÁMETROS'!$K$38,MATCH(U101,JC_L,0),MATCH(T101,CC_L,0))))))))),"") | AA101: =E91
V102: =IFERROR(IF(AA102="SEGURIDAD",OFFSET('PARÁMETROS'!$K$2,MATCH(U102,JC_SE,0),MATCH(T102,CC_SE,0)), IF(OR(AA102="DSRC/Estratégico",AA102="DSRC/Operativo"),OFFSET('PARÁMETROS'!$K$11,MATCH(U102,JC_DS,0),MATCH(T102,CC_DS,0)), IF(AA102="SALUD",OFFSET('PARÁMETROS'!$K$29,MATCH(U102,JC_SA,0),MATCH(T102,CC_SA,0)), IF(AA102="MEDIO AMBIENTE",OFFSET('PARÁMETROS'!$K$20,MATCH(U102,JC_MA,0),MATCH(T102,CC_MA,0)), IF(AA102="Rel. Gubernamentales",OFFSET('PARÁMETROS'!$K$48,MATCH(U102,JC_G,0),MATCH(T102,CC_G,0)), IF(AA102="OPERACIONAL",OFFSET('PARÁMETROS'!$K$56,MATCH(U102,JC_OP,0),MATCH(T102,CC_OP,0)), IF(AA102="FINANCIERO",OFFSET('PARÁMETROS'!$K$56,MATCH(U102,JC_FI,0),MATCH(T102,CC_FI,0)), OFFSET('PARÁMETROS'!$K$38,MATCH(U102,JC_L,0),MATCH(T102,CC_L,0))))))))),"") | AA102: =E91
...

Sheet PARÁMETROS
A1: C. Probabilidad (A x B) | J1: Jerarquía del Control | K1: Calidad del Control
B2: A. Exposición | C2: 1 | D2: 2 | E2: 3 | F2: 4 | G2: 5 | H2: 6 | K2: Efectividad del Control | L2: C. Menor a 50% | M2: B. 50% y 80% | N2: A. Mayor 80% | P2: FAMILIA DE PELIGROS - SEGURIDAD | R2: FAMILIA DE RIESGOS - SEGURIDAD | T2: FAMILIA DE CONTROLES/ACCIONES - SEGURIDAD | V2: FAMILIA DE VERIFICADORES - SEGURIDAD | X2: Verificadores | Z2: FAMILIA DE ASPECTOS - MEDIO AMBIENTE | AB2: FAMILIA DE IMPACTOS - MEDIO AMBIENTE | AD2: FAMILIA DE CONTROLES - MEDIO AMBIENTE | AF2: FAMILIA DE VERIFICADORES - MEDIO AMBIENTE | AH2: verificador MA | AJ2: FAMILIA PELIGROS - SALUD | AL2: FAMILIA RIESGOS - SALUD | AN2: FAMILIA CONTROLES - SALUD | AP2: FAMILIA DE VERIFICADORES - SALUD | AR2: FAMILIA PELIGROS - LEGAL | AT2: FAMILIA RIESGOS - LEGAL | AV2: FAMILIA CONTROLES - LEGAL | AX2: FAMILIA VERIFICADORES - LEGAL | AZ2: FAMILIA DE PELIGROS DSRC | BB2: FAMILIA RIESGOS - DSRC | BD2: FAMILIA CONTROLES - DSRC | BF2: FAMILIA VERIFICADORES - DSRC | BH2: FAMILIA DE PELIGROS RG | BJ2: FAMILIA RIESGOS - RG | BL2: FAMILIA CONTROLES - RG | BN2: FAMILIA VERIFICADORES - RG | BP2: FAMILIA DE PELIGROS OPERACIONAL | BR2: FAMILIA RIESGOS OPERACIONAL | BT2: FAMILIA CONTROLES OPERACIONALES | BV2: FAMILIA VERIFICADORES OPERACIONALES | BX2: FAMILIA DE PELIGROS - FINANCIEROS | BZ2: FAMILIA RIESGOS FINANCIEROS | CB2: FAMILIA CONTROLES FINANCIEROS | CD2: FAMILIA VERIFICADORES FINANCIEROS
A3: B. Posibilidad | B3: 1 | C3: 5 | D3: 5 | E3: 4 | F3: 4 | G3: 3 | H3: 3 | K3: 6. Eliminación | L3: Control/Acción Satisfactorio | M3: Control/Acción Satisfactorio | N3: Control/Acción Eficaz | P3: Agentes Biológicos (animales, insectos, bacterias, virus, etc.) | R3: Aplastamiento | T3: Eliminación | V3: Planilla de vigencia de Autorizaciones, Permisos y Licencias (Gubernamentales, legales, normativos) | X3: Seguimiento a la Planilla de vigencia de cursos, autorizaciones, competencias y/o certificaciones de personas y equipos | Z3: Cambio de uso de suelo natural por actividad industrial, cultivos u otros | AB3: Agotamiento del recurso mineral/ reservas y recursos geológicos | AD3: Eliminación del proceso | AF3: Acreditaciones | AH3: Seguimiento a la Planilla de vigencia de cursos, autorizaciones, competencias y/o certificaciones de personas y equipos | AJ3: A | AL3: AA | AR3: LEGAL | AT3: LEGAL | AV3: LEGAL | AX3: LEGAL | AZ3: Agotamiento de agua de pozos | BB3: Bloqueos/Marchas/Amenazas/Demandas Sociales | BD3: RC.3.1.1. Fortalecer la cadena productiva de Quinua en comunidades del área de intervención en coordinación con el Consejo Consultivo mediante alianzas estratégicas | BF3: Publicación de indicadores | BH3: RELACIONALES GUBERNAMENTALES | BJ3: RELACIONALES GUBERNAMENTALES | BL3: RELACIONALES GUBERNAMENTALES | BP3: Conflictos sociales | BR3: Daño a la propiedad pública o privada | BT3: Alarmas / señales / advertencias | BV3: Verificadores Operacionales | BX3: financiero | BZ3: financiero | CB3: financiero | CD3: financiero
B4: 2 | C4: 5 | D4: 5 | E4: 4 | F4: 3 | G4: 3 | H4: 3 | K4: 5. Sustitución/ Minimización | L4: Control/Acción Satisfactorio | M4: Control/Acción Satisfactorio | N4: Control/Acción Eficaz | P4: Agentes Físicos (iluminación excesiva/baja/inadecuada o sin iluminación) | R4: Arco eléctrico | T4: Sustitución | V4: Planillas de vigencia de Certificaciones / Competencias/ Capacitaciones | X4: Seguimiento al programa de reuniones y evaluaciones de compromiso con la seguridad | Z4: Consumo de agua de vertientes para fines humanos y pecuarios/ agua potable, abrevaderos y riego | AB4: Alteración del clima por cambios climáticos/ efecto invernadero | AD4: Eliminación sustancia peligrosa del proceso | AF4: Certificaciones | AH4: Seguimiento al programa de reuniones y evaluaciones de compromiso con la seguridad | AJ4: salud | AL4: SALUD | AN4: SALUD | AP4: SALUD | AR4: LEGAL | AT4: LEGAL | AV4: LEGAL | AX4: LEGAL | AZ4: Agua para ganado | BB4: Cierre de Proyectos de Desarrollo | BD4: RC.3.1.2. Fortalecer la cadena productiva de Camélidos en comunidades del área de intervención en coordinación con el Consejo Consultivo y las alianzas estratégicas | BF4: Planes y/o Programas | BH4: RELACIONALES GUBERNAMENTALES | BJ4: RELACIONALES GUBERNAMENTALES | BL4: RELACIONALES GUBERNAMENTALES | BN4: RELACIONALES GUBERNAMENTALES | BP4: Condiciones climatológicas | BR4: Fallas en sistema mecanizado de embarque / Infraestructura de atraque | BT4: Inspecciones | BV4: Publicación de Indicadores | BX4: financiero | BZ4: financiero | CB4: financiero | CD4: financiero
B5: 3 | C5: 4 | D5: 4 | E5: 4 | F5: 3 | G5: 2 | H5: 2 | K5: 4. Ingeniería | L5: Control/Acción No Eficaz | M5: Control/Acción Satisfactorio | N5: Control/Acción Eficaz | P5: Agentes Físicos (radiación) | R5: Asfixia / Ahogamiento | T5: Controles de Ingeniería | V5: Matriz de Requisitos Legales | X5: Seguimiento al programa de difusión de instructivos y capacitaciones internas | Z5: Consumo de agua subterránea para procesos industriales/ campo de pozos | AB5: Contaminación de aguas por derrame de sustancias peligrosas | AD5: Cambio de disposición de residuos peligrosos | AF5: Confiabilidad de mediciones de factores ambientales/equipos certificados | AH5: Seguimiento al programa de Inspecciones Interno | AJ5: salud | AL5: SALUD | AN5: SALUD | AP5: SALUD | AR5: LEGAL | AT5: LEGAL | AV5: LEGAL | AX5: LEGAL | AZ5: Agua por gravedad | BB5: Confrontaciones Sociales | BD5: RC.3.1.3. Fortalecer la cadena productiva de Turismo en comunidades del área de intervención en coordinación con el Consejo Consultivo mediante alianzas estratégicas. | BH5: RELACIONALES GUBERNAMENTALES | BJ5: RELACIONALES GUBERNAMENTALES | BL5: RELACIONALES GUBERNAMENTALES | BN5: RELACIONALES GUBERNAMENTALES | BP5: Transferencia de concentrados en PdM | BR5: Efecto negativo sobre la estabilidad física de taludes | BT5: Control de emergencias | BV5: Planes y/o Programas | BX5: financiero | BZ5: financiero | CB5: financiero | CD5: financiero
B6: 4 | C6: 4 | D6: 3 | E6: 3 | F6: 2 | G6: 2 | H6: 1 | K6: 3. Señalización/ Advertencias/ Alarma | L6: Control/Acción No Eficaz | M6: Control/Acción Satisfactorio | N6: Control/Acción Eficaz | P6: Agentes Físicos (ruido) | R6: Atrapamiento (entre objetos, por deslizamientos) | T6: Controles Ergonómicos | V6: Planes / Programas | X6: Seguimiento al programa de Inspecciones Interno | Z6: Consumo de aguas superficiales para fines agropecuarios/ abrevaderos y riego | AB6: Contaminación de suelo por derrame de sustancias peligrosas | AD6: Reemplazo de reactivos químicos de menor impacto | AF6: Informes con indicadores y verificadores ambientales | AH6: Seguimiento al programa de difusión de instructivos y capacitaciones internas | AJ6: salud | AL6: SALUD | AN6: SALUD | AP6: SALUD | AR6: LEGAL | AT6: LEGAL | AV6: LEGAL | AX6: LEGAL | AZ6: Cantidad y calidad de agua | BB6: Denuncias | BD6: RC.3.1.4. Fortalecer la Educación regular, alternativa y superior en el área de intervención en coordinación con el Consejo Consultivo y las alianzas estratégicas | BH6: RELACIONALES GUBERNAMENTALES | BJ6: RELACIONALES GUBERNAMENTALES | BL6: RELACIONALES GUBERNAMENTALES | BN6: RELACIONALES GUBERNAMENTALES | BP6: Extracción de recursos naturales renovables/ agregados para construcciones | BR6: Pérdida del patrimonio cultural/ arqueología | BT6: Instrucción operacional | BV6: Acreditaciones, Certificaciones, Permisos normativos | BX6: financiero | BZ6: financiero | CB6: financiero | CD6: financiero
B7: 5 | C7: 3 | D7: 3 | E7: 2 | F7: 2 | G7: 1 | H7: 1 | K7: 2. Administrativo/ Procedimientos/ Capacitación | L7: Control/Acción No Eficaz | M7: Control/Acción Satisfactorio | N7: Control/Acción Eficaz | P7: Agentes Físicos (ventilación) | R7: Atropello | T7: Controles de Salud Ocupacional | V7: Publicación de Indicadores | X7: Seguimiento al programa de inspecciones ISOP | Z7: Consumo de energía eléctrica | AB7: Contaminación del aire por gases orgánicos persistentes | AD7: Tecnología para disminuir consumo de agua natural/ recirculación | AF7: Matriz de Requisitos Legales ambientales en áreas operativas/soporte | AH7: Seguimiento al programa de inspecciones ISOP | AJ7: salud | AL7: SALUD | AN7: SALUD | AP7: SALUD | AR7: LEGAL | AT7: LEGAL | AV7: LEGAL | AX7: LEGAL | AZ7: Cierre de la mina | BB7: Perdida de Licencia Social para Operar de MSC | BD7: RC.3.1.5. Fortalecer el funcionamiento de centro Integral de salud de San Cristóbal y la red de salud Municipal, en coordinación con el Consejo consultivo y alianzas estratégicas. | BH7: RELACIONALES GUBERNAMENTALES | BJ7: RELACIONALES GUBERNAMENTALES | BL7: RELACIONALES GUBERNAMENTALES | BN7: RELACIONALES GUBERNAMENTALES | BP7: Remoción de lugares de patrimonio social de la comunidad | BR7: Baja en el movimiento de mineral en los frentes de carguío | BT7: Control de ingeniería | BX7: financiero | BZ7: financiero | CB7: financiero | CD7: financiero
B8: 6 | C8: 3 | D8: 3 | E8: 2 | F8: 1 | G8: 1 | H8: 1 | K8: 1. EPP | L8: Control/Acción No Eficaz | M8: Control/Acción No Eficaz | N8: Control/Acción Satisfactorio | P8: Agentes Físicos (vibración) | R8: Caída a distinto nivel (Menor a 1,80) | T8: Controles Sanitarios | V8: Verificadores Operacionales | X8: Seguimiento al programa de inspecciones IRO´S: Aislamiento | Z8: Consumo de recursos naturales no renovables/ hidrocarburos fósiles: petróleo y gas natural | AB8: Daño a la propiedad pública o privada | AD8: Mejora en la eficiencia del proceso/ optimización en uso de recursos naturales no renovables | AF8: Permisos normativos | AH8: Seguimiento al programa de inspecciones IRO´S: Sustancias Peligrosas | AJ8: salud | AL8: SALUD | AN8: SALUD | AP8: SALUD | AR8: LEGAL | AT8: LEGAL | AV8: LEGAL | AX8: LEGAL | AZ8: Conflicto políticas sociales externas a MSC | BB8: Perdidas económicas para Comunidades | BD8: RC.4.1.2. Realizar el manejo de quejas / preocupaciones y riesgos sociales de los grupos de interés del área de influencia de MSC | BH8: RELACIONALES GUBERNAMENTALES | BJ8: RELACIONALES GUBERNAMENTALES | BL8: RELACIONALES GUBERNAMENTALES | BN8: RELACIONALES GUBERNAMENTALES | BP8: Disponibilidad, utilización | BR8: Falta de continuidad en el movimiento de camiones | BT8: Procedimientos / Instructivos / Reglamentos y otros. | BX8: financiero | BZ8: financiero | CB8: financiero | CD8: financiero
P9: Agentes Químicos (gases, vapores, aerosoles, etc.) | R9: Caída al mismo nivel | T9: Autorizaciones, Permisos y Licencias (Gubernamentales, legales, normativos) | X9: Seguimiento al programa de inspecciones IRO´S: Izaje | Z9: Derrame de residuos peligrosos/ empetrolados, relaves de colas, lodos sépticos, otros | AB9: Degradación de la calidad de agua subterránea por aguas de proceso | AD9: Revegetación y rehabilitación de áreas perturbadas | AF9: Planes y programas | AH9: Seguimiento al programa de mantenimientos de equipos/ vehículos | AJ9: salud | AL9: SALUD | AN9: SALUD | AP9: SALUD | AR9: LEGAL | AT9: LEGAL | AV9: LEGAL | AX9: LEGAL | AZ9: Hospital 2do Nivel | BB9: Perdidas económicas para MSC | BD9: RC.4.1.3. Desarrollar estudios socio económicos en las comunidades de influencia directa para la gestión social | BH9: RELACIONALES GUBERNAMENTALES | BJ9: RELACIONALES GUBERNAMENTALES | BL9: RELACIONALES GUBERNAMENTALES | BN9: RELACIONALES GUBERNAMENTALES | BP9: Operación Planta | BR9: Falta de movimiento de mineral en frentes de carguío planificados | BT9: Sustitución | BX9: financiero | BZ9: financiero | CB9: financiero | CD9: financiero
B10: oportunidad | J10: Jerarquía del Control - DSRC | K10: Calidad del Control-DSRC | P10: Almacenamiento inadecuado de materiales, herramientas, etc. (en depósitos, estantes, etc.) | R10: Caída de altura (Igual o Mayor a 1,80) | T10: Certificaciones | X10: Seguimiento al programa de inspecciones IRO´S: Sustancias Peligrosas | Z10: Derrame de aguas de proceso/ aguas de colas, aguas de piscina de emergencia | AB10: Degradación de la calidad de cuerpos de agua superficial por descargas | AD10: Uso de geomembrana como aislante para prevención | AF10: Planillas de vigencia | AH10: Seguimiento y publicación de reportes de velocidades | AJ10: salud | AL10: SALUD | AN10: SALUD | AP10: SALUD | AR10: LEGAL | AT10: LEGAL | AV10: LEGAL | AX10: LEGAL | AZ10: Inapropiación del Desarrollo Económico Local por parte de las comunidades | BB10: Preocupaciones/Quejas/Determinación de las Comunidades/Inspecciones/Fiscalizaciones | BD10: RC.4.2.1. Monitorear el cumplimiento de los acuerdos y convenios entre empresa, comunidades y otras organizaciones. | BH10: RELACIONALES GUBERNAMENTALES | BJ10: RELACIONALES GUBERNAMENTALES | BL10: RELACIONALES GUBERNAMENTALES | BN10: RELACIONALES GUBERNAMENTALES | BP10: Disponibilidad | BR10: Baja en la alimentación de mineral | BT10: Certificaciones | BX10: financiero | BZ10: financiero | CB10: financiero | CD10: financiero
B11: prob | D11: 5 | E11: 4 | F11: 3 | G11: 2 | H11: 1 | K11: Efectividad del Control | L11: C. Menor a 50% | M11: B. 50% y 80% | N11: A. Mayor 80% | P11: Área de trabajo reducida, congestionada, acceso difícil o inadecuado | R11: Caída de objetos / materiales/roca | T11: Competencias | X11: Seguimiento al programa de inspecciones IRO´S: Taludes Frentes de Carguío Banquinas | Z11: Derrame de concentrados de minerales | AB11: Degradación de la flora natural | AD11: Riego de caminos para reducir emisión de polvo | AF11: Publicación de indicadores | AH11: Seguimiento y publicación de reportes/informes e indicadores internos | AJ11: salud | AL11: SALUD | AN11: SALUD | AP11: SALUD | AR11: LEGAL | AT11: LEGAL | AV11: LEGAL | AX11: LEGAL | AZ11: Operación Wila Khara Deposito de Colas | BD11: RC.4.2.2. Mitigar los impactos socio económicos ocasionados por las operaciones de MSC en las comunidades de San Cristóbal, Culpina K | BH11: RELACIONALES GUBERNAMENTALES | BJ11: RELACIONALES GUBERNAMENTALES | BL11: RELACIONALES GUBERNAMENTALES | BN11: RELACIONALES GUBERNAMENTALES | BR11: Baja en el tratamiento de mineral | BX11: financiero | BZ11: financiero | CB11: financiero | CD11: financiero
B12: Severidad | C12: 5 | D12: Altamente Implementable | E12: Altamente Implementable | F12: Implementable | G12: Implementable con Revisión | H12: No Recomendable su Implementación | K12: 6. Acuerdos estratégicos/Convenios estratégicos | L12: Control/Acción Satisfactorio | M12: Control/Acción Satisfactorio | N12: Control/Acción Eficaz | P12: Áreas de trabajo con desniveles o gradas | R12: Choque eléctrico | T12: Controles/Acciones de Emergencias | X12: Seguimiento al programa de inspecciones IRO´S: Trabajo Eléctrico - Actos | Z12: Derrame de hidrocarburos/ lubricantes y combustibles | AB12: Degradación del paisaje natural | AD12: Uso de cobertor para reducir emisión de polvo | AF12: Verificadores operacionales | AH12: Seguimiento al programa de monitoreo y análisis de factores ambientales | AJ12: salud | AL12: SALUD | AN12: SALUD | AP12: SALUD | AR12: LEGAL | AT12: LEGAL | AV12: LEGAL | AX12: LEGAL | AZ12: Pasivos ambientales generados por MSC | BD12: RC.4.2.3. Fortalecer la administración y operaciones de los servicios básicos en las comunidades San Cristóbal y Culpina K | BH12: RELACIONALES GUBERNAMENTALES | BJ12: RELACIONALES GUBERNAMENTALES | BL12: RELACIONALES GUBERNAMENTALES | BN12: RELACIONALES GUBERNAMENTALES | BX12: financiero | BZ12: financiero | CB12: financiero | CD12: financiero
C13: 4 | D13: Altamente Implementable | E13: Altamente Implementable | F13: Implementable | G13: Implementable con Revisión | H13: No Recomendable su Implementación | K13: 5. Acuerdos específicos/Convenios específicos | L13: Control/Acción Satisfactorio | M13: Control/Acción Satisfactorio | N13: Control/Acción Eficaz | P13: Condiciones climatológicas adversas (tormenta eléctrica, viento, nieve, lluvia, rayos UV, etc.) | R13: Colisión / Choque | T13: Capacitación/Entrenamiento | X13: Seguimiento al programa de inspecciones IRO´S: Trabajo Eléctrico - Condiciones | Z13: Derrame de sustancias peligrosas/ reactivos químicos y otros insumos industriales | AB13: Degradación o alteración de la fauna silvestre | AD13: Uso de barreras - diques para aguas de contacto | AJ13: salud | AL13: SALUD | AN13: SALUD | AP13: SALUD | AR13: LEGAL | AT13: LEGAL | AV13: LEGAL | AX13: LEGAL | AZ13: Reducción de nivel freático en Campo de Pozos | BD13: RC.4.2.4.Apoyar en la atención a los diferente grupos sociales de las comunidades del área de influencia directa de MSC. | BH13: RELACIONALES GUBERNAMENTALES | BJ13: RELACIONALES GUBERNAMENTALES | BL13: RELACIONALES GUBERNAMENTALES | BN13: RELACIONALES GUBERNAMENTALES | BX13: financiero | BZ13: financiero | CB13: financiero | CD13: financiero
C14: 3 | D14: Implementable | E14: Implementable | F14: Implementable con Revisión | G14: No Recomendable su Implementación | H14: No Recomendable su Implementación | K14: 4. Planes estratégicos | L14: Control/Acción No Eficaz | M14: Control/Acción Satisfactorio | N14: Control/Acción Eficaz | P14: Desorden y falta de limpieza | R14: Contacto con herramientas, objetos cortantes y/o punzantes (corte o incrustación) | T14: Instrucción Operacional | X14: Seguimiento al programa de inspecciones IRO´S: Trabajo en Altura | Z14: Descarga de aguas pluviales de área de mina, planta, campamento y otros | AB14: Disminución de agua subterránea/descenso del nivel freático | AD14: Mejora tecnológica - diseños de ingeniería | AJ14: salud | AL14: SALUD | AN14: SALUD | AP14: SALUD | AR14: LEGAL | AT14: LEGAL | AV14: LEGAL | AX14: LEGAL | BD14: RC.4.3.2.Apoyar la gestión del Uso Racional del agua en comunidades del área de influencia de MSC | BH14: RELACIONALES GUBERNAMENTALES | BJ14: RELACIONALES GUBERNAMENTALES | BL14: RELACIONALES GUBERNAMENTALES | BN14: RELACIONALES GUBERNAMENTALES
C15: 2 | D15: Implementable con Revisión | E15: Implementable con Revisión | F15: No Recomendable su Implementación | G15: No Recomendable su Implementación | H15: No Implementable | K15: 3. Intervenciones directas | L15: Control/Acción No Eficaz | M15: Control/Acción Satisfactorio | N15: Control/Acción Eficaz | P15: Energía almacenada que puede liberarse repentinamente | R15: Contacto con superficies/partículas/objetos calientes | T15: Procedimientos / Instructivos / Reglamentos y otros. | X15: Seguimiento al programa de inspecciones IRO´S: Trabajo en Espacios Confinados | Z15: Descarga de aguas residuales de lavado de vehículos (Truck shop, Toldos) | AB15: Disminución de nutrientes del suelo/ pérdida de calidad del suelo | AD15: Tratamiento de aguas residuales/ físico, químico, biológico | AJ15: salud | AL15: SALUD | AN15: SALUD | AP15: SALUD | AR15: LEGAL | AT15: LEGAL | AV15: LEGAL | AX15: LEGAL | BD15: RC.4.4.1. Mantener contactos permanentes con los grupos de interés del área de influencia directa | BH15: RELACIONALES GUBERNAMENTALES | BJ15: RELACIONALES GUBERNAMENTALES | BL15: RELACIONALES GUBERNAMENTALES | BN15: RELACIONALES GUBERNAMENTALES
C16: 1 | D16: No Recomendable su Implementación | E16: No Recomendable su Implementación | F16: No Recomendable su Implementación | G16: No Implementable | H16: No Implementable | K16: 2. Reuniones formales | L16: Control/Acción No Eficaz | M16: Control/Acción Satisfactorio | N16: Control/Acción Eficaz | P16: Equipo con partes / elementos en movimiento | R16: Contacto por proyección de materiales, partículas, objetos, etc. | T16: Inspecciones | X16: Seguimiento al programa de inspecciones IRO´S: Trabajo en Excavaciones | Z16: Descarga de aguas residuales de tratamiento de aguas servidas/ campamento, cocina | AB16: Disminución de recursos naturales no renovables / hidrocarburos fósiles | AD16: Mantenimiento preventivo de equipos- vehículos | AJ16: salud | AL16: SALUD | AN16: SALUD | AP16: SALUD | AR16: LEGAL | AT16: LEGAL | AV16: LEGAL | AX16: LEGAL | BD16: RC.4.4.3. Mantener contactos permanentes con los grupos de interés de Desarrollo Socio Económico. | BH16: RELACIONALES GUBERNAMENTALES | BJ16: RELACIONALES GUBERNAMENTALES | BL16: RELACIONALES GUBERNAMENTALES | BN16: RELACIONALES GUBERNAMENTALES
K17: 1. Relacionamientos | L17: Control/Acción No Eficaz | M17: Control/Acción No Eficaz | N17: Control/Acción Satisfactorio | P17: Equipo o línea energizada | R17: Contacto por proyección de rocas o fragmentos de rocas volantes | T17: Señales/ Advertencias/ Alarmas | X17: Seguimiento al programa de inspecciones IRO´S: Trabajos en Caliente | Z17: Descarga de colas de la planta | AB17: Efecto de degradación de la calidad del aire | AD17: Inspecciones planificadas y no planificadas | AJ17: salud | AL17: SALUD | AN17: SALUD | AP17: SALUD | AR17: LEGAL | AT17: LEGAL | AV17: LEGAL | AX17: LEGAL | BD17: RC.4.4.5. Atender oportunamente las solicitudes provenientes de las comunidades, la región y Potosí.
C18: 1 | P18: Estructuras a baja altura o con partes salientes | R18: Deslizamiento / Desprendimiento | T18: E.P.P. | X18: Seguimiento al programa de mantenimientos de equipos/ vehículos | Z18: Descarga de efluentes de área de mina | AB18: Efecto negativo sobre la estabilidad física de taludes | AD18: Verificación de velocidad de vehículos | AJ18: salud | AL18: SALUD | AN18: SALUD | AP18: SALUD | AR18: LEGAL | AT18: LEGAL | AV18: LEGAL | AX18: LEGAL
C19: 2 | J19: Jerarquía del Control - M.A. | K19: Calidad del Control-Medio Ambiente | P19: Gases comprimidos (transporte, uso, manipulación botellones) | R19: Desmoronamiento | X19: Seguimiento y publicación de reportes de velocidades | Z19: Emanación de olores | AB19: Efecto negativo sobre la salud humana | AD19: Simulacros de emergencia (Derrame) | AJ19: salud | AL19: SALUD | AN19: SALUD | AP19: SALUD | AR19: LEGAL | AT19: LEGAL | AV19: LEGAL | AX19: LEGAL
C20: 3 | K20: Efectividad del Control | L20: C. Menor a 50% | M20: B. 50% y 80% | N20: A. Mayor 80% | P20: Inestabilidad de taludes / terrenos | R20: Encandilamiento | X20: Seguimiento y publicación de reporte STOP o Seguimiento y publicación de reporte de observaciones conductuales | Z20: Emisión de gases de fuentes fijas/ incinerador, laboratorios, talleres y otros | AB20: Efectos fisiológicos sobre la salud humana | AD20: Hojas de seguridad de sustancias peligrosas | AJ20: salud | AL20: SALUD | AN20: SALUD | AP20: SALUD | AR20: LEGAL | AT20: LEGAL | AV20: LEGAL | AX20: LEGAL
C21: 4 | K21: 6. Eliminación | L21: Control/Acción Satisfactorio | M21: Control/Acción Satisfactorio | N21: Control/Acción Eficaz | P21: Izaje mecanizado de materiales / cargas suspendidas | R21: Estrés térmico, Exposición a ambientes fríos o calurosos | X21: Seguimiento a los programas preventivos y de control en salud | Z21: Emisión de gases de fuentes móviles/ vehículos | AB21: Pérdida de biodiversidad en áreas protegidas o restringidas | AD21: Autorización por instancia competente - sustancias peligrosas | AJ21: salud
C22: 5 | K22: 5. Sustitución/ Minimización | L22: Control/Acción Satisfactorio | M22: Control/Acción Satisfactorio | N22: Control/Acción Eficaz | P22: Manejo Manual de Carga / materiales | R22: Explosión | X22: Seguimiento y publicación de reportes/informes e indicadores internos | Z22: Emisión de sustancias agotadores de la capa de ozono/ sistemas de refrigeración | AB22: Pérdida de la cobertura vegetal | AD22: Señalización de sustancias y residuos peligrosos | AJ22: salud
K23: 4. Ingeniería | L23: Control/Acción No Eficaz | M23: Control/Acción Satisfactorio | N23: Control/Acción Eficaz | P23: Manejo Mecanizado de Materiales | R23: Exposición a Agentes biológicos | Z23: Extracción de recursos naturales no renovables/ minerales | AB23: Pérdida del patrimonio cultural/ arqueología | AD23: Higienización | AJ23: salud
K24: 3. Señalización/ Advertencias/ Alarma | L24: Control/Acción No Eficaz | M24: Control/Acción Satisfactorio | N24: Control/Acción Eficaz | P24: Manipulación/uso de herramientas, instrumentos, objetos (cortantes, punzantes, calientes, pesados, sin Verificación / Calibración, etc.) | R24: Exposición a Ambiente con Deficiencia de Oxígeno (Sofocación) | Z24: Extracción de recursos naturales renovables/ agregados para construcciones | AB24: Efecto invernadero cambio climático | AD24: Involucramiento del supervisor a través de inspecciones internas y otros | AJ24: salud
K25: 2. Administrativo/ Procedimientos/ Capacitación | L25: Control/Acción No Eficaz | M25: Control/Acción Satisfactorio | N25: Control/Acción Eficaz | P25: Piscinas, tazones, tanques o estanques sin protección | R25: Exposición a Ambiente/Atmósfera Peligrosa/Contaminada | Z25: Generación de polvo | AB25: Efectos a la biota | AD25: Certificaciones | AJ25: salud
K26: 1. EPP | L26: Control/Acción No Eficaz | M26: Control/Acción No Eficaz | N26: Control/Acción Satisfactorio | P26: Presencia de polvo, material particulado, humo o gas | R26: Exposición a Atmósfera Explosiva | Z26: Generación de residuos sólidos convencionales, orgánicos e industriales | AB26: Efectos a la biota de suelo y fauna | AD26: Control de emergencias ambientales | AJ26: salud
P27: Proyección de fragmentos de roca, materiales, partículas | R27: Exposición a Atmósfera Inflamable | Z27: Generación de ruido | AB27: Erosión al suelo, efecto a la calidad del suelo natural | AD27: Instructivos, procedimientos operacionales | AJ27: salud
J28: Jerarquía del Control - Salud | K28: Calidad del Control-Salud | P28: Psicosociales (Acoso, mobbing) | R28: Exposición a Condiciones Ergonómicas Ambientales / de Diseño del Puesto de Trabajo | Z28: Generación y disposición de residuos hospitalarios | AB28: Pérdida de recursos culturales | AD28: Instructivos generales y específicos | AJ28: salud
K29: Efectividad del Control | L29: C. Menor a 50% | M29: B. 50% y 80% | N29: A. Mayor 80% | P29: Remoción y limpieza de materiales acumulados | R29: Exposición a Humos Metálicos | Z29: Generación y disposición de residuos minero-metalúrgicos | AB29: Riesgos de derrames y efecto al suelo y aguas | AD29: Capacitación en manejo del proceso, sustancias, residuos y otros
K30: 6. Eliminación | L30: Control/Acción Satisfactorio | M30: Control/Acción Satisfactorio | N30: Control/Acción Eficaz | P30: Superficie Irregular, con obstrucciones, desnivelada, resbaladiza, congelada y/o blanda | R30: Exposición a Material Particulado | Z30: Generación y disposición de residuos peligrosos | AD30: Competencia para ejercer cargo
K31: 5. Sustitución/ Minimización | L31: Control/Acción Satisfactorio | M31: Control/Acción Satisfactorio | N31: Control/Acción Eficaz | P31: Superficies / partículas calientes | R31: Exposición a Ondas Expansivas | Z31: Incineración de residuos hospitalarios | AD31: Instructivos generales y específicos
K32: 4. Ingeniería | L32: Control/Acción No Eficaz | M32: Control/Acción Satisfactorio | N32: Control/Acción Eficaz | P32: Sustancias peligrosas (transporte, uso, manipulación) | R32: Exposición a Radiaciones Ionizantes / No ionizantes / UV | Z32: Manejo y consumo de sustancias peligrosas | AD32: Capacitación manejo del proceso, sustancias, residuos y otros
K33: 3. Señalización/ Advertencias/ Alarma | L33: Control/Acción No Eficaz | M33: Control/Acción Satisfactorio | N33: Control/Acción Eficaz | P33: Trabajo / circulación de equipo/vehículo (pesado / liviano) | R33: Exposición a Ruido | Z33: Remoción y manejo de top soil | AD33: Competencia para ejercer cargo
K34: 2. Administrativo/ Procedimientos/ Capacitación | L34: Control/Acción No Eficaz | M34: Control/Acción Satisfactorio | N34: Control/Acción Eficaz | P34: Trabajo en altura, sobre plataformas elevadas, escaleras, andamios, rampas o pisos sin barreras de protección (barandas o barreras rígidas). | R34: Exposición a Sustancias Peligrosas | Z34: Revegetación con especies introducidas | AD34: Planes de manejo de recursos naturales, riego, polvo, revegetación
K35: 1. EPP | L35: Control/Acción No Eficaz | M35: Control/Acción No Eficaz | N35: Control/Acción Satisfactorio | P35: Trabajo en caliente (soldadura, corte, desbaste) torchado, arco eléctrico, amolado, esmerilado, oxicorte, oxiflama, etc. | R35: Exposición a Vibración | Z35: Topografía y paisaje natural | AD35: Competencias
P36: Trabajo en Espacios Confinados (Clase I o II) | R36: Exposición a factores Psicosociales / Tensiones Mentales, Físicas o Fisiológicas | Z36: Uso de áreas protegidas o de recursos arqueológicos
J37: Jerarquía del Control - Legal | K37: Calidad del Control-Legal | P37: Trabajo en excavación (zanjas, aperturas, perforaciones, todo trabajo dentro una excavación) | R37: Golpeado contra | Z37: Gestión de lubricantes
K38: Efectividad del Control | L38: C. Menor a 50% | M38: B. 50% y 80% | N38: A. Mayor 80% | P38: Trabajos en cercanía de líneas eléctricas energizadas, tableros eléctricos, etc. | R38: Golpeado por | Z38: Gestión de sustancias peligrosas
K39: 6. Eliminación | L39: Control/Acción Satisfactorio | M39: Control/Acción Satisfactorio | N39: Control/Acción Eficaz | P39: Trabajos en cercanías de taludes o botaderos | R39: Incendio | Z39: Incineración de residuos hospitalarios
K40: 5. Sustitución/ Minimización | L40: Control/Acción Satisfactorio | M40: Control/Acción Satisfactorio | N40: Control/Acción Eficaz | P40: Tránsito de peatones en áreas de circulación vehicular o de equipos | R40: Inmersión | Z40: Incineración de residuos sólidos
K41: 4. Ingeniería | L41: Control/Acción No Eficaz | M41: Control/Acción Satisfactorio | N41: Control/Acción Eficaz | P41: Transporte de carga en movilidad o equipo móvil | R41: Liberación de energía peligrosa (hidráulica, neumática, eléctrica, radioactiva, etc.) | Z41: Intervención a lugares arqueológicos
K42: 3. Señalización/ Advertencias/ Alarma | L42: Control/Acción No Eficaz | M42: Control/Acción Satisfactorio | N42: Control/Acción Eficaz | P42: Transporte, manipulación o uso de explosivos | R42: Sobre esfuerzo | Z42: Lixiviación de residuos sólidos
K43: 2. Administrativo/ Procedimientos/ Capacitación | L43: Control/Acción No Eficaz | M43: Control/Acción Satisfactorio | N43: Control/Acción Eficaz | P43: Variables ergonómicas (movimientos repetitivos, posiciones incómodas, fatiga, estrés, sobre carga de trabajo, etc.) | R43: Tropezón | Z43: Manejo y consumo de sustancias peligrosas
K44: 1. EPP | L44: Control/Acción No Eficaz | M44: Control/Acción No Eficaz | N44: Control/Acción Satisfactorio | P44: Otros | R44: Vuelco | Z44: Remoción de la capa vegetal del suelo-top soil
P45: N/A | R45: Otros | Z45: Remoción de lugares de patrimonio social de la comunidad
J46: Jerarquía del Control - Rel. G | K46: Calidad del Control-Relaciones Gubernamentales | R46: N/A | Z46: Remoción de lugares propios de la fauna silvestre
K47: Efectividad del Control | L47: C. Menor a 50% | M47: B. 50% y 80% | N47: A. Mayor 80%
K48: 6. Eliminación | L48: Control/Acción Satisfactorio | M48: Control/Acción Satisfactorio | N48: Control/Acción Eficaz
K49: 5. Sustitución/ Minimización | L49: Control/Acción Satisfactorio | M49: Control/Acción Satisfactorio | N49: Control/Acción Eficaz
K50: 4. Ingeniería | L50: Control/Acción No Eficaz | M50: Control/Acción Satisfactorio | N50: Control/Acción Eficaz
K51: 3. Señalización/ Advertencias/ Alarma | L51: Control/Acción No Eficaz | M51: Control/Acción Satisfactorio | N51: Control/Acción Eficaz
K52: 2. Administrativo/ Procedimientos/ Capacitación | L52: Control/Acción No Eficaz | M52: Control/Acción Satisfactorio | N52: Control/Acción Eficaz
K53: 1. EPP | L53: Control/Acción No Eficaz | M53: Control/Acción No Eficaz | N53: Control/Acción Satisfactorio
J55: Jerarquía del Control - OPERACIONALES | K55: Calidad del Control-OPERACIONALES
K56: Efectividad del Control | L56: C. Menor a 50% | M56: B. 50% y 80% | N56: A. Mayor 80%
K57: 6. Eliminación | L57: Control/Acción Satisfactorio | M57: Control/Acción Satisfactorio | N57: Control/Acción Eficaz
K58: 5. Sustitución/ Minimización | L58: Control/Acción Satisfactorio | M58: Control/Acción Satisfactorio | N58: Control/Acción Eficaz
K59: 4. Ingeniería | L59: Control/Acción No Eficaz | M59: Control/Acción Satisfactorio | N59: Control/Acción Eficaz
K60: 3. Señalización/ Advertencias/ Alarma | L60: Control/Acción No Eficaz | M60: Control/Acción Satisfactorio | N60: Control/Acción Eficaz
K61: 2. Administrativo/ Procedimientos/ Capacitación | L61: Control/Acción No Eficaz | M61: Control/Acción Satisfactorio | N61: Control/Acción Eficaz
K62: 1. EPP | L62: Control/Acción No Eficaz | M62: Control/Acción No Eficaz | N62: Control/Acción Satisfactorio
J64: Jerarquía del Control - FINANCIEROS | K64: Calidad del Control-FINANCIEROS
K65: Efectividad del Control | L65: C. Menor a 50% | M65: B. 50% y 80% | N65: A. Mayor 80%
K66: 6. Eliminación | L66: Control/Acción Satisfactorio | M66: Control/Acción Satisfactorio | N66: Control/Acción Eficaz
K67: 5. Sustitución/ Minimización | L67: Control/Acción Satisfactorio | M67: Control/Acción Satisfactorio | N67: Control/Acción Eficaz
K68: 4. Ingeniería | L68: Control/Acción No Eficaz | M68: Control/Acción Satisfactorio | N68: Control/Acción Eficaz
K69: 3. Señalización/ Advertencias/ Alarma | L69: Control/Acción No Eficaz | M69: Control/Acción Satisfactorio | N69: Control/Acción Eficaz
K70: 2. Administrativo/ Procedimientos/ Capacitación | L70: Control/Acción No Eficaz | M70: Control/Acción Satisfactorio | N70: Control/Acción Eficaz
K71: 1. EPP | L71: Control/Acción No Eficaz | M71: Control/Acción No Eficaz | N71: Control/Acción Satisfactorio
AX92: PLANIFICACIÓN E INFORME DE INDICADORES GESTIÓN 2020 RRCC | BB92: PLANIFICACIÓN E INFORME DE INDICADORES GESTIÓN 2020 RRCC
AX93: PLANIFICACIÓN E INFORME DE INDICADORES GESTIÓN 2020 RRCC | BB93: PLANIFICACIÓN E INFORME DE INDICADORES GESTIÓN 2020 RRCC
AX94: PLANIFICACIÓN E INFORME DE INDICADORES GESTIÓN 2020 RRCC | BB94: PLANIFICACIÓN E INFORME DE INDICADORES GESTIÓN 2020 RRCC
AX95: PLANIFICACIÓN E INFORME DE INDICADORES GESTIÓN 2020 RRCC | BB95: PLANIFICACIÓN E INFORME DE INDICADORES GESTIÓN 2020 RRCC
AX96: PLANIFICACIÓN E INFORME DE INDICADORES GESTIÓN 2020 RRCC | BB96: PLANIFICACIÓN E INFORME DE INDICADORES GESTIÓN 2020 RRCC
AX97: PLANIFICACIÓN E INFORME DE INDICADORES GESTIÓN 2020 RRCC | BB97: PLANIFICACIÓN E INFORME DE INDICADORES GESTIÓN 2020 RRCC
AX98: PLANIFICACIÓN E INFORME DE INDICADORES GESTIÓN 2020 RRCC | BB98: PLANIFICACIÓN E INFORME DE INDICADORES GESTIÓN 2020 RRCC
AX99: PLANIFICACIÓN E INFORME DE INDICADORES GESTIÓN 2020 RRCC | BB99: PLANIFICACIÓN E INFORME DE INDICADORES GESTIÓN 2020 RRCC
AX100: PLANIFICACIÓN E INFORME DE INDICADORES GESTIÓN 2020 RRCC | BB100: PLANIFICACIÓN E INFORME DE INDICADORES GESTIÓN 2020 RRCC
AX101: PLANIFICACIÓN E INFORME DE INDICADORES GESTIÓN 2020 RRCC | BB101: PLANIFICACIÓN E INFORME DE INDICADORES GESTIÓN 2020 RRCC
AX102: PLANIFICACIÓN E INFORME DE INDICADORES GESTIÓN 2020 RRCC | BB102: PLANIFICACIÓN E INFORME DE INDICADORES GESTIÓN 2020 RRCC
AX103: PLANIFICACIÓN E INFORME DE INDICADORES GESTIÓN 2020 RRCC | BB103: PLANIFICACIÓN E INFORME DE INDICADORES GESTIÓN 2020 RRCC
... AX123: PLANIFICACIÓN E INFORME DE INDICADORES GESTIÓN 2020 DS | BB123: PLANIFICACIÓN E INFORME DE INDICADORES GESTIÓN 2020 DS
BB124: PLANIFICACIÓN E INFORME DE INDICADORES GESTIÓN 2020 RRCC
AX172: PLANIFICACIÓN E INFORME DE INDICADORES GESTIÓN 2020 RRCC
BE390: Recibir información constante de medios de comunicación y del grupo de enlaces comunitarios
