Workbook
Name Archivo: #REF!
Name Archivo: #REF!
Name data_supervision_: Sheet1!$P$2:$Y$154
Name data_supervision_: #REF!
Name Empresa: #REF!
Name Empresa: #REF!
Name Gerencia: #REF!
Name Gerencia: #REF!
Name SuperIntendencia: #REF!
Name SuperIntendencia: #REF!
Name Supervision: #REF!
Name Supervision: #REF!
Name tbl_Archivo: #REF!
Name tbl_Archivo: #REF!
Name tbl_Empresa: #REF!
Name tbl_Empresa: #REF!
Name tbl_gerencia: #REF!
Name tbl_gerencia: #REF!
Name tbl_SuperIntendencia: #REF!
Name tbl_SuperIntendencia: #REF!
Name tbl_Supervision: #REF!
Name tbl_Supervision: #REF!
Name tbl_version: #REF!
Name tbl_version: #REF!
Name tbl_vice: #REF!
Name tbl_vice: #REF!
Name version: #REF!
Name version: #REF!
Name Vicepresidencia: #REF!
Name Vicepresidencia: #REF!

Sheet MSC Lista Verific. Inspeccion
C1: INSPECCIÓN DE SEGURIDAD OPERATIVA (ISOP) | N1: 1.02.P06.F12 Revisión: 8
N3: INTERNA
A6: INFORMACIÓN GENERAL
A8: Gerencia: | C8: {=IFERROR(INDEX(Sheet1!AB3:AB437, MATCH(H8, Sheet1!Z3:Z437, 0)),"")} | F8: Supervisor: | M8: Inspección N°:
A9: Superintendencia: | C9: {=IFERROR(INDEX(Sheet1!AC3:AC437, MATCH(H8, Sheet1!Z3:Z437, 0)),"")} | F9: Lugar inspeccionado: | K9: Empresa: | M9: MSC
A10: Área: | C10: {=IFERROR(INDEX(Sheet1!AF3:AF437, MATCH(H8, Sheet1!Z3:Z437, 0)),"")} | F10: Fecha inspección (yyyy-mm-aa): | M10: Codigo: | N10: =IF(ISBLANK(H8),"",CONCATENATE("V",E11,"-G",F11,"-S",G11,"-SP",H11,"-AR",I11,"-E",J11,"-A01","-VR00","-F",TEXT(H10, "yyyymmdd")))
E11: {=INDEX(Sheet1!U3:U437, MATCH(H8, Sheet1!Z3:Z437, 0))} -> #N/A | F11: {=INDEX(Sheet1!V3:V437, MATCH(H8, Sheet1!Z3:Z437, 0))} -> #N/A | G11: {=IFERROR(INDEX(Sheet1!W3:W437, MATCH(H8, Sheet1!Z3:Z437, 0)),"")} | H11: {=IFERROR(INDEX(Sheet1!X3:X437, MATCH(H8, Sheet1!Z3:Z437, 0)),"")} | I11: {=IFERROR(INDEX(Sheet1!BJ3:BJ107, MATCH(C10, Sheet1!BK3:BK107, 0)),"")} | J11: {=IFERROR(INDEX(Sheet1!AM3:AM147, MATCH(M9, Sheet1!AN3:AN147, 0)),"")} -> 000
A12: EQUIPO DE INSPECCIÓN
A13: Nombre | F13: CARGO | N13: FIRMA
A14: 1.-
A15: 2.-
A16: 3.-
A17: 4.-
A18: 5.-
A19: 6.-
A21: VALORACIÓN & CRITERIO: | G21: CONFORMACIÓN DEL EQUIPO DE INSPECCIÓN
A22: Valoración | C22: Criterio | G22: ISOP para MSC | L22: ISOP para EECC
A23: 0 | C23: El ítem NO cumple o cumple menos del 50% de las veces (el ítem tiene más de dos desviaciones) | G23: Supervisor/coordinador del área inspeccionada. | L23: Supervisor de contrato
A24: 1 | C24: El ítem cumple entre el 51% al 70% de las veces (el ítem tiene dos desviaciones) | G24: Trabajadores del área por lo menos 1. | L24: Responsable de la EECC
A25: 2 | C25: El ítem cumple entre el 71% al 90% de las veces (el ítem tiene máximo una desviación) | G25: Personal de áreas invitadas por lo menos 1 | L25: Trabajadores de la EECC por lo menos 1.
A26: 3 | C26: El ítem cumple a cabalidad más del 91% (el ítem no tiene desviaciones) | G26: Comité Mixto por lo menos 1 (si se tiene en el área) | L26: Personal de MSC invitadas por lo menos 1
A27: N/A | C27: El ítem no es aplicable | L27: Comité Mixto por lo menos 1 o coordinador
A28: Nota | C28: El ítem en color rojo es obligatorio; si se coloca N/A, se debe justificar en los comentarios el motivo por el cual NO APLICA. | L28: Personal de HSEQ
A30: LISTA DE VERIFICACIÓN:
A31: A. INSPECCIÓN ISOP | F31: % Cumplimiento Global: | N31: =(F32+F46+F66+F75+F88+F134+F145)/(E32+E46+E66+E75+E88+E134+E145) -> 0
A32: 1. ORDEN Y ASEO (5Ss) | D32: Máximo Puntaje: | E32: =COUNTIF(F34:F45,"<>"&$A$27)*3 -> 36 | F32: =SUM(F34:F45) -> 0 | G32: Comentarios
D33: % Cumplimiento Alcanzado: | E33: =F32/E32 -> 0
A34: 1.1 | B34: ¿Se encuentran los materiales almacenados considerando tipo, categorías y grupo? (Ej. Eléctrico - Palas - Mangueras)?
A35: 1.2 | B35: ¿Los pasillos de circulación están libres de materiales u objetos que obstaculicen el tránsito?
A36: 1.3 | B36: ¿Las vías de circulación están demarcadas con franjas en áreas donde existen equipos, maquinarias, materiales que afecten a la libre circulación (Área de operación y/o Almacen)?
A37: 1.4 | B37: ¿Las estructuras de almacenamiento a baja altura están señalizadas y se controla el riesgo de "golpeado contra"?
A38: 1.5 | B38: ¿El lugar de trabajo se encuentra limpio, libre de residuos y desechos (en el piso u otros lugares que no sean basureros)?
A39: 1.6 | B39: ¿Se cuenta con recipientes (basureros) para la clasificación de residuos e identificados según el residuo que contiene?
A40: 1.7 | B40: ¿Los residuos se depositan en los recipientes que corresponden obedeciendo a su clasificación?
A41: 1.8 | B41: ¿Se promueve las 5'S (Clasificación, Orden, Limpieza, Normalización y Disciplina) en el lugar de trabajo mediante afiches o señalética?
A42: 1.9 | B42: ¿Las instalaciones cuentan con registro de sanitización, desratización, etc.?
A43: 1.10 | B43: ¿Los cables eléctricos están instalados (canalizados) de manera que no hay riesgo de tropiezos o daños a su aislamiento?
A44: 1.11 | B44: ¿Los materiales que puedan rodar están asegurados con cuñas, tacos u otros elementos que impidan su desplazamiento?
A45: 1.12 | B45: ¿Se encuentran todas las luminarias en funcionamiento, limpias y sin presentar opacidad notoria?
A46: 2. PREPARACIÓN PARA EMERGENCIAS | D46: Máximo Puntaje: | E46: =((COUNTIF(F49:F65,"<>"&$A$27)*3)) -> 51 | F46: =SUM(F49:F65) -> 0 | G46: Comentarios
D47: % Cumplimiento Alcanzado: | E47: =F46/E46 -> 0
A48: General | F48: =SUM(F49:F65) -> 0
A49: 2.1 | B49: ¿Las vías de evacuación y punto de reunión se encuentran expeditas, señalizadas, para garantizar una evacuación segura? Según la RM 849/2014
A50: 2.2 | B50: ¿Todos los trabajadores conocen el protocolo de comunicación de emergencias establecido en el Plan de Gestión de emergencias de MSC 3.02.P01.PL01. Como el 71227742 , 911, canal 6 (mina), canal 5? (Es necesario consultar a 3 personas para verificar esta información)
A51: 2.3 | B51: ¿Se realizó la inspección mensual de los sistemas de emergencia y se envió la evidencia al área de Emergencias (solo sistemas de emergencias propiedad de MSC)? (últimos 3 meses)
A52: 2.4 | B52: Se realiza el seguimiento de los hallazgos identificados de la inspección de sistemas de emergencias?
A53: 2.5 | B53: ¿Se cuenta con un listado ACTUALIZADO del personal para realizar el conteo en caso de evacuación (3.02.P01.F23 Registro de Personal para Conteo en Evacuación)?
A54: 2.6 | B54: ¿Los extintores portátiles se encuentran con su manómetro o indicador de presión en la posición o rango operable (zona verde), o en el caso de extintor de químico seco operado por cartucho, con el indicador de presión desactivado (abajo)?
A55: 2.7 | B55: ¿El adhesivo de identificación e instrucciones del extintor se encuentra visible y en estado legible?
A56: 2.8 | B56: ¿Los extintores portátiles se encuentran con su tarjeta de mantenimiento, con la fecha actualizada y vigente?
A57: 2.9 | B57: ¿Los extintores portátiles se inspeccionan mensualmente y se registra correctamente en la tarjeta de inspección correspondiente?
A58: 2.10 | B58: ¿Los extintores portátiles se mantienen limpios (libre de polvo u otras sustancias) y se encuentren en el lugar establecido?
A59: 2.11 | B59: ¿Los extintores que están expuestos a la intemperie se encuentran libres de daños por oxidación u otro posible deterioro?
A60: 2.12 | B60: ¿Los extintores portátiles cuentan con su soporte correctamente instalado, firme y asegurado, además de la señalización claramente visible?
... A65: 2.17 | B65: Los detectores de incendio se encuentran operativos? (ver destello intermitente color luz verde en dispositivo)
A66: 3. ELEMENTOS DE PROTECCIÓN PERSONAL | D66: Máximo Puntaje: | E66: =(COUNTIF(F68:F74,"<>"&$A$27))*3 -> 21 | F66: =SUM(F68:F74) -> 0 | G66: Comentarios
D67: % Cumplimiento Alcanzado: | E67: =F66/E66 -> 0
A68: 3.1 | B68: ¿El personal cuenta con el Equipo de Protección Personal (EPP) básico?
A69: 3.2 | B69: ¿El personal conoce y utiliza correctamente su Equipo de Protección Personal (EPP)?
A70: 3.3 | B70: ¿Los Equipo de Protección Personal (EPP) inspeccionados se encuentran sin un desgaste excesivo? (Inspeccionar los EPP de 3 trabajadores al azar)
A71: 3.4 | B71: ¿Los Equipos de Protección Personal (EPP) inspeccionados se encuentran sin deformaciones? (Inspeccionar los EPP de 3 trabajadores al azar)
A72: 3.5 | B72: ¿Los Equipos de Protección Personal (EPP) inspeccionados son de uso personal? (Inspeccionar los EPP de 3 trabajadores al azar)
A73: 3.6 | B73: ¿Los Equipos de Protección Personal (EPP) inspeccionados son los proporcionados por la empresa y se encuentran sin alteraciones en su diseño original? (Inspeccionar los EPP de 3 trabajadores al azar)
A74: 3.7 | B74: ¿El personal cuenta con Equipos de Protección Personal (EPP) adicionales de acuerdo a los riesgos específicos de su labor? (Inspeccionar los EPP de 3 trabajadores al azar)
A75: 4. HERRAMIENTAS DE MANO | D75: Máximo Puntaje: | E75: =COUNTIF(F77:F87,"<>"&$A$27)*3 -> 33 | F75: =SUM(F77:F87) -> 0 | G75: Comentarios
D76: % Cumplimiento Alcanzado: | E76: =F75/E75 -> 0
A77: 4.1 | B77: ¿Las herramientas se encuentran almacenadas en tableros, maletas o cajas portaherramientas designadas para su almacenamiento?
A78: 4.2 | B78: ¿Las herramientas fueron inspeccionadas y cuentan con la codificación correspondiente al trimestre actual?
A79: 4.3 | B79: ¿Las herramientas cuentan con sus mangos sanos y limpios, libres de astillas, rebabas o grasa?
A80: 4.4 | B80: ¿Los mazos de las herramientas de golpe están libres de rebabas y con zonas de impacto no redondeadas?
A81: 4.5 | B81: ¿Las herramientas eléctricas cuentan con mangos y protecciones de fábrica?
A82: 4.6 | B82: ¿Las herramientas eléctricas cuentan con conexión a tierra o doble aislamiento?
A83: 4.7 | B83: ¿Las herramientas eléctricas cuentan con su cable de alimentación en buenas condiciones, sin daños en su aislación, clavija o conexión al equipo?
A84: 4.8 | B84: ¿Las herramientas eléctricas y sus conductores de alimentación se encuentran libres de contacto con la humedad?
A85: 4.9 | B85: ¿Se observaron herramientas hechizas en el área de trabajo?
A86: 4.10 | B86: ¿Las herramientas en mal estado se encuentran identificadas con cinta de color rojo o tarjeta de "Fuera de Servicio" y lejos del alcance del personal ?
A87: 4.11 | B87: ¿El trabajador utiliza la herramienta para los fines que fue diseñada y fabricada?. Observar a 3 trabajadores
A88: 5.- INSTALACIONES DE FAENA/ OFICINAS | D88: Máximo Puntaje: | E88: =((COUNTIF(F91:F98,"<>"&$A$27)*3)+(COUNTIF(F100:F102,"<>"&$A$27)*3)+(COUNTIF(F104:F108,"<>"&$A$27)*3)+(COUNTIF(F110:F133,"<>"&$A$27)*3)) -> 120 | F88: =SUM(F90+F99+F103+F109) -> 0 | G88: Comentarios
D89: % Cumplimiento Alcanzado: | E89: =F88/E88 -> 0
A90: Oficinas y otros ambientes | F90: =SUM(F91:F98) -> 0
A91: 5.1 | B91: ¿En todos los aparatos y tomas de corriente eléctrica incluyendo los Schuko, se indica claramente su tensión?
A92: 5.2 | B92: ¿Los cables eléctricos se encuentran canalizados?. No incluye los cables de computadoras, teléfonos u otros
A93: 5.3 | B93: Los cables de las computadoras, teléfonos, celulares u otros, están ordenados y sujetados.
A94: 5.4 | B94: ¿Todos los equipos e instalaciones eléctricas han sido construidos, instalados y conservados de manera que prevengan el peligro de contacto con elementos energizados y el riesgo de incendio?
A95: 5.5 | B95: ¿Las repisas están ordenadas y sin riesgo de caída de elementos desde altura?
A96: 5.6 | B96: ¿Las sillas o asientos se encuentran limpios, en buen estado, con patas firmes, respaldo en su lugar, apoya brazos y tapiz sin daños?
A97: 5.7 | B97: ¿Las sillas o asientos cuentan con regulación de altura y ángulo de trabajo?
A98: 5.8 | B98: ¿Los cajones de escritorios se encuentran en buen estado, alineados en su guía y con su fondo firme y limpio?
A99: Calefactores Verticales, Calefactores de Radiación para techo/pared, Estufas | F99: =SUM(F100:F102) -> 0
A100: 5.9 | B100: Se realiza las inspecciones mensuales a los calefactores verticales, de techo o estufas según formulario 1.02.P06.F72 Inspección de Calefactores Verticales, Techo y Estufas.
A101: 5.10 | B101: ¿Los calefactores verticales, calefactores de radiación para techo, estufas se encuentran funcionando según sus capacidades definidas?.
A102: 5.11 | B102: Los calefactores verticales, estufas cuentan con su sistema de conexión eléctrica sin daños o deterioros.
A103: Cafeterías | F103: =SUM(F104:F108) -> 0
A104: 5.12 | B104: ¿El termo o caldera eléctrica se encuentra en un lugar seguro, sin riesgo de caídas o volcamiento, con su cable de alimentación en buenas condiciones, sin daños en su aislación, clavija o conexión al equipo?
A105: 5.13 | B105: ¿Las zonas de almacenamiento de alimentos se encuentran limpias y ordenadas?, los alimentos o conservas están dentro su fecha de vencimiento
A106: 5.14 | B106: ¿Las superficies de los muebles y mesones son lisas y de fácil limpieza?
A107: 5.15 | B107: ¿Se cuenta con abastecimiento de agua ?
A108: 5.16 | B108: ¿Los refrigeradores se encuentran limpios, sin alimentos vencidos o guardados por mucho tiempo?
A109: Duchas, Vestidores y Servicios Higiénicos | F109: =SUM(F110:F133) -> 0
A110: 5.17 | B110: ¿Existe registro de la sanitización o desinfección de las duchas, vestidores y servicios higiénicos (con certificado pegado en la instalación)?
...

Sheet ISOP
A1: codigo | B1: ID | C1: Gerencia | D1: SuperIntendencia | E1: Area | F1: Supervisor | G1: Lugar | H1: Fecha_Inspeccion | I1: Nro_Inspeccion | J1: Regla_oro | K1: Persona_Inspeccion1 | L1: Persona_Inspeccion2 | M1: Persona_Inspeccion3 | N1: Persona_Inspeccion4 | O1: Persona_Inspeccion5 | P1: Persona_Inspeccion6 | Q1: cargo1 | R1: cargo2 | S1: cargo3 | T1: cargo4 | U1: cargo5 | V1: cargo6 | W1: Aspectos_positivos_encontrados | X1: Aspectos_adicionales_encontrados
A2: ='MSC Lista Verific. Inspeccion'!N10 | B2: =TEXT($H$2,"yyyymmdd")&"-"&$G$2&"-"&TEXT(NOW(),"yyyymmddHHMMSS") -> yyyy0100-0-yyyy1003110802 | C2: ='MSC Lista Verific. Inspeccion'!C8 | D2: ='MSC Lista Verific. Inspeccion'!C9 | E2: ='MSC Lista Verific. Inspeccion'!C10 | F2: ='MSC Lista Verific. Inspeccion'!H8 -> 0 | G2: ='MSC Lista Verific. Inspeccion'!H9 -> 0 | H2: ='MSC Lista Verific. Inspeccion'!H10 -> 0 | I2: ='MSC Lista Verific. Inspeccion'!N8 -> 0 | J2: ='MSC Lista Verific. Inspeccion'!C1 -> INSPECCIÓN DE SEGURIDAD OPERATIVA (ISOP) | K2: ='MSC Lista Verific. Inspeccion'!B14 -> 0 | L2: ='MSC Lista Verific. Inspeccion'!B15 -> 0 | M2: ='MSC Lista Verific. Inspeccion'!B16 -> 0 | N2: ='MSC Lista Verific. Inspeccion'!B17 -> 0 | O2: ='MSC Lista Verific. Inspeccion'!B18 -> 0 | P2: ='MSC Lista Verific. Inspeccion'!B19 -> 0 | Q2: ='MSC Lista Verific. Inspeccion'!F14 -> 0 | R2: ='MSC Lista Verific. Inspeccion'!F15 -> 0 | S2: ='MSC Lista Verific. Inspeccion'!F16 -> 0 | T2: ='MSC Lista Verific. Inspeccion'!F17 -> 0 | U2: ='MSC Lista Verific. Inspeccion'!F18 -> 0 | V2: ='MSC Lista Verific. Inspeccion'!F19 -> 0 | W2: =_xludf.CONCAT('MSC Lista Verific. Inspeccion'!A166," ",'MSC Lista Verific. Inspeccion'!A167) -> #NAME? | X2: =_xludf.CONCAT('MSC Lista Verific. Inspeccion'!A169," ",'MSC Lista Verific. Inspeccion'!A170," ") -> #NAME?

Sheet ISOP2
A1: ID | B1: Item | C1: Sub_Item | D1: valor | E1: comentario
A2: =ISOP!$B$2 -> yyyy0100-0-yyyy1003110802 | B2: ='MSC Lista Verific. Inspeccion'!$A$32 -> 1. ORDEN Y ASEO (5Ss) | C2: ='MSC Lista Verific. Inspeccion'!A34 -> 1.1 | D2: ='MSC Lista Verific. Inspeccion'!F34 -> 0 | E2: ='MSC Lista Verific. Inspeccion'!G34 -> 0
A3: =ISOP!$B$2 -> yyyy0100-0-yyyy1003110802 | B3: ='MSC Lista Verific. Inspeccion'!$A$32 -> 1. ORDEN Y ASEO (5Ss) | C3: ='MSC Lista Verific. Inspeccion'!A35 -> 1.2 | D3: ='MSC Lista Verific. Inspeccion'!F35 -> 0 | E3: ='MSC Lista Verific. Inspeccion'!G35 -> 0
A4: =ISOP!$B$2 -> yyyy0100-0-yyyy1003110802 | B4: ='MSC Lista Verific. Inspeccion'!$A$32 -> 1. ORDEN Y ASEO (5Ss) | C4: ='MSC Lista Verific. Inspeccion'!A36 -> 1.3 | D4: ='MSC Lista Verific. Inspeccion'!F36 -> 0 | E4: ='MSC Lista Verific. Inspeccion'!G36 -> 0
A5: =ISOP!$B$2 -> yyyy0100-0-yyyy1003110802 | B5: ='MSC Lista Verific. Inspeccion'!$A$32 -> 1. ORDEN Y ASEO (5Ss) | C5: ='MSC Lista Verific. Inspeccion'!A37 -> 1.4 | D5: ='MSC Lista Verific. Inspeccion'!F37 -> 0 | E5: ='MSC Lista Verific. Inspeccion'!G37 -> 0
A6: =ISOP!$B$2 -> yyyy0100-0-yyyy1003110802 | B6: ='MSC Lista Verific. Inspeccion'!$A$32 -> 1. ORDEN Y ASEO (5Ss) | C6: ='MSC Lista Verific. Inspeccion'!A38 -> 1.5 | D6: ='MSC Lista Verific. Inspeccion'!F38 -> 0 | E6: ='MSC Lista Verific. Inspeccion'!G38 -> 0
A7: =ISOP!$B$2 -> yyyy0100-0-yyyy1003110802 | B7: ='MSC Lista Verific. Inspeccion'!$A$32 -> 1. ORDEN Y ASEO (5Ss) | C7: ='MSC Lista Verific. Inspeccion'!A39 -> 1.6 | D7: ='MSC Lista Verific. Inspeccion'!F39 -> 0 | E7: ='MSC Lista Verific. Inspeccion'!G39 -> 0
A8: =ISOP!$B$2 -> yyyy0100-0-yyyy1003110802 | B8: ='MSC Lista Verific. Inspeccion'!$A$32 -> 1. ORDEN Y ASEO (5Ss) | C8: ='MSC Lista Verific. Inspeccion'!A40 -> 1.7 | D8: ='MSC Lista Verific. Inspeccion'!F40 -> 0 | E8: ='MSC Lista Verific. Inspeccion'!G40 -> 0
A9: =ISOP!$B$2 -> yyyy0100-0-yyyy1003110802 | B9: ='MSC Lista Verific. Inspeccion'!$A$32 -> 1. ORDEN Y ASEO (5Ss) | C9: ='MSC Lista Verific. Inspeccion'!A41 -> 1.8 | D9: ='MSC Lista Verific. Inspeccion'!F41 -> 0 | E9: ='MSC Lista Verific. Inspeccion'!G41 -> 0
A10: =ISOP!$B$2 -> yyyy0100-0-yyyy1003110802 | B10: ='MSC Lista Verific. Inspeccion'!$A$32 -> 1. ORDEN Y ASEO (5Ss) | C10: ='MSC Lista Verific. Inspeccion'!A42 -> 1.9 | D10: ='MSC Lista Verific. Inspeccion'!F42 -> 0 | E10: ='MSC Lista Verific. Inspeccion'!G42 -> 0
A11: =ISOP!$B$2 -> yyyy0100-0-yyyy1003110802 | B11: ='MSC Lista Verific. Inspeccion'!$A$32 -> 1. ORDEN Y ASEO (5Ss) | C11: ='MSC Lista Verific. Inspeccion'!A43 -> 1.10 | D11: ='MSC Lista Verific. Inspeccion'!F43 -> 0 | E11: ='MSC Lista Verific. Inspeccion'!G43 -> 0
A12: =ISOP!$B$2 -> yyyy0100-0-yyyy1003110802 | B12: ='MSC Lista Verific. Inspeccion'!$A$32 -> 1. ORDEN Y ASEO (5Ss) | C12: ='MSC Lista Verific. Inspeccion'!A44 -> 1.11 | D12: ='MSC Lista Verific. Inspeccion'!F44 -> 0 | E12: ='MSC Lista Verific. Inspeccion'!G44 -> 0
A13: =ISOP!$B$2 -> yyyy0100-0-yyyy1003110802 | B13: ='MSC Lista Verific. Inspeccion'!$A$32 -> 1. ORDEN Y ASEO (5Ss) | C13: ='MSC Lista Verific. Inspeccion'!A45 -> 1.12 | D13: ='MSC Lista Verific. Inspeccion'!F45 -> 0 | E13: ='MSC Lista Verific. Inspeccion'!G45 -> 0
A14: =ISOP!$B$2 -> yyyy0100-0-yyyy1003110802 | B14: ='MSC Lista Verific. Inspeccion'!$A$46 -> 2. PREPARACIÓN PARA EMERGENCIAS | C14: ='MSC Lista Verific. Inspeccion'!A49 -> 2.1 | D14: ='MSC Lista Verific. Inspeccion'!F49 -> 0 | E14: ='MSC Lista Verific. Inspeccion'!G49 -> 0
A15: =ISOP!$B$2 -> yyyy0100-0-yyyy1003110802 | B15: ='MSC Lista Verific. Inspeccion'!$A$46 -> 2. PREPARACIÓN PARA EMERGENCIAS | C15: ='MSC Lista Verific. Inspeccion'!A50 -> 2.2 | D15: ='MSC Lista Verific. Inspeccion'!F50 -> 0 | E15: ='MSC Lista Verific. Inspeccion'!G50 -> 0
A16: =ISOP!$B$2 -> yyyy0100-0-yyyy1003110802 | B16: ='MSC Lista Verific. Inspeccion'!$A$46 -> 2. PREPARACIÓN PARA EMERGENCIAS | C16: ='MSC Lista Verific. Inspeccion'!A51 -> 2.3 | D16: ='MSC Lista Verific. Inspeccion'!F51 -> 0 | E16: ='MSC Lista Verific. Inspeccion'!G51 -> 0
A17: =ISOP!$B$2 -> yyyy0100-0-yyyy1003110802 | B17: ='MSC Lista Verific. Inspeccion'!$A$46 -> 2. PREPARACIÓN PARA EMERGENCIAS | C17: ='MSC Lista Verific. Inspeccion'!A52 -> 2.4 | D17: ='MSC Lista Verific. Inspeccion'!F52 -> 0 | E17: ='MSC Lista Verific. Inspeccion'!G52 -> 0
A18: =ISOP!$B$2 -> yyyy0100-0-yyyy1003110802 | B18: ='MSC Lista Verific. Inspeccion'!$A$46 -> 2. PREPARACIÓN PARA EMERGENCIAS | C18: ='MSC Lista Verific. Inspeccion'!A53 -> 2.5 | D18: ='MSC Lista Verific. Inspeccion'!F53 -> 0 | E18: ='MSC Lista Verific. Inspeccion'!G53 -> 0
A19: =ISOP!$B$2 -> yyyy0100-0-yyyy1003110802 | B19: ='MSC Lista Verific. Inspeccion'!$A$46 -> 2. PREPARACIÓN PARA EMERGENCIAS | C19: ='MSC Lista Verific. Inspeccion'!A54 -> 2.6 | D19: ='MSC Lista Verific. Inspeccion'!F54 -> 0 | E19: ='MSC Lista Verific. Inspeccion'!G54 -> 0
A20: =ISOP!$B$2 -> yyyy0100-0-yyyy1003110802 | B20: ='MSC Lista Verific. Inspeccion'!$A$46 -> 2. PREPARACIÓN PARA EMERGENCIAS | C20: ='MSC Lista Verific. Inspeccion'!A55 -> 2.7 | D20: ='MSC Lista Verific. Inspeccion'!F55 -> 0 | E20: ='MSC Lista Verific. Inspeccion'!G55 -> 0
A21: =ISOP!$B$2 -> yyyy0100-0-yyyy1003110802 | B21: ='MSC Lista Verific. Inspeccion'!$A$46 -> 2. PREPARACIÓN PARA EMERGENCIAS | C21: ='MSC Lista Verific. Inspeccion'!A56 -> 2.8 | D21: ='MSC Lista Verific. Inspeccion'!F56 -> 0 | E21: ='MSC Lista Verific. Inspeccion'!G56 -> 0
A22: =ISOP!$B$2 -> yyyy0100-0-yyyy1003110802 | B22: ='MSC Lista Verific. Inspeccion'!$A$46 -> 2. PREPARACIÓN PARA EMERGENCIAS | C22: ='MSC Lista Verific. Inspeccion'!A57 -> 2.9 | D22: ='MSC Lista Verific. Inspeccion'!F57 -> 0 | E22: ='MSC Lista Verific. Inspeccion'!G57 -> 0
A23: =ISOP!$B$2 -> yyyy0100-0-yyyy1003110802 | B23: ='MSC Lista Verific. Inspeccion'!$A$46 -> 2. PREPARACIÓN PARA EMERGENCIAS | C23: ='MSC Lista Verific. Inspeccion'!A58 -> 2.10 | D23: ='MSC Lista Verific. Inspeccion'!F58 -> 0 | E23: ='MSC Lista Verific. Inspeccion'!G58 -> 0
A24: =ISOP!$B$2 -> yyyy0100-0-yyyy1003110802 | B24: ='MSC Lista Verific. Inspeccion'!$A$46 -> 2. PREPARACIÓN PARA EMERGENCIAS | C24: ='MSC Lista Verific. Inspeccion'!A59 -> 2.11 | D24: ='MSC Lista Verific. Inspeccion'!F59 -> 0 | E24: ='MSC Lista Verific. Inspeccion'!G59 -> 0
A25: =ISOP!$B$2 -> yyyy0100-0-yyyy1003110802 | B25: ='MSC Lista Verific. Inspeccion'!$A$46 -> 2. PREPARACIÓN PARA EMERGENCIAS | C25: ='MSC Lista Verific. Inspeccion'!A60 -> 2.12 | D25: ='MSC Lista Verific. Inspeccion'!F60 -> 0 | E25: ='MSC Lista Verific. Inspeccion'!G60 -> 0
... A30: =ISOP!$B$2 -> yyyy0100-0-yyyy1003110802 | B30: ='MSC Lista Verific. Inspeccion'!$A$46 -> 2. PREPARACIÓN PARA EMERGENCIAS | C30: ='MSC Lista Verific. Inspeccion'!A65 -> 2.17 | D30: ='MSC Lista Verific. Inspeccion'!F65 -> 0 | E30: ='MSC Lista Verific. Inspeccion'!G65 -> 0
A31: =ISOP!$B$2 -> yyyy0100-0-yyyy1003110802 | B31: ='MSC Lista Verific. Inspeccion'!$A$66 -> 3. ELEMENTOS DE PROTECCIÓN PERSONAL | C31: ='MSC Lista Verific. Inspeccion'!A68 -> 3.1 | D31: ='MSC Lista Verific. Inspeccion'!F68 -> 0 | E31: ='MSC Lista Verific. Inspeccion'!G68 -> 0
A32: =ISOP!$B$2 -> yyyy0100-0-yyyy1003110802 | B32: ='MSC Lista Verific. Inspeccion'!$A$66 -> 3. ELEMENTOS DE PROTECCIÓN PERSONAL | C32: ='MSC Lista Verific. Inspeccion'!A69 -> 3.2 | D32: ='MSC Lista Verific. Inspeccion'!F69 -> 0 | E32: ='MSC Lista Verific. Inspeccion'!G69 -> 0
A33: =ISOP!$B$2 -> yyyy0100-0-yyyy1003110802 | B33: ='MSC Lista Verific. Inspeccion'!$A$66 -> 3. ELEMENTOS DE PROTECCIÓN PERSONAL | C33: ='MSC Lista Verific. Inspeccion'!A70 -> 3.3 | D33: ='MSC Lista Verific. Inspeccion'!F70 -> 0 | E33: ='MSC Lista Verific. Inspeccion'!G70 -> 0
A34: =ISOP!$B$2 -> yyyy0100-0-yyyy1003110802 | B34: ='MSC Lista Verific. Inspeccion'!$A$66 -> 3. ELEMENTOS DE PROTECCIÓN PERSONAL | C34: ='MSC Lista Verific. Inspeccion'!A71 -> 3.4 | D34: ='MSC Lista Verific. Inspeccion'!F71 -> 0 | E34: ='MSC Lista Verific. Inspeccion'!G71 -> 0
A35: =ISOP!$B$2 -> yyyy0100-0-yyyy1003110802 | B35: ='MSC Lista Verific. Inspeccion'!$A$66 -> 3. ELEMENTOS DE PROTECCIÓN PERSONAL | C35: ='MSC Lista Verific. Inspeccion'!A72 -> 3.5 | D35: ='MSC Lista Verific. Inspeccion'!F72 -> 0 | E35: ='MSC Lista Verific. Inspeccion'!G72 -> 0
A36: =ISOP!$B$2 -> yyyy0100-0-yyyy1003110802 | B36: ='MSC Lista Verific. Inspeccion'!$A$66 -> 3. ELEMENTOS DE PROTECCIÓN PERSONAL | C36: ='MSC Lista Verific. Inspeccion'!A73 -> 3.6 | D36: ='MSC Lista Verific. Inspeccion'!F73 -> 0 | E36: ='MSC Lista Verific. Inspeccion'!G73 -> 0
A37: =ISOP!$B$2 -> yyyy0100-0-yyyy1003110802 | B37: ='MSC Lista Verific. Inspeccion'!$A$66 -> 3. ELEMENTOS DE PROTECCIÓN PERSONAL | C37: ='MSC Lista Verific. Inspeccion'!A74 -> 3.7 | D37: ='MSC Lista Verific. Inspeccion'!F74 -> 0 | E37: ='MSC Lista Verific. Inspeccion'!G74 -> 0
A38: =ISOP!$B$2 -> yyyy0100-0-yyyy1003110802 | B38: ='MSC Lista Verific. Inspeccion'!$A$75 -> 4. HERRAMIENTAS DE MANO | C38: ='MSC Lista Verific. Inspeccion'!A77 -> 4.1 | D38: ='MSC Lista Verific. Inspeccion'!F77 -> 0 | E38: ='MSC Lista Verific. Inspeccion'!G77 -> 0
A39: =ISOP!$B$2 -> yyyy0100-0-yyyy1003110802 | B39: ='MSC Lista Verific. Inspeccion'!$A$75 -> 4. HERRAMIENTAS DE MANO | C39: ='MSC Lista Verific. Inspeccion'!A78 -> 4.2 | D39: ='MSC Lista Verific. Inspeccion'!F78 -> 0 | E39: ='MSC Lista Verific. Inspeccion'!G78 -> 0
A40: =ISOP!$B$2 -> yyyy0100-0-yyyy1003110802 | B40: ='MSC Lista Verific. Inspeccion'!$A$75 -> 4. HERRAMIENTAS DE MANO | C40: ='MSC Lista Verific. Inspeccion'!A79 -> 4.3 | D40: ='MSC Lista Verific. Inspeccion'!F79 -> 0 | E40: ='MSC Lista Verific. Inspeccion'!G79 -> 0
A41: =ISOP!$B$2 -> yyyy0100-0-yyyy1003110802 | B41: ='MSC Lista Verific. Inspeccion'!$A$75 -> 4. HERRAMIENTAS DE MANO | C41: ='MSC Lista Verific. Inspeccion'!A80 -> 4.4 | D41: ='MSC Lista Verific. Inspeccion'!F80 -> 0 | E41: ='MSC Lista Verific. Inspeccion'!G80 -> 0
A42: =ISOP!$B$2 -> yyyy0100-0-yyyy1003110802 | B42: ='MSC Lista Verific. Inspeccion'!$A$75 -> 4. HERRAMIENTAS DE MANO | C42: ='MSC Lista Verific. Inspeccion'!A81 -> 4.5 | D42: ='MSC Lista Verific. Inspeccion'!F81 -> 0 | E42: ='MSC Lista Verific. Inspeccion'!G81 -> 0
A43: =ISOP!$B$2 -> yyyy0100-0-yyyy1003110802 | B43: ='MSC Lista Verific. Inspeccion'!$A$75 -> 4. HERRAMIENTAS DE MANO | C43: ='MSC Lista Verific. Inspeccion'!A82 -> 4.6 | D43: ='MSC Lista Verific. Inspeccion'!F82 -> 0 | E43: ='MSC Lista Verific. Inspeccion'!G82 -> 0
A44: =ISOP!$B$2 -> yyyy0100-0-yyyy1003110802 | B44: ='MSC Lista Verific. Inspeccion'!$A$75 -> 4. HERRAMIENTAS DE MANO | C44: ='MSC Lista Verific. Inspeccion'!A83 -> 4.7 | D44: ='MSC Lista Verific. Inspeccion'!F83 -> 0 | E44: ='MSC Lista Verific. Inspeccion'!G83 -> 0
A45: =ISOP!$B$2 -> yyyy0100-0-yyyy1003110802 | B45: ='MSC Lista Verific. Inspeccion'!$A$75 -> 4. HERRAMIENTAS DE MANO | C45: ='MSC Lista Verific. Inspeccion'!A84 -> 4.8 | D45: ='MSC Lista Verific. Inspeccion'!F84 -> 0 | E45: ='MSC Lista Verific. Inspeccion'!G84 -> 0
A46: =ISOP!$B$2 -> yyyy0100-0-yyyy1003110802 | B46: ='MSC Lista Verific. Inspeccion'!$A$75 -> 4. HERRAMIENTAS DE MANO | C46: ='MSC Lista Verific. Inspeccion'!A85 -> 4.9 | D46: ='MSC Lista Verific. Inspeccion'!F85 -> 0 | E46: ='MSC Lista Verific. Inspeccion'!G85 -> 0
A47: =ISOP!$B$2 -> yyyy0100-0-yyyy1003110802 | B47: ='MSC Lista Verific. Inspeccion'!$A$75 -> 4. HERRAMIENTAS DE MANO | C47: ='MSC Lista Verific. Inspeccion'!A86 -> 4.10 | D47: ='MSC Lista Verific. Inspeccion'!F86 -> 0 | E47: ='MSC Lista Verific. Inspeccion'!G86 -> 0
A48: =ISOP!$B$2 -> yyyy0100-0-yyyy1003110802 | B48: ='MSC Lista Verific. Inspeccion'!$A$75 -> 4. HERRAMIENTAS DE MANO | C48: ='MSC Lista Verific. Inspeccion'!A87 -> 4.11 | D48: ='MSC Lista Verific. Inspeccion'!F87 -> 0 | E48: ='MSC Lista Verific. Inspeccion'!G87 -> 0
A49: =ISOP!$B$2 -> yyyy0100-0-yyyy1003110802 | B49: ='MSC Lista Verific. Inspeccion'!$A$88 -> 5.- INSTALACIONES DE FAENA/ OFICINAS | C49: ='MSC Lista Verific. Inspeccion'!A91 -> 5.1 | D49: ='MSC Lista Verific. Inspeccion'!F91 -> 0 | E49: ='MSC Lista Verific. Inspeccion'!G91 -> 0
A50: =ISOP!$B$2 -> yyyy0100-0-yyyy1003110802 | B50: ='MSC Lista Verific. Inspeccion'!$A$88 -> 5.- INSTALACIONES DE FAENA/ OFICINAS | C50: ='MSC Lista Verific. Inspeccion'!A92 -> 5.2 | D50: ='MSC Lista Verific. Inspeccion'!F92 -> 0 | E50: ='MSC Lista Verific. Inspeccion'!G92 -> 0
A51: =ISOP!$B$2 -> yyyy0100-0-yyyy1003110802 | B51: ='MSC Lista Verific. Inspeccion'!$A$88 -> 5.- INSTALACIONES DE FAENA/ OFICINAS | C51: ='MSC Lista Verific. Inspeccion'!A93 -> 5.3 | D51: ='MSC Lista Verific. Inspeccion'!F93 -> 0 | E51: ='MSC Lista Verific. Inspeccion'!G93 -> 0
A52: =ISOP!$B$2 -> yyyy0100-0-yyyy1003110802 | B52: ='MSC Lista Verific. Inspeccion'!$A$88 -> 5.- INSTALACIONES DE FAENA/ OFICINAS | C52: ='MSC Lista Verific. Inspeccion'!A94 -> 5.4 | D52: ='MSC Lista Verific. Inspeccion'!F94 -> 0 | E52: ='MSC Lista Verific. Inspeccion'!G94 -> 0
A53: =ISOP!$B$2 -> yyyy0100-0-yyyy1003110802 | B53: ='MSC Lista Verific. Inspeccion'!$A$88 -> 5.- INSTALACIONES DE FAENA/ OFICINAS | C53: ='MSC Lista Verific. Inspeccion'!A95 -> 5.5 | D53: ='MSC Lista Verific. Inspeccion'!F95 -> 0 | E53: ='MSC Lista Verific. Inspeccion'!G95 -> 0
A54: =ISOP!$B$2 -> yyyy0100-0-yyyy1003110802 | B54: ='MSC Lista Verific. Inspeccion'!$A$88 -> 5.- INSTALACIONES DE FAENA/ OFICINAS | C54: ='MSC Lista Verific. Inspeccion'!A96 -> 5.6 | D54: ='MSC Lista Verific. Inspeccion'!F96 -> 0 | E54: ='MSC Lista Verific. Inspeccion'!G96 -> 0
A55: =ISOP!$B$2 -> yyyy0100-0-yyyy1003110802 | B55: ='MSC Lista Verific. Inspeccion'!$A$88 -> 5.- INSTALACIONES DE FAENA/ OFICINAS | C55: ='MSC Lista Verific. Inspeccion'!A97 -> 5.7 | D55: ='MSC Lista Verific. Inspeccion'!F97 -> 0 | E55: ='MSC Lista Verific. Inspeccion'!G97 -> 0
A56: =ISOP!$B$2 -> yyyy0100-0-yyyy1003110802 | B56: ='MSC Lista Verific. Inspeccion'!$A$88 -> 5.- INSTALACIONES DE FAENA/ OFICINAS | C56: ='MSC Lista Verific. Inspeccion'!A98 -> 5.8 | D56: ='MSC Lista Verific. Inspeccion'!F98 -> 0 | E56: ='MSC Lista Verific. Inspeccion'!G98 -> 0
A57: =ISOP!$B$2 -> yyyy0100-0-yyyy1003110802 | B57: ='MSC Lista Verific. Inspeccion'!$A$88 -> 5.- INSTALACIONES DE FAENA/ OFICINAS | C57: ='MSC Lista Verific. Inspeccion'!A100 -> 5.9 | D57: ='MSC Lista Verific. Inspeccion'!F100 -> 0 | E57: ='MSC Lista Verific. Inspeccion'!G100 -> 0
A58: =ISOP!$B$2 -> yyyy0100-0-yyyy1003110802 | B58: ='MSC Lista Verific. Inspeccion'!$A$88 -> 5.- INSTALACIONES DE FAENA/ OFICINAS | C58: ='MSC Lista Verific. Inspeccion'!A101 -> 5.10 | D58: ='MSC Lista Verific. Inspeccion'!F101 -> 0 | E58: ='MSC Lista Verific. Inspeccion'!G101 -> 0
A59: =ISOP!$B$2 -> yyyy0100-0-yyyy1003110802 | B59: ='MSC Lista Verific. Inspeccion'!$A$88 -> 5.- INSTALACIONES DE FAENA/ OFICINAS | C59: ='MSC Lista Verific. Inspeccion'!A102 -> 5.11 | D59: ='MSC Lista Verific. Inspeccion'!F102 -> 0 | E59: ='MSC Lista Verific. Inspeccion'!G102 -> 0
A60: =ISOP!$B$2 -> yyyy0100-0-yyyy1003110802 | B60: ='MSC Lista Verific. Inspeccion'!$A$88 -> 5.- INSTALACIONES DE FAENA/ OFICINAS | C60: ='MSC Lista Verific. Inspeccion'!A104 -> 5.12 | D60: ='MSC Lista Verific. Inspeccion'!F104 -> 0 | E60: ='MSC Lista Verific. Inspeccion'!G104 -> 0
A61: =ISOP!$B$2 -> yyyy0100-0-yyyy1003110802 | B61: ='MSC Lista Verific. Inspeccion'!$A$88 -> 5.- INSTALACIONES DE FAENA/ OFICINAS | C61: ='MSC Lista Verific. Inspeccion'!A105 -> 5.13 | D61: ='MSC Lista Verific. Inspeccion'!F105 -> 0 | E61: ='MSC Lista Verific. Inspeccion'!G105 -> 0
A62: =ISOP!$B$2 -> yyyy0100-0-yyyy1003110802 | B62: ='MSC Lista Verific. Inspeccion'!$A$88 -> 5.- INSTALACIONES DE FAENA/ OFICINAS | C62: ='MSC Lista Verific. Inspeccion'!A106 -> 5.14 | D62: ='MSC Lista Verific. Inspeccion'!F106 -> 0 | E62: ='MSC Lista Verific. Inspeccion'!G106 -> 0
A63: =ISOP!$B$2 -> yyyy0100-0-yyyy1003110802 | B63: ='MSC Lista Verific. Inspeccion'!$A$88 -> 5.- INSTALACIONES DE FAENA/ OFICINAS | C63: ='MSC Lista Verific. Inspeccion'!A107 -> 5.15 | D63: ='MSC Lista Verific. Inspeccion'!F107 -> 0 | E63: ='MSC Lista Verific. Inspeccion'!G107 -> 0
A64: =ISOP!$B$2 -> yyyy0100-0-yyyy1003110802 | B64: ='MSC Lista Verific. Inspeccion'!$A$88 -> 5.- INSTALACIONES DE FAENA/ OFICINAS | C64: ='MSC Lista Verific. Inspeccion'!A108 -> 5.16 | D64: ='MSC Lista Verific. Inspeccion'!F108 -> 0 | E64: ='MSC Lista Verific. Inspeccion'!G108 -> 0
A65: =ISOP!$B$2 -> yyyy0100-0-yyyy1003110802 | B65: ='MSC Lista Verific. Inspeccion'!$A$88 -> 5.- INSTALACIONES DE FAENA/ OFICINAS | C65: ='MSC Lista Verific. Inspeccion'!A110 -> 5.17 | D65: ='MSC Lista Verific. Inspeccion'!F110 -> 0 | E65: ='MSC Lista Verific. Inspeccion'!G110 -> 0
A66: =ISOP!$B$2 -> yyyy0100-0-yyyy1003110802 | B66: ='MSC Lista Verific. Inspeccion'!$A$88 -> 5.- INSTALACIONES DE FAENA/ OFICINAS | C66: ='MSC Lista Verific. Inspeccion'!A111 -> 5.18 | D66: ='MSC Lista Verific. Inspeccion'!F111 -> 0 | E66: ='MSC Lista Verific. Inspeccion'!G111 -> 0
A67: =ISOP!$B$2 -> yyyy0100-0-yyyy1003110802 | B67: ='MSC Lista Verific. Inspeccion'!$A$88 -> 5.- INSTALACIONES DE FAENA/ OFICINAS | C67: ='MSC Lista Verific. Inspeccion'!A112 -> 5.19 | D67: ='MSC Lista Verific. Inspeccion'!F112 -> 0 | E67: ='MSC Lista Verific. Inspeccion'!G112 -> 0
A68: =ISOP!$B$2 -> yyyy0100-0-yyyy1003110802 | B68: ='MSC Lista Verific. Inspeccion'!$A$88 -> 5.- INSTALACIONES DE FAENA/ OFICINAS | C68: ='MSC Lista Verific. Inspeccion'!A113 -> 5.20 | D68: ='MSC Lista Verific. Inspeccion'!F113 -> 0 | E68: ='MSC Lista Verific. Inspeccion'!G113 -> 0
A69: =ISOP!$B$2 -> yyyy0100-0-yyyy1003110802 | B69: ='MSC Lista Verific. Inspeccion'!$A$88 -> 5.- INSTALACIONES DE FAENA/ OFICINAS | C69: ='MSC Lista Verific. Inspeccion'!A114 -> 5.21 | D69: ='MSC Lista Verific. Inspeccion'!F114 -> 0 | E69: ='MSC Lista Verific. Inspeccion'!G114 -> 0
A70: =ISOP!$B$2 -> yyyy0100-0-yyyy1003110802 | B70: ='MSC Lista Verific. Inspeccion'!$A$88 -> 5.- INSTALACIONES DE FAENA/ OFICINAS | C70: ='MSC Lista Verific. Inspeccion'!A115 -> 5.22 | D70: ='MSC Lista Verific. Inspeccion'!F115 -> 0 | E70: ='MSC Lista Verific. Inspeccion'!G115 -> 0
A71: =ISOP!$B$2 -> yyyy0100-0-yyyy1003110802 | B71: ='MSC Lista Verific. Inspeccion'!$A$88 -> 5.- INSTALACIONES DE FAENA/ OFICINAS | C71: ='MSC Lista Verific. Inspeccion'!A116 -> 5.23 | D71: ='MSC Lista Verific. Inspeccion'!F116 -> 0 | E71: ='MSC Lista Verific. Inspeccion'!G116 -> 0
A72: =ISOP!$B$2 -> yyyy0100-0-yyyy1003110802 | B72: ='MSC Lista Verific. Inspeccion'!$A$88 -> 5.- INSTALACIONES DE FAENA/ OFICINAS | C72: ='MSC Lista Verific. Inspeccion'!A117 -> 5.24 | D72: ='MSC Lista Verific. Inspeccion'!F117 -> 0 | E72: ='MSC Lista Verific. Inspeccion'!G117 -> 0
A73: =ISOP!$B$2 -> yyyy0100-0-yyyy1003110802 | B73: ='MSC Lista Verific. Inspeccion'!$A$88 -> 5.- INSTALACIONES DE FAENA/ OFICINAS | C73: ='MSC Lista Verific. Inspeccion'!A118 -> 5.25 | D73: ='MSC Lista Verific. Inspeccion'!F118 -> 0 | E73: ='MSC Lista Verific. Inspeccion'!G118 -> 0
A74: =ISOP!$B$2 -> yyyy0100-0-yyyy1003110802 | B74: ='MSC Lista Verific. Inspeccion'!$A$88 -> 5.- INSTALACIONES DE FAENA/ OFICINAS | C74: ='MSC Lista Verific. Inspeccion'!A119 -> 5.26 | D74: ='MSC Lista Verific. Inspeccion'!F119 -> 0 | E74: ='MSC Lista Verific. Inspeccion'!G119 -> 0
A75: =ISOP!$B$2 -> yyyy0100-0-yyyy1003110802 | B75: ='MSC Lista Verific. Inspeccion'!$A$88 -> 5.- INSTALACIONES DE FAENA/ OFICINAS | C75: ='MSC Lista Verific. Inspeccion'!A120 -> 5.27 | D75: ='MSC Lista Verific. Inspeccion'!F120 -> 0 | E75: ='MSC Lista Verific. Inspeccion'!G120 -> 0
A76: =ISOP!$B$2 -> yyyy0100-0-yyyy1003110802 | B76: ='MSC Lista Verific. Inspeccion'!$A$88 -> 5.- INSTALACIONES DE FAENA/ OFICINAS | C76: ='MSC Lista Verific. Inspeccion'!A121 -> 5.28 | D76: ='MSC Lista Verific. Inspeccion'!F121 -> 0 | E76: ='MSC Lista Verific. Inspeccion'!G121 -> 0
... A88: =ISOP!$B$2 -> yyyy0100-0-yyyy1003110802 | B88: ='MSC Lista Verific. Inspeccion'!$A$88 -> 5.- INSTALACIONES DE FAENA/ OFICINAS | C88: ='MSC Lista Verific. Inspeccion'!A133 -> 5.40 | D88: ='MSC Lista Verific. Inspeccion'!F133 -> 0 | E88: ='MSC Lista Verific. Inspeccion'!G133 -> 0
A89: =ISOP!$B$2 -> yyyy0100-0-yyyy1003110802 | B89: ='MSC Lista Verific. Inspeccion'!$A$134 -> 6.- SEÑALIZACIÓN | C89: ='MSC Lista Verific. Inspeccion'!A136 -> 6.1 | D89: ='MSC Lista Verific. Inspeccion'!F136 -> 0 | E89: ='MSC Lista Verific. Inspeccion'!G136 -> 0
A90: =ISOP!$B$2 -> yyyy0100-0-yyyy1003110802 | B90: ='MSC Lista Verific. Inspeccion'!$A$134 -> 6.- SEÑALIZACIÓN | C90: ='MSC Lista Verific. Inspeccion'!A137 -> 6.2 | D90: ='MSC Lista Verific. Inspeccion'!F137 -> 0 | E90: ='MSC Lista Verific. Inspeccion'!G137 -> 0
A91: =ISOP!$B$2 -> yyyy0100-0-yyyy1003110802 | B91: ='MSC Lista Verific. Inspeccion'!$A$134 -> 6.- SEÑALIZACIÓN | C91: ='MSC Lista Verific. Inspeccion'!A138 -> 6.3 | D91: ='MSC Lista Verific. Inspeccion'!F138 -> 0 | E91: ='MSC Lista Verific. Inspeccion'!G138 -> 0
A92: =ISOP!$B$2 -> yyyy0100-0-yyyy1003110802 | B92: ='MSC Lista Verific. Inspeccion'!$A$134 -> 6.- SEÑALIZACIÓN | C92: ='MSC Lista Verific. Inspeccion'!A139 -> 6.4 | D92: ='MSC Lista Verific. Inspeccion'!F139 -> 0 | E92: ='MSC Lista Verific. Inspeccion'!G139 -> 0
A93: =ISOP!$B$2 -> yyyy0100-0-yyyy1003110802 | B93: ='MSC Lista Verific. Inspeccion'!$A$134 -> 6.- SEÑALIZACIÓN | C93: ='MSC Lista Verific. Inspeccion'!A140 -> 6.5 | D93: ='MSC Lista Verific. Inspeccion'!F140 -> 0 | E93: ='MSC Lista Verific. Inspeccion'!G140 -> 0
A94: =ISOP!$B$2 -> yyyy0100-0-yyyy1003110802 | B94: ='MSC Lista Verific. Inspeccion'!$A$134 -> 6.- SEÑALIZACIÓN | C94: ='MSC Lista Verific. Inspeccion'!A141 -> 6.6 | D94: ='MSC Lista Verific. Inspeccion'!F141 -> 0 | E94: ='MSC Lista Verific. Inspeccion'!G141 -> 0
A95: =ISOP!$B$2 -> yyyy0100-0-yyyy1003110802 | B95: ='MSC Lista Verific. Inspeccion'!$A$134 -> 6.- SEÑALIZACIÓN | C95: ='MSC Lista Verific. Inspeccion'!A142 -> 6.7 | D95: ='MSC Lista Verific. Inspeccion'!F142 -> 0 | E95: ='MSC Lista Verific. Inspeccion'!G142 -> 0
A96: =ISOP!$B$2 -> yyyy0100-0-yyyy1003110802 | B96: ='MSC Lista Verific. Inspeccion'!$A$134 -> 6.- SEÑALIZACIÓN | C96: ='MSC Lista Verific. Inspeccion'!A143 -> 6.8 | D96: ='MSC Lista Verific. Inspeccion'!F143 -> 0 | E96: ='MSC Lista Verific. Inspeccion'!G143 -> 0
A97: =ISOP!$B$2 -> yyyy0100-0-yyyy1003110802 | B97: ='MSC Lista Verific. Inspeccion'!$A$134 -> 6.- SEÑALIZACIÓN | C97: ='MSC Lista Verific. Inspeccion'!A144 -> 6.9 | D97: ='MSC Lista Verific. Inspeccion'!F144 -> 0 | E97: ='MSC Lista Verific. Inspeccion'!G144 -> 0
A98: =ISOP!$B$2 -> yyyy0100-0-yyyy1003110802 | B98: ='MSC Lista Verific. Inspeccion'!$A$145 -> 7.- VEHÍCULOS/ ESTACIONAMIENTOS | C98: ='MSC Lista Verific. Inspeccion'!A147 -> 7.1 | D98: ='MSC Lista Verific. Inspeccion'!F147 -> 0 | E98: ='MSC Lista Verific. Inspeccion'!G147 -> 0
A99: =ISOP!$B$2 -> yyyy0100-0-yyyy1003110802 | B99: ='MSC Lista Verific. Inspeccion'!$A$145 -> 7.- VEHÍCULOS/ ESTACIONAMIENTOS | C99: ='MSC Lista Verific. Inspeccion'!A148 -> 7.2 | D99: ='MSC Lista Verific. Inspeccion'!F148 -> 0 | E99: ='MSC Lista Verific. Inspeccion'!G148 -> 0
A100: =ISOP!$B$2 -> yyyy0100-0-yyyy1003110802 | B100: ='MSC Lista Verific. Inspeccion'!$A$145 -> 7.- VEHÍCULOS/ ESTACIONAMIENTOS | C100: ='MSC Lista Verific. Inspeccion'!A149 -> 7.3 | D100: ='MSC Lista Verific. Inspeccion'!F149 -> 0 | E100: ='MSC Lista Verific. Inspeccion'!G149 -> 0
A101: =ISOP!$B$2 -> yyyy0100-0-yyyy1003110802 | B101: ='MSC Lista Verific. Inspeccion'!$A$145 -> 7.- VEHÍCULOS/ ESTACIONAMIENTOS | C101: ='MSC Lista Verific. Inspeccion'!A150 -> 7.4 | D101: ='MSC Lista Verific. Inspeccion'!F150 -> 0 | E101: ='MSC Lista Verific. Inspeccion'!G150 -> 0
A102: =ISOP!$B$2 -> yyyy0100-0-yyyy1003110802 | B102: ='MSC Lista Verific. Inspeccion'!$A$145 -> 7.- VEHÍCULOS/ ESTACIONAMIENTOS | C102: ='MSC Lista Verific. Inspeccion'!A151 -> 7.5 | D102: ='MSC Lista Verific. Inspeccion'!F151 -> 0 | E102: ='MSC Lista Verific. Inspeccion'!G151 -> 0
A103: =ISOP!$B$2 -> yyyy0100-0-yyyy1003110802 | B103: ='MSC Lista Verific. Inspeccion'!$A$145 -> 7.- VEHÍCULOS/ ESTACIONAMIENTOS | C103: ='MSC Lista Verific. Inspeccion'!A152 -> 7.6 | D103: ='MSC Lista Verific. Inspeccion'!F152 -> 0 | E103: ='MSC Lista Verific. Inspeccion'!G152 -> 0
A104: =ISOP!$B$2 -> yyyy0100-0-yyyy1003110802 | B104: ='MSC Lista Verific. Inspeccion'!$A$145 -> 7.- VEHÍCULOS/ ESTACIONAMIENTOS | C104: ='MSC Lista Verific. Inspeccion'!A153 -> 7.7 | D104: ='MSC Lista Verific. Inspeccion'!F153 -> 0 | E104: ='MSC Lista Verific. Inspeccion'!G153 -> 0
A105: =ISOP!$B$2 -> yyyy0100-0-yyyy1003110802 | B105: ='MSC Lista Verific. Inspeccion'!$A$145 -> 7.- VEHÍCULOS/ ESTACIONAMIENTOS | C105: ='MSC Lista Verific. Inspeccion'!A154 -> 7.8 | D105: ='MSC Lista Verific. Inspeccion'!F154 -> 0 | E105: ='MSC Lista Verific. Inspeccion'!G154 -> 0
A106: =ISOP!$B$2 -> yyyy0100-0-yyyy1003110802 | B106: ='MSC Lista Verific. Inspeccion'!$A$145 -> 7.- VEHÍCULOS/ ESTACIONAMIENTOS | C106: ='MSC Lista Verific. Inspeccion'!A155 -> 7.9 | D106: ='MSC Lista Verific. Inspeccion'!F155 -> 0 | E106: ='MSC Lista Verific. Inspeccion'!G155 -> 0
A107: =ISOP!$B$2 -> yyyy0100-0-yyyy1003110802 | B107: ='MSC Lista Verific. Inspeccion'!$A$145 -> 7.- VEHÍCULOS/ ESTACIONAMIENTOS | C107: ='MSC Lista Verific. Inspeccion'!A156 -> 7.10 | D107: ='MSC Lista Verific. Inspeccion'!F156 -> 0 | E107: ='MSC Lista Verific. Inspeccion'!G156 -> 0
A108: =ISOP!$B$2 -> yyyy0100-0-yyyy1003110802 | B108: ='MSC Lista Verific. Inspeccion'!$A$145 -> 7.- VEHÍCULOS/ ESTACIONAMIENTOS | C108: ='MSC Lista Verific. Inspeccion'!A157 -> 7.11 | D108: ='MSC Lista Verific. Inspeccion'!F157 -> 0 | E108: ='MSC Lista Verific. Inspeccion'!G157 -> 0
A109: =ISOP!$B$2 -> yyyy0100-0-yyyy1003110802 | B109: ='MSC Lista Verific. Inspeccion'!$A$145 -> 7.- VEHÍCULOS/ ESTACIONAMIENTOS | C109: ='MSC Lista Verific. Inspeccion'!A158 -> 7.12 | D109: ='MSC Lista Verific. Inspeccion'!F158 -> 0 | E109: ='MSC Lista Verific. Inspeccion'!G158 -> 0
... A113: =ISOP!$B$2 -> yyyy0100-0-yyyy1003110802 | B113: ='MSC Lista Verific. Inspeccion'!$A$145 -> 7.- VEHÍCULOS/ ESTACIONAMIENTOS | C113: ='MSC Lista Verific. Inspeccion'!A162 -> 7.16 | D113: ='MSC Lista Verific. Inspeccion'!F162 -> 0 | E113: ='MSC Lista Verific. Inspeccion'!G162 -> 0

Sheet Sheet1
L1: vice | M1: gere | N1: super | X1: cuidado con los codigos | AC1: PRESIDENCIA EJECUTIVA>VICEPRESIDENCIA DE DESARROLLO DE PROYECTOS>GERENCIA DE PROYECTOS>SUPERINTENDENCIA DE INGENIERÍA PLANTA>SUPERVISIÓN SÉNIOR DE PROYECTOS Y MODIFICACIONES> | DJ1: 6
A2: id | B2: Vicepresidencia | F2: id | G2: Gerencia | H2: ant_v | I2: ant_g | N2: id | O2: SuperIntendencia | P2: ant_v | Q2: ant_g | R2: ant_s | T2: nro | U2: vice_cod | V2: gere_cod | W2: superint_cod | X2: id | Y2: nombre_sp | Z2: Supervision | AA2: vice | AB2: gere | AC2: superinte | AD2: superv | AE2: superv_1 | AF2: area | AM2: id | AN2: Empresa | AS2: id | AT2: Archivo | AX2: id | AY2: version | BE2: Fecha (yyyymmdd) | BG2: Código | BH2: AREA1 | BJ2: Código | BK2: AREA | BM2: id | BO2: Vicepresidencia | BR2: Presi | BT2: VICEPRESIDENCIA_CORPORATIVA | BV2: GERENCIA_CORPORATIVA | BX2: SUPERINTENDENCIA_DE_ADQUISICIONES | BZ2: SUPERINTENDENCIA_DE_RELACIONES_INSTITUCIONALES | CB2: SUPERINTENDENCIA_DE_RELACIONES_PÚBLICAS | CD2: GERENCIA_CORPORATIVA_ | CF2: GERENCIA_DE_COMERCIALIZACIÓN_Y_SERVICIOS | CH2: SUPERINTENDENCIA_DE_ALMACENES_Y_CONTROL_DE_INVENTARIOS | CJ2: SUPERINTENDENCIA_DE_EXPORTACIONES | CL2: SUPERINTENDENCIA_DE_GESTION_COMERCIAL | CN2: SUPERINTENDENCIA_DE_LOGÍSTICA | CP2: SUPERINTENDENCIA_DE_MANEJO_DE_MATERIALES | CR2: GERENCIA_DE_MEDIO_AMBIENTE | CT2: SUPERINTENDENCIA_DE_MEDIO_AMBIENTE | CV2: GERENCIA_DE_RECURSOS_HUMANOS_Y_SERVICIOS_DE_PERSONAL | CX2: SUPERINTENDENCIA_DE_CAMPAMENTO | CZ2: SUPERINTENDENCIA_DE_RECURSOS_HUMANOS | DB2: SUPERINTENDENCIA_SÉNIOR_DE_SALUD | DD2: SUPERVISIÓN_SENIOR_DE_SEGURIDAD_FÍSICA | DF2: GERENCIA_DE_RELACIONES_COMUNITARIAS | DH2: SUPERINTENDENCIA_DE_DESARROLLO_SOSTENIBLE_Y_RELACIONES_COMUNITARIAS | DJ2: GERENCIA_DE_SEGURIDAD_INDUSTRIAL | DL2: SUPERINTENDENCIA_DE_SEGURIDAD_INDUSTRIAL | DN2: GERENCIA_DE_SERVICIOS_DE_TRANSPORTE_Y_AVIACIÓN | DP2: SUPERINTENDENCIA_DE_SERVICIOS_DE_AVIACIÓN | DR2: SUPERINTENDENCIA_DE_SERVICIOS_DE_TRANSPORTE_DE_PERSONAL | DT2: VICEPRESIDENCIA_DE_DESARROLLO_DE_PROYECTOS | DV2: GERENCIA_DE_PROYECTOS | DX2: SUPERINTENDENCIA_ADMINISTRATIVO_DE_OPERACIONES | DZ2: SUPERINTENDENCIA_DE_INGENIERÍA_PLANTA | EB2: VICEPRESIDENCIA_DE_FINANZAS | ED2: GERENCIA_DE_FINANZAS | EF2: SUPERINTENDENCIA_DE_CONTABILIDAD | EH2: SUPERINTENDENCIA_DE_IMPUESTOS | EJ2: SUPERINTENDENCIA_DE_PLANIFICACIÓN_FINANCIERA | EL2: GERENCIA_DE_TI_Y_DESARROLLO_DEL_NEGOCIO | EN2: SUPERINTENDENCIA_DE_DESARROLLO_DEL_NEGOCIO | EP2: SUPERINTENDENCIA_DE_TI | ER2: SUPERINTENDENCIA_DE_TO | ET2: SUPERVISIÓN_DE_SEGURIDAD_DE_LA_INFORMACIÓN_CISO | EV2: VICEPRESIDENCIA_DE_OPERACIONES | EX2: GERENCIA_DE_MANTENIMIENTO_MINA | EZ2: SUPERINTENDENCIA_SÉNIOR_DE_MANTENIMIENTO_MINA | FB2: SUPERINTENDENTE_DE_MANTENIMIENTO_MINA_PLANIFICACIÓN_Y_PROGRAMACIÓN | FD2: GERENCIA_DE_MANTENIMIENTO_PLANTA | FF2: SUPERINTENDENCIA_DE_MANTENIMIENTO_ELÉCTRICO_E_INSTRUMENTACIÓN_PLANTA | FH2: SUPERINTENDENCIA_DE_MANTENIMIENTO_INGENIERÍA_DE_CONFIABILIDAD | FJ2: SUPERINTENDENCIA_DE_MANTENIMIENTO_MEC._PLTA._CHANCADO_MOLIENDA_Y_LUBRICACIÓN | FL2: SUPERINTENDENCIA_DE_MANTENIMIENTO_MEC._PLTA._FLOT._FILTROS_TALLER_GRAL._Y_RH | FN2: SUPERINTENDENCIA_DE_MANTENIMIENTO_PLANIFICACIÓN | FP2: GERENCIA_DE_OPERACIONES_MINA | FR2: SUPERINTENDENCIA_DE_INGENIERÍA_MINA | FT2: SUPERINTENDENCIA_DE_OPERACIONES_MINA | FV2: SUPERINTENDENCIA_DE_SERVICIOS_DE_EXPLORACIÓN | FX2: SUPERVISIÓN_DE_ENTRENAMIENTO_MINA | FZ2: GERENCIA_DE_OPERACIONES_PLANTA | GB2: SUPERINTENDENCIA_DE_GESTIÓN_DE_RELAVES_Y_SERVICIOS_AUXILIARES | GD2: SUPERINTENDENCIA_DE_OPERACIONES_PLANTA | GF2: SUPERINTENDENCIA_DE_SERVICIOS_TÉCNICOS | GH2: GERENCIA_DE_OPERACIONES_PLANTA_
A3: 00 | B3: Presidencia Ejecutiva | E3: 01 | F3: 01 | G3: GERENCIA CORPORATIVA | H3: 01 | I3: 01 | L3: 1 | M3: 1 | N3: 01 | O3: SUPERINTENDENCIA DE ADQUISICIONES | P3: 1 | Q3: 1 | R3: 01 | T3: 1 | U3: 04 | V3: 11 | W3: 28 | X3: ASW | Y3: ACHO SURCO WILFREDO | Z3: ACHO SURCO WILFREDO - ELECTROMECÁNICO DE MANTENIMIENTO MINA | AA3: VICEPRESIDENCIA DE OPERACIONES | AB3: GERENCIA DE MANTENIMIENTO MINA | AC3: SUPERINTENDENCIA SÉNIOR DE INGENIERÍA Y SEGURIDAD DE EQUIPOS MÓVILES | AD3: SUPERINTENDENCIA DE MANTENIMIENTO MINA - EJECUCIÓN | AE3: SUPERVISIÓN DE MANTENIMIENTO MINA - CARGUÍO | AF3: MANTENIMIENTO MINA - EJECUCIÓN | AM3: 000 | AN3: MSC | AS3: 00 | AT3: PGR | AX3: 00 | AY3: version0 | BE3: 20240621 | BG3: 010 | BH3: 10 AREA MINA | BJ3: 01 | BK3: ADMINISTRATIVO DE OPERACIONES | BM3: 00 | BO3: Presidencia_Ejecutiva | BR3: Presidencia Ejecutiva | BT3: GERENCIA_CORPORATIVA | BV3: SUPERINTENDENCIA_DE_ADQUISICIONES | BX3: URIA_ALANES_CLAUDIA_FATIMA_-_SUPERVISOR_DE_ADQUISICIONES_DE_BIENES | BZ3: CASANOVA_AGUIRRE_JAIME_SANTIAGO_-_ESPECIALISTA_DE_GESTIONES_ADMINISTRATIVAS | CB3: DALENCE_ROJAS_PATRICIA_BEATRIZ_-_SUPERINTENDENTE_DE_RELACIONES_PÚBLICAS | CD3: IMAÑA_CASTRO_RUBEN_MARCELO_-_AUDITOR_INTERNO | CF3: SUPERINTENDENCIA_DE_ALMACENES_Y_CONTROL_DE_INVENTARIOS | CH3: CLAROS_MONTAÑO_JUAN_CARLOS_-_SUPERVISOR_SÉNIOR_DE_ALMACÉN_PLANTA_Y_COMBUSTIBLES | CJ3: CARBALLO_RIVERO_ROBERTO_ALCIDES_-_ANALISTA_SÉNIOR_DE_EXPORTACIONES | CL3: CAMARGO_TICONA_ARMANDO_RICARDO_-_SUPERINTENDENTE_DE_GESTIÓN_COMERCIAL | CN3: LLORENTY_SOLIZ_JORGE_AMED_-_SUPERVISOR_DE_EXPEDITING | CP3: MOLINA_DAVALOS_JESUS_ARMANDO_-_SUPERVISOR_DE_MANEJO_DE_MATERIALES_OPERACIONES_Y_ENTRENAMIENTO | CR3: SUPERINTENDENCIA_DE_MEDIO_AMBIENTE | CT3: MASSY_QUIROGA_NELSON_-_SUPERVISOR_DE_MEDIO_AMBIENTE | CV3: SUPERINTENDENCIA_DE_CAMPAMENTO | CX3: ACHÁ_RUIZ_MARCOS_ROBERTO_-_ESPECIALISTA_DE_COMEDOR_Y_ALIMENTOS | CZ3: ANDRADE_LANZA_WILDER_ELOY_-_SUPERVISOR_SÉNIOR_DE_CAPACITACIÓN | DB3: ARAMAYO_QUIROGA_CARLOS_ANDRES_-_SUPERVISOR_DE_SERVICIOS_Y_PROGRAMAS_DE_SALUD | DD3: CALCINA_CALIZAYA_EFRAÍN_-_SUPERVISOR_DE_SEGURIDAD_FÍSICA | DF3: SUPERINTENDENCIA_DE_DESARROLLO_SOSTENIBLE_Y_RELACIONES_COMUNITARIAS | DH3: AZURDUY_ROSSEL_VLADIMIR_PEDRO_-_SUPERVISOR_DE_DESARROLLO_SOSTENIBLE | DJ3: SUPERINTENDENCIA_DE_SEGURIDAD_INDUSTRIAL | DL3: CASTRO_TORRICO_MIGUEL_ANGEL_-_SUPERVISOR_DE_SEGURIDAD_INDUSTRIAL | DN3: SUPERINTENDENCIA_DE_SERVICIOS_DE_AVIACIÓN | DP3: ALBA_URQUIZO_FERNANDO_JUSTO_-_SUPERVISOR_DE_OPERACIONES_AÉREAS | DR3: AYALA_VENEROS_DOUGLAS_MAURICIO_-_SUPERINTENDENTE_DE_SERVICIOS_DE_TRANSPORTE_DE_PERSONAL | DT3: GERENCIA_DE_PROYECTOS | DV3: SUPERINTENDENCIA_ADMINISTRATIVO_DE_OPERACIONES | DX3: MAIDANA_TARQUINO_MARCELO_-_SUPERINTENDENTE_ADMINISTRATIVO_DE_OPERACIONES | DZ3: ANAYA_RODRIGUEZ_CRISTHIAN_FRANKLIN_-_SUPERVISOR_DE_DISEÑO_Y_CONSTRUCCIÓN | EB3: GERENCIA_DE_FINANZAS | ED3: SUPERINTENDENCIA_DE_CONTABILIDAD | EF3: BELTRÁN_RIOS_CLAUDIA_XIMENA_-_SUPERVISOR_DE_REPORTES_Y_CUMPLIMIENTO | EH3: TARDIO_ROMAY_IRMA_VICENTA_-_SUPERINTENDENTE_DE_IMPUESTOS | EJ3: RODRIGUEZ_CALDERÓN_JAIME_RAMIRO_-_SUPERINTENDENTE_DE_PLANIFICACIÓN_FINANCIERA_(FP&A) | EL3: SUPERINTENDENCIA_DE_DESARROLLO_DEL_NEGOCIO | EN3: REYES_ARISPE_GUSTAVO_JAVIER_-_SUPERINTENDENTE_DE_DESARROLLO_DEL_NEGOCIO | EP3: PEREZ_MONDACA_CARLOS_ALBERTO_-_SUPERVISOR_DE_APLICACIONES_DE_TI | ER3: MENDOZA_GOMEZ_DIEGO_ENRIQUE_-_SUPERINTENDENTE_DE_TO | ET3: JUAN_PABLO_OVIEDO_LLANOS_-_SUPERVISIÓN_DE_SEGURIDAD_DE_LA_INFORMACIÓN_(CISO) | EV3: GERENCIA_DE_MANTENIMIENTO_MINA | EX3: SUPERINTENDENCIA_SÉNIOR_DE_MANTENIMIENTO_MINA | EZ3: BALDERRAMA_HINOJOSA_JUAN_CARLOS_-_COORDINADOR_GENERAL_DE_MANTENIMIENTO_DE_VEHÍCULOS_Y_EQUIPOS_MÓVILES | FB3: TERÁN_GALATOIRE_ROBERTO_CARLOS_-_SUPERINTENDENTE_DE_MANTENIMIENTO_MINA_PLANIFICACIÓN_Y_PROGRAMACIÓN | FD3: SUPERINTENDENCIA_DE_MANTENIMIENTO_ELÉCTRICO_E_INSTRUMENTACIÓN_PLANTA | FF3: BALLADARES_ROCHA_SAUL_RAMIRO_-_SUPERVISOR_DE_MANTENIMIENTO | FH3: CRUZ_RODRIGUEZ_WILMERS_-_ANALISTA_SÉNIOR_DE_CONFIABILIDAD | FJ3: ALI SALGADO JHONNY AGUSTIN - SUPERVISOR DE MANTENIMIENTO | FL3: ADUANA ROCABADO OSCAR - SUPERVISOR DE MANTENIMIENTO | FN3: AGUAYO ROJAS VICTOR HUGO - PLANIFICADOR SÉNIOR DE MANTENIMIENTO | FP3: SUPERINTENDENCIA_DE_INGENIERÍA_MINA | FR3: AYARACHI FERNANDEZ ORLANDO - PLANIFICADOR SÉNIOR DE MINA A CORTO PLAZO | FT3: ALIAGA RODRIGUEZ MARIO ALBERTO - SUPERINTENDENTE DE OPERACIONES MINA | FX3: BASILIO TICONA CORNELIO YECID - RESPONSABLE DE ENTRENAMIENTO MINA | FZ3: SUPERINTENDENCIA_DE_GESTIÓN_DE_RELAVES_Y_SERVICIOS_AUXILIARES | GB3: CARREÑO UZQUIANO CARLOS HUGO - SUPERINTENDENTE DE GESTION DE RELAVES Y SERVICIOS AUXILIARES | GD3: CABRERA MAMANI RUBEN RODY - METALURGISTA DE PROCESO | GF3: JARPA CALLAHUANCA ARIEL JACINTO - JEFE DE TURNO | GH3: CHURATA HUARACHI WILBER - GERENTE DE OPERACIONES PLANTA
A4: 01 | B4: VICEPRESIDENCIA CORPORATIVA | E4: 01 | F4: 02 | G4: GERENCIA DE COMERCIALIZACIÓN Y SERVICIOS | H4: 01 | I4: 02 | L4: 1 | M4: 1 | N4: 02 | O4: SUPERINTENDENCIA DE RELACIONES INSTITUCIONALES | P4: 1 | Q4: 1 | R4: 02 | T4: 2 | U4: 04 | V4: 12 | W4: 32 | X4: ARO | Y4: ADUANA ROCABADO OSCAR | Z4: ADUANA ROCABADO OSCAR - SUPERVISOR DE MANTENIMIENTO | AA4: VICEPRESIDENCIA DE OPERACIONES | AB4: GERENCIA DE MANTENIMIENTO PLANTA | AC4: SUPERINTENDENCIA DE MANTENIMIENTO - MEC. PLTA. CHANCADO, MOLIENDA Y LUBRICACIÓN | AD4: SUPERVISIÓN DE MANTENIMIENTO - CHANCADO / CORREAS TRANSPORTADORAS | AF4: MANTENIMIENTO - CHANCADO / CORREAS TRANSPORTADORAS | AM4: 001 | AN4: Apraccuk | AS4: 01 | AT4: ISOP | AX4: 01 | AY4: version1 | BG4: 101 | BH4: 101 Frente de Carguío | BJ4: 02 | BK4: ADQUISICIONES | BM4: 01 | BO4: VICEPRESIDENCIA_CORPORATIVA | BT4: GERENCIA_DE_COMERCIALIZACIÓN_Y_SERVICIOS | BV4: SUPERINTENDENCIA_DE_RELACIONES_INSTITUCIONALES | BX4: ZAMORA_CORTEZ_LESLIE_MAGDA_-_SUPERVISOR_DE_ADQUISICIONES_DE_SERVICIOS | CF4: SUPERINTENDENCIA_DE_EXPORTACIONES | CH4: CLAVIJO_DOYNEL_MARCO_ANTONIO_-_SUPERVISOR_DE_CONTROL_DE_CALIDAD_DE_ALMACENES | CN4: TORREZ_SALDIAS_GONZALO_-_SUPERVISOR_DE_IMPORTACIONES | CP4: OJITO_ESTRADA_REMBERTO_-_SUPERINTENDENTE_DE_MANEJO_DE_MATERIALES | CV4: SUPERINTENDENCIA_DE_RECURSOS_HUMANOS | CX4: MAMANI_QUISPE_ERNESTO_-_SUPERVISOR_DE_GESTIÓN_DE_RESÍDUOS_Y_ÁREAS_VERDES | CZ4: CALIZAYA_MENA_MIKAELA_LISSETTE_-_SUPERVISOR_DE_ADMINISTRACIÓN_DE_RECURSOS_HUMANOS | DB4: ESTEPA_SUAREZ_CARMEN_ZULEMA_-_SUPERVISOR_DE_SERVICIOS_DE_SALUD_EXTERNA | DD4: LEAÑO_SAAVEDRA_MARCO_ANTONIO_-_SUPERVISOR_DE_SEGURIDAD_FÍSICA | DH4: NUÑEZ_MOLINA_MARCELO_MAURICIO_-_SUPERVISOR_DE_RESPONSABILIDAD_SOCIAL_EXTERNA | DL4: GUMUCIO_LÓPEZ_MIRKO_GEOVANY_-_SUPERVISOR_DE_HIGIENE_INDUSTRIAL | DN4: SUPERINTENDENCIA_DE_SERVICIOS_DE_TRANSPORTE_DE_PERSONAL | DP4: ROCA_FERNANDEZ_RAIMUNDO_-_SUPERVISOR_DE_MANTENIMIENTO_AERONÁUTICO | DR4: CRUZ_LOVERA_SANTOS_ADOLFO_-_COORDINADOR_TÉCNICO_OPERATIVO | DV4: SUPERINTENDENCIA_DE_INGENIERÍA_PLANTA | DZ4: FERNANDEZ_RUIZ_RAMIRO_-_SUPERINTENDENTE_DE_INGENIERIA_PLANTA | EB4: GERENCIA_DE_TI_Y_DESARROLLO_DEL_NEGOCIO | ED4: SUPERINTENDENCIA_DE_IMPUESTOS | EF4: MOSCOSO_ABRAHAM_JESUS_ALEJANDRO_-_SUPERVISOR_DE_TESORERÍA_Y_CUENTAS_POR_PAGAR | EL4: SUPERINTENDENCIA_DE_TI | EP4: VELARDE_LEON_CRISTIAN_HUMBERTO_-_SUPERVISOR_DE_INFRAESTRUCTURA_DE_TI | ER4: MERCADO_CHOQUETICLLA_FRANZ_ARIEL_-_SUPERVISOR_TO_MINA | EV4: GERENCIA_DE_MANTENIMIENTO_PLANTA | EX4: SUPERINTENDENTE_DE_MANTENIMIENTO_MINA_PLANIFICACIÓN_Y_PROGRAMACIÓN | EZ4: BADEA_ROMERO_ALEXANDRO_-_SUPERINTENDENCIA_SÉNIOR_DE_MANTENIMIENTO_MINA | FD4: SUPERINTENDENCIA_DE_MANTENIMIENTO_INGENIERÍA_DE_CONFIABILIDAD | FF4: CAPURATA_FLORES_OVIDIO_-_SUPERINTENDENTE_DE_MANTENIMIENTO | FH4: HERBAS_TORREZ_HENRY_-_SUPERVISOR_DE_ANÁLISIS_DE_CONFIABILIDAD | FJ4: CAMATA QUISPE EDILBER - SUPERVISOR DE MANTENIMIENTO | FL4: ARANDIA COCA MARCO ANTONIO - SUPERVISOR DE MANTENIMIENTO - MOLIENDA | FN4: FLORES GUTIERREZ NESTOR ROMAN - PLANIFICADOR SÉNIOR DE MANTENIMIENTO | FP4: SUPERINTENDENCIA_DE_OPERACIONES_MINA | FR4: BALDERRAMA ZÁRATE BORIZ MARCELO - SUPERVISOR DE SERVICIOS DE EXPLORACIÓN | FT4: CASTRO RAMIREZ MARCIAL - SUPERVISOR DE CARGUÍO Y ACARREO | FZ4: SUPERINTENDENCIA_DE_OPERACIONES_PLANTA | GB4: CASTEDO FRANCO CLAUDIO ANDRES - SUPERVISOR DE SERVICIOS AUXILIARES | GD4: CAYO CRUZ JAIME - METALURGISTA DE PROCESO | GF4: MIRANDA OSSIO RAFAEL JUAN - JEFE DE TURNO | GH4: COPA CALCINA EDDY EDWIN - COORDINADOR PRINCIPAL DE SISTEMAS DE AGUA
A5: 02 | B5: VICEPRESIDENCIA DE DESARROLLO DE PROYECTOS | E5: 01 | F5: 03 | G5: GERENCIA DE MEDIO AMBIENTE | H5: 01 | I5: 03 | L5: 1 | M5: 1 | N5: 03 | O5: SUPERINTENDENCIA DE RELACIONES PÚBLICAS | P5: 1 | Q5: 1 | R5: 03 | T5: 3 | U5: 01 | V5: 01 | X5: AGRE | Y5: AGREDA GOMEZ RODRIGO EMMANUEL | Z5: AGREDA GÓMEZ RODRIGO EMMANUEL - GERENTE CORPORATIVO | AA5: VICEPRESIDENCIA CORPORATIVA | AB5: GERENCIA CORPORATIVA | AF5: GERENCIA CORPORATIVA | AM5: 139 | AN5: ACHUPALLA | AS5: 02 | AT5: (IRO) - AISLAMIENTO | AX5: 02 | AY5: version2 | BG5: 102 | BH5: 102 Malla de Voladura | BJ5: 03 | BK5: ADQUISICIONES DE BIENES | BM5: 02 | BO5: VICEPRESIDENCIA_DE_DESARROLLO_DE_PROYECTOS | BT5: GERENCIA_DE_MEDIO_AMBIENTE | BV5: SUPERINTENDENCIA_DE_RELACIONES_PÚBLICAS | CF5: SUPERINTENDENCIA_DE_GESTION_COMERCIAL | CH5: GUTIERREZ_TORRES_LUGO_VINICIO_-_SUPERINTENDENTE_DE_EXPORTACIONES | CV5: SUPERINTENDENCIA_SÉNIOR_DE_SALUD | CX5: OSUNA_VACAFLOR_JOSE_DANIEL_-_SUPERVISOR_SÉNIOR_DE_CAMPAMENTO | CZ5: QUISPE_CASTRO_CRISTIAN_-_SUPERVISOR_SÉNIOR_DE_GESTIÓN_DE_RECURSOS_HUMANOS | DB5: MOHEBBI_ORTUÑO_VAHID_FLAVIO_-_SUPERVISOR_DE_SALUD_OCUPACIONAL | DD5: NAVAJAS_FLORES_RENE_GONZALO_-_SUPERVISOR_SÉNIOR_DE_SEGURIDAD_FÍSICA | DH5: RAMIREZ_VALVERDE_DELIO_-_SUPERVISOR_DE_RELACIONES_COMUNITARIAS | DL5: PEREZ_ROMERO_FRANZ_REYNALDO_-_SUPERVISOR_ELÉCTRICO_DE_SEGURIDAD_INDUSTRIAL-EMERGENCIAS | DR5: GONZÁLES_COPA_BASILIO_-_COORDINADOR_TÉCNICO_OPERATIVO | DZ5: MONTAÑO_ORTIZ_SERGIO_REINALDO_-_SUPERVISOR_SÉNIOR_DE_PROYECTOS_Y_MODIFICACIONES | ED5: SUPERINTENDENCIA_DE_PLANIFICACIÓN_FINANCIERA | EF5: URQUIDI_SELICH_MARIA_ALEJANDRA_-_SUPERVISOR_DE_CONTABILIDAD_Y_CUENTAS_POR_COBRAR | EL5: SUPERINTENDENCIA_DE_TO | ER5: SORIA_CONDORI_MARCO_ANTONIO_-_JEFE_TO_PLANTA | EV5: GERENCIA_DE_OPERACIONES_MINA | EZ5: CARVAJAL_ZABALA_GUIDO_MARCELO_-_SUPERVISOR_DE_MANTENIMIENTO_MINA | FD5: SUPERINTENDENCIA_DE_MANTENIMIENTO_MEC._PLTA._CHANCADO_MOLIENDA_Y_LUBRICACIÓN | FF5: GOMEZ_VELASCO_LIMBERT_-_SUPERVISOR_DE_MANTENIMIENTO | FH5: HUAYLLANI_DELGADO_JUAN_DE_DIOS_-_SUPERVISOR_DE_MANTENIMIENTO | FJ5: CARRASCO FLORES RAUL PEDRO - SUPERVISOR DE MANTENIMIENTO | FL5: GARCIA AGREDA MARCO ANTONIO - SUPERVISOR DE MANTENIMIENTO | FN5: PAUCARA HILARI DIONISIO - PLANIFICADOR SÉNIOR DE MANTENIMIENTO | FP5: SUPERINTENDENCIA_DE_SERVICIOS_DE_EXPLORACIÓN | FR5: CHACON RUIZ JUAN HERNAN - SUPERVISOR DE GEOLOGÍA | FT5: GARNICA NUGETT ROGER SERGIO - SUPERVISOR DE CARGUÍO Y ACARREO | FZ5: SUPERINTENDENCIA_DE_SERVICIOS_TÉCNICOS | GB5: DURAN SAPIENCIA RONALD ABEL - SUPERVISOR DE SERVICIOS AUXILIARES | GD5: CHOQUE PEREIRA CALIXTO - QUÍMICO SÉNIOR | GF5: RAMOS MAYORGA MARIN - JEFE DE TURNO
A6: 03 | B6: VICEPRESIDENCIA DE FINANZAS | E6: 01 | F6: 04 | G6: GERENCIA DE RECURSOS HUMANOS Y SERVICIOS DE PERSONAL | H6: 01 | I6: 04 | L6: 1 | M6: 1 | N6: 04 | O6: GERENCIA CORPORATIVA | P6: 1 | Q6: 1 | R6: 04 | T6: 4 | U6: 04 | V6: 12 | W6: 34 | X6: ARVH | Y6: AGUAYO ROJAS VICTOR HUGO | Z6: AGUAYO ROJAS VICTOR HUGO - PLANIFICADOR SÉNIOR DE MANTENIMIENTO | AA6: VICEPRESIDENCIA DE OPERACIONES | AB6: GERENCIA DE MANTENIMIENTO PLANTA | AC6: SUPERINTENDENCIA DE MANTENIMIENTO - PLANIFICACIÓN | AF6: MANTENIMIENTO - PLANIFICACIÓN | AM6: 140 | AN6: ACTIVA FITNESS | AS6: 03 | AT6: (IRO) - IZAJE | AX6: 03 | AY6: version3 | BG6: 103 | BH6: 103 Taller Llantas Mina | BJ6: 04 | BK6: ADQUISICIONES DE SERVICIOS | BM6: 03 | BO6: VICEPRESIDENCIA_DE_FINANZAS | BT6: GERENCIA_DE_RECURSOS_HUMANOS_Y_SERVICIOS_DE_PERSONAL | BV6: GERENCIA_CORPORATIVA_ | CF6: SUPERINTENDENCIA_DE_LOGÍSTICA | CH6: ORELLANA_LLANOS_ARIEL_ISAAC_-_SUPERVISOR_DE_CONTROL_DE_INVENTARIOS | CV6: SUPERVISIÓN_SENIOR_DE_SEGURIDAD_FÍSICA | CX6: RAMOS_COLQUE_AUDO_-_SUPERVISOR_DE_SERVICIOS_E_INFRAESTRUCTURA | CZ6: RIVERA_ARZABE_ANDRÉS_CRISTIAN_-_SUPERVISOR_DE_DESARROLLO_ORGANIZACIONAL | DL6: RODRIGUEZ_TAPIA_ALEJANDRO_-_SUPERVISOR_DE_SEGURIDAD_INDUSTRIAL | DR6: QUISPE_CAYO_GERMÁN_GILBERTO_-_COORDINADOR_TÉCNICO_OPERATIVO | DZ6: POMA_CRUZ_DAVID_RENE_-_SUPERVISOR_SÉNIOR_DE_PROYECTOS_Y_MODIFICACIONES | EL6: SUPERVISIÓN_DE_SEGURIDAD_DE_LA_INFORMACIÓN_CISO | EV6: GERENCIA_DE_OPERACIONES_PLANTA | EZ6: CONDARCO_GONZALES_TATIANA_LITZI_-_ANALISTA_SÉNIOR_DE_MANTENIMIENTO_MINA | FD6: SUPERINTENDENCIA_DE_MANTENIMIENTO_MEC._PLTA._FLOT._FILTROS_TALLER_GRAL._Y_RH | FF6: TORRICO_MORALES_ALEXANDER_WALBY_-_SUPERVISOR_DE_MANTENIMIENTO | FH6: LAZO_CAYO_WILSON_VICENTE_-_SUPERINTENDENTE_DE_MANTENIMIENTO | FJ6: CAYO BARTOLOME EDWIN VIDAL - SUPERVISOR DE MANTENIMIENTO | FL6: MUÑOZ ARANDIA ERICK RICARDO - SUPERVISOR DE MANTENIMIENTO | FN6: POQUECHOQUE MENESES JHONNY - PLANIFICADOR SÉNIOR DE MANTENIMIENTO | FP6: SUPERVISIÓN_DE_ENTRENAMIENTO_MINA | FR6: COLQUE FLORES HERIBERTO RAMIRO - SUPERVISOR DE OPERACIONES DEL SISTEMA DE CONTROL DE FLOTA | FT6: MAMANI DONAIRE LUCRECIO - COORDINADOR DE DRENAJE | FZ6: GERENCIA_DE_OPERACIONES_PLANTA_ | GB6: QUISPE RAMOS EUSEBIO - SUPERVISOR SERVICIOS AUXILIARES | GD6: LLAVE COLQUE ABRAHAM OVIDIO - COORDINADOR PRINCIPAL DE SISTEMAS DE AGUA | GF6: SAAVEDRA ANTEZANA FERNANDO ANTONIO - SUPERINTENDENTE DE SERVICIOS TECNICOS
A7: 04 | B7: VICEPRESIDENCIA DE OPERACIONES | E7: 01 | F7: 05 | G7: GERENCIA DE RELACIONES COMUNITARIAS | H7: 01 | I7: 05 | L7: 1 | M7: 2 | N7: 05 | O7: SUPERINTENDENCIA DE ALMACENES Y CONTROL DE INVENTARIOS | P7: 1 | Q7: 2 | R7: 01 | T7: 5 | U7: 01 | V7: 05 | W7: 15 | X7: ARNJ | Y7: AGUIRRE ROMAY NORMA JEANNETH | Z7: AGUIRRE ROMAY NORMA JEANNETH - ASISTENTE DE OFICINA EN POTOSÍ | AA7: VICEPRESIDENCIA CORPORATIVA | AB7: GERENCIA DE RELACIONES COMUNITARIAS | AC7: SUPERINTENDENCIA DE DESARROLLO SOSTENIBLE Y RELACIONES COMUNITARIAS | AD7: SUPERVISIÓN DE RESPONSABILIDAD SOCIAL EXTERNA | AF7: RESPONSABILIDAD SOCIAL EXTERNA | AM7: 002 | AN7: Banco Bisa | AS7: 04 | AT7: (IRO) - SUSTANCIAS PELIGROSAS | AX7: 04 | AY7: version4 | BG7: 104 | BH7: 104 Taller Equipos Mina | BJ7: 05 | BK7: ALMACÉN MINA | BM7: 04 | BO7: VICEPRESIDENCIA_DE_OPERACIONES | BT7: GERENCIA_DE_RELACIONES_COMUNITARIAS | CF7: SUPERINTENDENCIA_DE_MANEJO_DE_MATERIALES | CH7: VALVERDE_ROJAS_JORGE_-_SUPERVISOR_DE_ALMACÉN_MINA | CX7: SALVATIERRA_BAUTISTA_OSCAR_-_SUPERVISOR_OPERATIVO_DE_MANTENIMIENTO_CAMPAMENTO | CZ7: SILES_MUÑOZ_HUMBERTO_PABLO_-_SUPERVISOR_SÉNIOR_DE_RELACIONES_LABORALES | DR7: QUISPE_RAMOS_SANTOS_JAVIER_-_COORDINADOR_DE_OPERACIONES_DE_AERÓDROMO,_ASEO_Y_MANTENIMIENTO_PISTA | DZ7: RAMOS_GORDILLO_RENZO_MARTIN_-_SUPERVISOR_DE_PROYECTOS_Y_MODIFICACIONES | EZ7: GOMEZ_ECHENIQUE_JORGE_JOHANN_-_SUPERVISOR_SÉNIOR_DE_MANTENIMIENTO_MINA_-_REPARACIÓN_DE_COMPONENTES | FD7: SUPERINTENDENCIA_DE_MANTENIMIENTO_PLANIFICACIÓN | FF7: VIÑOLA_VARGAS_JOSE_LUIS_-_SUPERVISOR_DE_MANTENIMIENTO | FH7: PONCE_ANTEQUERA_ALAIN_ROLANDO_-_INGENIERO_SÉNIOR_DE_CONFIABILIDAD_ELÉCTRICA | FJ7: CONDARCO FUENTES JHONY - SUPERVISOR DE MANTENIMIENTO | FL7: NAVARRO LOROÑO JULIO DAVID - SUPERINTENDENTE DE MANTENIMIENTO | FN7: QUINTEROS SAUCEDO ROBERTO - PLANIFICADOR SÉNIOR DE MANTENIMIENTO | FR7: HUARACHI MAMANI NOEL OVIDIO - SUPERVISOR DE PERFORACIÓN Y VOLADURA | FT7: MAMANI MAMANI LUIS ORLANDO - SUPERVISOR DE CARGUÍO Y ACARREO | GD7: MALLCU LIMACHE GUIDO - METALURGISTA DE PROCESO | GF7: VIDAL DIAZ SILVIA ABIGAIL - INGENIERO SENIOR DE CONTROL AVANZADO
E8: 01 | F8: 06 | G8: GERENCIA DE SEGURIDAD INDUSTRIAL | H8: 01 | I8: 06 | L8: 1 | M8: 2 | N8: 06 | O8: SUPERINTENDENCIA DE EXPORTACIONES | P8: 1 | Q8: 2 | R8: 02 | T8: 6 | U8: 04 | V8: 11 | W8: 28 | X8: AEVH | Y8: AIZA EUGENIO VICTOR HUMBERTO | Z8: AIZA EUGENIO VICTOR HUMBERTO - ELECTROMECÁNICO DE MANTENIMIENTO MINA | AA8: VICEPRESIDENCIA DE OPERACIONES | AB8: GERENCIA DE MANTENIMIENTO MINA | AC8: SUPERINTENDENCIA SÉNIOR DE INGENIERÍA Y SEGURIDAD DE EQUIPOS MÓVILES | AD8: SUPERINTENDENCIA DE MANTENIMIENTO MINA - EJECUCIÓN | AE8: SUPERVISIÓN DE MANTENIMIENTO MINA - CARGUÍO | AF8: MANTENIMIENTO MINA - EJECUCIÓN | AM8: 003 | AN8: C & C | AS8: 05 | AT8: (IRO) - TALUDES FRENTES DE CARGUÍO BANQUINAS | AX8: 05 | AY8: version5 | BG8: 105 | BH8: 105 Almacenes Combustibles | BJ8: 06 | BK8: ALMACÉN PLANTA Y COMBUSTIBLES | BT8: GERENCIA_DE_SEGURIDAD_INDUSTRIAL | CX8: UNZUETA_CARDOZO_ALEJANDRA_-_ESPECIALISTA_DE_COMEDOR_Y_ALIMENTOS | DR8: QUISPE_VALDA_ELIAS_-_COORDINADOR_TÉCNICO_OPERATIVO | DZ8: TRUJILLO_LLANO_LEONARDO_-_SUPERVISOR_SÉNIOR_DE_PROYECTOS_Y_MODIFICACIONES | EZ8: HUARACHI_LEAÑO_RICHARD_ANTONIO_-_SUPERVISOR_SÉNIOR_DE_MANTENIMIENTO_MINA_-_SOLDADURA_Y_FABRICACIÓN | FH8: RAMIREZ_RIVEROS_RUPERTO_JUAN_-_ANALISTA_SÉNIOR_DE_CONFIABILIDAD | FJ8: LOPEZ QUIROGA ROSSIO KATTIA - SUPERVISOR DE MANTENIMIENTO | FN8: THOMPSON VELASQUEZ ERIK EDUARDO - SUPERINTENDENTE DE MANTENIMIENTO | FR8: PEREZ BERNA GUALBERTO - SUPERVISOR GEOTECNISTA | FT8: OROSCO ARANCIBIA JUAN CARLOS - SUPERVISOR DE CARGUÍO Y ACARREO | GD8: SÁNCHEZ RIVERA LIMBERT - QUÍMICO SÉNIOR | GF8: VILLAFUERTE SUAREZ BERNABE - JEFE DE TURNO
E9: 01 | F9: 07 | G9: GERENCIA DE SERVICIOS DE TRANSPORTE Y AVIACIÓN | H9: 01 | I9: 07 | L9: 1 | M9: 2 | N9: 07 | O9: SUPERINTENDENCIA DE GESTION COMERCIAL | P9: 1 | Q9: 2 | R9: 03 | T9: 7 | U9: 01 | V9: 01 | X9: ALBA | Y9: ALARCON LEAÑO BLANCA ANDREA | Z9: ALARCÓN LEAÑO BLANCA ANDREA - ESPECIALISTA DE SEGUROS Y GARANTÍAS | AA9: VICEPRESIDENCIA CORPORATIVA | AB9: GERENCIA CORPORATIVA | AF9: CORPORATIVA | AM9: 004 | AN9: Cayara | AS9: 06 | AT9: (IRO) - TRABAJO ELÉCTRICO (Actos Sub Estándar) | BG9: 106 | BH9: 106 Surtidor Combustibles | BJ9: 07 | BK9: ALMACENES Y CONTROL DE INVENTARIOS | BT9: GERENCIA_DE_SERVICIOS_DE_TRANSPORTE_Y_AVIACIÓN | DR9: SOUKUP_MANRIQUEZ_LIBUSE_-_ESPECIALISTA_DE_DISPOSICIÓN_DE_MATERIALES | EZ9: LAZO_CAYO_BLADIMIR_BRAULIO_-_SUPERVISOR_SÉNIOR_DE_GESTIÓN_DE_MANTENIMIENTO_DE_VEHÍCULOS_Y_EQUIPOS_MÓVILES | FJ9: MOLINA MORALES VLADIMIR DAVID - SUPERVISOR DE MANTENIMIENTO | FR9: ROCHA CHUGAR GROVER ANGEL - SUPERVISOR DE TOPOGRAFIA | FT9: QUISPE SALVATIERRA MARIN - COORDINADOR DE DRENAJE | GD9: SEMPÉRTEGUI VELASCO GUSTAVO FERNANDO - QUÍMICO SÉNIOR
E10: 02 | F10: 08 | G10: GERENCIA DE PROYECTOS | H10: 02 | I10: 01 | L10: 1 | M10: 2 | N10: 08 | O10: SUPERINTENDENCIA DE LOGÍSTICA | P10: 1 | Q10: 2 | R10: 04 | T10: 8 | U10: 03 | V10: 09 | W10: 21 | X10: AQMA | Y10: ALARCON QUISPE MARIA ANTONIETA | Z10: ALARCON QUISPE MARIA ANTONIETA - ANALISTA SÉNIOR CONTABLE | AA10: VICEPRESIDENCIA DE FINANZAS | AB10: GERENCIA DE FINANZAS | AC10: SUPERINTENDENCIA DE CONTABILIDAD | AD10: SUPERVISIÓN DE CONTABILIDAD Y CUENTAS POR COBRAR | AF10: CONTABILIDAD Y CUENTAS POR COBRAR | AM10: 144 | AN10: COINTAR | AS10: 07 | AT10: (IRO) - TRABAJO EN ALTURA | BG10: 107 | BH10: 107 Polvorín | BJ10: 08 | BK10: APLICACIONES DE TI | EZ10: NAVARRO_CALDERÓN_DANIEL_IVÁN_-_SUPERVISOR_DE_MANTENIMIENTO_MINA_-_PLANIFICACIÓN,_PROGRAMACIÓN_Y_CONFIABILIDAD | FJ10: PACO RAMOS ERICK MIROSLAV - SUPERVISOR DE MANTENIMIENTO | FR10: RODRIGUEZ ARCE ANTONIO - SUPERVISOR SENIOR DE PERFORACIÓN Y VOLADURA | GD10: TABOADA PRUDENCIO MARCELINO - JEFE DE LABORATORIO QUÍMICO
E11: 03 | F11: 09 | G11: GERENCIA DE FINANZAS | H11: 03 | I11: 01 | L11: 1 | M11: 2 | N11: 09 | O11: SUPERINTENDENCIA DE MANEJO DE MATERIALES | P11: 1 | Q11: 2 | R11: 05 | T11: 9 | U11: 01 | V11: 07 | W11: 17 | X11: AUFJ | Y11: ALBA URQUIZO FERNANDO JUSTO | Z11: ALBA URQUIZO FERNANDO JUSTO - SUPERVISOR DE OPERACIONES AÉREAS | AA11: VICEPRESIDENCIA CORPORATIVA | AB11: GERENCIA DE SERVICIOS DE TRANSPORTE Y AVIACIÓN | AC11: SUPERINTENDENCIA DE SERVICIOS DE AVIACIÓN | AD11: SUPERVISIÓN SÉNIOR DE SERVICIOS DE AVIACIÓN | AE11: SUPERVISIÓN DE OPERACIONES AÉREAS | AF11: SERVICIOS DE AVIACIÓN | AM11: 005 | AN11: Comser | AS11: 08 | AT11: (IRO) - TRABAJOS EN CALIENTE | BG11: 108 | BH11: 108 Almacenes Materiales | BJ11: 09 | BK11: CAMPAMENTO | EZ11: OSSIO_MEZA_EVANS_-_SUPERVISOR_DE_MANTENIMIENTO_MINA | FJ11: RUBIN DE CELIS CANDIA MIGUEL MARTIN - SUPERINTENDENTE DE MANTENIMIENTO
E12: 03 | F12: 10 | G12: GERENCIA DE TI, TO Y SISTEMA DE GESTIÓN | H12: 03 | I12: 02 | L12: 1 | M12: 3 | N12: 10 | O12: SUPERINTENDENCIA DE MEDIO AMBIENTE | P12: 1 | Q12: 3 | R12: 01 | T12: 10 | U12: 01 | V12: 03 | X12: AMGI | Y12: ALBIS MANCILLA GEOVANNY ISRAEL | Z12: ALBIS MANCILLA GEOVANNY ISRAEL - ANALISTA SENIOR EN OBRAS DE INFRAESTRUCTURA PARA EL CIERRE DE PROCESOS | AA12: VICEPRESIDENCIA CORPORATIVA | AB12: GERENCIA DE MEDIO AMBIENTE | AF12: GERENCIA DE MEDIO AMBIENTE | AM12: 006 | AN12: Cooperativa 11 de Julio | AS12: 09 | AT12: (IRO) - TRABAJOS EN ESPACIOS CONFINADOS | BG12: 109 | BH12: 109 Playas de Almacenamiento | BJ12: 10 | BK12: CAPACITACIÓN | EZ12: RAMIREZ_MENDEZ_VICTOR_HUGO_-_SUPERVISOR_ENCARGADO_DE_REPARACIÓN_DE_COMPONENTES_MANTENIMIENTO_MINA | FJ12: YUCRA YUCRA HAROLD ZACARIAS - SUPERVISOR DE MANTENIMIENTO
E13: 04 | F13: 11 | G13: GERENCIA DE MANTENIMIENTO MINA | H13: 04 | I13: 01 | L13: 1 | M13: 4 | N13: 11 | O13: SUPERINTENDENCIA DE CAMPAMENTO | P13: 1 | Q13: 4 | R13: 01 | T13: 11 | U13: 01 | V13: 01 | W13: 02 | X13: AMDC | Y13: ALFARO MIRANDA DAYSI CINTHIA | Z13: ALFARO MIRANDA DAYSI CINTHIA - SUPERINTENDENTE DE RELACIONES INSTITUCIONALES | AA13: VICEPRESIDENCIA CORPORATIVA | AB13: GERENCIA CORPORATIVA | AC13: SUPERINTENDENCIA DE RELACIONES INSTITUCIONALES | AF13: RELACIONES INSTITUCIONALES | AM13: 007 | AN13: Cooperativa Nor Lipez | AS13: 10 | AT13: (IRO) - TRABAJOS EN EXCAVACIONES | BG13: 110 | BH13: 110 Almacenes Reactivos | BJ13: 11 | BK13: CARGUÍO Y ACARREO | EZ13: TINTAYA_QUENTA_JUAN_ROBERTO_-_SUPERVISOR_SÉNIOR_DE_MANTENIMIENTO_MINA
E14: 04 | F14: 12 | G14: GERENCIA DE MANTENIMIENTO PLANTA | H14: 04 | I14: 02 | L14: 1 | M14: 4 | N14: 12 | O14: SUPERINTENDENCIA DE RECURSOS HUMANOS | P14: 1 | Q14: 4 | R14: 02 | T14: 12 | U14: 01 | V14: 05 | W14: 15 | X14: AA | Y14: ALI AYDEE | Z14: ALI AYDEE - ENCARGADO DE PROYECTOS SOCIALES | AA14: VICEPRESIDENCIA CORPORATIVA | AB14: GERENCIA DE RELACIONES COMUNITARIAS | AC14: SUPERINTENDENCIA DE DESARROLLO SOSTENIBLE Y RELACIONES COMUNITARIAS | AD14: SUPERVISIÓN DE RELACIONES COMUNITARIAS | AF14: RELACIONES COMUNITARIAS | AM14: 008 | AN14: Cooperativa San Cristóbal de Lípez | AS14: 11 | AT14: (IRO) - TRABAJO ELÉCTRICO (Condiciones Sub Estándar) | BG14: 111 | BH14: 111 Deposito de Material estéril | BJ14: 12 | BK14: CONTABILIDAD | EZ14: VARGAS_SALAZAR_MARTIN_JORGE_-_SUPERVISOR_DE_MANTENIMIENTO_MINA
E15: 04 | F15: 13 | G15: GERENCIA DE OPERACIONES MINA | H15: 04 | I15: 03 | L15: 1 | M15: 4 | N15: 13 | O15: SUPERINTENDENCIA SÉNIOR DE SALUD | P15: 1 | Q15: 4 | R15: 03 | T15: 13 | U15: 04 | V15: 14 | W15: 40 | X15: ACSA | Y15: ALI CALCINA SAUL ALBERTO | Z15: ALI CALCINA SAUL ALBERTO - OFICIAL DE AISLAMIENTO | AA15: VICEPRESIDENCIA DE OPERACIONES | AB15: GERENCIA DE OPERACIONES PLANTA | AC15: SUPERINTENDENCIA DE OPERACIONES PLANTA | AF15: OPERACIONES PLANTA | AM15: 009 | AN15: Emp. Trans. Mackay Taborga | AS15: 12 | AT15: STOP | BG15: 112 | BH15: 112 Camino de Acarreo | BJ15: 13 | BK15: CONTABILIDAD Y CUENTAS POR COBRAR
E16: 04 | F16: 14 | G16: GERENCIA DE OPERACIONES PLANTA | H16: 04 | I16: 04 | L16: 1 | M16: 4 | N16: 14 | O16: SUPERVISIÓN SENIOR DE SEGURIDAD FÍSICA | P16: 1 | Q16: 4 | R16: 04 | T16: 14 | U16: 01 | V16: 04 | W16: 11 | X16: ACM | Y16: ALI COLQUE MARINA | Z16: ALÍ COLQUE MARINA - ASISTENTE DE COMEDOR Y ALIMENTOS | AA16: VICEPRESIDENCIA CORPORATIVA | AB16: GERENCIA DE RECURSOS HUMANOS Y SERVICIOS DE PERSONAL | AC16: SUPERINTENDENCIA DE CAMPAMENTO | AF16: CAMPAMENTO | AM16: 010 | AN16: ENTEL | AS16: 13 | AT16: ISE | BG16: 113 | BH16: 113 Camino de acceso | BJ16: 14 | BK16: CONTROL DE CALIDAD DE ALMACENES
L17: 1 | M17: 5 | N17: 15 | O17: SUPERINTENDENCIA DE DESARROLLO SOSTENIBLE Y RELACIONES COMUNITARIAS | P17: 1 | Q17: 5 | R17: 01 | T17: 15 | U17: 04 | V17: 13 | X17: AGIL | Y17: ALI GONZALES ISAAC LEONCIO | Z17: ALÍ GONZÁLES ISAAC LEONCIO - INSTRUCTOR DE ENTRENAMIENTO MINA | AA17: VICEPRESIDENCIA DE OPERACIONES | AB17: GERENCIA DE OPERACIONES MINA | AF17: OPERACIONES MINA | AM17: 011 | AN17: ESMI | AS17: 14 | AT17: CAPACITACION | BG17: 114 | BH17: 114 Zonas de Acopio Mineral | BJ17: 15 | BK17: CONTROL DE INVENTARIOS
L18: 1 | M18: 6 | N18: 16 | O18: SUPERINTENDENCIA DE SEGURIDAD INDUSTRIAL | P18: 1 | Q18: 6 | R18: 01 | T18: 16 | U18: 04 | V18: 14 | W18: 40 | X18: AP | Y18: ALI PABLO | Z18: ALI PABLO - CAPATAZ DE FILTROS Y CARGUÍO | AA18: VICEPRESIDENCIA DE OPERACIONES | AB18: GERENCIA DE OPERACIONES PLANTA | AC18: SUPERINTENDENCIA DE OPERACIONES PLANTA | AF18: OPERACIONES PLANTA | AM18: 012 | AN18: Eurocom | AS18: 15 | AT18: PLSEG (Planilla Seguimiento) | BG18: 115 | BH18: 115 Comedores | BJ18: 16 | BK18: CORPORATIVA
L19: 1 | M19: 7 | N19: 17 | O19: SUPERINTENDENCIA DE SERVICIOS DE AVIACIÓN | P19: 1 | Q19: 7 | R19: 01 | T19: 17 | U19: 04 | V19: 12 | W19: 33 | X19: ASJA | Y19: ALI SALGADO JHONNY AGUSTIN | Z19: ALI SALGADO JHONNY AGUSTIN - SUPERVISOR DE MANTENIMIENTO | AA19: VICEPRESIDENCIA DE OPERACIONES | AB19: GERENCIA DE MANTENIMIENTO PLANTA | AC19: SUPERINTENDENCIA DE MANTENIMIENTO - MEC. PLTA. FLOT., FILTROS, TALLER GRAL. Y RH | AD19: SUPERVISIÓN DE MANTENIMIENTO - FILTRACIÓN Y CARGUÍO | AF19: MEC. PLTA. FLOT., FILTROS, TALLER GRAL. Y RH | AM19: 013 | AN19: Fanexa | AS19: 16 | AT19: INCIDENTES | BG19: 116 | BH19: 116 Cafeterías | BJ19: 17 | BK19: DESARROLLO ORGANIZACIONAL Y BIENESTAR LABORAL
L20: 1 | M20: 7 | N20: 18 | O20: SUPERINTENDENCIA DE SERVICIOS DE TRANSPORTE DE PERSONAL | P20: 1 | Q20: 7 | R20: 02 | T20: 18 | U20: 04 | V20: 13 | W20: 36 | X20: AYF | Y20: ALI YAÑEZ FREDDY | Z20: ALI YAÑEZ FREDDY - CAPATAZ OPERATIVO MINA | AA20: VICEPRESIDENCIA DE OPERACIONES | AB20: GERENCIA DE OPERACIONES MINA | AC20: SUPERINTENDENCIA DE OPERACIONES MINA | AD20: SUPERVISIÓN DE CARGUÍO Y ACARREO | AF20: OPERACIONES MINA | AM20: 014 | AN20: FCA | AS20: 17 | BG20: 117 | BH20: 117 Oficinas | BJ20: 18 | BK20: DESARROLLO SOSTENIBLE
L21: 2 | M21: 8 | N21: 19 | O21: SUPERINTENDENCIA ADMINISTRATIVO DE OPERACIONES | P21: 2 | Q21: 1 | R21: 01 | T21: 19 | U21: 04 | V21: 13 | W21: 36 | X21: ARMA | Y21: ALIAGA RODRIGUEZ MARIO ALBERTO | Z21: ALIAGA RODRIGUEZ MARIO ALBERTO - SUPERINTENDENTE DE OPERACIONES MINA | AA21: VICEPRESIDENCIA DE OPERACIONES | AB21: GERENCIA DE OPERACIONES MINA | AC21: SUPERINTENDENCIA DE OPERACIONES MINA | AF21: OPERACIONES MINA | AM21: 015 | AN21: Finning | AS21: 18 | BG21: 118 | BH21: 118 Estacionamiento de Vehículos | BJ21: 19 | BK21: DESARROLLO SOSTENIBLE Y RELACIONES COMUNITARIAS
L22: 2 | M22: 8 | N22: 20 | O22: SUPERINTENDENCIA DE INGENIERÍA PLANTA | P22: 2 | Q22: 1 | R22: 02 | T22: 20 | U22: 04 | V22: 13 | W22: 35 | X22: AGA | Y22: ALY GONZALES ALBERTO | Z22: ALY GONZÁLES ALBERTO - COORDINADOR DE PERFORACIÓN Y VOLADURA | AA22: VICEPRESIDENCIA DE OPERACIONES | AB22: GERENCIA DE OPERACIONES MINA | AC22: SUPERINTENDENCIA SÉNIOR DE INGENIERÍA MINA | AD22: SUPERVISIÓN SÉNIOR DE PERFORACIÓN Y VOLADURA | AF22: PERFORACIÓN Y VOLADURA | AM22: 016 | AN22: Fundación San Cristóbal | AS22: 19 | BG22: 119 | BH22: 119 Casa de Cambio | BJ22: 20 | BK22: ELECTRICO DE SEGURIDAD INDUSTRIAL/ EMERGENCIAS
L23: 3 | M23: 9 | N23: 21 | O23: SUPERINTENDENCIA DE CONTABILIDAD | P23: 3 | Q23: 1 | R23: 01 | T23: 21 | U23: 02 | V23: 08 | W23: 20 | X23: ARCF | Y23: ANAYA RODRIGUEZ CRISTHIAN FRANKLIN | Z23: ANAYA RODRIGUEZ CRISTHIAN FRANKLIN - SUPERVISOR DE DISEÑO Y CONSTRUCCIÓN | AA23: VICEPRESIDENCIA DE DESARROLLO DE PROYECTOS | AB23: GERENCIA DE PROYECTOS | AC23: SUPERINTENDENCIA DE INGENIERÍA PLANTA | AD23: SUPERVISIÓN SÉNIOR DE PROYECTOS Y MODIFICACIONES | AF23: PROYECTOS Y MODIFICACIONES | AM23: 017 | AN23: Geotec | AS23: 20 | BG23: 120 | BH23: 120 Truck Shop | BJ23: 21 | BK23: EXPORTACIONES
L24: 3 | M24: 9 | N24: 22 | O24: SUPERINTENDENCIA DE IMPUESTOS | P24: 3 | Q24: 1 | R24: 02 | T24: 22 | U24: 01 | V24: 04 | W24: 12 | X24: ALWE | Y24: ANDRADE LANZA WILDER ELOY | Z24: ANDRADE LANZA WILDER ELOY - SUPERVISOR SÉNIOR DE DESARROLLO ORGANIZACIONAL Y BIENESTAR LABORAL | AA24: VICEPRESIDENCIA CORPORATIVA | AB24: GERENCIA DE RECURSOS HUMANOS Y SERVICIOS DE PERSONAL | AC24: SUPERINTENDENCIA DE RECURSOS HUMANOS | AD24: SUPERVISIÓN SÉNIOR DE DESARROLLO ORGANIZACIONAL Y BIENESTAR LABORAL | AF24: DESARROLLO ORGANIZACIONAL Y BIENESTAR LABORAL | AM24: 142 | AN24: GEO AGUAS | AS24: 21 | BG24: 121 | BH24: 121 Exploraciones Geológica | BJ24: 22 | BK24: FINANZAS
L25: 3 | M25: 9 | N25: 23 | O25: SUPERINTENDENCIA DE PLANIFICACIÓN FINANCIERA (FP&A) | P25: 3 | Q25: 1 | R25: 03 | T25: 23 | U25: 01 | V25: 06 | X25: ATMP | Y25: ANTEZANA TORREZ MARCO PAUL | Z25: ANTEZANA TORREZ MARCO PAUL - GERENTE DE SEGURIDAD INDUSTRIAL | AA25: VICEPRESIDENCIA CORPORATIVA | AB25: GERENCIA DE SEGURIDAD INDUSTRIAL | AF25: GERENCIA DE SEGURIDAD INDUSTRIAL | AM25: 018 | AN25: Hexagon Inc. | AS25: 22 | BG25: 122 | BH25: 122 Campo Marina | BJ25: 23 | BK25: GEOLOGÍA
L26: 3 | M26: 10 | N26: 24 | O26: SUPERINTENDENCIA DE SISTEMA DE GESTIÓN | P26: 3 | Q26: 2 | R26: 01 | T26: 24 | U26: 01 | V26: 06 | W26: 16 | X26: AMJF | Y26: ANZA MORALES JORGE FELIX | Z26: ANZA MORALES JORGE FELIX - INGENIERO DE HIGIENE INDUSTRIAL | AA26: VICEPRESIDENCIA CORPORATIVA | AB26: GERENCIA DE SEGURIDAD INDUSTRIAL | AC26: SUPERINTENDENCIA DE SEGURIDAD INDUSTRIAL | AF26: SEGURIDAD INDUSTRIAL | AM26: 019 | AN26: INSEIN SRL | AS26: 23 | BG26: 123 | BH26: 123 Campo Roma | BJ26: 24 | BK26: GEOTECNIA
L27: 3 | M27: 10 | N27: 25 | O27: SUPERINTENDENCIA DE TI | P27: 3 | Q27: 2 | R27: 02 | T27: 25 | U27: 01 | V27: 04 | W27: 13 | X27: AQBR | Y27: APAZA QUEVEDO BORIS RODRIGO | Z27: APAZA QUEVEDO BORIS RODRIGO - ANALISTA SÉNIOR DE GESTIÓN DE INFORMACIÓN EN SALUD | AA27: VICEPRESIDENCIA CORPORATIVA | AB27: GERENCIA DE RECURSOS HUMANOS Y SERVICIOS DE PERSONAL | AC27: SUPERINTENDENCIA SÉNIOR DE SALUD | AF27: SALUD | AM27: 020 | AN27: Jayula | AS27: 24 | BG27: 124 | BH27: 124 Antenas Comunicación Dispach | BJ27: 25 | BK27: GERENCIA CORPORATIVA
L28: 3 | M28: 10 | N28: 26 | O28: SUPERINTENDENCIA DE TO | P28: 3 | Q28: 2 | R28: 03 | T28: 26 | U28: 01 | V28: 04 | W28: 13 | X28: AQCA | Y28: ARAMAYO QUIROGA CARLOS ANDRES | Z28: ARAMAYO QUIROGA CARLOS ANDRES - SUPERVISOR DE SERVICIOS Y PROGRAMAS DE SALUD | AA28: VICEPRESIDENCIA CORPORATIVA | AB28: GERENCIA DE RECURSOS HUMANOS Y SERVICIOS DE PERSONAL | AC28: SUPERINTENDENCIA SÉNIOR DE SALUD | AD28: SUPERVISIÓN DE SERVICIOS Y PROGRAMAS DE SALUD | AF28: SERVICIOS Y PROGRAMAS DE SALUD | AM28: 021 | AN28: Juan Carlos Huaranca Ariste (Consultor) | AS28: 25 | BG28: 125 | BH28: 125 Chancador Parker | BJ28: 26 | BK28: GERENCIA DE COMERCIALIZACIÓN Y SERVICIOS | EV28: GERENCIA DE OPERACIONES PLANTA | EX28: =SUBSTITUTE(EV28," ","_") -> GERENCIA_DE_OPERACIONES_PLANTA
L29: 3 | M29: 10 | N29: 27 | O29: SUPERVISIÓN DE SEGURIDAD DE LA INFORMACIÓN (CISO) | P29: 3 | Q29: 2 | R29: 04 | T29: 27 | U29: 04 | V29: 12 | W29: 32 | X29: ACMA | Y29: ARANDIA COCA MARCO ANTONIO | Z29: ARANDIA COCA MARCO ANTONIO - SUPERVISOR DE MANTENIMIENTO - MOLIENDA | AA29: VICEPRESIDENCIA DE OPERACIONES | AB29: GERENCIA DE MANTENIMIENTO PLANTA | AC29: SUPERINTENDENCIA DE MANTENIMIENTO - MEC. PLTA. CHANCADO, MOLIENDA Y LUBRICACIÓN | AF29: MEC. PLTA. CHANCADO, MOLIENDA Y LUBRICACIÓN | AM29: 022 | AN29: Komatsu | AS29: 26 | BG29: 126 | BH29: 126 Plataforma 3 Gigantes | BJ29: 27 | BK29: GERENCIA DE FINANZAS | EV29: SUPERINTENDENCIA DE GESTIÓN DE RELAVES Y SERVICIOS AUXILIARES | EX29: =SUBSTITUTE(EV29," ","_") -> SUPERINTENDENCIA_DE_GESTIÓN_DE_RELAVES_Y_SERVICIOS_AUXILIARES
L30: 4 | M30: 11 | N30: 28 | O30: SUPERINTENDENCIA SÉNIOR DE INGENIERÍA Y SEGURIDAD DE EQUIPOS MÓVILES | P30: 4 | Q30: 1 | R30: 01 | T30: 28 | U30: 03 | V30: 09 | X30: ASJC | Y30: ARANIBAR SAPIENCIA JUAN CARLOS | Z30: ARANIBAR SAPIENCIA JUAN CARLOS - ESPECIALISTA EN GESTIÓN DE DATOS Y AUTOMATIZACIÓN | AA30: VICEPRESIDENCIA DE FINANZAS | AB30: GERENCIA DE FINANZAS | AF30: FINANZAS | AM30: 138 | AN30: KLIMAX LTDA | AS30: 27 | BG30: 127 | BH30: 127 Área de Perforación | BJ30: 28 | BK30: GERENCIA DE MANTENIMIENTO MINA | EV30: SUPERINTENDENCIA DE OPERACIONES PLANTA | EX30: =SUBSTITUTE(EV30," ","_") -> SUPERINTENDENCIA_DE_OPERACIONES_PLANTA
L31: 4 | M31: 11 | N31: 29 | O31: SUPERINTENDENTE DE MANTENIMIENTO MINA PLANIFICACIÓN Y PROGRAMACIÓN | P31: 4 | Q31: 1 | R31: 02 | T31: 29 | U31: 04 | V31: 11 | W31: 28 | X31: AEOB | Y31: ARION ESCOBAR OMAR BERNARDO | Z31: ARIÓN ESCOBAR OMAR BERNARDO - COORDINADOR PRINCIPAL DE MANTENIMIENTO MINA | AA31: VICEPRESIDENCIA DE OPERACIONES | AB31: GERENCIA DE MANTENIMIENTO MINA | AC31: SUPERINTENDENCIA SÉNIOR DE INGENIERÍA Y SEGURIDAD DE EQUIPOS MÓVILES | AD31: SUPERINTENDENCIA DE MANTENIMIENTO MINA - EJECUCIÓN | AE31: SUPERVISIÓN DE MANTENIMIENTO MINA - ACARREO | AF31: MANTENIMIENTO MINA - EJECUCIÓN | AM31: 023 | AN31: LEDUC | AS31: 28 | BG31: 128 | BH31: 128 Bahías Mina | BJ31: 29 | BK31: GERENCIA DE MANTENIMIENTO PLANTA | EV31: SUPERINTENDENCIA DE SERVICIOS TÉCNICOS | EX31: =SUBSTITUTE(EV31," ","_") -> SUPERINTENDENCIA_DE_SERVICIOS_TÉCNICOS
L32: 4 | M32: 12 | N32: 30 | O32: SUPERINTENDENCIA DE MANTENIMIENTO - ELÉCTRICO E INSTRUMENTACIÓN PLANTA | P32: 4 | Q32: 2 | R32: 01 | T32: 30 | U32: 01 | V32: 01 | W32: 03 | X32: AANC | Y32: ARMATA AGREDA NILDA CARMEN | Z32: ARMATA AGREDA NILDA CARMEN - ASISTENTE EJECUTIVA | AA32: VICEPRESIDENCIA CORPORATIVA | AB32: GERENCIA CORPORATIVA | AC32: SUPERINTENDENCIA DE RELACIONES PÚBLICAS | AF32: RELACIONES PÚBLICAS | AM32: 024 | AN32: Maldonado Exploraciones | AS32: 29 | BG32: 129 | BH32: 129 Taller Soldadura Mina | BJ32: 30 | BK32: GERENCIA DE MEDIO AMBIENTE | EV32: GERENCIA DE OPERACIONES PLANTA | EX32: =SUBSTITUTE(EV32," ","_") -> GERENCIA_DE_OPERACIONES_PLANTA
L33: 4 | M33: 12 | N33: 31 | O33: SUPERINTENDENCIA DE MANTENIMIENTO - INGENIERÍA DE CONFIABILIDAD | P33: 4 | Q33: 2 | R33: 02 | T33: 31 | U33: 04 | V33: 11 | W33: 28 | X33: ALE | Y33: AYALA LLAVE EDWIN | Z33: AYALA LLAVE EDWIN - ELECTROMECÁNICO DE MANTENIMIENTO MINA A | AA33: VICEPRESIDENCIA DE OPERACIONES | AB33: GERENCIA DE MANTENIMIENTO MINA | AC33: SUPERINTENDENCIA SÉNIOR DE INGENIERÍA Y SEGURIDAD DE EQUIPOS MÓVILES | AD33: SUPERINTENDENCIA DE MANTENIMIENTO MINA - EJECUCIÓN | AE33: SUPERVISIÓN DE MANTENIMIENTO MINA - ACARREO | AF33: MANTENIMIENTO MINA - EJECUCIÓN | AM33: 145 | AN33: MB White Metals Service & Constructions Ltda. | BG33: 020 | BH33: 20 AREA PROCESOS | BJ33: 31 | BK33: GERENCIA DE OPERACIONES MINA | EX33: =SUBSTITUTE(EV33," ","_")
L34: 4 | M34: 12 | N34: 32 | O34: SUPERINTENDENCIA DE MANTENIMIENTO - MEC. PLTA. CHANCADO, MOLIENDA Y LUBRICACIÓN | P34: 4 | Q34: 2 | R34: 03 | T34: 32 | U34: 01 | V34: 07 | W34: 18 | X34: AVDM | Y34: AYALA VENEROS DOUGLAS MAURICIO | Z34: AYALA VENEROS DOUGLAS MAURICIO - SUPERINTENDENTE DE SERVICIOS DE TRANSPORTE DE PERSONAL | AA34: VICEPRESIDENCIA CORPORATIVA | AB34: GERENCIA DE SERVICIOS DE TRANSPORTE Y AVIACIÓN | AC34: SUPERINTENDENCIA DE SERVICIOS DE TRANSPORTE DE PERSONAL | AF34: SERVICIOS DE TRANSPORTE DE PERSONAL | AM34: 025 | AN34: MegaMaquinaria | BG34: 201 | BH34: 201 Chancadora Primario | BJ34: 32 | BK34: GERENCIA DE OPERACIONES PLANTA | EX34: =SUBSTITUTE(EV34," ","_")
L35: 4 | M35: 12 | N35: 33 | O35: SUPERINTENDENCIA DE MANTENIMIENTO - MEC. PLTA. FLOT., FILTROS, TALLER GRAL. Y RH | P35: 4 | Q35: 2 | R35: 04 | T35: 33 | U35: 04 | V35: 13 | W35: 35 | X35: AFJL | Y35: AYARACHI FERNANDEZ JOSE LUIS | Z35: AYARACHI FERNÁNDEZ JOSE LUIS - PLANIFICADOR DE MINA A LARGO PLAZO | AA35: VICEPRESIDENCIA DE OPERACIONES | AB35: GERENCIA DE OPERACIONES MINA | AC35: SUPERINTENDENCIA SÉNIOR DE INGENIERÍA MINA | AF35: INGENIERÍA MINA | AM35: 026 | AN35: MELBI | BG35: 202 | BH35: 202 Separación de Finos | BJ35: 33 | BK35: GERENCIA DE PROYECTOS | EX35: =SUBSTITUTE(EV35," ","_")
L36: 4 | M36: 12 | N36: 34 | O36: SUPERINTENDENCIA DE MANTENIMIENTO - PLANIFICACIÓN | P36: 4 | Q36: 2 | R36: 05 | T36: 34 | U36: 04 | V36: 13 | W36: 35 | X36: AFO | Y36: AYARACHI FERNANDEZ ORLANDO | Z36: AYARACHI FERNANDEZ ORLANDO - PLANIFICADOR SÉNIOR DE MINA A CORTO PLAZO | AA36: VICEPRESIDENCIA DE OPERACIONES | AB36: GERENCIA DE OPERACIONES MINA | AC36: SUPERINTENDENCIA SÉNIOR DE INGENIERÍA MINA | AF36: INGENIERÍA MINA | AM36: 027 | AN36: Metso:Outotec | BG36: 203 | BH36: 203 Correa Transportadora CV 3 | BJ36: 34 | BK36: GERENCIA DE RECURSOS HUMANOS Y SERVICIOS DE PERSONAL | EX36: =SUBSTITUTE(EV36," ","_")
L37: 4 | M37: 13 | N37: 35 | O37: SUPERINTENDENCIA SÉNIOR DE INGENIERÍA MINA | P37: 4 | Q37: 3 | R37: 01 | T37: 35 | U37: 04 | V37: 11 | W37: 28 | X37: ARJA | Y37: AYAVIRI RAMOS JOSE ANGEL | Z37: AYAVIRI RAMOS JOSÉ ANGEL - ELECTROMECÁNICO DE MANTENIMIENTO MINA B | AA37: VICEPRESIDENCIA DE OPERACIONES | AB37: GERENCIA DE MANTENIMIENTO MINA | AC37: SUPERINTENDENCIA SÉNIOR DE INGENIERÍA Y SEGURIDAD DE EQUIPOS MÓVILES | AD37: SUPERINTENDENCIA DE MANTENIMIENTO MINA - EJECUCIÓN | AE37: SUPERVISIÓN DE MANTENIMIENTO MINA - ACARREO | AF37: MANTENIMIENTO MINA - EJECUCIÓN | AM37: 141 | AN37: MIRIAN QUISPE | BG37: 204 | BH37: 204 Otras Correas Transportadoras | BJ37: 35 | BK37: GERENCIA DE RELACIONES COMUNITARIAS | EX37: =SUBSTITUTE(EV37," ","_")
L38: 4 | M38: 13 | N38: 36 | O38: SUPERINTENDENCIA DE OPERACIONES MINA | P38: 4 | Q38: 3 | R38: 02 | T38: 36 | U38: 01 | V38: 05 | W38: 15 | X38: ARVP | Y38: AZURDUY ROSSEL VLADIMIR PEDRO | Z38: AZURDUY ROSSEL VLADIMIR PEDRO - SUPERVISOR DE DESARROLLO SOSTENIBLE | AA38: VICEPRESIDENCIA CORPORATIVA | AB38: GERENCIA DE RELACIONES COMUNITARIAS | AC38: SUPERINTENDENCIA DE DESARROLLO SOSTENIBLE Y RELACIONES COMUNITARIAS | AD38: SUPERVISIÓN DE DESARROLLO SOSTENIBLE | AF38: DESARROLLO SOSTENIBLE | AM38: 028 | AN38: NEUMA BOLIVIA S.R.L. | BG38: 205 | BH38: 205 Pila de Acopio DOMO | BJ38: 36 | BK38: GERENCIA DE SEGURIDAD INDUSTRIAL | EX38: =SUBSTITUTE(EV38," ","_")
L39: 4 | M39: 13 | N39: 37 | O39: SUPERINTENDENCIA DE SERVICIOS DE EXPLORACIÓN | P39: 4 | Q39: 3 | R39: 03 | T39: 37 | U39: 04 | V39: 11 | W39: 28 | X39: BRA | Y39: BADEA ROMERO ALEXANDRO | Z39: BADEA ROMERO ALEXANDRO - SUPERINTENDENTE SÉNIOR DE INGENIERÍA Y SEGURIDAD DE EQUIPOS MÓVILES | AA39: VICEPRESIDENCIA DE OPERACIONES | AB39: GERENCIA DE MANTENIMIENTO MINA | AC39: SUPERINTENDENCIA SÉNIOR DE INGENIERÍA Y SEGURIDAD DE EQUIPOS MÓVILES | AF39: INGENIERÍA Y SEGURIDAD DE EQUIPOS MÓVILES | AM39: 029 | AN39: NEWREST | BG39: 206 | BH39: 206 Stock de Reserva | BJ39: 37 | BK39: GERENCIA DE SERVICIOS DE TRANSPORTE Y AVIACIÓN | EX39: =SUBSTITUTE(EV39," ","_")
L40: 4 | M40: 13 | N40: 38 | O40: SUPERVISIÓN DE ENTRENAMIENTO MINA | P40: 4 | Q40: 3 | R40: 04 | T40: 38 | U40: 04 | V40: 12 | W40: 33 | X40: BPJC | Y40: BALBOA PATTY JUAN CARLOS | Z40: BALBOA PATTY JUAN CARLOS - ESPECIALISTA SOLDADOR/TUBERO | AA40: VICEPRESIDENCIA DE OPERACIONES | AB40: GERENCIA DE MANTENIMIENTO PLANTA | AC40: SUPERINTENDENCIA DE MANTENIMIENTO - MEC. PLTA. FLOT., FILTROS, TALLER GRAL. Y RH | AD40: SUPERVISIÓN DE MANTENIMIENTO - GENERAL Y SOLDADURA | AF40: MANTENIMIENTO - GENERAL Y SOLDADURA | AM40: 030 | AN40: OPEC | BG40: 207 | BH40: 207 Túnel transportación | BJ40: 38 | BK40: GERENCIA DE TI, TO Y SISTEMA DE GESTIÓN | EX40: =SUBSTITUTE(EV40," ","_")
L41: 4 | M41: 14 | N41: 39 | O41: SUPERINTENDENCIA DE GESTIÓN DE RELAVES Y SERVICIOS AUXILIARES | P41: 4 | Q41: 4 | R41: 01 | T41: 39 | U41: 01 | V41: 02 | W41: 05 | X41: BMA | Y41: BALCAZAR MANUEL ALEJANDRO | Z41: BALCAZAR MANUEL ALEJANDRO - ANALISTA SÉNIOR DE CONTROL DE INVENTARIOS | AA41: VICEPRESIDENCIA CORPORATIVA | AB41: GERENCIA DE COMERCIALIZACIÓN Y SERVICIOS | AC41: SUPERINTENDENCIA DE ALMACENES Y CONTROL DE INVENTARIOS | AD41: SUPERVISIÓN DE CONTROL DE INVENTARIOS | AF41: CONTROL DE INVENTARIOS | AM41: 031 | AN41: REMSA | BG41: 208 | BH41: 208 Lechada de Cal | BJ41: 39 | BK41: GESTION COMERCIAL | EX41: =SUBSTITUTE(EV41," ","_")
L42: 4 | M42: 14 | N42: 40 | O42: SUPERINTENDENCIA DE OPERACIONES PLANTA | P42: 4 | Q42: 4 | R42: 02 | T42: 40 | U42: 04 | V42: 11 | W42: 28 | X42: BHJC | Y42: BALDERRAMA HINOJOSA JUAN CARLOS | Z42: BALDERRAMA HINOJOSA JUAN CARLOS - COORDINADOR GENERAL DE MANTENIMIENTO DE VEHÍCULOS Y EQUIPOS MÓVILES | AA42: VICEPRESIDENCIA DE OPERACIONES | AB42: GERENCIA DE MANTENIMIENTO MINA | AC42: SUPERINTENDENCIA SÉNIOR DE INGENIERÍA Y SEGURIDAD DE EQUIPOS MÓVILES | AD42: SUPERVISIÓN SÉNIOR DE GESTIÓN DE MANTENIMIENTO DE VEHÍCULOS Y EQUIPOS MÓVILES | AF42: GESTIÓN DE MANTENIMIENTO DE VEHÍCULOS Y EQUIPOS MÓVILES | AM42: 137 | AN42: REMAFIL | BG42: 209 | BH42: 209 Molienda | BJ42: 40 | BK42: GESTIÓN DE MANTENIMIENTO DE VEHÍCULOS Y EQUIPOS MÓVILES
L43: 4 | M43: 14 | N43: 41 | O43: SUPERINTENDENCIA DE SERVICIOS TÉCNICOS | P43: 4 | Q43: 4 | R43: 03 | T43: 41 | U43: 04 | V43: 13 | W43: 37 | X43: BZBM | Y43: BALDERRAMA ZARATE BORIZ MARCELO | Z43: BALDERRAMA ZÁRATE BORIZ MARCELO - SUPERVISOR DE SERVICIOS DE EXPLORACIÓN | AA43: VICEPRESIDENCIA DE OPERACIONES | AB43: GERENCIA DE OPERACIONES MINA | AC43: SUPERINTENDENCIA DE SERVICIOS DE EXPLORACIÓN | AF43: SERVICIOS DE EXPLORACIÓN | AM43: 032 | AN43: Rolando Dominguez Moreno | BG43: 210 | BH43: 210 Flotación | BJ43: 41 | BK43: GESTIÓN DE RECURSOS HUMANOS
L44: 4 | M44: 14 | N44: 42 | O44: GERENCIA DE OPERACIONES PLANTA | P44: 4 | Q44: 4 | R44: 05 | T44: 42 | U44: 04 | V44: 12 | W44: 30 | X44: BRSR | Y44: BALLADARES ROCHA SAUL RAMIRO | Z44: BALLADARES ROCHA SAUL RAMIRO - SUPERVISOR DE MANTENIMIENTO | AA44: VICEPRESIDENCIA DE OPERACIONES | AB44: GERENCIA DE MANTENIMIENTO PLANTA | AC44: SUPERINTENDENCIA DE MANTENIMIENTO - ELÉCTRICO E INSTRUMENTACIÓN PLANTA | AF44: MANTENIMIENTO - ELÉCTRICO E INSTRUMENTACIÓN PLANTA | AM44: 033 | AN44: SafetyPro | BG44: 211 | BH44: 211 Espesadores | BJ44: 42 | BK44: GESTIÓN DE RELAVES Y SERVICIOS AUXILIARES
T45: 43 | U45: 04 | V45: 12 | W45: 32 | X45: BGB | Y45: BALLESTEROS GUTIERREZ BENIGNO | Z45: BALLESTEROS GUTIERREZ BENIGNO - ESPECIALISTA DE MANTENIMIENTO MECÁNICO / LUBRICACIÓN | AA45: VICEPRESIDENCIA DE OPERACIONES | AB45: GERENCIA DE MANTENIMIENTO PLANTA | AC45: SUPERINTENDENCIA DE MANTENIMIENTO - MEC. PLTA. CHANCADO, MOLIENDA Y LUBRICACIÓN | AD45: SUPERVISIÓN DE MANTENIMIENTO - CHANCADO / CORREAS TRANSPORTADORAS | AF45: MANTENIMIENTO - CHANCADO / CORREAS TRANSPORTADORAS | AM45: 034 | AN45: SC Tesa | BG45: 212 | BH45: 212 Pila de Relaves | BJ45: 43 | BK45: IMPUESTOS
T46: 44 | U46: 01 | V46: 04 | W46: 12 | X46: BDRA | Y46: BALLIVIAN DONOSO RAFAEL ALBERTO | Z46: BALLIVIAN DONOSO RAFAEL ALBERTO - SUPERINTENDENTE DE RECURSOS HUMANOS | AA46: VICEPRESIDENCIA CORPORATIVA | AB46: GERENCIA DE RECURSOS HUMANOS Y SERVICIOS DE PERSONAL | AC46: SUPERINTENDENCIA DE RECURSOS HUMANOS | AF46: RECURSOS HUMANOS | AM46: 035 | AN46: SEINCAL | BG46: 213 | BH46: 213 Salas Eléctricas | BJ46: 44 | BK46: INFRAESTRUCTURA DE TI
T47: 45 | U47: 04 | V47: 14 | W47: 40 | X47: BBJM | Y47: BAPTISTA BAUTISTA JUAN MARCELO | Z47: BAPTISTA BAUTISTA JUAN MARCELO - CAPATAZ DE FLOTACIÓN Y MOLIENDA | AA47: VICEPRESIDENCIA DE OPERACIONES | AB47: GERENCIA DE OPERACIONES PLANTA | AC47: SUPERINTENDENCIA DE OPERACIONES PLANTA | AF47: OPERACIONES PLANTA | AM47: 036 | AN47: Semconst | BG47: 214 | BH47: 214 Sub Estación Eléctrica | BJ47: 45 | BK47: INGENIERÍA MINA
T48: 46 | U48: 03 | V48: 09 | W48: 21 | X48: BCP | Y48: BAPTISTA CABEZAS PATRICIA | Z48: BAPTISTA CABEZAS PATRICIA - ANALISTA SÉNIOR CONTABLE | AA48: VICEPRESIDENCIA DE FINANZAS | AB48: GERENCIA DE FINANZAS | AC48: SUPERINTENDENCIA DE CONTABILIDAD | AD48: SUPERVISIÓN DE REPORTES Y CUMPLIMIENTO | AF48: REPORTES Y CUMPLIMIENTO | AM48: 139 | AN48: SILEX | BG48: 215 | BH48: 215 Laboratorio Químico | BJ48: 46 | BK48: INGENIERÍA PLANTA
T49: 47 | U49: 01 | V49: 07 | W49: 17 | X49: BRLF | Y49: BARBA RIVERO LUIS FERNANDO | Z49: BARBA RIVERO LUIS FERNANDO - ENCARGADO DE REGISTROS Y ALMACÉN DE PARTES AERONÁUTICAS | AA49: VICEPRESIDENCIA CORPORATIVA | AB49: GERENCIA DE SERVICIOS DE TRANSPORTE Y AVIACIÓN | AC49: SUPERINTENDENCIA DE SERVICIOS DE AVIACIÓN | AF49: SERVICIOS DE AVIACIÓN | AM49: 037 | AN49: SPECTROLAB | BG49: 216 | BH49: 216 Laboratorio Metalúrgico | BJ49: 47 | BK49: INGENIERÍA Y SEGURIDAD DE EQUIPOS MÓVILES
T50: 48 | U50: 01 | V50: 05 | W50: 15 | X50: BBVM | Y50: BARRIOS BARZOLA VIVIAN MARGOT | Z50: BARRIOS BARZOLA VIVIAN MARGOT - ANALISTA SENIOR DE CAPITAL SOCIAL | AA50: VICEPRESIDENCIA CORPORATIVA | AB50: GERENCIA DE RELACIONES COMUNITARIAS | AC50: SUPERINTENDENCIA DE DESARROLLO SOSTENIBLE Y RELACIONES COMUNITARIAS | AF50: DESARROLLO SOSTENIBLE Y RELACIONES COMUNITARIAS | AM50: 038 | AN50: STT | BG50: 217 | BH50: 217 Oficinas | BJ50: 48 | BK50: LOGÍSTICA
T51: 49 | U51: 03 | V51: 10 | W51: 26 | X51: BAAB | Y51: BASILIO ACHA ALEX BORIS | Z51: BASILIO ACHA ALEX BORIS - INGENIERO DE APLICACIONES TO PLANTA | AA51: VICEPRESIDENCIA DE FINANZAS | AB51: GERENCIA DE TI, TO Y SISTEMA DE GESTIÓN | AC51: SUPERINTENDENCIA DE TO | AF51: TO | AM51: 133 | AN51: Tesorera | BG51: 218 | BH51: 218 Sala de Control | BJ51: 49 | BK51: MANEJO DE MATERIALES
T52: 50 | U52: 04 | V52: 12 | W52: 34 | X52: BCO | Y52: BASILIO CALCINA OSCAR | Z52: BASILIO CALCINA OSCAR - ESPECIALISTA DE PLANIFICACIÓN DE MANTENIMIENTO | AA52: VICEPRESIDENCIA DE OPERACIONES | AB52: GERENCIA DE MANTENIMIENTO PLANTA | AC52: SUPERINTENDENCIA DE MANTENIMIENTO - PLANIFICACIÓN | AF52: MANTENIMIENTO - PLANIFICACIÓN | AM52: 039 | AN52: TrackNet | BG52: 219 | BH52: 219 Cafetería | BJ52: 50 | BK52: MANEJO DE MATERIALES OPERACIONES MINA
T53: 51 | U53: 04 | V53: 13 | X53: BTCY | Y53: BASILIO TICONA CORNELIO YECID | Z53: BASILIO TICONA CORNELIO YECID - RESPONSABLE DE ENTRENAMIENTO MINA | AA53: VICEPRESIDENCIA DE OPERACIONES | AB53: GERENCIA DE OPERACIONES MINA | AF53: OPERACIONES MINA | AM53: 040 | AN53: Trans Omar | BG53: 220 | BH53: 220 Casa de Cambio | BJ53: 51 | BK53: MANTENIMIENTO - ELÉCTRICO E INSTRUMENTACIÓN PLANTA
T54: 52 | U54: 04 | V54: 13 | W54: 35 | X54: BTPN | Y54: BASILIO TICONA PAUL NIELS | Z54: BASILIO TICONA PAUL NIELS - GEÓLOGO DE MINA - MAPEO | AA54: VICEPRESIDENCIA DE OPERACIONES | AB54: GERENCIA DE OPERACIONES MINA | AC54: SUPERINTENDENCIA SÉNIOR DE INGENIERÍA MINA | AD54: SUPERVISIÓN DE GEOLOGÍA | AF54: GEOLOGÍA | AM54: 041 | AN54: TTMB | BG54: 221 | BH54: 221 Planta Osmosis | BJ54: 52 | BK54: MANTENIMIENTO - CHANCADO / CORREAS TRANSPORTADORAS
T55: 53 | U55: 04 | V55: 11 | W55: 28 | X55: BVR | Y55: BASILIO VENIZ RUBEN | Z55: BASILIO VENIZ RUBÉN - ELECTROMECÁNICO DE MANTENIMIENTO MINA A | AA55: VICEPRESIDENCIA DE OPERACIONES | AB55: GERENCIA DE MANTENIMIENTO MINA | AC55: SUPERINTENDENCIA SÉNIOR DE INGENIERÍA Y SEGURIDAD DE EQUIPOS MÓVILES | AD55: SUPERINTENDENCIA DE MANTENIMIENTO MINA - EJECUCIÓN | AE55: SUPERVISIÓN DE MANTENIMIENTO MINA - ACARREO | AF55: MANTENIMIENTO MINA - EJECUCIÓN | AM55: 134 | AN55: UATF | BG55: 222 | BH55: 222 Caminos de Acceso | BJ55: 53 | BK55: MANTENIMIENTO - CONFIABILIDAD ELÉCTRICO
T56: 54 | U56: 04 | V56: 14 | W56: 40 | X56: BBBF | Y56: BAUTISTA BAPTISTA BENITO FILEMON | Z56: BAUTISTA BAPTISTA BENITO FILEMON - CAPATAZ DE FILTROS Y CARGUÍO | AA56: VICEPRESIDENCIA DE OPERACIONES | AB56: GERENCIA DE OPERACIONES PLANTA | AC56: SUPERINTENDENCIA DE OPERACIONES PLANTA | AF56: OPERACIONES PLANTA | AM56: 143 | AN56: VOLTA ENERGY | BG56: 223 | BH56: 223 Líneas de Concentrado a Filtros | BJ56: 54 | BK56: MANTENIMIENTO - ELÉCTRICO
T57: 55 | U57: 01 | V57: 02 | W57: 05 | X57: BCE | Y57: BAUTISTA CORDOVA EUFRONIO | Z57: BAUTISTA CÓRDOVA EUFRONIO - OPERADOR DE ALMACÉN | AA57: VICEPRESIDENCIA CORPORATIVA | AB57: GERENCIA DE COMERCIALIZACIÓN Y SERVICIOS | AC57: SUPERINTENDENCIA DE ALMACENES Y CONTROL DE INVENTARIOS | AD57: SUPERVISIÓN SÉNIOR DE ALMACÉN PLANTA Y COMBUSTIBLES | AF57: ALMACÉN PLANTA Y COMBUSTIBLES | AM57: 042 | AN57: WET Chemical Bolivia SRL | BG57: 224 | BH57: 224 Filtros | BJ57: 55 | BK57: MANTENIMIENTO - FLOTACIÓN Y ESPESADORES
T58: 56 | U58: 04 | V58: 14 | W58: 40 | X58: BYJ | Y58: BAUTISTA YUCRA JOSE | Z58: BAUTISTA YUCRA JOSE - OFICIAL DE AISLAMIENTO | AA58: VICEPRESIDENCIA DE OPERACIONES | AB58: GERENCIA DE OPERACIONES PLANTA | AC58: SUPERINTENDENCIA DE OPERACIONES PLANTA | AF58: OPERACIONES PLANTA | AM58: 043 | AN58: Wila Kara | BG58: 225 | BH58: 225 Secado | BJ58: 56 | BK58: MANTENIMIENTO - GENERAL Y SOLDADURA
T59: 57 | U59: 03 | V59: 09 | W59: 21 | X59: BRCX | Y59: BELTRAN RIOS CLAUDIA XIMENA | Z59: BELTRÁN RIOS CLAUDIA XIMENA - SUPERVISOR DE REPORTES Y CUMPLIMIENTO | AA59: VICEPRESIDENCIA DE FINANZAS | AB59: GERENCIA DE FINANZAS | AC59: SUPERINTENDENCIA DE CONTABILIDAD | AD59: SUPERVISIÓN DE REPORTES Y CUMPLIMIENTO | AF59: REPORTES Y CUMPLIMIENTO | AM59: 044 | AN59: zzz829 | BG59: 226 | BH59: 226 Carguío | BJ59: 57 | BK59: MANTENIMIENTO - INGENIERÍA DE CONFIABILIDAD
T60: 58 | U60: 04 | V60: 14 | W60: 40 | X60: BQJA | Y60: BERNA QUISPE JOSE ANTONIO | Z60: BERNA QUISPE JOSÉ ANTONIO - CAPATAZ DE CHANCADOR PRIMARIO | AA60: VICEPRESIDENCIA DE OPERACIONES | AB60: GERENCIA DE OPERACIONES PLANTA | AC60: SUPERINTENDENCIA DE OPERACIONES PLANTA | AF60: OPERACIONES PLANTA | AM60: 045 | AN60: zzzAlanoca | BG60: 227 | BH60: 227 Patio de Carga Ferroviario | BJ60: 58 | BK60: MANTENIMIENTO - INSTRUMENTACIÓN
T61: 59 | U61: 01 | V61: 04 | W61: 11 | X61: BQJC | Y61: BERNA QUISPE JUAN CARLOS | Z61: BERNA QUISPE JUAN CARLOS - ASISTENTE DE SERVICIOS DE CAMPAMENTO | AA61: VICEPRESIDENCIA CORPORATIVA | AB61: GERENCIA DE RECURSOS HUMANOS Y SERVICIOS DE PERSONAL | AC61: SUPERINTENDENCIA DE CAMPAMENTO | AD61: SUPERVISIÓN SÉNIOR DE CAMPAMENTO | AE61: SUPERVISIÓN DE HOSPEDAJE, RECREACIONES E INVENTARIOS | AF61: CAMPAMENTO | AM61: 046 | AN61: zzzASOMEC | BG61: 228 | BH61: 228 Almacén de Concentrados | BJ61: 59 | BK61: MANTENIMIENTO - LUBRICACIÓN, PUENTES GRÚA/LABORATORIOS
T62: 60 | U62: 04 | V62: 14 | W62: 40 | X62: BCIB | Y62: BERNAL CRUZ IVAN BENITO | Z62: BERNAL CRUZ IVAN BENITO - OFICIAL DE AISLAMIENTO | AA62: VICEPRESIDENCIA DE OPERACIONES | AB62: GERENCIA DE OPERACIONES PLANTA | AC62: SUPERINTENDENCIA DE OPERACIONES PLANTA | AF62: OPERACIONES PLANTA | AM62: 047 | AN62: zzzAtlas Copco | BG62: 229 | BH62: 229 Taller Ferroviario | BJ62: 60 | BK62: MANTENIMIENTO - MEC. PLTA. FLOT., FILTROS, TALLER GRAL. Y RH
T63: 61 | U63: 03 | V63: 10 | W63: 24 | X63: BDMV | Y63: BLOCK DAZA MARIE VERENA | Z63: BLOCK DAZA MARIE VERENA - ANALISTA SÉNIOR DE GESTIÓN DE PROCESOS Y MEJORA CONTINUA | AA63: VICEPRESIDENCIA DE FINANZAS | AB63: GERENCIA DE TI, TO Y SISTEMA DE GESTIÓN | AC63: SUPERINTENDENCIA DE SISTEMA DE GESTIÓN | AF63: SISTEMA DE GESTIÓN | AM63: 048 | AN63: zzzBELLO | BG63: 230 | BH63: 230 Campos de Pozos | BJ63: 61 | BK63: MANTENIMIENTO - MOLIENDA
T64: 62 | U64: 03 | V64: 10 | W64: 26 | X64: BAOM | Y64: BRAVO AYLLON OMAR MIGUEL | Z64: BRAVO AYLLON OMAR MIGUEL - ANALISTA SÉNIOR APLICACIONES TO MINA | AA64: VICEPRESIDENCIA DE FINANZAS | AB64: GERENCIA DE TI, TO Y SISTEMA DE GESTIÓN | AC64: SUPERINTENDENCIA DE TO | AD64: SUPERVISIÓN TO MINA | AF64: TO MINA | AM64: 049 | AN64: zzzCabletel | BG64: 231 | BH64: 231 Taller de Pozos | BJ64: 62 | BK64: MANTENIMIENTO - PLANIFICACIÓN
T65: 63 | U65: 03 | V65: 09 | X65: BDLTUABJ | Y65: BUSTILLOS DE LA TORRE UGARTE ALEJANDRO BLASCO JORGE | Z65: BUSTILLOS DE LA TORRE UGARTE ALEJANDRO BLASCO JORGE - GERENTE DE FINANZAS | AA65: VICEPRESIDENCIA DE FINANZAS | AB65: GERENCIA DE FINANZAS | AF65: GERENCIA DE FINANZAS | AM65: 050 | AN65: zzzCarlos Caballero | BG65: 232 | BH65: 232 Línea de Colas | BJ65: 63 | BK65: MANTENIMIENTO - RECURSOS HÍDRICOS Y VÍAS FERREAS
T66: 64 | U66: 04 | V66: 11 | W66: 28 | X66: BFER | Y66: BUSTOS FERNANDEZ EDWIN ROLANDO | Z66: BUSTOS FERNÁNDEZ EDWIN ROLANDO - COORDINADOR DE MANTENIMIENTO MINA | AA66: VICEPRESIDENCIA DE OPERACIONES | AB66: GERENCIA DE MANTENIMIENTO MINA | AC66: SUPERINTENDENCIA SÉNIOR DE INGENIERÍA Y SEGURIDAD DE EQUIPOS MÓVILES | AD66: SUPERINTENDENCIA DE MANTENIMIENTO MINA - EJECUCIÓN | AE66: SUPERVISIÓN DE MANTENIMIENTO MINA - CARGUÍO | AF66: MANTENIMIENTO MINA - EJECUCIÓN | AM66: 051 | AN66: zzzCasobra | BG66: 233 | BH66: 233 Laguna de Colas Willa Khara | BJ66: 64 | BK66: MANTENIMIENTO GENERACIÓN Y AIRE ACONDICIONADO INDUSTRIAL
T67: 65 | U67: 04 | V67: 12 | W67: 33 | X67: CCE | Y67: CABRERA CABRERA EDGAR | Z67: CABRERA CABRERA EDGAR - ESPECIALISTA DE MANTENIMIENTO MECÁNICO / LUBRICACIÓN | AA67: VICEPRESIDENCIA DE OPERACIONES | AB67: GERENCIA DE MANTENIMIENTO PLANTA | AC67: SUPERINTENDENCIA DE MANTENIMIENTO - MEC. PLTA. FLOT., FILTROS, TALLER GRAL. Y RH | AD67: SUPERVISIÓN DE MANTENIMIENTO - FLOTACIÓN Y ESPESADORES | AF67: MANTENIMIENTO - FLOTACIÓN Y ESPESADORES | AM67: 052 | AN67: zzzCatering San Cristobal | BG67: 234 | BH67: 234 Líneas Captación de Agua | BJ67: 65 | BK67: MANTENIMIENTO MINA - EJECUCIÓN
T68: 66 | U68: 04 | V68: 11 | W68: 28 | X68: CCW | Y68: CABRERA CHOQUE WILLSON | Z68: CABRERA CHOQUE WILLSON - ELECTROMECÁNICO DE MANTENIMIENTO MINA | AA68: VICEPRESIDENCIA DE OPERACIONES | AB68: GERENCIA DE MANTENIMIENTO MINA | AC68: SUPERINTENDENCIA SÉNIOR DE INGENIERÍA Y SEGURIDAD DE EQUIPOS MÓVILES | AD68: SUPERINTENDENCIA DE MANTENIMIENTO MINA - EJECUCIÓN | AE68: SUPERVISIÓN DE MANTENIMIENTO MINA - CARGUÍO | AF68: MANTENIMIENTO MINA - EJECUCIÓN | AM68: 053 | AN68: zzzCBA | BG68: 235 | BH68: 235 Planta tratamiento de Agua – Osmosis | BJ68: 66 | BK68: MANTENIMIENTO MINA- REPARACIÓN Y COMPONENTES
T69: 67 | U69: 04 | V69: 14 | W69: 41 | X69: CMRR | Y69: CABRERA MAMANI RUBEN RODY | Z69: CABRERA MAMANI RUBEN RODY - METALURGISTA DE PROCESO | AA69: VICEPRESIDENCIA DE OPERACIONES | AB69: GERENCIA DE OPERACIONES PLANTA | AC69: SUPERINTENDENCIA DE SERVICIOS TÉCNICOS | AF69: SERVICIOS TÉCNICOS | AM69: 054 | AN69: zzzCIS | BG69: 236 | BH69: 236 Dique almacenamiento de Agua | BJ69: 67 | BK69: MANTENIMIENTO PLANTA
T70: 68 | U70: 01 | V70: 04 | W70: 14 | X70: CBL | Y70: CALCINA BERNA LEONARDO | Z70: CALCINA BERNA LEONARDO - RESPONSABLE DE SEGURIDAD DE TURNO | AA70: VICEPRESIDENCIA CORPORATIVA | AB70: GERENCIA DE RECURSOS HUMANOS Y SERVICIOS DE PERSONAL | AC70: SUPERVISIÓN SENIOR DE SEGURIDAD FÍSICA | AD70: SUPERVISIÓN DE SEGURIDAD FÍSICA | AF70: SEGURIDAD FÍSICA | AM70: 055 | AN70: zzzCONGAR | BG70: 237 | BH70: 237 Estacionamiento de Vehículos | BJ70: 68 | BK70: MANTTO. MINA - PLANIFICACIÓN, PROGRAMACIÓN Y CONFIABILIDAD
T71: 69 | U71: 01 | V71: 04 | W71: 12 | X71: CCE | Y71: CALCINA CALCINA EDWIN | Z71: CALCINA CALCINA EDWIN - ANALISTA SÉNIOR DE SOPORTE DE RECURSOS HUMANOS | AA71: VICEPRESIDENCIA CORPORATIVA | AB71: GERENCIA DE RECURSOS HUMANOS Y SERVICIOS DE PERSONAL | AC71: SUPERINTENDENCIA DE RECURSOS HUMANOS | AD71: SUPERVISIÓN DE CAPACITACIÓN | AF71: CAPACITACIÓN | AM71: 056 | AN71: zzzCONSTEC & ASOCIADOS | BG71: 238 | BH71: 238 Parada de Buses | BJ71: 69 | BK71: MEC. PLTA. CHANCADO, MOLIENDA Y LUBRICACIÓN
T72: 70 | U72: 04 | V72: 13 | W72: 36 | X72: CCET | Y72: CALCINA CALCINA EMETERIO TELEDONIO | Z72: CALCINA CALCINA EMETERIO TELEDONIO - COORDINADOR DE GUARDIA | AA72: VICEPRESIDENCIA DE OPERACIONES | AB72: GERENCIA DE OPERACIONES MINA | AC72: SUPERINTENDENCIA DE OPERACIONES MINA | AD72: SUPERVISIÓN DE CARGUÍO Y ACARREO | AF72: CARGUÍO Y ACARREO | AM72: 057 | AN72: zzzCoop. Luxar | BG72: 239 | BH72: 239 Bombas Bosther | BJ72: 70 | BK72: MEC. PLTA. FLOT., FILTROS, TALLER GRAL. Y RH
T73: 71 | U73: 01 | V73: 04 | W73: 14 | X73: CCE | Y73: CALCINA CALIZAYA EFRAIN | Z73: CALCINA CALIZAYA EFRAÍN - SUPERVISOR DE SEGURIDAD FÍSICA | AA73: VICEPRESIDENCIA CORPORATIVA | AB73: GERENCIA DE RECURSOS HUMANOS Y SERVICIOS DE PERSONAL | AC73: SUPERVISIÓN SENIOR DE SEGURIDAD FÍSICA | AD73: SUPERVISIÓN DE SEGURIDAD FÍSICA | AF73: SEGURIDAD FÍSICA | AM73: 058 | AN73: zzzCooperativa Centenario Uyuni | BG73: 240 | BH73: 240 Almacen Cores | BJ73: 71 | BK73: MEDIO AMBIENTE
T74: 72 | U74: 04 | V74: 14 | W74: 40 | X74: CCJV | Y74: CALCINA COLQUE JUAN VIANEY | Z74: CALCINA COLQUE JUAN VIANEY - CAPATAZ DE CHANCADOR PRIMARIO | AA74: VICEPRESIDENCIA DE OPERACIONES | AB74: GERENCIA DE OPERACIONES PLANTA | AC74: SUPERINTENDENCIA DE OPERACIONES PLANTA | AF74: OPERACIONES PLANTA | AM74: 059 | AN74: zzzCopa | BG74: 241 | BH74: 241 Hidro-Ciclones | BJ74: 72 | BK74: OPERACIONES DEL SISTEMA DE CONTROL DE FLOTA
T75: 73 | U75: 04 | V75: 13 | W75: 36 | X75: CCI | Y75: CALCINA COPA IVER | Z75: CALCINA COPA IVER - COORDINADOR DE GUARDIA | AA75: VICEPRESIDENCIA DE OPERACIONES | AB75: GERENCIA DE OPERACIONES MINA | AC75: SUPERINTENDENCIA DE OPERACIONES MINA | AD75: SUPERVISIÓN DE CARGUÍO Y ACARREO | AF75: CARGUÍO Y ACARREO | AM75: 060 | AN75: zzzCruz del Norte | BG75: 242 | BH75: 242 Bombas de Colas | BJ75: 73 | BK75: OPERACIONES MINA
T76: 74 | U76: 01 | V76: 02 | W76: 05 | X76: CFD | Y76: CALCINA FLORES DIGNO | Z76: CALCINA FLORES DIGNO - OPERADOR DE ALMACÉN | AA76: VICEPRESIDENCIA CORPORATIVA | AB76: GERENCIA DE COMERCIALIZACIÓN Y SERVICIOS | AC76: SUPERINTENDENCIA DE ALMACENES Y CONTROL DE INVENTARIOS | AD76: SUPERVISIÓN SÉNIOR DE ALMACÉN PLANTA Y COMBUSTIBLES | AF76: ALMACÉN PLANTA Y COMBUSTIBLES | AM76: 061 | AN76: zzzDicsa Komatsu | BG76: 030 | BH76: 30 AREA ADMINISTRATIVA | BJ76: 74 | BK76: OPERACIONES PLANTA
T77: 75 | U77: 04 | V77: 11 | W77: 28 | X77: CGMH | Y77: CALCINA GONZALES MILTON HERNAN | Z77: CALCINA GONZÁLES MILTON HERNÁN - ELECTROMECÁNICO DE MANTENIMIENTO MINA A | AA77: VICEPRESIDENCIA DE OPERACIONES | AB77: GERENCIA DE MANTENIMIENTO MINA | AC77: SUPERINTENDENCIA SÉNIOR DE INGENIERÍA Y SEGURIDAD DE EQUIPOS MÓVILES | AD77: SUPERINTENDENCIA DE MANTENIMIENTO MINA - EJECUCIÓN | AE77: SUPERVISIÓN DE MANTENIMIENTO MINA - CARGUÍO | AF77: MANTENIMIENTO MINA - EJECUCIÓN | AM77: 062 | AN77: zzzEdeser | BG77: 301 | BH77: 301 Oficinas | BJ77: 75 | BK77: PERFORACIÓN Y VOLADURA
T78: 76 | U78: 04 | V78: 11 | W78: 28 | X78: CMHF | Y78: CALCINA MURAÑA HUGO FAUSTINO | Z78: CALCINA MURAÑA HUGO FAUSTINO - ELECTROMECÁNICO DE MANTENIMIENTO MINA A | AA78: VICEPRESIDENCIA DE OPERACIONES | AB78: GERENCIA DE MANTENIMIENTO MINA | AC78: SUPERINTENDENCIA SÉNIOR DE INGENIERÍA Y SEGURIDAD DE EQUIPOS MÓVILES | AD78: SUPERINTENDENCIA DE MANTENIMIENTO MINA - EJECUCIÓN | AE78: SUPERVISIÓN DE MANTENIMIENTO MINA - CARGUÍO | AF78: MANTENIMIENTO MINA - EJECUCIÓN | AM78: 063 | AN78: zzzEncuadernaciones Tigre | BG78: 302 | BH78: 302 Salas Reunión | BJ78: 76 | BK78: PLANIFICACIÓN FINANCIERA (FP&A)
T79: 77 | U79: 01 | V79: 02 | W79: 05 | X79: CQR | Y79: CALCINA QUISPE RAFAEL | Z79: CALCINA QUISPE RAFAEL - COORDINADOR DE ALMACÉN | AA79: VICEPRESIDENCIA CORPORATIVA | AB79: GERENCIA DE COMERCIALIZACIÓN Y SERVICIOS | AC79: SUPERINTENDENCIA DE ALMACENES Y CONTROL DE INVENTARIOS | AD79: SUPERVISIÓN SÉNIOR DE ALMACÉN PLANTA Y COMBUSTIBLES | AF79: ALMACÉN PLANTA Y COMBUSTIBLES | AM79: 064 | AN79: zzzENDE SyC | BG79: 303 | BH79: 303 Recepción | BJ79: 77 | BK79: PLANIFICACIÓN Y CONTROL DE PROYECTOS
T80: 78 | U80: 04 | V80: 13 | W80: 36 | X80: CQRA | Y80: CALCINA QUISPE RAUL ALBERTO | Z80: CALCINA QUISPE RAÚL ALBERTO - INSTRUCTOR OPERATIVO MINA | AA80: VICEPRESIDENCIA DE OPERACIONES | AB80: GERENCIA DE OPERACIONES MINA | AC80: SUPERINTENDENCIA DE OPERACIONES MINA | AD80: SUPERVISIÓN DE CARGUÍO Y ACARREO | AF80: CARGUÍO Y ACARREO | AM80: 065 | AN80: zzzExaltación Lazo | BG80: 304 | BH80: 304 Cafetería | BJ80: 78 | BK80: PROYECTOS Y MODIFICACIONES
T81: 79 | U81: 01 | V81: 04 | W81: 12 | X81: CMML | Y81: CALIZAYA MENA MIKAELA LISSETTE | Z81: CALIZAYA MENA MIKAELA LISSETTE - ESPECIALISTA SÉNIOR DE RECURSOS HUMANOS | AA81: VICEPRESIDENCIA CORPORATIVA | AB81: GERENCIA DE RECURSOS HUMANOS Y SERVICIOS DE PERSONAL | AC81: SUPERINTENDENCIA DE RECURSOS HUMANOS | AF81: RECURSOS HUMANOS | AM81: 066 | AN81: zzzFamen | BG81: 305 | BH81: 305 Estacionamiento Vehículos | BJ81: 79 | BK81: RECURSOS HUMANOS
T82: 80 | U82: 04 | V82: 13 | W82: 35 | X82: CFT | Y82: CALLE FLORES TIBURCIO | Z82: CALLE FLORES TIBURCIO - INSTRUCTOR OPERATIVO MINA | AA82: VICEPRESIDENCIA DE OPERACIONES | AB82: GERENCIA DE OPERACIONES MINA | AC82: SUPERINTENDENCIA SÉNIOR DE INGENIERÍA MINA | AD82: SUPERVISIÓN SÉNIOR DE PERFORACIÓN Y VOLADURA | AF82: PERFORACIÓN Y VOLADURA | AM82: 067 | AN82: zzzFeprom | BG82: 306 | BH82: 306 Pasillos peatonales | BJ82: 80 | BK82: RECURSOS HUMANOS Y SERVICIOS DE PERSONAL
T83: 81 | U83: 04 | V83: 11 | W83: 28 | X83: CHMR | Y83: CALLE HUANCA MAX RUBEN | Z83: CALLE HUANCA MAX RUBEN - COORDINADOR PRINCIPAL DE MANTENIMIENTO MINA | AA83: VICEPRESIDENCIA DE OPERACIONES | AB83: GERENCIA DE MANTENIMIENTO MINA | AC83: SUPERINTENDENCIA SÉNIOR DE INGENIERÍA Y SEGURIDAD DE EQUIPOS MÓVILES | AD83: SUPERINTENDENCIA DE MANTENIMIENTO MINA - EJECUCIÓN | AE83: SUPERVISIÓN DE MANTENIMIENTO MINA - ACARREO | AF83: MANTENIMIENTO MINA - EJECUCIÓN | AM83: 068 | AN83: zzzGALVEC | BG83: 307 | BH83: 307 Cafetería | BJ83: 81 | BK83: RELACIONES COMUNITARIAS
T84: 82 | U84: 04 | V84: 12 | W84: 33 | X84: CRMC | Y84: CALLE RODRIGUEZ MODESTO CRESENCIO | Z84: CALLE RODRIGUEZ MODESTO CRESENCIO - ESPECIALISTA DE MANTENIMIENTO MECÁNICO / LUBRICACIÓN | AA84: VICEPRESIDENCIA DE OPERACIONES | AB84: GERENCIA DE MANTENIMIENTO PLANTA | AC84: SUPERINTENDENCIA DE MANTENIMIENTO - MEC. PLTA. FLOT., FILTROS, TALLER GRAL. Y RH | AD84: SUPERVISIÓN DE MANTENIMIENTO - FLOTACIÓN Y ESPESADORES | AF84: MANTENIMIENTO - FLOTACIÓN Y ESPESADORES | AM84: 069 | AN84: zzzGCM | BG84: 308 | BH84: 308 Estacionamiento de Vehículos | BJ84: 82 | BK84: RELACIONES INSTITUCIONALES
T85: 83 | U85: 04 | V85: 11 | W85: 28 | X85: CJA | Y85: CALLEJAS JUAREZ ALBERTO | Z85: CALLEJAS JUAREZ ALBERTO - COORDINADOR DE MANTENIMIENTO MINA | AA85: VICEPRESIDENCIA DE OPERACIONES | AB85: GERENCIA DE MANTENIMIENTO MINA | AC85: SUPERINTENDENCIA SÉNIOR DE INGENIERÍA Y SEGURIDAD DE EQUIPOS MÓVILES | AD85: SUPERINTENDENCIA DE MANTENIMIENTO MINA - EJECUCIÓN | AE85: SUPERVISIÓN DE MANTENIMIENTO MINA - ACARREO | AF85: MANTENIMIENTO MINA - EJECUCIÓN | AM85: 070 | AN85: zzzGCR (Bridgestone Minning Solutions) | BG85: 040 | BH85: 40 AREA ALMACEN GENERAL | BJ85: 83 | BK85: RELACIONES LABORALES
T86: 84 | U86: 04 | V86: 11 | W86: 28 | X86: CBR | Y86: CALLISAYA BELTRAN RUBEN | Z86: CALLISAYA BELTRÁN RUBEN - ELECTROMECÁNICO DE MANTENIMIENTO MINA | AA86: VICEPRESIDENCIA DE OPERACIONES | AB86: GERENCIA DE MANTENIMIENTO MINA | AC86: SUPERINTENDENCIA SÉNIOR DE INGENIERÍA Y SEGURIDAD DE EQUIPOS MÓVILES | AD86: SUPERINTENDENCIA DE MANTENIMIENTO MINA - EJECUCIÓN | AE86: SUPERVISIÓN DE MANTENIMIENTO MINA - ACARREO | AF86: MANTENIMIENTO MINA - EJECUCIÓN | AM86: 071 | AN86: zzzGerimex | BG86: 401 | BH86: 401 Oficinas | BJ86: 84 | BK86: RELACIONES PÚBLICAS
T87: 85 | U87: 01 | V87: 02 | W87: 07 | X87: CTAR | Y87: CAMARGO TICONA ARMANDO RICARDO | Z87: CAMARGO TICONA ARMANDO RICARDO - SUPERINTENDENTE DE GESTIÓN COMERCIAL | AA87: VICEPRESIDENCIA CORPORATIVA | AB87: GERENCIA DE COMERCIALIZACIÓN Y SERVICIOS | AC87: SUPERINTENDENCIA DE GESTION COMERCIAL | AF87: GESTION COMERCIAL | AM87: 072 | AN87: zzzGround Force | BG87: 402 | BH87: 402 Almacén Central | BJ87: 85 | BK87: REPORTES Y CUMPLIMIENTO | BT87: id | BU87: Gerencia
T88: 86 | U88: 01 | V88: 04 | W88: 14 | X88: CFB | Y88: CAMATA FLORES BENITO | Z88: CAMATA FLORES BENITO - RESPONSABLE DE SEGURIDAD DE TURNO | AA88: VICEPRESIDENCIA CORPORATIVA | AB88: GERENCIA DE RECURSOS HUMANOS Y SERVICIOS DE PERSONAL | AC88: SUPERVISIÓN SENIOR DE SEGURIDAD FÍSICA | AD88: SUPERVISIÓN DE SEGURIDAD FÍSICA | AF88: SEGURIDAD FÍSICA | AM88: 073 | AN88: zzzHansa | BG88: 403 | BH88: 403 Patio de Recepción | BJ88: 86 | BK88: RESPONSABILIDAD SOCIAL EXTERNA | BR88: 01 | BT88: 01 | BU88: GERENCIA CORPORATIVA
T89: 87 | U89: 04 | V89: 12 | W89: 33 | X89: CQE | Y89: CAMATA QUISPE EDILBER | Z89: CAMATA QUISPE EDILBER - SUPERVISOR DE MANTENIMIENTO | AA89: VICEPRESIDENCIA DE OPERACIONES | AB89: GERENCIA DE MANTENIMIENTO PLANTA | AC89: SUPERINTENDENCIA DE MANTENIMIENTO - MEC. PLTA. FLOT., FILTROS, TALLER GRAL. Y RH | AF89: MANTENIMIENTO - MEC. PLTA. FLOT., FILTROS, TALLER GRAL. Y RH | AM89: 074 | AN89: zzzIndumotora | BG89: 404 | BH89: 404 Estacionamiento de Vehículos | BJ89: 87 | BK89: SALUD | BR89: 01 | BT89: 02 | BU89: GERENCIA DE COMERCIALIZACIÓN Y SERVICIOS
T90: 88 | U90: 01 | V90: 04 | W90: 12 | X90: CZRF | Y90: CAMPERO ZAPATA RILKE FRANZ | Z90: CAMPERO ZAPATA RILKE FRANZ - SUPERVISOR DE CAPACITACIÓN | AA90: VICEPRESIDENCIA CORPORATIVA | AB90: GERENCIA DE RECURSOS HUMANOS Y SERVICIOS DE PERSONAL | AC90: SUPERINTENDENCIA DE RECURSOS HUMANOS | AD90: SUPERVISIÓN DE CAPACITACIÓN | AF90: CAPACITACIÓN | AM90: 075 | AN90: zzzINFOCAL | BG90: 405 | BH90: 405 Almacenamiento Toldos | BJ90: 88 | BK90: SEGURIDAD DE LA INFORMACIÓN (CISO) | BR90: 01 | BT90: 03 | BU90: GERENCIA DE MEDIO AMBIENTE
T91: 89 | U91: 01 | V91: 02 | X91: CBBT | Y91: CAMPUZANO BOLAÑOS BERTHA TERESA | Z91: CAMPUZANO BOLAÑOS BERTHA TERESA - GERENTE DE COMERCIALIZACIÓN Y SERVICIOS | AA91: VICEPRESIDENCIA CORPORATIVA | AB91: GERENCIA DE COMERCIALIZACIÓN Y SERVICIOS | AF91: GERENCIA DE COMERCIALIZACIÓN Y SERVICIOS | AM91: 076 | AN91: zzzIngeniería de Tranportes | BG91: 406 | BH91: 406 Surtidor de Combustibles | BJ91: 89 | BK91: SEGURIDAD FÍSICA | BR91: 01 | BT91: 04 | BU91: GERENCIA DE RECURSOS HUMANOS Y SERVICIOS DE PERSONAL
T92: 90 | U92: 01 | V92: 01 | W92: 03 | X92: CMO | Y92: CANDIA MANSILLA OSWALDO | Z92: CANDIA MANSILLA OSWALDO - SUPERINTENDENTE DE RELACIONES PÚBLICAS | AA92: VICEPRESIDENCIA CORPORATIVA | AB92: GERENCIA CORPORATIVA | AC92: SUPERINTENDENCIA DE RELACIONES PÚBLICAS | AF92: RELACIONES PÚBLICAS | AM92: 077 | AN92: zzzIntertek | BG92: 407 | BH92: 407 Playas de Almacenamiento Materiales | BJ92: 90 | BK92: SEGURIDAD INDUSTRIAL | BR92: 01 | BT92: 05 | BU92: GERENCIA DE RELACIONES COMUNITARIAS
T93: 91 | U93: 03 | V93: 10 | W93: 25 | X93: CRRO | Y93: CANDIA ROJAS RICARDO OMAR | Z93: CANDIA ROJAS RICARDO OMAR - ADMINISTRADOR DE APLICACIONES DE TI | AA93: VICEPRESIDENCIA DE FINANZAS | AB93: GERENCIA DE TI, TO Y SISTEMA DE GESTIÓN | AC93: SUPERINTENDENCIA DE TI | AD93: SUPERVISIÓN DE APLICACIONES DE TI | AF93: APLICACIONES DE TI | AM93: 078 | AN93: zzzIS/IT | BG93: 408 | BH93: 408 Almacén Reactivo | BJ93: 91 | BK93: SERVICIOS AUXILIARES | BR93: 01 | BT93: 06 | BU93: GERENCIA DE SEGURIDAD INDUSTRIAL
T94: 92 | U94: 04 | V94: 14 | W94: 40 | X94: CMJJ | Y94: CANIZARES MAMANI JUAN JOSE | Z94: CANIZARES MAMANI JUAN JOSE - CAPATAZ DE FLOTACIÓN Y MOLIENDA | AA94: VICEPRESIDENCIA DE OPERACIONES | AB94: GERENCIA DE OPERACIONES PLANTA | AC94: SUPERINTENDENCIA DE OPERACIONES PLANTA | AF94: OPERACIONES PLANTA | AM94: 079 | AN94: zzzJ&R | BG94: 409 | BH94: 409 Almacén Lubricantes | BJ94: 92 | BK94: SERVICIOS DE AVIACIÓN | BR94: 01 | BT94: 07 | BU94: GERENCIA DE SERVICIOS DE TRANSPORTE Y AVIACIÓN
T95: 93 | U95: 04 | V95: 12 | W95: 30 | X95: CFO | Y95: CAPURATA FLORES OVIDIO | Z95: CAPURATA FLORES OVIDIO - SUPERINTENDENTE DE MANTENIMIENTO | AA95: VICEPRESIDENCIA DE OPERACIONES | AB95: GERENCIA DE MANTENIMIENTO PLANTA | AC95: SUPERINTENDENCIA DE MANTENIMIENTO - ELÉCTRICO E INSTRUMENTACIÓN PLANTA | AF95: MANTENIMIENTO - ELÉCTRICO E INSTRUMENTACIÓN PLANTA | AM95: 080 | AN95: zzzJayula | BG95: 410 | BH95: 410 Almacén Botellones Presurizados | BJ95: 93 | BK95: SERVICIOS DE EXPLORACIÓN | BR95: 02 | BT95: 01 | BU95: GERENCIA DE PROYECTOS
T96: 94 | U96: 01 | V96: 02 | W96: 06 | X96: CRRA | Y96: CARBALLO RIVERO ROBERTO ALCIDES | Z96: CARBALLO RIVERO ROBERTO ALCIDES - ANALISTA SÉNIOR DE EXPORTACIONES | AA96: VICEPRESIDENCIA CORPORATIVA | AB96: GERENCIA DE COMERCIALIZACIÓN Y SERVICIOS | AC96: SUPERINTENDENCIA DE EXPORTACIONES | AF96: EXPORTACIONES | AM96: 081 | AN96: zzzJCM | BG96: 411 | BH96: 411 Parada de Buses | BJ96: 94 | BK96: SERVICIOS DE SALUD EXTERNA | BR96: 03 | BT96: 01 | BU96: GERENCIA DE FINANZAS
T97: 95 | U97: 04 | V97: 11 | W97: 28 | X97: CVA | Y97: CARDENAS VILLCA ABEL | Z97: CARDENAS VILLCA ABEL - ELECTROMECÁNICO DE MANTENIMIENTO MINA B | AA97: VICEPRESIDENCIA DE OPERACIONES | AB97: GERENCIA DE MANTENIMIENTO MINA | AC97: SUPERINTENDENCIA SÉNIOR DE INGENIERÍA Y SEGURIDAD DE EQUIPOS MÓVILES | AD97: SUPERINTENDENCIA DE MANTENIMIENTO MINA - EJECUCIÓN | AE97: SUPERVISIÓN DE MANTENIMIENTO MINA - CARGUÍO | AF97: MANTENIMIENTO MINA - EJECUCIÓN | AM97: 082 | AN97: zzzJL. Machine | BG97: 412 | BH97: 412 Almacén Bolas | BJ97: 95 | BK97: SERVICIOS DE TRANSPORTE DE PERSONAL | BR97: 03 | BT97: 02 | BU97: GERENCIA DE TI Y DESARROLLO DEL NEGOCIO
T98: 96 | U98: 04 | V98: 12 | W98: 33 | X98: CFRP | Y98: CARRASCO FLORES RAUL PEDRO | Z98: CARRASCO FLORES RAUL PEDRO - SUPERVISOR DE MANTENIMIENTO | AA98: VICEPRESIDENCIA DE OPERACIONES | AB98: GERENCIA DE MANTENIMIENTO PLANTA | AC98: SUPERINTENDENCIA DE MANTENIMIENTO - MEC. PLTA. FLOT., FILTROS, TALLER GRAL. Y RH | AD98: SUPERVISIÓN DE MANTENIMIENTO - GENERAL Y SOLDADURA | AF98: MANTENIMIENTO - GENERAL Y SOLDADURA | AM98: 083 | AN98: zzzKALTECH | BG98: 050 | BH98: 50 AREA MANTENIMIENTO GENERAL | BJ98: 96 | BK98: SERVICIOS TÉCNICOS | BR98: 04 | BT98: 01 | BU98: GERENCIA DE MANTENIMIENTO MINA
T99: 97 | U99: 04 | V99: 14 | W99: 39 | X99: CUCH | Y99: CARREÑO UZQUIANO CARLOS HUGO | Z99: CARREÑO UZQUIANO CARLOS HUGO - SUPERINTENDENTE DE GESTIÓN DE RELAVES Y SERVICIOS AUXILIARES | AA99: VICEPRESIDENCIA DE OPERACIONES | AB99: GERENCIA DE OPERACIONES PLANTA | AC99: SUPERINTENDENCIA DE GESTIÓN DE RELAVES Y SERVICIOS AUXILIARES | AF99: GESTIÓN DE RELAVES Y SERVICIOS AUXILIARES | AM99: 084 | AN99: zzzLopez Miranda | BG99: 501 | BH99: 501 Oficinas | BJ99: 97 | BK99: SERVICIOS Y PROGRAMAS DE SALUD | BR99: 04 | BT99: 02 | BU99: GERENCIA DE MANTENIMIENTO PLANTA
T100: 98 | U100: 04 | V100: 11 | W100: 28 | X100: CZGM | Y100: CARVAJAL ZABALA GUIDO MARCELO | Z100: CARVAJAL ZABALA GUIDO MARCELO - SUPERVISOR DE MANTENIMIENTO MINA | AA100: VICEPRESIDENCIA DE OPERACIONES | AB100: GERENCIA DE MANTENIMIENTO MINA | AC100: SUPERINTENDENCIA SÉNIOR DE INGENIERÍA Y SEGURIDAD DE EQUIPOS MÓVILES | AD100: SUPERINTENDENCIA DE MANTENIMIENTO MINA - EJECUCIÓN | AE100: SUPERVISIÓN DE MANTENIMIENTO MINA - ACARREO | AF100: MANTENIMIENTO MINA - EJECUCIÓN | AM100: 085 | AN100: zzzLuis Ampuero | BG100: 502 | BH100: 502 Sala Reunión | BJ100: 98 | BK100: SISTEMA DE GESTIÓN | BR100: 04 | BT100: 03 | BU100: GERENCIA DE OPERACIONES MINA
...
