Workbook
Name OP_prob: 'PARÁMETROS'!$D$11:$H$11
Name p_o: 'PARÁMETROS'!$C$18:$C$22
Name CC_L: 'PARÁMETROS'!$L$38:$N$38
Name CC_SA: 'PARÁMETROS'!$L$29:$N$29
Name FR_G: 'PARÁMETROS'!$BH$3:$BH$30
Name FC_G: 'PARÁMETROS'!$BJ$3:$BJ$30
Name FC_FI: 'PARÁMETROS'!$BZ$3:$BZ$30
Name FR_SE: 'PARÁMETROS'!$R$3:$R$46
Name FC_DS: 'PARÁMETROS'!$BB$3:$BB$26
Name FV_OP: 'PARÁMETROS'!$BT$3:$BT$11
Name JC_SE: 'PARÁMETROS'!$K$3:$K$8
Name FP_SE: 'PARÁMETROS'!$P$3:$P$45
Name FV_MA: 'PARÁMETROS'!$AF$3:$AF$12
Name FP_G: 'PARÁMETROS'!$BF$3:$BF$30
Name JC_DS: 'PARÁMETROS'!$K$12:$K$17
Name FV_L: 'PARÁMETROS'!$AV$3:$AV$30
Name FV_G: 'PARÁMETROS'!$BL$3:$BL$30
Name JC_SA: 'PARÁMETROS'!$K$30:$K$35
Name FI_MA: 'PARÁMETROS'!$AB$3:$AB$29
Name CC_SE: 'PARÁMETROS'!$L$2:$N$2
Name CC_G: 'PARÁMETROS'!$L$47:$N$47
Name FV_SA: 'PARÁMETROS'!$AN$3:$AN$30
Name FV_DS: 'PARÁMETROS'!$BD$3:$BD$7
Name FC_L: 'PARÁMETROS'!$AT$3:$AT$30
Name FR_L: 'PARÁMETROS'!$AR$3:$AR$30
Name FR_SA: 'PARÁMETROS'!$AJ$3:$AJ$30
Name VS: 'PARÁMETROS'!$X$3:$X$22
Name JC_G: 'PARÁMETROS'!$K$48:$K$53
Name FC_SE: 'PARÁMETROS'!$T$3:$T$19
Name Op_Sev: 'PARÁMETROS'!$C$12:$C$16
Name CC_DS: 'PARÁMETROS'!$L$11:$N$11
Name FP_FI: 'PARÁMETROS'!$BV$3:$BV$30
Name FP_SA: 'PARÁMETROS'!$AH$3:$AH$30
Name FP_op: 'PARÁMETROS'!$BN$3:$BN$10
Name JC_FI: 'PARÁMETROS'!$K$66:$K$71
Name JC_L: 'PARÁMETROS'!$K$39:$K$44
Name FR_FI: 'PARÁMETROS'!$BX$3:$BX$30
Name FV_FI: 'PARÁMETROS'!$CB$3:$CB$30
Name CC_MA: 'PARÁMETROS'!$L$20:$N$20
Name Oportunidad: 'PARÁMETROS'!$D$12:$H$16
Name JC_OP: 'PARÁMETROS'!$K$57:$K$62
Name FR_OP: 'PARÁMETROS'!$BP$3:$BP$11
Name FC_MA: 'PARÁMETROS'!$AD$3:$AD$35
Name JC_MA: 'PARÁMETROS'!$K$21:$K$26
Name FV_SE: 'PARÁMETROS'!$V$3:$V$8
Name FR_DS: 'PARÁMETROS'!$AZ$3:$AZ$16
Name CC_FI: 'PARÁMETROS'!$L$65:$N$65
Name FC_SA: 'PARÁMETROS'!$AL$3:$AL$30
Name CC_OP: 'PARÁMETROS'!$L$56:$N$56
Name FP_DS: 'PARÁMETROS'!$AX$3:$AX$24
Name FP_L: 'PARÁMETROS'!$AP$3:$AP$30
Name FA_MA: 'PARÁMETROS'!$Z$3:$Z$46
Name FC_OP: 'PARÁMETROS'!$BR$3:$BR$11

Sheet MATRIZ DE RIESGOS_2024
D1: IDENTIFICACIÓN, EVALUACIÓN DE RIESGOS | W1: 1.02.P06.F01
W2: INTERNA
A3: Gerencia / Superintendencia Senior : | E3: GERENCIA DE MANTENIMIENTO Y SERVICIOS DE SOPORTE | P3: Elaborador por : | Q3: Erick Muñoz Arandia | S3: Revisado y aprobado por : | T3: MIGUEL MARTIN RUBIN DE CELIS CANDIA
A4: Superintendencia : | E4: SUPERINTENDENCIA DE MANTENIMIENTO - MEC. PLANTA CHANCADO, MOLIENDA Y LUBRICACION
A5: Área / Departamento : | E5: Mantenimiento Chancado | P5: Fecha : | Q5: 05 / Dic / 2024 | S5: Fecha: | T5: 02 / Ene / 2025
A6: N° | B6: Área / Proceso / Alcance | C6: Actividad / Tarea / Grupo de Interés | D6: Condición Normal, Anormal, Emergencia o Factor | E6: Seguridad, Salud, Medio Ambiente, Legal, Responsabilidad Social, Otro | F6: Familia Peligro/ Aspecto / Evento | G6: Descripción Peligro / Aspecto / Evento | H6: Familia Riesgo / Impacto / Consecuencia | I6: Descripción Riesgo / Impacto / Coonsecuencia | J6: Riesgo / Impacto | P6: Familia de Controles | Q6: Medidas de Prevención, Control y Mitigación | R6: Familia de Verificadores | S6: Verificadores | T6: Calidad del Control | U6: Jerarquía de Control | V6: Eficacia del Control / Acción | W6: Nivel de Riesgo / Impacto Actual | X6: Incidentes Ocurridos | Y6: Trazabilidad / Historial / Observaciones Actual
J7: Exposición | K7: Posibilidad | L7: Probabilidad (R/I) | M7: Severidad | N7: Resultado de Evaluación Riesgo / Iimpacto | O7: Nivel de Riesgo / Iimpacto Inicial Puro
A8: 1 | B8: Mantenimiento Chancador | C8: Desmontaje y montaje de componentes del Chancador Primario (araña, cóncavos, eje principal) | D8: Normal | E8: Seguridad | F8: Trabajo / circulación de equipo/vehículo (pesado / liviano) | G8: Equipo de mina en operación, en el área de trabajo | H8: Aplastamiento | I8: Atropellamiento con equipo de operación minera que circulan por el chancador | J8: 5 | K8: 2 | L8: =IF(OR(J8<>"",K8<>""),OFFSET('PARÁMETROS'!$B$2,K8,J8),"") -> 3 | M8: 5 | N8: =IFERROR(L8*M8,"") -> 15 | O8: =IF(N8="","",IFERROR(IF(N8<=2,"ACEPTABLE",IF(N8<=6,"BAJA",IF(N8<=10,"ACEPTABLE CON REVISIÓN",IF(N8<=15,"SUSTANCIAL","INACEPTABLE")))),"")) -> SUSTANCIAL | P8: Señales/ Advertencias/ Alarmas | Q8: Señalizar con Conos de Seguridad y letrero de Camino Cerrado durante trabajos de Mantenimiento de Chancador | R8: Publicación de Indicadores | S8: Seguimiento y publicación de reporte STOP o Seguimiento y publicación de reporte de observaciones conductuales | T8: A. Mayor 80% | U8: 3. Señalización/ Advertencias/ Alarma | V8: =IFERROR(IF(AA8="SEGURIDAD",OFFSET('PARÁMETROS'!$K$2,MATCH(U8,JC_SE,0),MATCH(T8,CC_SE,0)), IF(OR(AA8="DSRC/Estratégico",AA8="DSRC/Operativo"),OFFSET('PARÁMETROS'!$K$11,MATCH(U8,JC_DS,0),MATCH(T8,CC_DS,0)), IF(AA8="SALUD",OFFSET('PARÁMETROS'!$K$29,MATCH(U8,JC_SA,0),MATCH(T8,CC_SA,0)), IF(AA8="MEDIO AMBIENTE",OFFSET('PARÁMETROS'!$K$20,MATCH(U8,JC_MA,0),MATCH(T8,CC_MA,0)), IF(AA8="Rel. Gubernamentales",OFFSET('PARÁMETROS'!$K$48,MATCH(U8,JC_G,0),MATCH(T8,CC_G,0)), IF(AA8="OPERACIONAL",OFFSET('PARÁMETROS'!$K$56,MATCH(U8,JC_OP,0),MATCH(T8,CC_OP,0)), IF(AA8="FINANCIERO",OFFSET('PARÁMETROS'!$K$56,MATCH(U8,JC_FI,0),MATCH(T8,CC_FI,0)), OFFSET('PARÁMETROS'!$K$38,MATCH(U8,JC_L,0),MATCH(T8,CC_L,0))))))))),"") -> Control/Acción Eficaz | W8: =IF(E8="","", IF(COUNTA( V8)-COUNTBLANK( V8)=1, IF(O8="INACEPTABLE",IF(COUNTIF( V8,"Control/Acción Eficaz")>=1,"SUSTANCIAL","INACEPTABLE"), IF(O8="SUSTANCIAL",IF(COUNTIF( V8,"Control/Acción Eficaz")>=1,"ACEPTABLE CON REVISIÓN","SUSTANCIAL"), IF(O8="ACEPTABLE CON REVISIÓN",IF(COUNTIF( V8,"Control/Acción Eficaz")>=1,"BAJA","ACEPTABLE CON REVISIÓN"), IF(O8="BAJA",IF(COUNTIF( V8,"Control/Acción Eficaz")>=1,"ACEPTABLE","BAJA"),)))), IF(COUNTA( V8)-COUNTBLANK( V8)=2, IF(O8="INACEPTABLE",IF(COUNTIF( V8,"Control/Acción Eficaz")=2,"ACEPTABLE CON REVISIÓN", IF(OR(AND(COUNTIF( V8,"Control/Acción Eficaz")=1,COUNTIF( V8,"Control/Acción Satisfactorio")=1), AND(COUNTIF( V8,"Control/Acción Eficaz")=1,COUNTIF( V8,"Control/Acción No Eficaz")=1)),"SUSTANCIAL","INACEPTABLE")), IF(O8="SUSTANCIAL",IF(COUNTIF( V8,"Control/Acción Eficaz")=2,"BAJA", IF(OR(AND(COUNTIF( V8,"Control/Acción Eficaz")=1,COUNTIF( V8,"Control/Acción Satisfactorio")=1), AND(COUNTIF( V8,"Control/Acción Eficaz")=1,COUNTIF( V8,"Control/Acción No Eficaz")=1)),"ACEPTABLE CON REVISIÓN ","SUSTANCIAL")), IF(O8="ACEPTABLE CON REVISIÓN",IF(COUNTIF( V8,"Control/Acción Eficaz")=2,"ACEPTABLE", IF(OR(AND(COUNTIF( V8,"Control/Acción Eficaz")=1,COUNTIF( V8,"Control/Acción Satisfactorio")=1), AND(COUNTIF( V8,"Control/Acción Eficaz")=1,COUNTIF( V8,"Control/Acción No Eficaz")=1)),"BAJA","ACEPTABLE CON REVISIÓN")), IF(O8="BAJA",IF(COUNTIF( V8,"Control/Acción Eficaz")>=2,"ACEPTABLE","BAJA"),)))), IF(COUNTA( V8)-COUNTBLANK( V8)>=3, IF(O8="INACEPTABLE", IF(COUNTBLANK( V8)=COUNTA( V8),"", IF(COUNTIF( V8,"Control/Acción No Eficaz")>=2,"INACEPTABLE", IF(AND(COUNTIF( V8,"Control/Acción No Eficaz")=0,COUNTIF( V8,"Control/Acción Eficaz")>=2),"ACEPTABLE CON REVISIÓN ","SUSTANCIAL"))), IF(O8="SUSTANCIAL", IF(COUNTBLANK( V8)=COUNTA( V8),"", IF(COUNTIF( V8,"Control/Acción No Eficaz")>=2,"SUSTANCIAL", IF(AND(COUNTIF( V8,"Control/Acción No Eficaz")=0,COUNTIF( V8,"Control/Acción Eficaz")>=2),"BAJA","ACEPTABLE CON REVISIÓN"))), IF(O8="ACEPTABLE CON REVISIÓN", IF(COUNTBLANK( V8)=COUNTA( V8),"", IF(COUNTIF( V8,"Control/Acción No Eficaz")>=2,"ACEPTABLE CON REVISIÓN", IF(AND(COUNTIF( V8,"Control/Acción No Eficaz")=0,COUNTIF( V8,"Control/Acción Eficaz")>=2),"ACEPTABLE","BAJA"))), IF(O8="BAJA", IF(COUNTBLANK( V8)=COUNTA( V8),"", IF(AND(COUNTBLANK( V8)<1,COUNTA( V8)=1), IF(COUNTIF( V8,"Control/Acción No Eficaz")>=2,"BAJA", IF(AND(COUNTIF( V8,"Control/Acción No Eficaz")=0,COUNTIF( V8,"Control/Acción Eficaz")>=2),"ACEPTABLE","BAJA")), IF(COUNTIF( V8,"Control/Acción No Eficaz")>=2,"BAJA", IF(AND(COUNTIF( V8,"Control/Acción No Eficaz")=0,COUNTIF( V8,"Control/Acción Eficaz")>=2),"ACEPTABLE","BAJA")))), IF(COUNTIF( V8,"")>=5,"",O8))))), "")))) -> ACEPTABLE CON REVISIÓN | Z8: OK | AA8: =E8 -> Seguridad
A9: 2 | B9: Mantenimiento Chancador | C9: Desmontaje y montaje de componentes del Chancador Primario (araña, cóncavos, eje principal) | D9: Normal | E9: Seguridad | F9: Trabajo en altura, sobre plataformas elevadas, escaleras, andamios, rampas o pisos sin barreras de protección (barandas o barreras rígidas). | G9: Trabajo en altura cerca del perímetro del buzón de descarga parte superior, montaje y desmontaje de componentes de chancador primario | H9: Caída de altura (Igual o Mayor a 1,80) | I9: Al realizar trabajos en la parte superior del buzón existe el riesgo de caída a distinto nivel | J9: 3 | K9: 2 | L9: =IF(OR(J9<>"",K9<>""),OFFSET('PARÁMETROS'!$B$2,K9,J9),"") -> 4 | M9: 5 | N9: =IFERROR(L9*M9,"") -> 20 | O9: =IF(N9="","",IFERROR(IF(N9<=2,"ACEPTABLE",IF(N9<=6,"BAJA",IF(N9<=10,"ACEPTABLE CON REVISIÓN",IF(N9<=15,"SUSTANCIAL","INACEPTABLE")))),"")) -> INACEPTABLE | P9: Competencias | Q9: Contar con personal competente para realizar Trabajo en Altura | R9: Planillas de vigencia de Certificaciones / Competencias/ Capacitaciones | S9: Seguimiento a la Planilla de vigencia de cursos, autorizaciones, competencias y/o certificaciones de personas y equipos | T9: A. Mayor 80% | U9: 2. Administrativo/ Procedimientos/ Capacitación | V9: =IFERROR(IF(AA9="SEGURIDAD",OFFSET('PARÁMETROS'!$K$2,MATCH(U9,JC_SE,0),MATCH(T9,CC_SE,0)), IF(OR(AA9="DSRC/Estratégico",AA9="DSRC/Operativo"),OFFSET('PARÁMETROS'!$K$11,MATCH(U9,JC_DS,0),MATCH(T9,CC_DS,0)), IF(AA9="SALUD",OFFSET('PARÁMETROS'!$K$29,MATCH(U9,JC_SA,0),MATCH(T9,CC_SA,0)), IF(AA9="MEDIO AMBIENTE",OFFSET('PARÁMETROS'!$K$20,MATCH(U9,JC_MA,0),MATCH(T9,CC_MA,0)), IF(AA9="Rel. Gubernamentales",OFFSET('PARÁMETROS'!$K$48,MATCH(U9,JC_G,0),MATCH(T9,CC_G,0)), IF(AA9="OPERACIONAL",OFFSET('PARÁMETROS'!$K$56,MATCH(U9,JC_OP,0),MATCH(T9,CC_OP,0)), IF(AA9="FINANCIERO",OFFSET('PARÁMETROS'!$K$56,MATCH(U9,JC_FI,0),MATCH(T9,CC_FI,0)), OFFSET('PARÁMETROS'!$K$38,MATCH(U9,JC_L,0),MATCH(T9,CC_L,0))))))))),"") -> Control/Acción Eficaz | W9: =IF(E9="","", IF(COUNTA( V9:V26)-COUNTBLANK( V9:V26)=1, IF(O9="INACEPTABLE",IF(COUNTIF( V9:V26,"Control/Acción Eficaz")>=1,"SUSTANCIAL","INACEPTABLE"), IF(O9="SUSTANCIAL",IF(COUNTIF( V9:V26,"Control/Acción Eficaz")>=1,"ACEPTABLE CON REVISIÓN","SUSTANCIAL"), IF(O9="ACEPTABLE CON REVISIÓN",IF(COUNTIF( V9:V26,"Control/Acción Eficaz")>=1,"BAJA","ACEPTABLE CON REVISIÓN"), IF(O9="BAJA",IF(COUNTIF( V9:V26,"Control/Acción Eficaz")>=1,"ACEPTABLE","BAJA"),)))), IF(COUNTA( V9:V26)-COUNTBLANK( V9:V26)=2, IF(O9="INACEPTABLE",IF(COUNTIF( V9:V26,"Control/Acción Eficaz")=2,"ACEPTABLE CON REVISIÓN", IF(OR(AND(COUNTIF( V9:V26,"Control/Acción Eficaz")=1,COUNTIF( V9:V26,"Control/Acción Satisfactorio")=1), AND(COUNTIF( V9:V26,"Control/Acción Eficaz")=1,COUNTIF( V9:V26,"Control/Acción No Eficaz")=1)),"SUSTANCIAL","INACEPTABLE")), IF(O9="SUSTANCIAL",IF(COUNTIF( V9:V26,"Control/Acción Eficaz")=2,"BAJA", IF(OR(AND(COUNTIF( V9:V26,"Control/Acción Eficaz")=1,COUNTIF( V9:V26,"Control/Acción Satisfactorio")=1), AND(COUNTIF( V9:V26,"Control/Acción Eficaz")=1,COUNTIF( V9:V26,"Control/Acción No Eficaz")=1)),"ACEPTABLE CON REVISIÓN ","SUSTANCIAL")), IF(O9="ACEPTABLE CON REVISIÓN",IF(COUNTIF( V9:V26,"Control/Acción Eficaz")=2,"ACEPTABLE", IF(OR(AND(COUNTIF( V9:V26,"Control/Acción Eficaz")=1,COUNTIF( V9:V26,"Control/Acción Satisfactorio")=1), AND(COUNTIF( V9:V26,"Control/Acción Eficaz")=1,COUNTIF( V9:V26,"Control/Acción No Eficaz")=1)),"BAJA","ACEPTABLE CON REVISIÓN")), IF(O9="BAJA",IF(COUNTIF( V9:V26,"Control/Acción Eficaz")>=2,"ACEPTABLE","BAJA"),)))), IF(COUNTA( V9:V26)-COUNTBLANK( V9:V26)>=3, IF(O9="INACEPTABLE", IF(COUNTBLANK( V9:V26)=COUNTA( V9:V26),"", IF(COUNTIF( V9:V26,"Control/Acción No Eficaz")>=2,"INACEPTABLE", IF(AND(COUNTIF( V9:V26,"Control/Acción No Eficaz")=0,COUNTIF( V9:V26,"Control/Acción Eficaz")>=2),"ACEPTABLE CON REVISIÓN ","SUSTANCIAL"))), IF(O9="SUSTANCIAL", IF(COUNTBLANK( V9:V26)=COUNTA( V9:V26),"", IF(COUNTIF( V9:V26,"Control/Acción No Eficaz")>=2,"SUSTANCIAL", IF(AND(COUNTIF( V9:V26,"Control/Acción No Eficaz")=0,COUNTIF( V9:V26,"Control/Acción Eficaz")>=2),"BAJA","ACEPTABLE CON REVISIÓN"))), IF(O9="ACEPTABLE CON REVISIÓN", IF(COUNTBLANK( V9:V26)=COUNTA( V9:V26),"", IF(COUNTIF( V9:V26,"Control/Acción No Eficaz")>=2,"ACEPTABLE CON REVISIÓN", IF(AND(COUNTIF( V9:V26,"Control/Acción No Eficaz")=0,COUNTIF( V9:V26,"Control/Acción Eficaz")>=2),"ACEPTABLE","BAJA"))), IF(O9="BAJA", IF(COUNTBLANK( V9:V26)=COUNTA( V9:V26),"", IF(AND(COUNTBLANK( V9:V26)<1,COUNTA( V9:V26)=1), IF(COUNTIF( V9:V26,"Control/Acción No Eficaz")>=2,"BAJA", IF(AND(COUNTIF( V9:V26,"Control/Acción No Eficaz")=0,COUNTIF( V9:V26,"Control/Acción Eficaz")>=2),"ACEPTABLE","BAJA")), IF(COUNTIF( V9:V26,"Control/Acción No Eficaz")>=2,"BAJA", IF(AND(COUNTIF( V9:V26,"Control/Acción No Eficaz")=0,COUNTIF( V9:V26,"Control/Acción Eficaz")>=2),"ACEPTABLE","BAJA")))), IF(COUNTIF( V9:V26,"")>=5,"",O9))))), "")))) -> SUSTANCIAL | Z9: OK | AA9: =E9 -> Seguridad
P10: Capacitación/Entrenamiento | Q10: Capacitar al personal sobre los estándares del Instructivo de Trabajo en Altura 1.02.P06.I15 | R10: Planes / Programas | S10: Seguimiento al programa de difusión de instructivos y capacitaciones internas | T10: B. 50% y 80% | U10: 2. Administrativo/ Procedimientos/ Capacitación | V10: =IFERROR(IF(AA10="SEGURIDAD",OFFSET('PARÁMETROS'!$K$2,MATCH(U10,JC_SE,0),MATCH(T10,CC_SE,0)), IF(OR(AA10="DSRC/Estratégico",AA10="DSRC/Operativo"),OFFSET('PARÁMETROS'!$K$11,MATCH(U10,JC_DS,0),MATCH(T10,CC_DS,0)), IF(AA10="SALUD",OFFSET('PARÁMETROS'!$K$29,MATCH(U10,JC_SA,0),MATCH(T10,CC_SA,0)), IF(AA10="MEDIO AMBIENTE",OFFSET('PARÁMETROS'!$K$20,MATCH(U10,JC_MA,0),MATCH(T10,CC_MA,0)), IF(AA10="Rel. Gubernamentales",OFFSET('PARÁMETROS'!$K$48,MATCH(U10,JC_G,0),MATCH(T10,CC_G,0)), IF(AA10="OPERACIONAL",OFFSET('PARÁMETROS'!$K$56,MATCH(U10,JC_OP,0),MATCH(T10,CC_OP,0)), IF(AA10="FINANCIERO",OFFSET('PARÁMETROS'!$K$56,MATCH(U10,JC_FI,0),MATCH(T10,CC_FI,0)), OFFSET('PARÁMETROS'!$K$38,MATCH(U10,JC_L,0),MATCH(T10,CC_L,0))))))))),"") -> Control/Acción Satisfactorio | Z10: OK | AA10: =E9 -> Seguridad
P11: Capacitación/Entrenamiento | Q11: Contar con Personal con curso vigente en Gestión de Riesgos (ART/VPT) | R11: Planillas de vigencia de Certificaciones / Competencias/ Capacitaciones | S11: Seguimiento a la Planilla de vigencia de cursos, autorizaciones, competencias y/o certificaciones de personas y equipos | T11: A. Mayor 80% | U11: 2. Administrativo/ Procedimientos/ Capacitación | V11: =IFERROR(IF(AA11="SEGURIDAD",OFFSET('PARÁMETROS'!$K$2,MATCH(U11,JC_SE,0),MATCH(T11,CC_SE,0)), IF(OR(AA11="DSRC/Estratégico",AA11="DSRC/Operativo"),OFFSET('PARÁMETROS'!$K$11,MATCH(U11,JC_DS,0),MATCH(T11,CC_DS,0)), IF(AA11="SALUD",OFFSET('PARÁMETROS'!$K$29,MATCH(U11,JC_SA,0),MATCH(T11,CC_SA,0)), IF(AA11="MEDIO AMBIENTE",OFFSET('PARÁMETROS'!$K$20,MATCH(U11,JC_MA,0),MATCH(T11,CC_MA,0)), IF(AA11="Rel. Gubernamentales",OFFSET('PARÁMETROS'!$K$48,MATCH(U11,JC_G,0),MATCH(T11,CC_G,0)), IF(AA11="OPERACIONAL",OFFSET('PARÁMETROS'!$K$56,MATCH(U11,JC_OP,0),MATCH(T11,CC_OP,0)), IF(AA11="FINANCIERO",OFFSET('PARÁMETROS'!$K$56,MATCH(U11,JC_FI,0),MATCH(T11,CC_FI,0)), OFFSET('PARÁMETROS'!$K$38,MATCH(U11,JC_L,0),MATCH(T11,CC_L,0))))))))),"") -> Control/Acción Eficaz | Z11: OK | AA11: =E9 -> Seguridad
P12: Capacitación/Entrenamiento | Q12: Capacitar al personal sobre respuesta ante emergencias descrito del Plan de Emergencia 2.04.P05.E20 | R12: Planes / Programas | S12: Seguimiento al programa de difusión de instructivos y capacitaciones internas | T12: B. 50% y 80% | U12: 2. Administrativo/ Procedimientos/ Capacitación | V12: =IFERROR(IF(AA12="SEGURIDAD",OFFSET('PARÁMETROS'!$K$2,MATCH(U12,JC_SE,0),MATCH(T12,CC_SE,0)), IF(OR(AA12="DSRC/Estratégico",AA12="DSRC/Operativo"),OFFSET('PARÁMETROS'!$K$11,MATCH(U12,JC_DS,0),MATCH(T12,CC_DS,0)), IF(AA12="SALUD",OFFSET('PARÁMETROS'!$K$29,MATCH(U12,JC_SA,0),MATCH(T12,CC_SA,0)), IF(AA12="MEDIO AMBIENTE",OFFSET('PARÁMETROS'!$K$20,MATCH(U12,JC_MA,0),MATCH(T12,CC_MA,0)), IF(AA12="Rel. Gubernamentales",OFFSET('PARÁMETROS'!$K$48,MATCH(U12,JC_G,0),MATCH(T12,CC_G,0)), IF(AA12="OPERACIONAL",OFFSET('PARÁMETROS'!$K$56,MATCH(U12,JC_OP,0),MATCH(T12,CC_OP,0)), IF(AA12="FINANCIERO",OFFSET('PARÁMETROS'!$K$56,MATCH(U12,JC_FI,0),MATCH(T12,CC_FI,0)), OFFSET('PARÁMETROS'!$K$38,MATCH(U12,JC_L,0),MATCH(T12,CC_L,0))))))))),"") -> Control/Acción Satisfactorio | Z12: OK | AA12: =E9 -> Seguridad
P13: Controles/Acciones de Emergencias | Q13: Difundir la ruta de evacuación para caso de emergencia, punto de reunión y protocolo de emergencia | R13: Planes / Programas | S13: Seguimiento al programa de reuniones y evaluaciones de compromiso con la seguridad | T13: B. 50% y 80% | U13: 2. Administrativo/ Procedimientos/ Capacitación | V13: =IFERROR(IF(AA13="SEGURIDAD",OFFSET('PARÁMETROS'!$K$2,MATCH(U13,JC_SE,0),MATCH(T13,CC_SE,0)), IF(OR(AA13="DSRC/Estratégico",AA13="DSRC/Operativo"),OFFSET('PARÁMETROS'!$K$11,MATCH(U13,JC_DS,0),MATCH(T13,CC_DS,0)), IF(AA13="SALUD",OFFSET('PARÁMETROS'!$K$29,MATCH(U13,JC_SA,0),MATCH(T13,CC_SA,0)), IF(AA13="MEDIO AMBIENTE",OFFSET('PARÁMETROS'!$K$20,MATCH(U13,JC_MA,0),MATCH(T13,CC_MA,0)), IF(AA13="Rel. Gubernamentales",OFFSET('PARÁMETROS'!$K$48,MATCH(U13,JC_G,0),MATCH(T13,CC_G,0)), IF(AA13="OPERACIONAL",OFFSET('PARÁMETROS'!$K$56,MATCH(U13,JC_OP,0),MATCH(T13,CC_OP,0)), IF(AA13="FINANCIERO",OFFSET('PARÁMETROS'!$K$56,MATCH(U13,JC_FI,0),MATCH(T13,CC_FI,0)), OFFSET('PARÁMETROS'!$K$38,MATCH(U13,JC_L,0),MATCH(T13,CC_L,0))))))))),"") -> Control/Acción Satisfactorio | Z13: OK | AA13: =E9 -> Seguridad
P14: Controles de Ingeniería | Q14: Contar con radio comunicación o Handy en las área de trabajo | R14: Publicación de Indicadores | S14: Seguimiento y publicación de reporte STOP o Seguimiento y publicación de reporte de observaciones conductuales | T14: B. 50% y 80% | U14: 4. Ingeniería | V14: =IFERROR(IF(AA14="SEGURIDAD",OFFSET('PARÁMETROS'!$K$2,MATCH(U14,JC_SE,0),MATCH(T14,CC_SE,0)), IF(OR(AA14="DSRC/Estratégico",AA14="DSRC/Operativo"),OFFSET('PARÁMETROS'!$K$11,MATCH(U14,JC_DS,0),MATCH(T14,CC_DS,0)), IF(AA14="SALUD",OFFSET('PARÁMETROS'!$K$29,MATCH(U14,JC_SA,0),MATCH(T14,CC_SA,0)), IF(AA14="MEDIO AMBIENTE",OFFSET('PARÁMETROS'!$K$20,MATCH(U14,JC_MA,0),MATCH(T14,CC_MA,0)), IF(AA14="Rel. Gubernamentales",OFFSET('PARÁMETROS'!$K$48,MATCH(U14,JC_G,0),MATCH(T14,CC_G,0)), IF(AA14="OPERACIONAL",OFFSET('PARÁMETROS'!$K$56,MATCH(U14,JC_OP,0),MATCH(T14,CC_OP,0)), IF(AA14="FINANCIERO",OFFSET('PARÁMETROS'!$K$56,MATCH(U14,JC_FI,0),MATCH(T14,CC_FI,0)), OFFSET('PARÁMETROS'!$K$38,MATCH(U14,JC_L,0),MATCH(T14,CC_L,0))))))))),"") -> Control/Acción Satisfactorio | Z14: OK | AA14: =E9 -> Seguridad
P15: Capacitación/Entrenamiento | Q15: Capacitar al personal sobre los estándares del Manual de Reglas de Oro, Trabajo en Altura 1.02.P06.MT02. | R15: Planes / Programas | S15: Seguimiento al programa de difusión de instructivos y capacitaciones internas | T15: B. 50% y 80% | U15: 2. Administrativo/ Procedimientos/ Capacitación | V15: =IFERROR(IF(AA15="SEGURIDAD",OFFSET('PARÁMETROS'!$K$2,MATCH(U15,JC_SE,0),MATCH(T15,CC_SE,0)), IF(OR(AA15="DSRC/Estratégico",AA15="DSRC/Operativo"),OFFSET('PARÁMETROS'!$K$11,MATCH(U15,JC_DS,0),MATCH(T15,CC_DS,0)), IF(AA15="SALUD",OFFSET('PARÁMETROS'!$K$29,MATCH(U15,JC_SA,0),MATCH(T15,CC_SA,0)), IF(AA15="MEDIO AMBIENTE",OFFSET('PARÁMETROS'!$K$20,MATCH(U15,JC_MA,0),MATCH(T15,CC_MA,0)), IF(AA15="Rel. Gubernamentales",OFFSET('PARÁMETROS'!$K$48,MATCH(U15,JC_G,0),MATCH(T15,CC_G,0)), IF(AA15="OPERACIONAL",OFFSET('PARÁMETROS'!$K$56,MATCH(U15,JC_OP,0),MATCH(T15,CC_OP,0)), IF(AA15="FINANCIERO",OFFSET('PARÁMETROS'!$K$56,MATCH(U15,JC_FI,0),MATCH(T15,CC_FI,0)), OFFSET('PARÁMETROS'!$K$38,MATCH(U15,JC_L,0),MATCH(T15,CC_L,0))))))))),"") -> Control/Acción Satisfactorio | Z15: OK | AA15: =E9 -> Seguridad
P16: Procedimientos / Instructivos / Reglamentos y otros. | Q16: Cumplir com los estandares del Instructivo de Trabajos en Altura 1.02.P06.I15 | R16: Planes / Programas | S16: Seguimiento al programa de inspecciones IRO´S: Trabajo en Altura | T16: B. 50% y 80% | U16: 2. Administrativo/ Procedimientos/ Capacitación | V16: =IFERROR(IF(AA16="SEGURIDAD",OFFSET('PARÁMETROS'!$K$2,MATCH(U16,JC_SE,0),MATCH(T16,CC_SE,0)), IF(OR(AA16="DSRC/Estratégico",AA16="DSRC/Operativo"),OFFSET('PARÁMETROS'!$K$11,MATCH(U16,JC_DS,0),MATCH(T16,CC_DS,0)), IF(AA16="SALUD",OFFSET('PARÁMETROS'!$K$29,MATCH(U16,JC_SA,0),MATCH(T16,CC_SA,0)), IF(AA16="MEDIO AMBIENTE",OFFSET('PARÁMETROS'!$K$20,MATCH(U16,JC_MA,0),MATCH(T16,CC_MA,0)), IF(AA16="Rel. Gubernamentales",OFFSET('PARÁMETROS'!$K$48,MATCH(U16,JC_G,0),MATCH(T16,CC_G,0)), IF(AA16="OPERACIONAL",OFFSET('PARÁMETROS'!$K$56,MATCH(U16,JC_OP,0),MATCH(T16,CC_OP,0)), IF(AA16="FINANCIERO",OFFSET('PARÁMETROS'!$K$56,MATCH(U16,JC_FI,0),MATCH(T16,CC_FI,0)), OFFSET('PARÁMETROS'!$K$38,MATCH(U16,JC_L,0),MATCH(T16,CC_L,0))))))))),"") -> Control/Acción Satisfactorio | Z16: NO APLICA, PUESTO QUE NO PODRIA INGRESAR AL SECTOR UN EQUIPO DE PLATAFORMA ELEVADORA | AA16: =E9 -> Seguridad
P17: Controles de Ingeniería | Q17: Contar con puntos de anclajes y líneas de vida validados y/o certificados | R17: Planes / Programas | S17: Seguimiento al programa de inspecciones IRO´S: Trabajo en Altura | T17: A. Mayor 80% | U17: 4. Ingeniería | V17: =IFERROR(IF(AA17="SEGURIDAD",OFFSET('PARÁMETROS'!$K$2,MATCH(U17,JC_SE,0),MATCH(T17,CC_SE,0)), IF(OR(AA17="DSRC/Estratégico",AA17="DSRC/Operativo"),OFFSET('PARÁMETROS'!$K$11,MATCH(U17,JC_DS,0),MATCH(T17,CC_DS,0)), IF(AA17="SALUD",OFFSET('PARÁMETROS'!$K$29,MATCH(U17,JC_SA,0),MATCH(T17,CC_SA,0)), IF(AA17="MEDIO AMBIENTE",OFFSET('PARÁMETROS'!$K$20,MATCH(U17,JC_MA,0),MATCH(T17,CC_MA,0)), IF(AA17="Rel. Gubernamentales",OFFSET('PARÁMETROS'!$K$48,MATCH(U17,JC_G,0),MATCH(T17,CC_G,0)), IF(AA17="OPERACIONAL",OFFSET('PARÁMETROS'!$K$56,MATCH(U17,JC_OP,0),MATCH(T17,CC_OP,0)), IF(AA17="FINANCIERO",OFFSET('PARÁMETROS'!$K$56,MATCH(U17,JC_FI,0),MATCH(T17,CC_FI,0)), OFFSET('PARÁMETROS'!$K$38,MATCH(U17,JC_L,0),MATCH(T17,CC_L,0))))))))),"") -> Control/Acción Eficaz | Z17: OK | AA17: =E9 -> Seguridad
P18: Capacitación/Entrenamiento | Q18: Difundir Hoja ZAP SI-164 "Importancia de la Inspección del Arnés y Conectores" | R18: Planillas de vigencia de Certificaciones / Competencias/ Capacitaciones | S18: Seguimiento al programa de reuniones y evaluaciones de compromiso con la seguridad | T18: A. Mayor 80% | U18: 2. Administrativo/ Procedimientos/ Capacitación | V18: =IFERROR(IF(AA18="SEGURIDAD",OFFSET('PARÁMETROS'!$K$2,MATCH(U18,JC_SE,0),MATCH(T18,CC_SE,0)), IF(OR(AA18="DSRC/Estratégico",AA18="DSRC/Operativo"),OFFSET('PARÁMETROS'!$K$11,MATCH(U18,JC_DS,0),MATCH(T18,CC_DS,0)), IF(AA18="SALUD",OFFSET('PARÁMETROS'!$K$29,MATCH(U18,JC_SA,0),MATCH(T18,CC_SA,0)), IF(AA18="MEDIO AMBIENTE",OFFSET('PARÁMETROS'!$K$20,MATCH(U18,JC_MA,0),MATCH(T18,CC_MA,0)), IF(AA18="Rel. Gubernamentales",OFFSET('PARÁMETROS'!$K$48,MATCH(U18,JC_G,0),MATCH(T18,CC_G,0)), IF(AA18="OPERACIONAL",OFFSET('PARÁMETROS'!$K$56,MATCH(U18,JC_OP,0),MATCH(T18,CC_OP,0)), IF(AA18="FINANCIERO",OFFSET('PARÁMETROS'!$K$56,MATCH(U18,JC_FI,0),MATCH(T18,CC_FI,0)), OFFSET('PARÁMETROS'!$K$38,MATCH(U18,JC_L,0),MATCH(T18,CC_L,0))))))))),"") -> Control/Acción Eficaz | Z18: OK | AA18: =E9 -> Seguridad
P19: Capacitación/Entrenamiento | Q19: Difundir Hoja ZAP SI-107 "Uso correcto de la Cola de Vida durante los Trabajos en Altura" | R19: Planillas de vigencia de Certificaciones / Competencias/ Capacitaciones | S19: Seguimiento al programa de reuniones y evaluaciones de compromiso con la seguridad | T19: A. Mayor 80% | U19: 2. Administrativo/ Procedimientos/ Capacitación | V19: =IFERROR(IF(AA19="SEGURIDAD",OFFSET('PARÁMETROS'!$K$2,MATCH(U19,JC_SE,0),MATCH(T19,CC_SE,0)), IF(OR(AA19="DSRC/Estratégico",AA19="DSRC/Operativo"),OFFSET('PARÁMETROS'!$K$11,MATCH(U19,JC_DS,0),MATCH(T19,CC_DS,0)), IF(AA19="SALUD",OFFSET('PARÁMETROS'!$K$29,MATCH(U19,JC_SA,0),MATCH(T19,CC_SA,0)), IF(AA19="MEDIO AMBIENTE",OFFSET('PARÁMETROS'!$K$20,MATCH(U19,JC_MA,0),MATCH(T19,CC_MA,0)), IF(AA19="Rel. Gubernamentales",OFFSET('PARÁMETROS'!$K$48,MATCH(U19,JC_G,0),MATCH(T19,CC_G,0)), IF(AA19="OPERACIONAL",OFFSET('PARÁMETROS'!$K$56,MATCH(U19,JC_OP,0),MATCH(T19,CC_OP,0)), IF(AA19="FINANCIERO",OFFSET('PARÁMETROS'!$K$56,MATCH(U19,JC_FI,0),MATCH(T19,CC_FI,0)), OFFSET('PARÁMETROS'!$K$38,MATCH(U19,JC_L,0),MATCH(T19,CC_L,0))))))))),"") -> Control/Acción Eficaz | Z19: OK | AA19: =E9 -> Seguridad
P20: E.P.P. | Q20: Usar Sistema de Protección Contra Caídas (Arnés, Conector con absorbedor de energía, conector de restricción, posicionamiento y autoretractiles) | R20: Planes / Programas | S20: Seguimiento al programa de inspecciones IRO´S: Trabajo en Altura | T20: B. 50% y 80% | U20: 1. EPP | V20: =IFERROR(IF(AA20="SEGURIDAD",OFFSET('PARÁMETROS'!$K$2,MATCH(U20,JC_SE,0),MATCH(T20,CC_SE,0)), IF(OR(AA20="DSRC/Estratégico",AA20="DSRC/Operativo"),OFFSET('PARÁMETROS'!$K$11,MATCH(U20,JC_DS,0),MATCH(T20,CC_DS,0)), IF(AA20="SALUD",OFFSET('PARÁMETROS'!$K$29,MATCH(U20,JC_SA,0),MATCH(T20,CC_SA,0)), IF(AA20="MEDIO AMBIENTE",OFFSET('PARÁMETROS'!$K$20,MATCH(U20,JC_MA,0),MATCH(T20,CC_MA,0)), IF(AA20="Rel. Gubernamentales",OFFSET('PARÁMETROS'!$K$48,MATCH(U20,JC_G,0),MATCH(T20,CC_G,0)), IF(AA20="OPERACIONAL",OFFSET('PARÁMETROS'!$K$56,MATCH(U20,JC_OP,0),MATCH(T20,CC_OP,0)), IF(AA20="FINANCIERO",OFFSET('PARÁMETROS'!$K$56,MATCH(U20,JC_FI,0),MATCH(T20,CC_FI,0)), OFFSET('PARÁMETROS'!$K$38,MATCH(U20,JC_L,0),MATCH(T20,CC_L,0))))))))),"") -> Control/Acción No Eficaz | Z20: OK | AA20: =E9 -> Seguridad
P21: Capacitación/Entrenamiento | Q21: Contar con el curso de Inducción General OHS (2.04.P05.E20 Inducción Plan de Emergencia ) | R21: Planillas de vigencia de Certificaciones / Competencias/ Capacitaciones | S21: Seguimiento a la Planilla de vigencia de cursos, autorizaciones, competencias y/o certificaciones de personas y equipos | T21: A. Mayor 80% | U21: 2. Administrativo/ Procedimientos/ Capacitación | V21: =IFERROR(IF(AA21="SEGURIDAD",OFFSET('PARÁMETROS'!$K$2,MATCH(U21,JC_SE,0),MATCH(T21,CC_SE,0)), IF(OR(AA21="DSRC/Estratégico",AA21="DSRC/Operativo"),OFFSET('PARÁMETROS'!$K$11,MATCH(U21,JC_DS,0),MATCH(T21,CC_DS,0)), IF(AA21="SALUD",OFFSET('PARÁMETROS'!$K$29,MATCH(U21,JC_SA,0),MATCH(T21,CC_SA,0)), IF(AA21="MEDIO AMBIENTE",OFFSET('PARÁMETROS'!$K$20,MATCH(U21,JC_MA,0),MATCH(T21,CC_MA,0)), IF(AA21="Rel. Gubernamentales",OFFSET('PARÁMETROS'!$K$48,MATCH(U21,JC_G,0),MATCH(T21,CC_G,0)), IF(AA21="OPERACIONAL",OFFSET('PARÁMETROS'!$K$56,MATCH(U21,JC_OP,0),MATCH(T21,CC_OP,0)), IF(AA21="FINANCIERO",OFFSET('PARÁMETROS'!$K$56,MATCH(U21,JC_FI,0),MATCH(T21,CC_FI,0)), OFFSET('PARÁMETROS'!$K$38,MATCH(U21,JC_L,0),MATCH(T21,CC_L,0))))))))),"") -> Control/Acción Eficaz | Z21: OK | AA21: =E9 -> Seguridad
P22: Controles de Salud Ocupacional | Q22: Realizar la evaluación de Salud Ocupacional al personal. | R22: Planes / Programas | S22: Seguimiento a los programas preventivos y de control en salud | T22: B. 50% y 80% | U22: 2. Administrativo/ Procedimientos/ Capacitación | V22: =IFERROR(IF(AA22="SEGURIDAD",OFFSET('PARÁMETROS'!$K$2,MATCH(U22,JC_SE,0),MATCH(T22,CC_SE,0)), IF(OR(AA22="DSRC/Estratégico",AA22="DSRC/Operativo"),OFFSET('PARÁMETROS'!$K$11,MATCH(U22,JC_DS,0),MATCH(T22,CC_DS,0)), IF(AA22="SALUD",OFFSET('PARÁMETROS'!$K$29,MATCH(U22,JC_SA,0),MATCH(T22,CC_SA,0)), IF(AA22="MEDIO AMBIENTE",OFFSET('PARÁMETROS'!$K$20,MATCH(U22,JC_MA,0),MATCH(T22,CC_MA,0)), IF(AA22="Rel. Gubernamentales",OFFSET('PARÁMETROS'!$K$48,MATCH(U22,JC_G,0),MATCH(T22,CC_G,0)), IF(AA22="OPERACIONAL",OFFSET('PARÁMETROS'!$K$56,MATCH(U22,JC_OP,0),MATCH(T22,CC_OP,0)), IF(AA22="FINANCIERO",OFFSET('PARÁMETROS'!$K$56,MATCH(U22,JC_FI,0),MATCH(T22,CC_FI,0)), OFFSET('PARÁMETROS'!$K$38,MATCH(U22,JC_L,0),MATCH(T22,CC_L,0))))))))),"") -> Control/Acción Satisfactorio | Z22: OK | AA22: =E9 -> Seguridad
P23: Inspecciones | Q23: Inspección de arnés y conectores de acuerdo a formulario 1.02.P06.F19 | R23: Planes / Programas | S23: Seguimiento al programa de inspecciones IRO´S: Trabajo en Altura | T23: B. 50% y 80% | U23: 2. Administrativo/ Procedimientos/ Capacitación | V23: =IFERROR(IF(AA23="SEGURIDAD",OFFSET('PARÁMETROS'!$K$2,MATCH(U23,JC_SE,0),MATCH(T23,CC_SE,0)), IF(OR(AA23="DSRC/Estratégico",AA23="DSRC/Operativo"),OFFSET('PARÁMETROS'!$K$11,MATCH(U23,JC_DS,0),MATCH(T23,CC_DS,0)), IF(AA23="SALUD",OFFSET('PARÁMETROS'!$K$29,MATCH(U23,JC_SA,0),MATCH(T23,CC_SA,0)), IF(AA23="MEDIO AMBIENTE",OFFSET('PARÁMETROS'!$K$20,MATCH(U23,JC_MA,0),MATCH(T23,CC_MA,0)), IF(AA23="Rel. Gubernamentales",OFFSET('PARÁMETROS'!$K$48,MATCH(U23,JC_G,0),MATCH(T23,CC_G,0)), IF(AA23="OPERACIONAL",OFFSET('PARÁMETROS'!$K$56,MATCH(U23,JC_OP,0),MATCH(T23,CC_OP,0)), IF(AA23="FINANCIERO",OFFSET('PARÁMETROS'!$K$56,MATCH(U23,JC_FI,0),MATCH(T23,CC_FI,0)), OFFSET('PARÁMETROS'!$K$38,MATCH(U23,JC_L,0),MATCH(T23,CC_L,0))))))))),"") -> Control/Acción Satisfactorio | Z23: OK | AA23: =E9 -> Seguridad
P24: E.P.P. | Q24: Usar Sistema de Protección Contra Caídas (Arnés, Conector con absorbedor de energía, conector de restricción, posicionamiento y autoretractiles) | R24: Planes / Programas | S24: Seguimiento al programa de inspecciones IRO´S: Trabajo en Altura | T24: A. Mayor 80% | U24: 1. EPP | V24: =IFERROR(IF(AA24="SEGURIDAD",OFFSET('PARÁMETROS'!$K$2,MATCH(U24,JC_SE,0),MATCH(T24,CC_SE,0)), IF(OR(AA24="DSRC/Estratégico",AA24="DSRC/Operativo"),OFFSET('PARÁMETROS'!$K$11,MATCH(U24,JC_DS,0),MATCH(T24,CC_DS,0)), IF(AA24="SALUD",OFFSET('PARÁMETROS'!$K$29,MATCH(U24,JC_SA,0),MATCH(T24,CC_SA,0)), IF(AA24="MEDIO AMBIENTE",OFFSET('PARÁMETROS'!$K$20,MATCH(U24,JC_MA,0),MATCH(T24,CC_MA,0)), IF(AA24="Rel. Gubernamentales",OFFSET('PARÁMETROS'!$K$48,MATCH(U24,JC_G,0),MATCH(T24,CC_G,0)), IF(AA24="OPERACIONAL",OFFSET('PARÁMETROS'!$K$56,MATCH(U24,JC_OP,0),MATCH(T24,CC_OP,0)), IF(AA24="FINANCIERO",OFFSET('PARÁMETROS'!$K$56,MATCH(U24,JC_FI,0),MATCH(T24,CC_FI,0)), OFFSET('PARÁMETROS'!$K$38,MATCH(U24,JC_L,0),MATCH(T24,CC_L,0))))))))),"") -> Control/Acción Satisfactorio | Z24: OK | AA24: =E9 -> Seguridad
P25: Señales/ Advertencias/ Alarmas | Q25: Señalizar Áreas de trabajo, almacenaje de materiales y pasillos de circulación | R25: Publicación de Indicadores | S25: Seguimiento y publicación de reporte STOP o Seguimiento y publicación de reporte de observaciones conductuales | T25: A. Mayor 80% | U25: 3. Señalización/ Advertencias/ Alarma | V25: =IFERROR(IF(AA25="SEGURIDAD",OFFSET('PARÁMETROS'!$K$2,MATCH(U25,JC_SE,0),MATCH(T25,CC_SE,0)), IF(OR(AA25="DSRC/Estratégico",AA25="DSRC/Operativo"),OFFSET('PARÁMETROS'!$K$11,MATCH(U25,JC_DS,0),MATCH(T25,CC_DS,0)), IF(AA25="SALUD",OFFSET('PARÁMETROS'!$K$29,MATCH(U25,JC_SA,0),MATCH(T25,CC_SA,0)), IF(AA25="MEDIO AMBIENTE",OFFSET('PARÁMETROS'!$K$20,MATCH(U25,JC_MA,0),MATCH(T25,CC_MA,0)), IF(AA25="Rel. Gubernamentales",OFFSET('PARÁMETROS'!$K$48,MATCH(U25,JC_G,0),MATCH(T25,CC_G,0)), IF(AA25="OPERACIONAL",OFFSET('PARÁMETROS'!$K$56,MATCH(U25,JC_OP,0),MATCH(T25,CC_OP,0)), IF(AA25="FINANCIERO",OFFSET('PARÁMETROS'!$K$56,MATCH(U25,JC_FI,0),MATCH(T25,CC_FI,0)), OFFSET('PARÁMETROS'!$K$38,MATCH(U25,JC_L,0),MATCH(T25,CC_L,0))))))))),"") -> Control/Acción Eficaz | Z25: OK | AA25: =E9 -> Seguridad
P26: Procedimientos / Instructivos / Reglamentos y otros. | Q26: Implementar formularios ART/VPT según Guía para la Identificación y Evaluación de Riesgos 1.02.P06.I01 para realizar trabajo de Desmontaje y montaje de componentes del Chancador Primario (araña, cóncavos, eje principal) | R26: Planes / Programas | S26: Seguimiento al programa de inspecciones IRO´S: Trabajo en Altura | T26: B. 50% y 80% | U26: 2. Administrativo/ Procedimientos/ Capacitación | V26: =IFERROR(IF(AA26="SEGURIDAD",OFFSET('PARÁMETROS'!$K$2,MATCH(U26,JC_SE,0),MATCH(T26,CC_SE,0)), IF(OR(AA26="DSRC/Estratégico",AA26="DSRC/Operativo"),OFFSET('PARÁMETROS'!$K$11,MATCH(U26,JC_DS,0),MATCH(T26,CC_DS,0)), IF(AA26="SALUD",OFFSET('PARÁMETROS'!$K$29,MATCH(U26,JC_SA,0),MATCH(T26,CC_SA,0)), IF(AA26="MEDIO AMBIENTE",OFFSET('PARÁMETROS'!$K$20,MATCH(U26,JC_MA,0),MATCH(T26,CC_MA,0)), IF(AA26="Rel. Gubernamentales",OFFSET('PARÁMETROS'!$K$48,MATCH(U26,JC_G,0),MATCH(T26,CC_G,0)), IF(AA26="OPERACIONAL",OFFSET('PARÁMETROS'!$K$56,MATCH(U26,JC_OP,0),MATCH(T26,CC_OP,0)), IF(AA26="FINANCIERO",OFFSET('PARÁMETROS'!$K$56,MATCH(U26,JC_FI,0),MATCH(T26,CC_FI,0)), OFFSET('PARÁMETROS'!$K$38,MATCH(U26,JC_L,0),MATCH(T26,CC_L,0))))))))),"") -> Control/Acción Satisfactorio | Z26: Además de la documentación que se señala (ART/VPT), debe incluirse la obligatoriedad a contar con PT para Trabajo en Altura vigente | AA26: SE ADICIONA EL CUMPLIMIENTO AL INSTRUCTIVO DE ALTURA
A27: 3 | B27: Mantenimiento Chancador | C27: Desmontaje y montaje de componentes del Chancador Primario (araña, cóncavos, eje principal) | D27: Normal | E27: Seguridad | F27: Energía almacenada que puede liberarse repentinamente | G27: Falta de aislamiento o aislamiento incompleto de equipos de procesos a sufrir mantenimiento | H27: Liberación de energía peligrosa (hidráulica, neumática, eléctrica, radioactiva, etc.) | I27: Contacto con energía peligrosa, presión de agua, presión de aire, energía térmica, energía eléctrica | J27: 2 | K27: 2 | L27: =IF(OR(J27<>"",K27<>""),OFFSET('PARÁMETROS'!$B$2,K27,J27),"") -> 5 | M27: 5 | N27: =IFERROR(L27*M27,"") -> 25 | O27: =IF(N27="","",IFERROR(IF(N27<=2,"ACEPTABLE",IF(N27<=6,"BAJA",IF(N27<=10,"ACEPTABLE CON REVISIÓN",IF(N27<=15,"SUSTANCIAL","INACEPTABLE")))),"")) -> INACEPTABLE | P27: Capacitación/Entrenamiento | Q27: Capacitar al personal sobre los estándares del Instructivo de Aislamiento de equipos 1.02.P06.I24 | R27: Planes / Programas | S27: Seguimiento al programa de difusión de instructivos y capacitaciones internas | T27: C. Menor a 50% | U27: 2. Administrativo/ Procedimientos/ Capacitación | V27: =IFERROR(IF(AA27="SEGURIDAD",OFFSET('PARÁMETROS'!$K$2,MATCH(U27,JC_SE,0),MATCH(T27,CC_SE,0)), IF(OR(AA27="DSRC/Estratégico",AA27="DSRC/Operativo"),OFFSET('PARÁMETROS'!$K$11,MATCH(U27,JC_DS,0),MATCH(T27,CC_DS,0)), IF(AA27="SALUD",OFFSET('PARÁMETROS'!$K$29,MATCH(U27,JC_SA,0),MATCH(T27,CC_SA,0)), IF(AA27="MEDIO AMBIENTE",OFFSET('PARÁMETROS'!$K$20,MATCH(U27,JC_MA,0),MATCH(T27,CC_MA,0)), IF(AA27="Rel. Gubernamentales",OFFSET('PARÁMETROS'!$K$48,MATCH(U27,JC_G,0),MATCH(T27,CC_G,0)), IF(AA27="OPERACIONAL",OFFSET('PARÁMETROS'!$K$56,MATCH(U27,JC_OP,0),MATCH(T27,CC_OP,0)), IF(AA27="FINANCIERO",OFFSET('PARÁMETROS'!$K$56,MATCH(U27,JC_FI,0),MATCH(T27,CC_FI,0)), OFFSET('PARÁMETROS'!$K$38,MATCH(U27,JC_L,0),MATCH(T27,CC_L,0))))))))),"") -> Control/Acción No Eficaz | W27: =IF(E27="","", IF(COUNTA( V27:V39)-COUNTBLANK( V27:V39)=1, IF(O27="INACEPTABLE",IF(COUNTIF( V27:V39,"Control/Acción Eficaz")>=1,"SUSTANCIAL","INACEPTABLE"), IF(O27="SUSTANCIAL",IF(COUNTIF( V27:V39,"Control/Acción Eficaz")>=1,"ACEPTABLE CON REVISIÓN","SUSTANCIAL"), IF(O27="ACEPTABLE CON REVISIÓN",IF(COUNTIF( V27:V39,"Control/Acción Eficaz")>=1,"BAJA","ACEPTABLE CON REVISIÓN"), IF(O27="BAJA",IF(COUNTIF( V27:V39,"Control/Acción Eficaz")>=1,"ACEPTABLE","BAJA"),)))), IF(COUNTA( V27:V39)-COUNTBLANK( V27:V39)=2, IF(O27="INACEPTABLE",IF(COUNTIF( V27:V39,"Control/Acción Eficaz")=2,"ACEPTABLE CON REVISIÓN", IF(OR(AND(COUNTIF( V27:V39,"Control/Acción Eficaz")=1,COUNTIF( V27:V39,"Control/Acción Satisfactorio")=1), AND(COUNTIF( V27:V39,"Control/Acción Eficaz")=1,COUNTIF( V27:V39,"Control/Acción No Eficaz")=1)),"SUSTANCIAL","INACEPTABLE")), IF(O27="SUSTANCIAL",IF(COUNTIF( V27:V39,"Control/Acción Eficaz")=2,"BAJA", IF(OR(AND(COUNTIF( V27:V39,"Control/Acción Eficaz")=1,COUNTIF( V27:V39,"Control/Acción Satisfactorio")=1), AND(COUNTIF( V27:V39,"Control/Acción Eficaz")=1,COUNTIF( V27:V39,"Control/Acción No Eficaz")=1)),"ACEPTABLE CON REVISIÓN ","SUSTANCIAL")), IF(O27="ACEPTABLE CON REVISIÓN",IF(COUNTIF( V27:V39,"Control/Acción Eficaz")=2,"ACEPTABLE", IF(OR(AND(COUNTIF( V27:V39,"Control/Acción Eficaz")=1,COUNTIF( V27:V39,"Control/Acción Satisfactorio")=1), AND(COUNTIF( V27:V39,"Control/Acción Eficaz")=1,COUNTIF( V27:V39,"Control/Acción No Eficaz")=1)),"BAJA","ACEPTABLE CON REVISIÓN")), IF(O27="BAJA",IF(COUNTIF( V27:V39,"Control/Acción Eficaz")>=2,"ACEPTABLE","BAJA"),)))), IF(COUNTA( V27:V39)-COUNTBLANK( V27:V39)>=3, IF(O27="INACEPTABLE", IF(COUNTBLANK( V27:V39)=COUNTA( V27:V39),"", IF(COUNTIF( V27:V39,"Control/Acción No Eficaz")>=2,"INACEPTABLE", IF(AND(COUNTIF( V27:V39,"Control/Acción No Eficaz")=0,COUNTIF( V27:V39,"Control/Acción Eficaz")>=2),"ACEPTABLE CON REVISIÓN ","SUSTANCIAL"))), IF(O27="SUSTANCIAL", IF(COUNTBLANK( V27:V39)=COUNTA( V27:V39),"", IF(COUNTIF( V27:V39,"Control/Acción No Eficaz")>=2,"SUSTANCIAL", IF(AND(COUNTIF( V27:V39,"Control/Acción No Eficaz")=0,COUNTIF( V27:V39,"Control/Acción Eficaz")>=2),"BAJA","ACEPTABLE CON REVISIÓN"))), IF(O27="ACEPTABLE CON REVISIÓN", IF(COUNTBLANK( V27:V39)=COUNTA( V27:V39),"", IF(COUNTIF( V27:V39,"Control/Acción No Eficaz")>=2,"ACEPTABLE CON REVISIÓN", IF(AND(COUNTIF( V27:V39,"Control/Acción No Eficaz")=0,COUNTIF( V27:V39,"Control/Acción Eficaz")>=2),"ACEPTABLE","BAJA"))), IF(O27="BAJA", IF(COUNTBLANK( V27:V39)=COUNTA( V27:V39),"", IF(AND(COUNTBLANK( V27:V39)<1,COUNTA( V27:V39)=1), IF(COUNTIF( V27:V39,"Control/Acción No Eficaz")>=2,"BAJA", IF(AND(COUNTIF( V27:V39,"Control/Acción No Eficaz")=0,COUNTIF( V27:V39,"Control/Acción Eficaz")>=2),"ACEPTABLE","BAJA")), IF(COUNTIF( V27:V39,"Control/Acción No Eficaz")>=2,"BAJA", IF(AND(COUNTIF( V27:V39,"Control/Acción No Eficaz")=0,COUNTIF( V27:V39,"Control/Acción Eficaz")>=2),"ACEPTABLE","BAJA")))), IF(COUNTIF( V27:V39,"")>=5,"",O27))))), "")))) -> INACEPTABLE | Z27: OK | AA27: =E27 -> Seguridad
P28: Competencias | Q28: Contar con personal competente en Control de Energías (Bloqueo y Etiquetado) | R28: Planillas de vigencia de Certificaciones / Competencias/ Capacitaciones | S28: Seguimiento a la Planilla de vigencia de cursos, autorizaciones, competencias y/o certificaciones de personas y equipos | T28: A. Mayor 80% | U28: 2. Administrativo/ Procedimientos/ Capacitación | V28: =IFERROR(IF(AA28="SEGURIDAD",OFFSET('PARÁMETROS'!$K$2,MATCH(U28,JC_SE,0),MATCH(T28,CC_SE,0)), IF(OR(AA28="DSRC/Estratégico",AA28="DSRC/Operativo"),OFFSET('PARÁMETROS'!$K$11,MATCH(U28,JC_DS,0),MATCH(T28,CC_DS,0)), IF(AA28="SALUD",OFFSET('PARÁMETROS'!$K$29,MATCH(U28,JC_SA,0),MATCH(T28,CC_SA,0)), IF(AA28="MEDIO AMBIENTE",OFFSET('PARÁMETROS'!$K$20,MATCH(U28,JC_MA,0),MATCH(T28,CC_MA,0)), IF(AA28="Rel. Gubernamentales",OFFSET('PARÁMETROS'!$K$48,MATCH(U28,JC_G,0),MATCH(T28,CC_G,0)), IF(AA28="OPERACIONAL",OFFSET('PARÁMETROS'!$K$56,MATCH(U28,JC_OP,0),MATCH(T28,CC_OP,0)), IF(AA28="FINANCIERO",OFFSET('PARÁMETROS'!$K$56,MATCH(U28,JC_FI,0),MATCH(T28,CC_FI,0)), OFFSET('PARÁMETROS'!$K$38,MATCH(U28,JC_L,0),MATCH(T28,CC_L,0))))))))),"") -> Control/Acción Eficaz | Z28: OK | AA28: =E27 -> Seguridad
P29: Capacitación/Entrenamiento | Q29: Capacitar al personal sobre los estándares del Instructivo de Aislamiento de equipos 1.02.P06.I24 | R29: Planes / Programas | S29: Seguimiento al programa de difusión de instructivos y capacitaciones internas | T29: B. 50% y 80% | U29: 2. Administrativo/ Procedimientos/ Capacitación | V29: =IFERROR(IF(AA29="SEGURIDAD",OFFSET('PARÁMETROS'!$K$2,MATCH(U29,JC_SE,0),MATCH(T29,CC_SE,0)), IF(OR(AA29="DSRC/Estratégico",AA29="DSRC/Operativo"),OFFSET('PARÁMETROS'!$K$11,MATCH(U29,JC_DS,0),MATCH(T29,CC_DS,0)), IF(AA29="SALUD",OFFSET('PARÁMETROS'!$K$29,MATCH(U29,JC_SA,0),MATCH(T29,CC_SA,0)), IF(AA29="MEDIO AMBIENTE",OFFSET('PARÁMETROS'!$K$20,MATCH(U29,JC_MA,0),MATCH(T29,CC_MA,0)), IF(AA29="Rel. Gubernamentales",OFFSET('PARÁMETROS'!$K$48,MATCH(U29,JC_G,0),MATCH(T29,CC_G,0)), IF(AA29="OPERACIONAL",OFFSET('PARÁMETROS'!$K$56,MATCH(U29,JC_OP,0),MATCH(T29,CC_OP,0)), IF(AA29="FINANCIERO",OFFSET('PARÁMETROS'!$K$56,MATCH(U29,JC_FI,0),MATCH(T29,CC_FI,0)), OFFSET('PARÁMETROS'!$K$38,MATCH(U29,JC_L,0),MATCH(T29,CC_L,0))))))))),"") -> Control/Acción Satisfactorio | Z29: OK | AA29: =E27 -> Seguridad
P30: Señales/ Advertencias/ Alarmas | Q30: Señalizar área de trabajo al realizar el control de energía | R30: Publicación de Indicadores | S30: Seguimiento y publicación de reporte STOP o Seguimiento y publicación de reporte de observaciones conductuales | T30: B. 50% y 80% | U30: 3. Señalización/ Advertencias/ Alarma | V30: =IFERROR(IF(AA30="SEGURIDAD",OFFSET('PARÁMETROS'!$K$2,MATCH(U30,JC_SE,0),MATCH(T30,CC_SE,0)), IF(OR(AA30="DSRC/Estratégico",AA30="DSRC/Operativo"),OFFSET('PARÁMETROS'!$K$11,MATCH(U30,JC_DS,0),MATCH(T30,CC_DS,0)), IF(AA30="SALUD",OFFSET('PARÁMETROS'!$K$29,MATCH(U30,JC_SA,0),MATCH(T30,CC_SA,0)), IF(AA30="MEDIO AMBIENTE",OFFSET('PARÁMETROS'!$K$20,MATCH(U30,JC_MA,0),MATCH(T30,CC_MA,0)), IF(AA30="Rel. Gubernamentales",OFFSET('PARÁMETROS'!$K$48,MATCH(U30,JC_G,0),MATCH(T30,CC_G,0)), IF(AA30="OPERACIONAL",OFFSET('PARÁMETROS'!$K$56,MATCH(U30,JC_OP,0),MATCH(T30,CC_OP,0)), IF(AA30="FINANCIERO",OFFSET('PARÁMETROS'!$K$56,MATCH(U30,JC_FI,0),MATCH(T30,CC_FI,0)), OFFSET('PARÁMETROS'!$K$38,MATCH(U30,JC_L,0),MATCH(T30,CC_L,0))))))))),"") -> Control/Acción Satisfactorio | Z30: OK | AA30: =E27 -> Seguridad
P31: Capacitación/Entrenamiento | Q31: Contar con el curso de Inducción General OHS (2.04.P05.E20 Inducción Plan de Emergencia ) | R31: Planillas de vigencia de Certificaciones / Competencias/ Capacitaciones | S31: Seguimiento a la Planilla de vigencia de cursos, autorizaciones, competencias y/o certificaciones de personas y equipos | T31: A. Mayor 80% | U31: 2. Administrativo/ Procedimientos/ Capacitación | V31: =IFERROR(IF(AA31="SEGURIDAD",OFFSET('PARÁMETROS'!$K$2,MATCH(U31,JC_SE,0),MATCH(T31,CC_SE,0)), IF(OR(AA31="DSRC/Estratégico",AA31="DSRC/Operativo"),OFFSET('PARÁMETROS'!$K$11,MATCH(U31,JC_DS,0),MATCH(T31,CC_DS,0)), IF(AA31="SALUD",OFFSET('PARÁMETROS'!$K$29,MATCH(U31,JC_SA,0),MATCH(T31,CC_SA,0)), IF(AA31="MEDIO AMBIENTE",OFFSET('PARÁMETROS'!$K$20,MATCH(U31,JC_MA,0),MATCH(T31,CC_MA,0)), IF(AA31="Rel. Gubernamentales",OFFSET('PARÁMETROS'!$K$48,MATCH(U31,JC_G,0),MATCH(T31,CC_G,0)), IF(AA31="OPERACIONAL",OFFSET('PARÁMETROS'!$K$56,MATCH(U31,JC_OP,0),MATCH(T31,CC_OP,0)), IF(AA31="FINANCIERO",OFFSET('PARÁMETROS'!$K$56,MATCH(U31,JC_FI,0),MATCH(T31,CC_FI,0)), OFFSET('PARÁMETROS'!$K$38,MATCH(U31,JC_L,0),MATCH(T31,CC_L,0))))))))),"") -> Control/Acción Eficaz | Z31: OK | AA31: =E27 -> Seguridad
P32: Capacitación/Entrenamiento | Q32: Capacitar al personal sobre respuesta ante emergencias descrito del Plan de Emergencia 2.04.P05.E20 | R32: Planes / Programas | S32: Seguimiento al programa de difusión de instructivos y capacitaciones internas | T32: B. 50% y 80% | U32: 2. Administrativo/ Procedimientos/ Capacitación | V32: =IFERROR(IF(AA32="SEGURIDAD",OFFSET('PARÁMETROS'!$K$2,MATCH(U32,JC_SE,0),MATCH(T32,CC_SE,0)), IF(OR(AA32="DSRC/Estratégico",AA32="DSRC/Operativo"),OFFSET('PARÁMETROS'!$K$11,MATCH(U32,JC_DS,0),MATCH(T32,CC_DS,0)), IF(AA32="SALUD",OFFSET('PARÁMETROS'!$K$29,MATCH(U32,JC_SA,0),MATCH(T32,CC_SA,0)), IF(AA32="MEDIO AMBIENTE",OFFSET('PARÁMETROS'!$K$20,MATCH(U32,JC_MA,0),MATCH(T32,CC_MA,0)), IF(AA32="Rel. Gubernamentales",OFFSET('PARÁMETROS'!$K$48,MATCH(U32,JC_G,0),MATCH(T32,CC_G,0)), IF(AA32="OPERACIONAL",OFFSET('PARÁMETROS'!$K$56,MATCH(U32,JC_OP,0),MATCH(T32,CC_OP,0)), IF(AA32="FINANCIERO",OFFSET('PARÁMETROS'!$K$56,MATCH(U32,JC_FI,0),MATCH(T32,CC_FI,0)), OFFSET('PARÁMETROS'!$K$38,MATCH(U32,JC_L,0),MATCH(T32,CC_L,0))))))))),"") -> Control/Acción Satisfactorio | Z32: OK | AA32: =E27 -> Seguridad
P33: Controles/Acciones de Emergencias | Q33: Difundir la ruta de evacuación para caso de emergencia, punto de reunión y protocolo de emergencia | R33: Planes / Programas | S33: Seguimiento al programa de reuniones y evaluaciones de compromiso con la seguridad | T33: B. 50% y 80% | U33: 2. Administrativo/ Procedimientos/ Capacitación | V33: =IFERROR(IF(AA33="SEGURIDAD",OFFSET('PARÁMETROS'!$K$2,MATCH(U33,JC_SE,0),MATCH(T33,CC_SE,0)), IF(OR(AA33="DSRC/Estratégico",AA33="DSRC/Operativo"),OFFSET('PARÁMETROS'!$K$11,MATCH(U33,JC_DS,0),MATCH(T33,CC_DS,0)), IF(AA33="SALUD",OFFSET('PARÁMETROS'!$K$29,MATCH(U33,JC_SA,0),MATCH(T33,CC_SA,0)), IF(AA33="MEDIO AMBIENTE",OFFSET('PARÁMETROS'!$K$20,MATCH(U33,JC_MA,0),MATCH(T33,CC_MA,0)), IF(AA33="Rel. Gubernamentales",OFFSET('PARÁMETROS'!$K$48,MATCH(U33,JC_G,0),MATCH(T33,CC_G,0)), IF(AA33="OPERACIONAL",OFFSET('PARÁMETROS'!$K$56,MATCH(U33,JC_OP,0),MATCH(T33,CC_OP,0)), IF(AA33="FINANCIERO",OFFSET('PARÁMETROS'!$K$56,MATCH(U33,JC_FI,0),MATCH(T33,CC_FI,0)), OFFSET('PARÁMETROS'!$K$38,MATCH(U33,JC_L,0),MATCH(T33,CC_L,0))))))))),"") -> Control/Acción Satisfactorio | Z33: OK | AA33: =E27 -> Seguridad
P34: E.P.P. | Q34: Usar EPP básico y adicional (Casco, botines de Seguridad, Lentes), guantes y carrilera de casco | R34: Publicación de Indicadores | S34: Seguimiento y publicación de reporte STOP o Seguimiento y publicación de reporte de observaciones conductuales | T34: B. 50% y 80% | U34: 1. EPP | V34: =IFERROR(IF(AA34="SEGURIDAD",OFFSET('PARÁMETROS'!$K$2,MATCH(U34,JC_SE,0),MATCH(T34,CC_SE,0)), IF(OR(AA34="DSRC/Estratégico",AA34="DSRC/Operativo"),OFFSET('PARÁMETROS'!$K$11,MATCH(U34,JC_DS,0),MATCH(T34,CC_DS,0)), IF(AA34="SALUD",OFFSET('PARÁMETROS'!$K$29,MATCH(U34,JC_SA,0),MATCH(T34,CC_SA,0)), IF(AA34="MEDIO AMBIENTE",OFFSET('PARÁMETROS'!$K$20,MATCH(U34,JC_MA,0),MATCH(T34,CC_MA,0)), IF(AA34="Rel. Gubernamentales",OFFSET('PARÁMETROS'!$K$48,MATCH(U34,JC_G,0),MATCH(T34,CC_G,0)), IF(AA34="OPERACIONAL",OFFSET('PARÁMETROS'!$K$56,MATCH(U34,JC_OP,0),MATCH(T34,CC_OP,0)), IF(AA34="FINANCIERO",OFFSET('PARÁMETROS'!$K$56,MATCH(U34,JC_FI,0),MATCH(T34,CC_FI,0)), OFFSET('PARÁMETROS'!$K$38,MATCH(U34,JC_L,0),MATCH(T34,CC_L,0))))))))),"") -> Control/Acción No Eficaz | Z34: OK | AA34: =E27 -> Seguridad
P35: Capacitación/Entrenamiento | Q35: Difundir Hoja ZAP SI-050 "Pasos para aislamiento con candados personales" | R35: Planillas de vigencia de Certificaciones / Competencias/ Capacitaciones | S35: Seguimiento al programa de reuniones y evaluaciones de compromiso con la seguridad | T35: A. Mayor 80% | U35: 2. Administrativo/ Procedimientos/ Capacitación | V35: =IFERROR(IF(AA35="SEGURIDAD",OFFSET('PARÁMETROS'!$K$2,MATCH(U35,JC_SE,0),MATCH(T35,CC_SE,0)), IF(OR(AA35="DSRC/Estratégico",AA35="DSRC/Operativo"),OFFSET('PARÁMETROS'!$K$11,MATCH(U35,JC_DS,0),MATCH(T35,CC_DS,0)), IF(AA35="SALUD",OFFSET('PARÁMETROS'!$K$29,MATCH(U35,JC_SA,0),MATCH(T35,CC_SA,0)), IF(AA35="MEDIO AMBIENTE",OFFSET('PARÁMETROS'!$K$20,MATCH(U35,JC_MA,0),MATCH(T35,CC_MA,0)), IF(AA35="Rel. Gubernamentales",OFFSET('PARÁMETROS'!$K$48,MATCH(U35,JC_G,0),MATCH(T35,CC_G,0)), IF(AA35="OPERACIONAL",OFFSET('PARÁMETROS'!$K$56,MATCH(U35,JC_OP,0),MATCH(T35,CC_OP,0)), IF(AA35="FINANCIERO",OFFSET('PARÁMETROS'!$K$56,MATCH(U35,JC_FI,0),MATCH(T35,CC_FI,0)), OFFSET('PARÁMETROS'!$K$38,MATCH(U35,JC_L,0),MATCH(T35,CC_L,0))))))))),"") -> Control/Acción Eficaz | Z35: OK | AA35: =E27 -> Seguridad
P36: Capacitación/Entrenamiento | Q36: Difundir Hoja ZAP SI-051 "Candado personal de aislamiento y tarjeta de peligro" | R36: Planillas de vigencia de Certificaciones / Competencias/ Capacitaciones | S36: Seguimiento al programa de reuniones y evaluaciones de compromiso con la seguridad | T36: A. Mayor 80% | U36: 2. Administrativo/ Procedimientos/ Capacitación | V36: =IFERROR(IF(AA36="SEGURIDAD",OFFSET('PARÁMETROS'!$K$2,MATCH(U36,JC_SE,0),MATCH(T36,CC_SE,0)), IF(OR(AA36="DSRC/Estratégico",AA36="DSRC/Operativo"),OFFSET('PARÁMETROS'!$K$11,MATCH(U36,JC_DS,0),MATCH(T36,CC_DS,0)), IF(AA36="SALUD",OFFSET('PARÁMETROS'!$K$29,MATCH(U36,JC_SA,0),MATCH(T36,CC_SA,0)), IF(AA36="MEDIO AMBIENTE",OFFSET('PARÁMETROS'!$K$20,MATCH(U36,JC_MA,0),MATCH(T36,CC_MA,0)), IF(AA36="Rel. Gubernamentales",OFFSET('PARÁMETROS'!$K$48,MATCH(U36,JC_G,0),MATCH(T36,CC_G,0)), IF(AA36="OPERACIONAL",OFFSET('PARÁMETROS'!$K$56,MATCH(U36,JC_OP,0),MATCH(T36,CC_OP,0)), IF(AA36="FINANCIERO",OFFSET('PARÁMETROS'!$K$56,MATCH(U36,JC_FI,0),MATCH(T36,CC_FI,0)), OFFSET('PARÁMETROS'!$K$38,MATCH(U36,JC_L,0),MATCH(T36,CC_L,0))))))))),"") -> Control/Acción Eficaz | Z36: OK
P37: Controles de Ingeniería | Q37: Contar con dispositivos de bloqueos físicos de energías almacenadas | R37: Publicación de Indicadores | S37: Seguimiento y publicación de reporte STOP o Seguimiento y publicación de reporte de observaciones conductuales | T37: B. 50% y 80% | U37: 4. Ingeniería | V37: =IFERROR(IF(AA37="SEGURIDAD",OFFSET('PARÁMETROS'!$K$2,MATCH(U37,JC_SE,0),MATCH(T37,CC_SE,0)), IF(OR(AA37="DSRC/Estratégico",AA37="DSRC/Operativo"),OFFSET('PARÁMETROS'!$K$11,MATCH(U37,JC_DS,0),MATCH(T37,CC_DS,0)), IF(AA37="SALUD",OFFSET('PARÁMETROS'!$K$29,MATCH(U37,JC_SA,0),MATCH(T37,CC_SA,0)), IF(AA37="MEDIO AMBIENTE",OFFSET('PARÁMETROS'!$K$20,MATCH(U37,JC_MA,0),MATCH(T37,CC_MA,0)), IF(AA37="Rel. Gubernamentales",OFFSET('PARÁMETROS'!$K$48,MATCH(U37,JC_G,0),MATCH(T37,CC_G,0)), IF(AA37="OPERACIONAL",OFFSET('PARÁMETROS'!$K$56,MATCH(U37,JC_OP,0),MATCH(T37,CC_OP,0)), IF(AA37="FINANCIERO",OFFSET('PARÁMETROS'!$K$56,MATCH(U37,JC_FI,0),MATCH(T37,CC_FI,0)), OFFSET('PARÁMETROS'!$K$38,MATCH(U37,JC_L,0),MATCH(T37,CC_L,0))))))))),"") -> Control/Acción Satisfactorio | Z37: OK | AA37: =E27 -> Seguridad
P38: Competencias | Q38: Contar con personal competente en Control de Energías (Bloqueo y Etiquetado) | R38: Planillas de vigencia de Certificaciones / Competencias/ Capacitaciones | S38: Seguimiento a la Planilla de vigencia de cursos, autorizaciones, competencias y/o certificaciones de personas y equipos | T38: A. Mayor 80% | U38: 2. Administrativo/ Procedimientos/ Capacitación | V38: =IFERROR(IF(AA38="SEGURIDAD",OFFSET('PARÁMETROS'!$K$2,MATCH(U38,JC_SE,0),MATCH(T38,CC_SE,0)), IF(OR(AA38="DSRC/Estratégico",AA38="DSRC/Operativo"),OFFSET('PARÁMETROS'!$K$11,MATCH(U38,JC_DS,0),MATCH(T38,CC_DS,0)), IF(AA38="SALUD",OFFSET('PARÁMETROS'!$K$29,MATCH(U38,JC_SA,0),MATCH(T38,CC_SA,0)), IF(AA38="MEDIO AMBIENTE",OFFSET('PARÁMETROS'!$K$20,MATCH(U38,JC_MA,0),MATCH(T38,CC_MA,0)), IF(AA38="Rel. Gubernamentales",OFFSET('PARÁMETROS'!$K$48,MATCH(U38,JC_G,0),MATCH(T38,CC_G,0)), IF(AA38="OPERACIONAL",OFFSET('PARÁMETROS'!$K$56,MATCH(U38,JC_OP,0),MATCH(T38,CC_OP,0)), IF(AA38="FINANCIERO",OFFSET('PARÁMETROS'!$K$56,MATCH(U38,JC_FI,0),MATCH(T38,CC_FI,0)), OFFSET('PARÁMETROS'!$K$38,MATCH(U38,JC_L,0),MATCH(T38,CC_L,0))))))))),"") -> Control/Acción Eficaz | Z38: OK | AA38: =E27 -> Seguridad
P39: Procedimientos / Instructivos / Reglamentos y otros. | Q39: Implementar formularios ART/VPT según Guía para la Identificación y Evaluación de Riesgos 1.02.P06.I01 para realizar trabajo de Desmontaje y montaje de componentes del Chancador Primario (araña, cóncavos, eje principal) | R39: Publicación de Indicadores | S39: Seguimiento y publicación de reporte STOP o Seguimiento y publicación de reporte de observaciones conductuales | T39: B. 50% y 80% | U39: 2. Administrativo/ Procedimientos/ Capacitación | V39: =IFERROR(IF(AA39="SEGURIDAD",OFFSET('PARÁMETROS'!$K$2,MATCH(U39,JC_SE,0),MATCH(T39,CC_SE,0)), IF(OR(AA39="DSRC/Estratégico",AA39="DSRC/Operativo"),OFFSET('PARÁMETROS'!$K$11,MATCH(U39,JC_DS,0),MATCH(T39,CC_DS,0)), IF(AA39="SALUD",OFFSET('PARÁMETROS'!$K$29,MATCH(U39,JC_SA,0),MATCH(T39,CC_SA,0)), IF(AA39="MEDIO AMBIENTE",OFFSET('PARÁMETROS'!$K$20,MATCH(U39,JC_MA,0),MATCH(T39,CC_MA,0)), IF(AA39="Rel. Gubernamentales",OFFSET('PARÁMETROS'!$K$48,MATCH(U39,JC_G,0),MATCH(T39,CC_G,0)), IF(AA39="OPERACIONAL",OFFSET('PARÁMETROS'!$K$56,MATCH(U39,JC_OP,0),MATCH(T39,CC_OP,0)), IF(AA39="FINANCIERO",OFFSET('PARÁMETROS'!$K$56,MATCH(U39,JC_FI,0),MATCH(T39,CC_FI,0)), OFFSET('PARÁMETROS'!$K$38,MATCH(U39,JC_L,0),MATCH(T39,CC_L,0))))))))),"") -> Control/Acción Satisfactorio | Z39: OK | AA39: =E27 -> Seguridad
A40: 4 | B40: Mantenimiento Chancador | C40: Desmontaje y montaje de componentes del Chancador Primario (araña, cóncavos, eje principal) | D40: Normal | E40: Seguridad | F40: Manipulación/uso de herramientas, instrumentos, objetos (cortantes, punzantes, calientes, pesados, sin Verificación / Calibración, etc.) | G40: Manipulación de herramientas manuales, herramientas defectuosas o inadecuadas (combos, llaves, palas) | H40: Golpeado por | I40: Golpes en las manos y pies por uso de herramienta defectuosa, zafe de llaves, u otros | J40: 3 | K40: 3 | L40: =IF(OR(J40<>"",K40<>""),OFFSET('PARÁMETROS'!$B$2,K40,J40),"") -> 4 | M40: 3 | N40: =IFERROR(L40*M40,"") -> 12 | O40: =IF(N40="","",IFERROR(IF(N40<=2,"ACEPTABLE",IF(N40<=6,"BAJA",IF(N40<=10,"ACEPTABLE CON REVISIÓN",IF(N40<=15,"SUSTANCIAL","INACEPTABLE")))),"")) -> SUSTANCIAL | P40: Capacitación/Entrenamiento | Q40: Capacitar al personal los estándares del Instructivo de Manipulación Manual de Cargas 1.02.P06.I14 | R40: Planes / Programas | S40: Seguimiento al programa de difusión de instructivos y capacitaciones internas | T40: B. 50% y 80% | U40: 2. Administrativo/ Procedimientos/ Capacitación | V40: =IFERROR(IF(AA40="SEGURIDAD",OFFSET('PARÁMETROS'!$K$2,MATCH(U40,JC_SE,0),MATCH(T40,CC_SE,0)), IF(OR(AA40="DSRC/Estratégico",AA40="DSRC/Operativo"),OFFSET('PARÁMETROS'!$K$11,MATCH(U40,JC_DS,0),MATCH(T40,CC_DS,0)), IF(AA40="SALUD",OFFSET('PARÁMETROS'!$K$29,MATCH(U40,JC_SA,0),MATCH(T40,CC_SA,0)), IF(AA40="MEDIO AMBIENTE",OFFSET('PARÁMETROS'!$K$20,MATCH(U40,JC_MA,0),MATCH(T40,CC_MA,0)), IF(AA40="Rel. Gubernamentales",OFFSET('PARÁMETROS'!$K$48,MATCH(U40,JC_G,0),MATCH(T40,CC_G,0)), IF(AA40="OPERACIONAL",OFFSET('PARÁMETROS'!$K$56,MATCH(U40,JC_OP,0),MATCH(T40,CC_OP,0)), IF(AA40="FINANCIERO",OFFSET('PARÁMETROS'!$K$56,MATCH(U40,JC_FI,0),MATCH(T40,CC_FI,0)), OFFSET('PARÁMETROS'!$K$38,MATCH(U40,JC_L,0),MATCH(T40,CC_L,0))))))))),"") -> Control/Acción Satisfactorio | W40: =IF(E40="","", IF(COUNTA( V40:V50)-COUNTBLANK( V40:V50)=1, IF(O40="INACEPTABLE",IF(COUNTIF( V40:V50,"Control/Acción Eficaz")>=1,"SUSTANCIAL","INACEPTABLE"), IF(O40="SUSTANCIAL",IF(COUNTIF( V40:V50,"Control/Acción Eficaz")>=1,"ACEPTABLE CON REVISIÓN","SUSTANCIAL"), IF(O40="ACEPTABLE CON REVISIÓN",IF(COUNTIF( V40:V50,"Control/Acción Eficaz")>=1,"BAJA","ACEPTABLE CON REVISIÓN"), IF(O40="BAJA",IF(COUNTIF( V40:V50,"Control/Acción Eficaz")>=1,"ACEPTABLE","BAJA"),)))), IF(COUNTA( V40:V50)-COUNTBLANK( V40:V50)=2, IF(O40="INACEPTABLE",IF(COUNTIF( V40:V50,"Control/Acción Eficaz")=2,"ACEPTABLE CON REVISIÓN", IF(OR(AND(COUNTIF( V40:V50,"Control/Acción Eficaz")=1,COUNTIF( V40:V50,"Control/Acción Satisfactorio")=1), AND(COUNTIF( V40:V50,"Control/Acción Eficaz")=1,COUNTIF( V40:V50,"Control/Acción No Eficaz")=1)),"SUSTANCIAL","INACEPTABLE")), IF(O40="SUSTANCIAL",IF(COUNTIF( V40:V50,"Control/Acción Eficaz")=2,"BAJA", IF(OR(AND(COUNTIF( V40:V50,"Control/Acción Eficaz")=1,COUNTIF( V40:V50,"Control/Acción Satisfactorio")=1), AND(COUNTIF( V40:V50,"Control/Acción Eficaz")=1,COUNTIF( V40:V50,"Control/Acción No Eficaz")=1)),"ACEPTABLE CON REVISIÓN ","SUSTANCIAL")), IF(O40="ACEPTABLE CON REVISIÓN",IF(COUNTIF( V40:V50,"Control/Acción Eficaz")=2,"ACEPTABLE", IF(OR(AND(COUNTIF( V40:V50,"Control/Acción Eficaz")=1,COUNTIF( V40:V50,"Control/Acción Satisfactorio")=1), AND(COUNTIF( V40:V50,"Control/Acción Eficaz")=1,COUNTIF( V40:V50,"Control/Acción No Eficaz")=1)),"BAJA","ACEPTABLE CON REVISIÓN")), IF(O40="BAJA",IF(COUNTIF( V40:V50,"Control/Acción Eficaz")>=2,"ACEPTABLE","BAJA"),)))), IF(COUNTA( V40:V50)-COUNTBLANK( V40:V50)>=3, IF(O40="INACEPTABLE", IF(COUNTBLANK( V40:V50)=COUNTA( V40:V50),"", IF(COUNTIF( V40:V50,"Control/Acción No Eficaz")>=2,"INACEPTABLE", IF(AND(COUNTIF( V40:V50,"Control/Acción No Eficaz")=0,COUNTIF( V40:V50,"Control/Acción Eficaz")>=2),"ACEPTABLE CON REVISIÓN ","SUSTANCIAL"))), IF(O40="SUSTANCIAL", IF(COUNTBLANK( V40:V50)=COUNTA( V40:V50),"", IF(COUNTIF( V40:V50,"Control/Acción No Eficaz")>=2,"SUSTANCIAL", IF(AND(COUNTIF( V40:V50,"Control/Acción No Eficaz")=0,COUNTIF( V40:V50,"Control/Acción Eficaz")>=2),"BAJA","ACEPTABLE CON REVISIÓN"))), IF(O40="ACEPTABLE CON REVISIÓN", IF(COUNTBLANK( V40:V50)=COUNTA( V40:V50),"", IF(COUNTIF( V40:V50,"Control/Acción No Eficaz")>=2,"ACEPTABLE CON REVISIÓN", IF(AND(COUNTIF( V40:V50,"Control/Acción No Eficaz")=0,COUNTIF( V40:V50,"Control/Acción Eficaz")>=2),"ACEPTABLE","BAJA"))), IF(O40="BAJA", IF(COUNTBLANK( V40:V50)=COUNTA( V40:V50),"", IF(AND(COUNTBLANK( V40:V50)<1,COUNTA( V40:V50)=1), IF(COUNTIF( V40:V50,"Control/Acción No Eficaz")>=2,"BAJA", IF(AND(COUNTIF( V40:V50,"Control/Acción No Eficaz")=0,COUNTIF( V40:V50,"Control/Acción Eficaz")>=2),"ACEPTABLE","BAJA")), IF(COUNTIF( V40:V50,"Control/Acción No Eficaz")>=2,"BAJA", IF(AND(COUNTIF( V40:V50,"Control/Acción No Eficaz")=0,COUNTIF( V40:V50,"Control/Acción Eficaz")>=2),"ACEPTABLE","BAJA")))), IF(COUNTIF( V40:V50,"")>=5,"",O40))))), "")))) -> ACEPTABLE CON REVISIÓN | Z40: OK | AA40: =E40 -> Seguridad
P41: Capacitación/Entrenamiento | Q41: Contar con personal capacitado en el curso vigente en Gestión de Riesgos (ART/VPT) | R41: Planillas de vigencia de Certificaciones / Competencias/ Capacitaciones | S41: Seguimiento a la Planilla de vigencia de cursos, autorizaciones, competencias y/o certificaciones de personas y equipos | T41: B. 50% y 80% | U41: 2. Administrativo/ Procedimientos/ Capacitación | V41: =IFERROR(IF(AA41="SEGURIDAD",OFFSET('PARÁMETROS'!$K$2,MATCH(U41,JC_SE,0),MATCH(T41,CC_SE,0)), IF(OR(AA41="DSRC/Estratégico",AA41="DSRC/Operativo"),OFFSET('PARÁMETROS'!$K$11,MATCH(U41,JC_DS,0),MATCH(T41,CC_DS,0)), IF(AA41="SALUD",OFFSET('PARÁMETROS'!$K$29,MATCH(U41,JC_SA,0),MATCH(T41,CC_SA,0)), IF(AA41="MEDIO AMBIENTE",OFFSET('PARÁMETROS'!$K$20,MATCH(U41,JC_MA,0),MATCH(T41,CC_MA,0)), IF(AA41="Rel. Gubernamentales",OFFSET('PARÁMETROS'!$K$48,MATCH(U41,JC_G,0),MATCH(T41,CC_G,0)), IF(AA41="OPERACIONAL",OFFSET('PARÁMETROS'!$K$56,MATCH(U41,JC_OP,0),MATCH(T41,CC_OP,0)), IF(AA41="FINANCIERO",OFFSET('PARÁMETROS'!$K$56,MATCH(U41,JC_FI,0),MATCH(T41,CC_FI,0)), OFFSET('PARÁMETROS'!$K$38,MATCH(U41,JC_L,0),MATCH(T41,CC_L,0))))))))),"") -> Control/Acción Satisfactorio | Z41: OK | AA41: =E40 -> Seguridad
P42: Capacitación/Entrenamiento | Q42: Difundir hoja ZAP SI-084 "Levantamiento manual de cargas" | R42: Planes / Programas | S42: Seguimiento al programa de reuniones y evaluaciones de compromiso con la seguridad | T42: B. 50% y 80% | U42: 2. Administrativo/ Procedimientos/ Capacitación | V42: =IFERROR(IF(AA42="SEGURIDAD",OFFSET('PARÁMETROS'!$K$2,MATCH(U42,JC_SE,0),MATCH(T42,CC_SE,0)), IF(OR(AA42="DSRC/Estratégico",AA42="DSRC/Operativo"),OFFSET('PARÁMETROS'!$K$11,MATCH(U42,JC_DS,0),MATCH(T42,CC_DS,0)), IF(AA42="SALUD",OFFSET('PARÁMETROS'!$K$29,MATCH(U42,JC_SA,0),MATCH(T42,CC_SA,0)), IF(AA42="MEDIO AMBIENTE",OFFSET('PARÁMETROS'!$K$20,MATCH(U42,JC_MA,0),MATCH(T42,CC_MA,0)), IF(AA42="Rel. Gubernamentales",OFFSET('PARÁMETROS'!$K$48,MATCH(U42,JC_G,0),MATCH(T42,CC_G,0)), IF(AA42="OPERACIONAL",OFFSET('PARÁMETROS'!$K$56,MATCH(U42,JC_OP,0),MATCH(T42,CC_OP,0)), IF(AA42="FINANCIERO",OFFSET('PARÁMETROS'!$K$56,MATCH(U42,JC_FI,0),MATCH(T42,CC_FI,0)), OFFSET('PARÁMETROS'!$K$38,MATCH(U42,JC_L,0),MATCH(T42,CC_L,0))))))))),"") -> Control/Acción Satisfactorio | Z42: OK | AA42: =E40 -> Seguridad
P43: Señales/ Advertencias/ Alarmas | Q43: Señalizar áreas de trabajo, almacenaje de materiales y pasillos de circulación con cinta de color amarillo/rojo | R43: Planes / Programas | S43: Seguimiento al programa de inspecciones ISOP | T43: B. 50% y 80% | U43: 3. Señalización/ Advertencias/ Alarma | V43: =IFERROR(IF(AA43="SEGURIDAD",OFFSET('PARÁMETROS'!$K$2,MATCH(U43,JC_SE,0),MATCH(T43,CC_SE,0)), IF(OR(AA43="DSRC/Estratégico",AA43="DSRC/Operativo"),OFFSET('PARÁMETROS'!$K$11,MATCH(U43,JC_DS,0),MATCH(T43,CC_DS,0)), IF(AA43="SALUD",OFFSET('PARÁMETROS'!$K$29,MATCH(U43,JC_SA,0),MATCH(T43,CC_SA,0)), IF(AA43="MEDIO AMBIENTE",OFFSET('PARÁMETROS'!$K$20,MATCH(U43,JC_MA,0),MATCH(T43,CC_MA,0)), IF(AA43="Rel. Gubernamentales",OFFSET('PARÁMETROS'!$K$48,MATCH(U43,JC_G,0),MATCH(T43,CC_G,0)), IF(AA43="OPERACIONAL",OFFSET('PARÁMETROS'!$K$56,MATCH(U43,JC_OP,0),MATCH(T43,CC_OP,0)), IF(AA43="FINANCIERO",OFFSET('PARÁMETROS'!$K$56,MATCH(U43,JC_FI,0),MATCH(T43,CC_FI,0)), OFFSET('PARÁMETROS'!$K$38,MATCH(U43,JC_L,0),MATCH(T43,CC_L,0))))))))),"") -> Control/Acción Satisfactorio | Z43: OK | AA43: =E40 -> Seguridad
P44: Capacitación/Entrenamiento | Q44: Capacitar al personal sobre los estándares del Manual de Reglas de Oro, Trabajo de Izaje 1.02.P06.MT02. | R44: Planes / Programas | S44: Seguimiento al programa de difusión de instructivos y capacitaciones internas | T44: B. 50% y 80% | U44: 2. Administrativo/ Procedimientos/ Capacitación | V44: =IFERROR(IF(AA44="SEGURIDAD",OFFSET('PARÁMETROS'!$K$2,MATCH(U44,JC_SE,0),MATCH(T44,CC_SE,0)), IF(OR(AA44="DSRC/Estratégico",AA44="DSRC/Operativo"),OFFSET('PARÁMETROS'!$K$11,MATCH(U44,JC_DS,0),MATCH(T44,CC_DS,0)), IF(AA44="SALUD",OFFSET('PARÁMETROS'!$K$29,MATCH(U44,JC_SA,0),MATCH(T44,CC_SA,0)), IF(AA44="MEDIO AMBIENTE",OFFSET('PARÁMETROS'!$K$20,MATCH(U44,JC_MA,0),MATCH(T44,CC_MA,0)), IF(AA44="Rel. Gubernamentales",OFFSET('PARÁMETROS'!$K$48,MATCH(U44,JC_G,0),MATCH(T44,CC_G,0)), IF(AA44="OPERACIONAL",OFFSET('PARÁMETROS'!$K$56,MATCH(U44,JC_OP,0),MATCH(T44,CC_OP,0)), IF(AA44="FINANCIERO",OFFSET('PARÁMETROS'!$K$56,MATCH(U44,JC_FI,0),MATCH(T44,CC_FI,0)), OFFSET('PARÁMETROS'!$K$38,MATCH(U44,JC_L,0),MATCH(T44,CC_L,0))))))))),"") -> Control/Acción Satisfactorio | Z44: OK | AA44: =E40 -> Seguridad
P45: Inspecciones | Q45: Inspección Pre-Uso de Elementos Accesorios de Izaje - Eslingas, Estrobos, Grilletes y Ganchos Colocar la cinta del color del mes que corresponda de acuerdo al instructivo de Codificación de Colores para Inspección 1.02.P06.I33 | R45: Planes / Programas | S45: Seguimiento al programa de inspecciones IRO´S: Izaje | T45: B. 50% y 80% | U45: 2. Administrativo/ Procedimientos/ Capacitación | V45: =IFERROR(IF(AA45="SEGURIDAD",OFFSET('PARÁMETROS'!$K$2,MATCH(U45,JC_SE,0),MATCH(T45,CC_SE,0)), IF(OR(AA45="DSRC/Estratégico",AA45="DSRC/Operativo"),OFFSET('PARÁMETROS'!$K$11,MATCH(U45,JC_DS,0),MATCH(T45,CC_DS,0)), IF(AA45="SALUD",OFFSET('PARÁMETROS'!$K$29,MATCH(U45,JC_SA,0),MATCH(T45,CC_SA,0)), IF(AA45="MEDIO AMBIENTE",OFFSET('PARÁMETROS'!$K$20,MATCH(U45,JC_MA,0),MATCH(T45,CC_MA,0)), IF(AA45="Rel. Gubernamentales",OFFSET('PARÁMETROS'!$K$48,MATCH(U45,JC_G,0),MATCH(T45,CC_G,0)), IF(AA45="OPERACIONAL",OFFSET('PARÁMETROS'!$K$56,MATCH(U45,JC_OP,0),MATCH(T45,CC_OP,0)), IF(AA45="FINANCIERO",OFFSET('PARÁMETROS'!$K$56,MATCH(U45,JC_FI,0),MATCH(T45,CC_FI,0)), OFFSET('PARÁMETROS'!$K$38,MATCH(U45,JC_L,0),MATCH(T45,CC_L,0))))))))),"") -> Control/Acción Satisfactorio | Z45: OK | AA45: =E40 -> Seguridad
P46: Instrucción Operacional | Q46: Inspeccionar las herramientas que NO tengan formulario de inspección con las cintas de color establecidas en el instructivo 1.02.P06.F20 Codificación de Colores para Inspección | R46: Planes / Programas | S46: Seguimiento al programa de inspecciones ISOP | T46: B. 50% y 80% | U46: 2. Administrativo/ Procedimientos/ Capacitación | V46: =IFERROR(IF(AA46="SEGURIDAD",OFFSET('PARÁMETROS'!$K$2,MATCH(U46,JC_SE,0),MATCH(T46,CC_SE,0)), IF(OR(AA46="DSRC/Estratégico",AA46="DSRC/Operativo"),OFFSET('PARÁMETROS'!$K$11,MATCH(U46,JC_DS,0),MATCH(T46,CC_DS,0)), IF(AA46="SALUD",OFFSET('PARÁMETROS'!$K$29,MATCH(U46,JC_SA,0),MATCH(T46,CC_SA,0)), IF(AA46="MEDIO AMBIENTE",OFFSET('PARÁMETROS'!$K$20,MATCH(U46,JC_MA,0),MATCH(T46,CC_MA,0)), IF(AA46="Rel. Gubernamentales",OFFSET('PARÁMETROS'!$K$48,MATCH(U46,JC_G,0),MATCH(T46,CC_G,0)), IF(AA46="OPERACIONAL",OFFSET('PARÁMETROS'!$K$56,MATCH(U46,JC_OP,0),MATCH(T46,CC_OP,0)), IF(AA46="FINANCIERO",OFFSET('PARÁMETROS'!$K$56,MATCH(U46,JC_FI,0),MATCH(T46,CC_FI,0)), OFFSET('PARÁMETROS'!$K$38,MATCH(U46,JC_L,0),MATCH(T46,CC_L,0))))))))),"") -> Control/Acción Satisfactorio | Z46: OK | AA46: =E40 -> Seguridad
P47: Capacitación/Entrenamiento | Q47: Difundir Hoja ZAP SI-066 "Uso de herramientas manuales" | R47: Planillas de vigencia de Certificaciones / Competencias/ Capacitaciones | S47: Seguimiento al programa de reuniones y evaluaciones de compromiso con la seguridad | T47: A. Mayor 80% | U47: 2. Administrativo/ Procedimientos/ Capacitación | V47: =IFERROR(IF(AA47="SEGURIDAD",OFFSET('PARÁMETROS'!$K$2,MATCH(U47,JC_SE,0),MATCH(T47,CC_SE,0)), IF(OR(AA47="DSRC/Estratégico",AA47="DSRC/Operativo"),OFFSET('PARÁMETROS'!$K$11,MATCH(U47,JC_DS,0),MATCH(T47,CC_DS,0)), IF(AA47="SALUD",OFFSET('PARÁMETROS'!$K$29,MATCH(U47,JC_SA,0),MATCH(T47,CC_SA,0)), IF(AA47="MEDIO AMBIENTE",OFFSET('PARÁMETROS'!$K$20,MATCH(U47,JC_MA,0),MATCH(T47,CC_MA,0)), IF(AA47="Rel. Gubernamentales",OFFSET('PARÁMETROS'!$K$48,MATCH(U47,JC_G,0),MATCH(T47,CC_G,0)), IF(AA47="OPERACIONAL",OFFSET('PARÁMETROS'!$K$56,MATCH(U47,JC_OP,0),MATCH(T47,CC_OP,0)), IF(AA47="FINANCIERO",OFFSET('PARÁMETROS'!$K$56,MATCH(U47,JC_FI,0),MATCH(T47,CC_FI,0)), OFFSET('PARÁMETROS'!$K$38,MATCH(U47,JC_L,0),MATCH(T47,CC_L,0))))))))),"") -> Control/Acción Eficaz | Z47: OK | AA47: =E40 -> Seguridad
P48: Capacitación/Entrenamiento | Q48: Difundir Hoja ZAP SI-078 "Modificación de equipos y herramientas" | R48: Planillas de vigencia de Certificaciones / Competencias/ Capacitaciones | S48: Seguimiento al programa de reuniones y evaluaciones de compromiso con la seguridad | T48: A. Mayor 80% | U48: 2. Administrativo/ Procedimientos/ Capacitación | V48: =IFERROR(IF(AA48="SEGURIDAD",OFFSET('PARÁMETROS'!$K$2,MATCH(U48,JC_SE,0),MATCH(T48,CC_SE,0)), IF(OR(AA48="DSRC/Estratégico",AA48="DSRC/Operativo"),OFFSET('PARÁMETROS'!$K$11,MATCH(U48,JC_DS,0),MATCH(T48,CC_DS,0)), IF(AA48="SALUD",OFFSET('PARÁMETROS'!$K$29,MATCH(U48,JC_SA,0),MATCH(T48,CC_SA,0)), IF(AA48="MEDIO AMBIENTE",OFFSET('PARÁMETROS'!$K$20,MATCH(U48,JC_MA,0),MATCH(T48,CC_MA,0)), IF(AA48="Rel. Gubernamentales",OFFSET('PARÁMETROS'!$K$48,MATCH(U48,JC_G,0),MATCH(T48,CC_G,0)), IF(AA48="OPERACIONAL",OFFSET('PARÁMETROS'!$K$56,MATCH(U48,JC_OP,0),MATCH(T48,CC_OP,0)), IF(AA48="FINANCIERO",OFFSET('PARÁMETROS'!$K$56,MATCH(U48,JC_FI,0),MATCH(T48,CC_FI,0)), OFFSET('PARÁMETROS'!$K$38,MATCH(U48,JC_L,0),MATCH(T48,CC_L,0))))))))),"") -> Control/Acción Eficaz | Z48: OK | AA48: =E40 -> Seguridad
P49: E.P.P. | Q49: Usar EPP básico y adicional (Casco, botines de Seguridad, Lentes), guantes y carrilera de casco | R49: Publicación de Indicadores | S49: Seguimiento y publicación de reporte STOP o Seguimiento y publicación de reporte de observaciones conductuales | T49: A. Mayor 80% | U49: 1. EPP | V49: =IFERROR(IF(AA49="SEGURIDAD",OFFSET('PARÁMETROS'!$K$2,MATCH(U49,JC_SE,0),MATCH(T49,CC_SE,0)), IF(OR(AA49="DSRC/Estratégico",AA49="DSRC/Operativo"),OFFSET('PARÁMETROS'!$K$11,MATCH(U49,JC_DS,0),MATCH(T49,CC_DS,0)), IF(AA49="SALUD",OFFSET('PARÁMETROS'!$K$29,MATCH(U49,JC_SA,0),MATCH(T49,CC_SA,0)), IF(AA49="MEDIO AMBIENTE",OFFSET('PARÁMETROS'!$K$20,MATCH(U49,JC_MA,0),MATCH(T49,CC_MA,0)), IF(AA49="Rel. Gubernamentales",OFFSET('PARÁMETROS'!$K$48,MATCH(U49,JC_G,0),MATCH(T49,CC_G,0)), IF(AA49="OPERACIONAL",OFFSET('PARÁMETROS'!$K$56,MATCH(U49,JC_OP,0),MATCH(T49,CC_OP,0)), IF(AA49="FINANCIERO",OFFSET('PARÁMETROS'!$K$56,MATCH(U49,JC_FI,0),MATCH(T49,CC_FI,0)), OFFSET('PARÁMETROS'!$K$38,MATCH(U49,JC_L,0),MATCH(T49,CC_L,0))))))))),"") -> Control/Acción Satisfactorio | Z49: OK | AA49: =E40 -> Seguridad
P50: Capacitación/Entrenamiento | Q50: Capacitar al personal sobre los estándares técnicos escritos en los Instructivos específicos de Mantenimiento Chancado | R50: Planes / Programas | S50: Seguimiento al programa de difusión de instructivos y capacitaciones internas | T50: C. Menor a 50% | U50: 2. Administrativo/ Procedimientos/ Capacitación | V50: =IFERROR(IF(AA50="SEGURIDAD",OFFSET('PARÁMETROS'!$K$2,MATCH(U50,JC_SE,0),MATCH(T50,CC_SE,0)), IF(OR(AA50="DSRC/Estratégico",AA50="DSRC/Operativo"),OFFSET('PARÁMETROS'!$K$11,MATCH(U50,JC_DS,0),MATCH(T50,CC_DS,0)), IF(AA50="SALUD",OFFSET('PARÁMETROS'!$K$29,MATCH(U50,JC_SA,0),MATCH(T50,CC_SA,0)), IF(AA50="MEDIO AMBIENTE",OFFSET('PARÁMETROS'!$K$20,MATCH(U50,JC_MA,0),MATCH(T50,CC_MA,0)), IF(AA50="Rel. Gubernamentales",OFFSET('PARÁMETROS'!$K$48,MATCH(U50,JC_G,0),MATCH(T50,CC_G,0)), IF(AA50="OPERACIONAL",OFFSET('PARÁMETROS'!$K$56,MATCH(U50,JC_OP,0),MATCH(T50,CC_OP,0)), IF(AA50="FINANCIERO",OFFSET('PARÁMETROS'!$K$56,MATCH(U50,JC_FI,0),MATCH(T50,CC_FI,0)), OFFSET('PARÁMETROS'!$K$38,MATCH(U50,JC_L,0),MATCH(T50,CC_L,0))))))))),"") -> Control/Acción No Eficaz | Z50: OK | AA50: =E40 -> Seguridad
A51: 5 | B51: Mantenimiento Chancador | C51: Desmontaje y montaje de componentes del Chancador Primario (araña, cóncavos, eje principal) | D51: Normal | E51: Seguridad | F51: Izaje mecanizado de materiales / cargas suspendidas | G51: Piezas de dimensiones importantes izadas por grúas | H51: Aplastamiento | I51: Aplastamiento de miembros, o personas, traumas graves o muerte | J51: 4 | K51: 2 | L51: =IF(OR(J51<>"",K51<>""),OFFSET('PARÁMETROS'!$B$2,K51,J51),"") -> 3 | M51: 5 | N51: =IFERROR(L51*M51,"") -> 15 | O51: =IF(N51="","",IFERROR(IF(N51<=2,"ACEPTABLE",IF(N51<=6,"BAJA",IF(N51<=10,"ACEPTABLE CON REVISIÓN",IF(N51<=15,"SUSTANCIAL","INACEPTABLE")))),"")) -> SUSTANCIAL | P51: Capacitación/Entrenamiento | Q51: Capacitar al personal los estándares del Instructivo de Manipulación Manual de Cargas 1.02.P06.I14 | R51: Planes / Programas | S51: Seguimiento al programa de difusión de instructivos y capacitaciones internas | T51: B. 50% y 80% | U51: 2. Administrativo/ Procedimientos/ Capacitación | V51: =IFERROR(IF(AA51="SEGURIDAD",OFFSET('PARÁMETROS'!$K$2,MATCH(U51,JC_SE,0),MATCH(T51,CC_SE,0)), IF(OR(AA51="DSRC/Estratégico",AA51="DSRC/Operativo"),OFFSET('PARÁMETROS'!$K$11,MATCH(U51,JC_DS,0),MATCH(T51,CC_DS,0)), IF(AA51="SALUD",OFFSET('PARÁMETROS'!$K$29,MATCH(U51,JC_SA,0),MATCH(T51,CC_SA,0)), IF(AA51="MEDIO AMBIENTE",OFFSET('PARÁMETROS'!$K$20,MATCH(U51,JC_MA,0),MATCH(T51,CC_MA,0)), IF(AA51="Rel. Gubernamentales",OFFSET('PARÁMETROS'!$K$48,MATCH(U51,JC_G,0),MATCH(T51,CC_G,0)), IF(AA51="OPERACIONAL",OFFSET('PARÁMETROS'!$K$56,MATCH(U51,JC_OP,0),MATCH(T51,CC_OP,0)), IF(AA51="FINANCIERO",OFFSET('PARÁMETROS'!$K$56,MATCH(U51,JC_FI,0),MATCH(T51,CC_FI,0)), OFFSET('PARÁMETROS'!$K$38,MATCH(U51,JC_L,0),MATCH(T51,CC_L,0))))))))),"") -> Control/Acción Satisfactorio | W51: =IF(E51="","", IF(COUNTA( V51:V61)-COUNTBLANK( V51:V61)=1, IF(O51="INACEPTABLE",IF(COUNTIF( V51:V61,"Control/Acción Eficaz")>=1,"SUSTANCIAL","INACEPTABLE"), IF(O51="SUSTANCIAL",IF(COUNTIF( V51:V61,"Control/Acción Eficaz")>=1,"ACEPTABLE CON REVISIÓN","SUSTANCIAL"), IF(O51="ACEPTABLE CON REVISIÓN",IF(COUNTIF( V51:V61,"Control/Acción Eficaz")>=1,"BAJA","ACEPTABLE CON REVISIÓN"), IF(O51="BAJA",IF(COUNTIF( V51:V61,"Control/Acción Eficaz")>=1,"ACEPTABLE","BAJA"),)))), IF(COUNTA( V51:V61)-COUNTBLANK( V51:V61)=2, IF(O51="INACEPTABLE",IF(COUNTIF( V51:V61,"Control/Acción Eficaz")=2,"ACEPTABLE CON REVISIÓN", IF(OR(AND(COUNTIF( V51:V61,"Control/Acción Eficaz")=1,COUNTIF( V51:V61,"Control/Acción Satisfactorio")=1), AND(COUNTIF( V51:V61,"Control/Acción Eficaz")=1,COUNTIF( V51:V61,"Control/Acción No Eficaz")=1)),"SUSTANCIAL","INACEPTABLE")), IF(O51="SUSTANCIAL",IF(COUNTIF( V51:V61,"Control/Acción Eficaz")=2,"BAJA", IF(OR(AND(COUNTIF( V51:V61,"Control/Acción Eficaz")=1,COUNTIF( V51:V61,"Control/Acción Satisfactorio")=1), AND(COUNTIF( V51:V61,"Control/Acción Eficaz")=1,COUNTIF( V51:V61,"Control/Acción No Eficaz")=1)),"ACEPTABLE CON REVISIÓN ","SUSTANCIAL")), IF(O51="ACEPTABLE CON REVISIÓN",IF(COUNTIF( V51:V61,"Control/Acción Eficaz")=2,"ACEPTABLE", IF(OR(AND(COUNTIF( V51:V61,"Control/Acción Eficaz")=1,COUNTIF( V51:V61,"Control/Acción Satisfactorio")=1), AND(COUNTIF( V51:V61,"Control/Acción Eficaz")=1,COUNTIF( V51:V61,"Control/Acción No Eficaz")=1)),"BAJA","ACEPTABLE CON REVISIÓN")), IF(O51="BAJA",IF(COUNTIF( V51:V61,"Control/Acción Eficaz")>=2,"ACEPTABLE","BAJA"),)))), IF(COUNTA( V51:V61)-COUNTBLANK( V51:V61)>=3, IF(O51="INACEPTABLE", IF(COUNTBLANK( V51:V61)=COUNTA( V51:V61),"", IF(COUNTIF( V51:V61,"Control/Acción No Eficaz")>=2,"INACEPTABLE", IF(AND(COUNTIF( V51:V61,"Control/Acción No Eficaz")=0,COUNTIF( V51:V61,"Control/Acción Eficaz")>=2),"ACEPTABLE CON REVISIÓN ","SUSTANCIAL"))), IF(O51="SUSTANCIAL", IF(COUNTBLANK( V51:V61)=COUNTA( V51:V61),"", IF(COUNTIF( V51:V61,"Control/Acción No Eficaz")>=2,"SUSTANCIAL", IF(AND(COUNTIF( V51:V61,"Control/Acción No Eficaz")=0,COUNTIF( V51:V61,"Control/Acción Eficaz")>=2),"BAJA","ACEPTABLE CON REVISIÓN"))), IF(O51="ACEPTABLE CON REVISIÓN", IF(COUNTBLANK( V51:V61)=COUNTA( V51:V61),"", IF(COUNTIF( V51:V61,"Control/Acción No Eficaz")>=2,"ACEPTABLE CON REVISIÓN", IF(AND(COUNTIF( V51:V61,"Control/Acción No Eficaz")=0,COUNTIF( V51:V61,"Control/Acción Eficaz")>=2),"ACEPTABLE","BAJA"))), IF(O51="BAJA", IF(COUNTBLANK( V51:V61)=COUNTA( V51:V61),"", IF(AND(COUNTBLANK( V51:V61)<1,COUNTA( V51:V61)=1), IF(COUNTIF( V51:V61,"Control/Acción No Eficaz")>=2,"BAJA", IF(AND(COUNTIF( V51:V61,"Control/Acción No Eficaz")=0,COUNTIF( V51:V61,"Control/Acción Eficaz")>=2),"ACEPTABLE","BAJA")), IF(COUNTIF( V51:V61,"Control/Acción No Eficaz")>=2,"BAJA", IF(AND(COUNTIF( V51:V61,"Control/Acción No Eficaz")=0,COUNTIF( V51:V61,"Control/Acción Eficaz")>=2),"ACEPTABLE","BAJA")))), IF(COUNTIF( V51:V61,"")>=5,"",O51))))), "")))) -> BAJA | AA51: =E51 -> Seguridad
P52: Señales/ Advertencias/ Alarmas | Q52: Señalizar áreas de trabajo, almacenaje de materiales y pasillos de circulación con cinta de color amarillo/rojo | R52: Planes / Programas | S52: Seguimiento al programa de inspecciones ISOP | T52: B. 50% y 80% | U52: 3. Señalización/ Advertencias/ Alarma | V52: =IFERROR(IF(AA52="SEGURIDAD",OFFSET('PARÁMETROS'!$K$2,MATCH(U52,JC_SE,0),MATCH(T52,CC_SE,0)), IF(OR(AA52="DSRC/Estratégico",AA52="DSRC/Operativo"),OFFSET('PARÁMETROS'!$K$11,MATCH(U52,JC_DS,0),MATCH(T52,CC_DS,0)), IF(AA52="SALUD",OFFSET('PARÁMETROS'!$K$29,MATCH(U52,JC_SA,0),MATCH(T52,CC_SA,0)), IF(AA52="MEDIO AMBIENTE",OFFSET('PARÁMETROS'!$K$20,MATCH(U52,JC_MA,0),MATCH(T52,CC_MA,0)), IF(AA52="Rel. Gubernamentales",OFFSET('PARÁMETROS'!$K$48,MATCH(U52,JC_G,0),MATCH(T52,CC_G,0)), IF(AA52="OPERACIONAL",OFFSET('PARÁMETROS'!$K$56,MATCH(U52,JC_OP,0),MATCH(T52,CC_OP,0)), IF(AA52="FINANCIERO",OFFSET('PARÁMETROS'!$K$56,MATCH(U52,JC_FI,0),MATCH(T52,CC_FI,0)), OFFSET('PARÁMETROS'!$K$38,MATCH(U52,JC_L,0),MATCH(T52,CC_L,0))))))))),"") -> Control/Acción Satisfactorio | Z52: OK | AA52: =E51 -> Seguridad
P53: Procedimientos / Instructivos / Reglamentos y otros. | Q53: Señalizar el área de trabajo según el instructivo Señalización Fija Delimitación Temporal de Áreas de Trabajo 1.02.P06.I38 | R53: Publicación de Indicadores | S53: Seguimiento y publicación de reporte STOP o Seguimiento y publicación de reporte de observaciones conductuales | T53: B. 50% y 80% | U53: 2. Administrativo/ Procedimientos/ Capacitación | V53: =IFERROR(IF(AA53="SEGURIDAD",OFFSET('PARÁMETROS'!$K$2,MATCH(U53,JC_SE,0),MATCH(T53,CC_SE,0)), IF(OR(AA53="DSRC/Estratégico",AA53="DSRC/Operativo"),OFFSET('PARÁMETROS'!$K$11,MATCH(U53,JC_DS,0),MATCH(T53,CC_DS,0)), IF(AA53="SALUD",OFFSET('PARÁMETROS'!$K$29,MATCH(U53,JC_SA,0),MATCH(T53,CC_SA,0)), IF(AA53="MEDIO AMBIENTE",OFFSET('PARÁMETROS'!$K$20,MATCH(U53,JC_MA,0),MATCH(T53,CC_MA,0)), IF(AA53="Rel. Gubernamentales",OFFSET('PARÁMETROS'!$K$48,MATCH(U53,JC_G,0),MATCH(T53,CC_G,0)), IF(AA53="OPERACIONAL",OFFSET('PARÁMETROS'!$K$56,MATCH(U53,JC_OP,0),MATCH(T53,CC_OP,0)), IF(AA53="FINANCIERO",OFFSET('PARÁMETROS'!$K$56,MATCH(U53,JC_FI,0),MATCH(T53,CC_FI,0)), OFFSET('PARÁMETROS'!$K$38,MATCH(U53,JC_L,0),MATCH(T53,CC_L,0))))))))),"") -> Control/Acción Satisfactorio | Z53: OK | AA53: =E51 -> Seguridad
P54: Capacitación/Entrenamiento | Q54: Difundir hoja ZAP SI-110 "Seguridad en área de Izaje" | R54: Planillas de vigencia de Certificaciones / Competencias/ Capacitaciones | S54: Seguimiento al programa de reuniones y evaluaciones de compromiso con la seguridad | T54: B. 50% y 80% | U54: 2. Administrativo/ Procedimientos/ Capacitación | V54: =IFERROR(IF(AA54="SEGURIDAD",OFFSET('PARÁMETROS'!$K$2,MATCH(U54,JC_SE,0),MATCH(T54,CC_SE,0)), IF(OR(AA54="DSRC/Estratégico",AA54="DSRC/Operativo"),OFFSET('PARÁMETROS'!$K$11,MATCH(U54,JC_DS,0),MATCH(T54,CC_DS,0)), IF(AA54="SALUD",OFFSET('PARÁMETROS'!$K$29,MATCH(U54,JC_SA,0),MATCH(T54,CC_SA,0)), IF(AA54="MEDIO AMBIENTE",OFFSET('PARÁMETROS'!$K$20,MATCH(U54,JC_MA,0),MATCH(T54,CC_MA,0)), IF(AA54="Rel. Gubernamentales",OFFSET('PARÁMETROS'!$K$48,MATCH(U54,JC_G,0),MATCH(T54,CC_G,0)), IF(AA54="OPERACIONAL",OFFSET('PARÁMETROS'!$K$56,MATCH(U54,JC_OP,0),MATCH(T54,CC_OP,0)), IF(AA54="FINANCIERO",OFFSET('PARÁMETROS'!$K$56,MATCH(U54,JC_FI,0),MATCH(T54,CC_FI,0)), OFFSET('PARÁMETROS'!$K$38,MATCH(U54,JC_L,0),MATCH(T54,CC_L,0))))))))),"") -> Control/Acción Satisfactorio | Z54: OK | AA54: =E51 -> Seguridad
P55: Capacitación/Entrenamiento | Q55: Capacitar al personal los estándares del Instructivo de Manipulación Manual de Cargas 1.02.P06.I14 | R55: Planes / Programas | S55: Seguimiento al programa de difusión de instructivos y capacitaciones internas | T55: B. 50% y 80% | U55: 2. Administrativo/ Procedimientos/ Capacitación | V55: =IFERROR(IF(AA55="SEGURIDAD",OFFSET('PARÁMETROS'!$K$2,MATCH(U55,JC_SE,0),MATCH(T55,CC_SE,0)), IF(OR(AA55="DSRC/Estratégico",AA55="DSRC/Operativo"),OFFSET('PARÁMETROS'!$K$11,MATCH(U55,JC_DS,0),MATCH(T55,CC_DS,0)), IF(AA55="SALUD",OFFSET('PARÁMETROS'!$K$29,MATCH(U55,JC_SA,0),MATCH(T55,CC_SA,0)), IF(AA55="MEDIO AMBIENTE",OFFSET('PARÁMETROS'!$K$20,MATCH(U55,JC_MA,0),MATCH(T55,CC_MA,0)), IF(AA55="Rel. Gubernamentales",OFFSET('PARÁMETROS'!$K$48,MATCH(U55,JC_G,0),MATCH(T55,CC_G,0)), IF(AA55="OPERACIONAL",OFFSET('PARÁMETROS'!$K$56,MATCH(U55,JC_OP,0),MATCH(T55,CC_OP,0)), IF(AA55="FINANCIERO",OFFSET('PARÁMETROS'!$K$56,MATCH(U55,JC_FI,0),MATCH(T55,CC_FI,0)), OFFSET('PARÁMETROS'!$K$38,MATCH(U55,JC_L,0),MATCH(T55,CC_L,0))))))))),"") -> Control/Acción Satisfactorio | Z55: OK | AA55: =E51 -> Seguridad
P56: E.P.P. | Q56: Usar EPP básico y adicional (Casco, botines de Seguridad, Lentes), guantes y carrilera de casco | R56: Publicación de Indicadores | S56: Seguimiento y publicación de reporte STOP o Seguimiento y publicación de reporte de observaciones conductuales | T56: A. Mayor 80% | U56: 1. EPP | V56: =IFERROR(IF(AA56="SEGURIDAD",OFFSET('PARÁMETROS'!$K$2,MATCH(U56,JC_SE,0),MATCH(T56,CC_SE,0)), IF(OR(AA56="DSRC/Estratégico",AA56="DSRC/Operativo"),OFFSET('PARÁMETROS'!$K$11,MATCH(U56,JC_DS,0),MATCH(T56,CC_DS,0)), IF(AA56="SALUD",OFFSET('PARÁMETROS'!$K$29,MATCH(U56,JC_SA,0),MATCH(T56,CC_SA,0)), IF(AA56="MEDIO AMBIENTE",OFFSET('PARÁMETROS'!$K$20,MATCH(U56,JC_MA,0),MATCH(T56,CC_MA,0)), IF(AA56="Rel. Gubernamentales",OFFSET('PARÁMETROS'!$K$48,MATCH(U56,JC_G,0),MATCH(T56,CC_G,0)), IF(AA56="OPERACIONAL",OFFSET('PARÁMETROS'!$K$56,MATCH(U56,JC_OP,0),MATCH(T56,CC_OP,0)), IF(AA56="FINANCIERO",OFFSET('PARÁMETROS'!$K$56,MATCH(U56,JC_FI,0),MATCH(T56,CC_FI,0)), OFFSET('PARÁMETROS'!$K$38,MATCH(U56,JC_L,0),MATCH(T56,CC_L,0))))))))),"") -> Control/Acción Satisfactorio | Z56: OK | AA56: =E51 -> Seguridad
P57: Capacitación/Entrenamiento | Q57: Contar con personal capacitado en el curso vigente en Gestión de Riesgos (ART/VPT) | R57: Planillas de vigencia de Certificaciones / Competencias/ Capacitaciones | S57: Seguimiento a la Planilla de vigencia de cursos, autorizaciones, competencias y/o certificaciones de personas y equipos | T57: A. Mayor 80% | U57: 2. Administrativo/ Procedimientos/ Capacitación | V57: =IFERROR(IF(AA57="SEGURIDAD",OFFSET('PARÁMETROS'!$K$2,MATCH(U57,JC_SE,0),MATCH(T57,CC_SE,0)), IF(OR(AA57="DSRC/Estratégico",AA57="DSRC/Operativo"),OFFSET('PARÁMETROS'!$K$11,MATCH(U57,JC_DS,0),MATCH(T57,CC_DS,0)), IF(AA57="SALUD",OFFSET('PARÁMETROS'!$K$29,MATCH(U57,JC_SA,0),MATCH(T57,CC_SA,0)), IF(AA57="MEDIO AMBIENTE",OFFSET('PARÁMETROS'!$K$20,MATCH(U57,JC_MA,0),MATCH(T57,CC_MA,0)), IF(AA57="Rel. Gubernamentales",OFFSET('PARÁMETROS'!$K$48,MATCH(U57,JC_G,0),MATCH(T57,CC_G,0)), IF(AA57="OPERACIONAL",OFFSET('PARÁMETROS'!$K$56,MATCH(U57,JC_OP,0),MATCH(T57,CC_OP,0)), IF(AA57="FINANCIERO",OFFSET('PARÁMETROS'!$K$56,MATCH(U57,JC_FI,0),MATCH(T57,CC_FI,0)), OFFSET('PARÁMETROS'!$K$38,MATCH(U57,JC_L,0),MATCH(T57,CC_L,0))))))))),"") -> Control/Acción Eficaz | Z57: OK | AA57: =E51 -> Seguridad
P58: Controles de Ingeniería | Q58: Usar líneas de viento para guía de carga | R58: Planes / Programas | S58: Seguimiento al programa de inspecciones IRO´S: Izaje | T58: B. 50% y 80% | U58: 4. Ingeniería | V58: =IFERROR(IF(AA58="SEGURIDAD",OFFSET('PARÁMETROS'!$K$2,MATCH(U58,JC_SE,0),MATCH(T58,CC_SE,0)), IF(OR(AA58="DSRC/Estratégico",AA58="DSRC/Operativo"),OFFSET('PARÁMETROS'!$K$11,MATCH(U58,JC_DS,0),MATCH(T58,CC_DS,0)), IF(AA58="SALUD",OFFSET('PARÁMETROS'!$K$29,MATCH(U58,JC_SA,0),MATCH(T58,CC_SA,0)), IF(AA58="MEDIO AMBIENTE",OFFSET('PARÁMETROS'!$K$20,MATCH(U58,JC_MA,0),MATCH(T58,CC_MA,0)), IF(AA58="Rel. Gubernamentales",OFFSET('PARÁMETROS'!$K$48,MATCH(U58,JC_G,0),MATCH(T58,CC_G,0)), IF(AA58="OPERACIONAL",OFFSET('PARÁMETROS'!$K$56,MATCH(U58,JC_OP,0),MATCH(T58,CC_OP,0)), IF(AA58="FINANCIERO",OFFSET('PARÁMETROS'!$K$56,MATCH(U58,JC_FI,0),MATCH(T58,CC_FI,0)), OFFSET('PARÁMETROS'!$K$38,MATCH(U58,JC_L,0),MATCH(T58,CC_L,0))))))))),"") -> Control/Acción Satisfactorio | Z58: OK | AA58: =E51 -> Seguridad
P59: Inspecciones | Q59: Inspección Pre-Uso de Elementos Accesorios de Izaje - Eslingas, Estrobos, Grilletes y Ganchos Colocar la cinta del color del mes que corresponda de acuerdo al instructivo de Codificación de Colores para Inspección 1.02.P06.I33 | R59: Planes / Programas | S59: Seguimiento al programa de inspecciones IRO´S: Izaje | T59: B. 50% y 80% | U59: 2. Administrativo/ Procedimientos/ Capacitación | V59: =IFERROR(IF(AA59="SEGURIDAD",OFFSET('PARÁMETROS'!$K$2,MATCH(U59,JC_SE,0),MATCH(T59,CC_SE,0)), IF(OR(AA59="DSRC/Estratégico",AA59="DSRC/Operativo"),OFFSET('PARÁMETROS'!$K$11,MATCH(U59,JC_DS,0),MATCH(T59,CC_DS,0)), IF(AA59="SALUD",OFFSET('PARÁMETROS'!$K$29,MATCH(U59,JC_SA,0),MATCH(T59,CC_SA,0)), IF(AA59="MEDIO AMBIENTE",OFFSET('PARÁMETROS'!$K$20,MATCH(U59,JC_MA,0),MATCH(T59,CC_MA,0)), IF(AA59="Rel. Gubernamentales",OFFSET('PARÁMETROS'!$K$48,MATCH(U59,JC_G,0),MATCH(T59,CC_G,0)), IF(AA59="OPERACIONAL",OFFSET('PARÁMETROS'!$K$56,MATCH(U59,JC_OP,0),MATCH(T59,CC_OP,0)), IF(AA59="FINANCIERO",OFFSET('PARÁMETROS'!$K$56,MATCH(U59,JC_FI,0),MATCH(T59,CC_FI,0)), OFFSET('PARÁMETROS'!$K$38,MATCH(U59,JC_L,0),MATCH(T59,CC_L,0))))))))),"") -> Control/Acción Satisfactorio | Z59: OK | AA59: =E51 -> Seguridad
P60: Certificaciones | Q60: Contar con Certificación de equipos de izaje, Puentes Grúas con Cabina, Puentes Grúas, Monorrieles, Man Lift y otros | R60: Planes / Programas | S60: Seguimiento al programa de inspecciones IRO´S: Izaje | T60: A. Mayor 80% | U60: 2. Administrativo/ Procedimientos/ Capacitación | V60: =IFERROR(IF(AA60="SEGURIDAD",OFFSET('PARÁMETROS'!$K$2,MATCH(U60,JC_SE,0),MATCH(T60,CC_SE,0)), IF(OR(AA60="DSRC/Estratégico",AA60="DSRC/Operativo"),OFFSET('PARÁMETROS'!$K$11,MATCH(U60,JC_DS,0),MATCH(T60,CC_DS,0)), IF(AA60="SALUD",OFFSET('PARÁMETROS'!$K$29,MATCH(U60,JC_SA,0),MATCH(T60,CC_SA,0)), IF(AA60="MEDIO AMBIENTE",OFFSET('PARÁMETROS'!$K$20,MATCH(U60,JC_MA,0),MATCH(T60,CC_MA,0)), IF(AA60="Rel. Gubernamentales",OFFSET('PARÁMETROS'!$K$48,MATCH(U60,JC_G,0),MATCH(T60,CC_G,0)), IF(AA60="OPERACIONAL",OFFSET('PARÁMETROS'!$K$56,MATCH(U60,JC_OP,0),MATCH(T60,CC_OP,0)), IF(AA60="FINANCIERO",OFFSET('PARÁMETROS'!$K$56,MATCH(U60,JC_FI,0),MATCH(T60,CC_FI,0)), OFFSET('PARÁMETROS'!$K$38,MATCH(U60,JC_L,0),MATCH(T60,CC_L,0))))))))),"") -> Control/Acción Eficaz | Z60: OK | AA60: =E51 -> Seguridad
P61: Alarmas / señales / advertencias | Q61: Señalizar el área de trabajo según el instructivo Señalización Fija Delimitación Temporal de Áreas de Trabajo 1.02.P06.I38 (Trabajos en Izaje) | R61: Planes / Programas | S61: Seguimiento al programa de inspecciones IRO´S: Izaje | T61: B. 50% y 80% | U61: 3. Señalización/ Advertencias/ Alarma | V61: =IFERROR(IF(AA61="SEGURIDAD",OFFSET('PARÁMETROS'!$K$2,MATCH(U61,JC_SE,0),MATCH(T61,CC_SE,0)), IF(OR(AA61="DSRC/Estratégico",AA61="DSRC/Operativo"),OFFSET('PARÁMETROS'!$K$11,MATCH(U61,JC_DS,0),MATCH(T61,CC_DS,0)), IF(AA61="SALUD",OFFSET('PARÁMETROS'!$K$29,MATCH(U61,JC_SA,0),MATCH(T61,CC_SA,0)), IF(AA61="MEDIO AMBIENTE",OFFSET('PARÁMETROS'!$K$20,MATCH(U61,JC_MA,0),MATCH(T61,CC_MA,0)), IF(AA61="Rel. Gubernamentales",OFFSET('PARÁMETROS'!$K$48,MATCH(U61,JC_G,0),MATCH(T61,CC_G,0)), IF(AA61="OPERACIONAL",OFFSET('PARÁMETROS'!$K$56,MATCH(U61,JC_OP,0),MATCH(T61,CC_OP,0)), IF(AA61="FINANCIERO",OFFSET('PARÁMETROS'!$K$56,MATCH(U61,JC_FI,0),MATCH(T61,CC_FI,0)), OFFSET('PARÁMETROS'!$K$38,MATCH(U61,JC_L,0),MATCH(T61,CC_L,0))))))))),"") -> Control/Acción Satisfactorio | Z61: OK | AA61: =E51 -> Seguridad
A62: 6 | B62: Mantenimiento Chancador | C62: Desmontaje y montaje de componentes del Chancador Primario (araña, cóncavos, eje principal) | D62: Normal | E62: Seguridad | F62: Trabajo en caliente (soldadura, corte, desbaste) torchado, arco eléctrico, amolado, esmerilado, oxicorte, oxiflama, etc. | G62: Trabajos de soldadura que generan calor y son fuente de ignición | H62: Incendio | I62: Incendio generado por contacto de chispas incandescentes o calor con materiales inflamables y/o combustible | J62: 2 | K62: 2 | L62: =IF(OR(J62<>"",K62<>""),OFFSET('PARÁMETROS'!$B$2,K62,J62),"") -> 5 | M62: 4 | N62: =IFERROR(L62*M62,"") -> 20 | O62: =IF(N62="","",IFERROR(IF(N62<=2,"ACEPTABLE",IF(N62<=6,"BAJA",IF(N62<=10,"ACEPTABLE CON REVISIÓN",IF(N62<=15,"SUSTANCIAL","INACEPTABLE")))),"")) -> INACEPTABLE | P62: Capacitación/Entrenamiento | Q62: Capacitar al personal sobre los estándares del Instructivo de Soldadura con arco eléctrico 1.02.P06.I04 | R62: Planes / Programas | S62: Seguimiento al programa de difusión de instructivos y capacitaciones internas | T62: C. Menor a 50% | U62: 2. Administrativo/ Procedimientos/ Capacitación | V62: =IFERROR(IF(AA62="SEGURIDAD",OFFSET('PARÁMETROS'!$K$2,MATCH(U62,JC_SE,0),MATCH(T62,CC_SE,0)), IF(OR(AA62="DSRC/Estratégico",AA62="DSRC/Operativo"),OFFSET('PARÁMETROS'!$K$11,MATCH(U62,JC_DS,0),MATCH(T62,CC_DS,0)), IF(AA62="SALUD",OFFSET('PARÁMETROS'!$K$29,MATCH(U62,JC_SA,0),MATCH(T62,CC_SA,0)), IF(AA62="MEDIO AMBIENTE",OFFSET('PARÁMETROS'!$K$20,MATCH(U62,JC_MA,0),MATCH(T62,CC_MA,0)), IF(AA62="Rel. Gubernamentales",OFFSET('PARÁMETROS'!$K$48,MATCH(U62,JC_G,0),MATCH(T62,CC_G,0)), IF(AA62="OPERACIONAL",OFFSET('PARÁMETROS'!$K$56,MATCH(U62,JC_OP,0),MATCH(T62,CC_OP,0)), IF(AA62="FINANCIERO",OFFSET('PARÁMETROS'!$K$56,MATCH(U62,JC_FI,0),MATCH(T62,CC_FI,0)), OFFSET('PARÁMETROS'!$K$38,MATCH(U62,JC_L,0),MATCH(T62,CC_L,0))))))))),"") -> Control/Acción No Eficaz | W62: =IF(E62="","", IF(COUNTA( V62:V79)-COUNTBLANK( V62:V79)=1, IF(O62="INACEPTABLE",IF(COUNTIF( V62:V79,"Control/Acción Eficaz")>=1,"SUSTANCIAL","INACEPTABLE"), IF(O62="SUSTANCIAL",IF(COUNTIF( V62:V79,"Control/Acción Eficaz")>=1,"ACEPTABLE CON REVISIÓN","SUSTANCIAL"), IF(O62="ACEPTABLE CON REVISIÓN",IF(COUNTIF( V62:V79,"Control/Acción Eficaz")>=1,"BAJA","ACEPTABLE CON REVISIÓN"), IF(O62="BAJA",IF(COUNTIF( V62:V79,"Control/Acción Eficaz")>=1,"ACEPTABLE","BAJA"),)))), IF(COUNTA( V62:V79)-COUNTBLANK( V62:V79)=2, IF(O62="INACEPTABLE",IF(COUNTIF( V62:V79,"Control/Acción Eficaz")=2,"ACEPTABLE CON REVISIÓN", IF(OR(AND(COUNTIF( V62:V79,"Control/Acción Eficaz")=1,COUNTIF( V62:V79,"Control/Acción Satisfactorio")=1), AND(COUNTIF( V62:V79,"Control/Acción Eficaz")=1,COUNTIF( V62:V79,"Control/Acción No Eficaz")=1)),"SUSTANCIAL","INACEPTABLE")), IF(O62="SUSTANCIAL",IF(COUNTIF( V62:V79,"Control/Acción Eficaz")=2,"BAJA", IF(OR(AND(COUNTIF( V62:V79,"Control/Acción Eficaz")=1,COUNTIF( V62:V79,"Control/Acción Satisfactorio")=1), AND(COUNTIF( V62:V79,"Control/Acción Eficaz")=1,COUNTIF( V62:V79,"Control/Acción No Eficaz")=1)),"ACEPTABLE CON REVISIÓN ","SUSTANCIAL")), IF(O62="ACEPTABLE CON REVISIÓN",IF(COUNTIF( V62:V79,"Control/Acción Eficaz")=2,"ACEPTABLE", IF(OR(AND(COUNTIF( V62:V79,"Control/Acción Eficaz")=1,COUNTIF( V62:V79,"Control/Acción Satisfactorio")=1), AND(COUNTIF( V62:V79,"Control/Acción Eficaz")=1,COUNTIF( V62:V79,"Control/Acción No Eficaz")=1)),"BAJA","ACEPTABLE CON REVISIÓN")), IF(O62="BAJA",IF(COUNTIF( V62:V79,"Control/Acción Eficaz")>=2,"ACEPTABLE","BAJA"),)))), IF(COUNTA( V62:V79)-COUNTBLANK( V62:V79)>=3, IF(O62="INACEPTABLE", IF(COUNTBLANK( V62:V79)=COUNTA( V62:V79),"", IF(COUNTIF( V62:V79,"Control/Acción No Eficaz")>=2,"INACEPTABLE", IF(AND(COUNTIF( V62:V79,"Control/Acción No Eficaz")=0,COUNTIF( V62:V79,"Control/Acción Eficaz")>=2),"ACEPTABLE CON REVISIÓN ","SUSTANCIAL"))), IF(O62="SUSTANCIAL", IF(COUNTBLANK( V62:V79)=COUNTA( V62:V79),"", IF(COUNTIF( V62:V79,"Control/Acción No Eficaz")>=2,"SUSTANCIAL", IF(AND(COUNTIF( V62:V79,"Control/Acción No Eficaz")=0,COUNTIF( V62:V79,"Control/Acción Eficaz")>=2),"BAJA","ACEPTABLE CON REVISIÓN"))), IF(O62="ACEPTABLE CON REVISIÓN", IF(COUNTBLANK( V62:V79)=COUNTA( V62:V79),"", IF(COUNTIF( V62:V79,"Control/Acción No Eficaz")>=2,"ACEPTABLE CON REVISIÓN", IF(AND(COUNTIF( V62:V79,"Control/Acción No Eficaz")=0,COUNTIF( V62:V79,"Control/Acción Eficaz")>=2),"ACEPTABLE","BAJA"))), IF(O62="BAJA", IF(COUNTBLANK( V62:V79)=COUNTA( V62:V79),"", IF(AND(COUNTBLANK( V62:V79)<1,COUNTA( V62:V79)=1), IF(COUNTIF( V62:V79,"Control/Acción No Eficaz")>=2,"BAJA", IF(AND(COUNTIF( V62:V79,"Control/Acción No Eficaz")=0,COUNTIF( V62:V79,"Control/Acción Eficaz")>=2),"ACEPTABLE","BAJA")), IF(COUNTIF( V62:V79,"Control/Acción No Eficaz")>=2,"BAJA", IF(AND(COUNTIF( V62:V79,"Control/Acción No Eficaz")=0,COUNTIF( V62:V79,"Control/Acción Eficaz")>=2),"ACEPTABLE","BAJA")))), IF(COUNTIF( V62:V79,"")>=5,"",O62))))), "")))) -> INACEPTABLE | Z62: OK | AA62: =E62 -> Seguridad
P63: Inspecciones | Q63: Inspección de Equipos de Soldar según formulario 1.02.P06.F4 Inspeccion Equipos de Soldar | R63: Planes / Programas | S63: Seguimiento al programa de inspecciones IRO´S: Trabajos en Caliente | T63: B. 50% y 80% | U63: 2. Administrativo/ Procedimientos/ Capacitación | V63: =IFERROR(IF(AA63="SEGURIDAD",OFFSET('PARÁMETROS'!$K$2,MATCH(U63,JC_SE,0),MATCH(T63,CC_SE,0)), IF(OR(AA63="DSRC/Estratégico",AA63="DSRC/Operativo"),OFFSET('PARÁMETROS'!$K$11,MATCH(U63,JC_DS,0),MATCH(T63,CC_DS,0)), IF(AA63="SALUD",OFFSET('PARÁMETROS'!$K$29,MATCH(U63,JC_SA,0),MATCH(T63,CC_SA,0)), IF(AA63="MEDIO AMBIENTE",OFFSET('PARÁMETROS'!$K$20,MATCH(U63,JC_MA,0),MATCH(T63,CC_MA,0)), IF(AA63="Rel. Gubernamentales",OFFSET('PARÁMETROS'!$K$48,MATCH(U63,JC_G,0),MATCH(T63,CC_G,0)), IF(AA63="OPERACIONAL",OFFSET('PARÁMETROS'!$K$56,MATCH(U63,JC_OP,0),MATCH(T63,CC_OP,0)), IF(AA63="FINANCIERO",OFFSET('PARÁMETROS'!$K$56,MATCH(U63,JC_FI,0),MATCH(T63,CC_FI,0)), OFFSET('PARÁMETROS'!$K$38,MATCH(U63,JC_L,0),MATCH(T63,CC_L,0))))))))),"") -> Control/Acción Satisfactorio | Z63: CAMBIAR NUMERO DE FORMULARIO A 1.02.P06.F42_Inspeccion_Equipos_de_Soldar_Rev.1 | AA63: =E62 -> Seguridad
P64: Capacitación/Entrenamiento | Q64: Capacitar al personal sobre los estándares del Instructivo de Operación de Oxicorte 1.02.P06.I05 | R64: Planes / Programas | S64: Seguimiento al programa de difusión de instructivos y capacitaciones internas | T64: C. Menor a 50% | U64: 2. Administrativo/ Procedimientos/ Capacitación | V64: =IFERROR(IF(AA64="SEGURIDAD",OFFSET('PARÁMETROS'!$K$2,MATCH(U64,JC_SE,0),MATCH(T64,CC_SE,0)), IF(OR(AA64="DSRC/Estratégico",AA64="DSRC/Operativo"),OFFSET('PARÁMETROS'!$K$11,MATCH(U64,JC_DS,0),MATCH(T64,CC_DS,0)), IF(AA64="SALUD",OFFSET('PARÁMETROS'!$K$29,MATCH(U64,JC_SA,0),MATCH(T64,CC_SA,0)), IF(AA64="MEDIO AMBIENTE",OFFSET('PARÁMETROS'!$K$20,MATCH(U64,JC_MA,0),MATCH(T64,CC_MA,0)), IF(AA64="Rel. Gubernamentales",OFFSET('PARÁMETROS'!$K$48,MATCH(U64,JC_G,0),MATCH(T64,CC_G,0)), IF(AA64="OPERACIONAL",OFFSET('PARÁMETROS'!$K$56,MATCH(U64,JC_OP,0),MATCH(T64,CC_OP,0)), IF(AA64="FINANCIERO",OFFSET('PARÁMETROS'!$K$56,MATCH(U64,JC_FI,0),MATCH(T64,CC_FI,0)), OFFSET('PARÁMETROS'!$K$38,MATCH(U64,JC_L,0),MATCH(T64,CC_L,0))))))))),"") -> Control/Acción No Eficaz | Z64: OK | AA64: =E62 -> Seguridad
P65: Capacitación/Entrenamiento | Q65: Capacitar al personal sobre los estándares del Instructivo de Almacenamiento, Transporte, Uso e Inspección de Cilindros para Gases Comprimidos 1.02.P06.I12 | R65: Planes / Programas | S65: Seguimiento al programa de difusión de instructivos y capacitaciones internas | T65: C. Menor a 50% | U65: 2. Administrativo/ Procedimientos/ Capacitación | V65: =IFERROR(IF(AA65="SEGURIDAD",OFFSET('PARÁMETROS'!$K$2,MATCH(U65,JC_SE,0),MATCH(T65,CC_SE,0)), IF(OR(AA65="DSRC/Estratégico",AA65="DSRC/Operativo"),OFFSET('PARÁMETROS'!$K$11,MATCH(U65,JC_DS,0),MATCH(T65,CC_DS,0)), IF(AA65="SALUD",OFFSET('PARÁMETROS'!$K$29,MATCH(U65,JC_SA,0),MATCH(T65,CC_SA,0)), IF(AA65="MEDIO AMBIENTE",OFFSET('PARÁMETROS'!$K$20,MATCH(U65,JC_MA,0),MATCH(T65,CC_MA,0)), IF(AA65="Rel. Gubernamentales",OFFSET('PARÁMETROS'!$K$48,MATCH(U65,JC_G,0),MATCH(T65,CC_G,0)), IF(AA65="OPERACIONAL",OFFSET('PARÁMETROS'!$K$56,MATCH(U65,JC_OP,0),MATCH(T65,CC_OP,0)), IF(AA65="FINANCIERO",OFFSET('PARÁMETROS'!$K$56,MATCH(U65,JC_FI,0),MATCH(T65,CC_FI,0)), OFFSET('PARÁMETROS'!$K$38,MATCH(U65,JC_L,0),MATCH(T65,CC_L,0))))))))),"") -> Control/Acción No Eficaz | Z65: OK | AA65: =E62 -> Seguridad
P66: Inspecciones | Q66: Realizar inspección de Cilindros para Gases Comprimidos de acuerdo a formulario 1.02.P06.F20 | R66: Planes / Programas | S66: Seguimiento al programa de inspecciones IRO´S: Trabajos en Caliente | T66: A. Mayor 80% | U66: 2. Administrativo/ Procedimientos/ Capacitación | V66: =IFERROR(IF(AA66="SEGURIDAD",OFFSET('PARÁMETROS'!$K$2,MATCH(U66,JC_SE,0),MATCH(T66,CC_SE,0)), IF(OR(AA66="DSRC/Estratégico",AA66="DSRC/Operativo"),OFFSET('PARÁMETROS'!$K$11,MATCH(U66,JC_DS,0),MATCH(T66,CC_DS,0)), IF(AA66="SALUD",OFFSET('PARÁMETROS'!$K$29,MATCH(U66,JC_SA,0),MATCH(T66,CC_SA,0)), IF(AA66="MEDIO AMBIENTE",OFFSET('PARÁMETROS'!$K$20,MATCH(U66,JC_MA,0),MATCH(T66,CC_MA,0)), IF(AA66="Rel. Gubernamentales",OFFSET('PARÁMETROS'!$K$48,MATCH(U66,JC_G,0),MATCH(T66,CC_G,0)), IF(AA66="OPERACIONAL",OFFSET('PARÁMETROS'!$K$56,MATCH(U66,JC_OP,0),MATCH(T66,CC_OP,0)), IF(AA66="FINANCIERO",OFFSET('PARÁMETROS'!$K$56,MATCH(U66,JC_FI,0),MATCH(T66,CC_FI,0)), OFFSET('PARÁMETROS'!$K$38,MATCH(U66,JC_L,0),MATCH(T66,CC_L,0))))))))),"") -> Control/Acción Eficaz | Z66: OK | AA66: =E62 -> Seguridad
P67: Controles de Ingeniería | Q67: Instalar sistemas de seguridad en líneas de oxicorte (válvulas anti retroceso) | R67: Planes / Programas | S67: Seguimiento al programa de inspecciones IRO´S: Trabajos en Caliente | T67: B. 50% y 80% | U67: 4. Ingeniería | V67: =IFERROR(IF(AA67="SEGURIDAD",OFFSET('PARÁMETROS'!$K$2,MATCH(U67,JC_SE,0),MATCH(T67,CC_SE,0)), IF(OR(AA67="DSRC/Estratégico",AA67="DSRC/Operativo"),OFFSET('PARÁMETROS'!$K$11,MATCH(U67,JC_DS,0),MATCH(T67,CC_DS,0)), IF(AA67="SALUD",OFFSET('PARÁMETROS'!$K$29,MATCH(U67,JC_SA,0),MATCH(T67,CC_SA,0)), IF(AA67="MEDIO AMBIENTE",OFFSET('PARÁMETROS'!$K$20,MATCH(U67,JC_MA,0),MATCH(T67,CC_MA,0)), IF(AA67="Rel. Gubernamentales",OFFSET('PARÁMETROS'!$K$48,MATCH(U67,JC_G,0),MATCH(T67,CC_G,0)), IF(AA67="OPERACIONAL",OFFSET('PARÁMETROS'!$K$56,MATCH(U67,JC_OP,0),MATCH(T67,CC_OP,0)), IF(AA67="FINANCIERO",OFFSET('PARÁMETROS'!$K$56,MATCH(U67,JC_FI,0),MATCH(T67,CC_FI,0)), OFFSET('PARÁMETROS'!$K$38,MATCH(U67,JC_L,0),MATCH(T67,CC_L,0))))))))),"") -> Control/Acción Satisfactorio | Z67: OK | AA67: =E62 -> Seguridad
P68: Capacitación/Entrenamiento | Q68: Capacitar al personal sobre los estándares del Instructivo de Uso de Amoladora Eléctrica 1.02.P06.I37 | R68: Planes / Programas | S68: Seguimiento al programa de difusión de instructivos y capacitaciones internas | T68: C. Menor a 50% | U68: 2. Administrativo/ Procedimientos/ Capacitación | V68: =IFERROR(IF(AA68="SEGURIDAD",OFFSET('PARÁMETROS'!$K$2,MATCH(U68,JC_SE,0),MATCH(T68,CC_SE,0)), IF(OR(AA68="DSRC/Estratégico",AA68="DSRC/Operativo"),OFFSET('PARÁMETROS'!$K$11,MATCH(U68,JC_DS,0),MATCH(T68,CC_DS,0)), IF(AA68="SALUD",OFFSET('PARÁMETROS'!$K$29,MATCH(U68,JC_SA,0),MATCH(T68,CC_SA,0)), IF(AA68="MEDIO AMBIENTE",OFFSET('PARÁMETROS'!$K$20,MATCH(U68,JC_MA,0),MATCH(T68,CC_MA,0)), IF(AA68="Rel. Gubernamentales",OFFSET('PARÁMETROS'!$K$48,MATCH(U68,JC_G,0),MATCH(T68,CC_G,0)), IF(AA68="OPERACIONAL",OFFSET('PARÁMETROS'!$K$56,MATCH(U68,JC_OP,0),MATCH(T68,CC_OP,0)), IF(AA68="FINANCIERO",OFFSET('PARÁMETROS'!$K$56,MATCH(U68,JC_FI,0),MATCH(T68,CC_FI,0)), OFFSET('PARÁMETROS'!$K$38,MATCH(U68,JC_L,0),MATCH(T68,CC_L,0))))))))),"") -> Control/Acción No Eficaz | Z68: OK | AA68: =E62 -> Seguridad
P69: Inspecciones | Q69: Inspección de Amoladoras según formulario 1.02.P06.F39 | R69: Planes / Programas | S69: Seguimiento al programa de inspecciones IRO´S: Trabajos en Caliente | T69: B. 50% y 80% | U69: 2. Administrativo/ Procedimientos/ Capacitación | V69: =IFERROR(IF(AA69="SEGURIDAD",OFFSET('PARÁMETROS'!$K$2,MATCH(U69,JC_SE,0),MATCH(T69,CC_SE,0)), IF(OR(AA69="DSRC/Estratégico",AA69="DSRC/Operativo"),OFFSET('PARÁMETROS'!$K$11,MATCH(U69,JC_DS,0),MATCH(T69,CC_DS,0)), IF(AA69="SALUD",OFFSET('PARÁMETROS'!$K$29,MATCH(U69,JC_SA,0),MATCH(T69,CC_SA,0)), IF(AA69="MEDIO AMBIENTE",OFFSET('PARÁMETROS'!$K$20,MATCH(U69,JC_MA,0),MATCH(T69,CC_MA,0)), IF(AA69="Rel. Gubernamentales",OFFSET('PARÁMETROS'!$K$48,MATCH(U69,JC_G,0),MATCH(T69,CC_G,0)), IF(AA69="OPERACIONAL",OFFSET('PARÁMETROS'!$K$56,MATCH(U69,JC_OP,0),MATCH(T69,CC_OP,0)), IF(AA69="FINANCIERO",OFFSET('PARÁMETROS'!$K$56,MATCH(U69,JC_FI,0),MATCH(T69,CC_FI,0)), OFFSET('PARÁMETROS'!$K$38,MATCH(U69,JC_L,0),MATCH(T69,CC_L,0))))))))),"") -> Control/Acción Satisfactorio | Z69: OK | AA69: =E62 -> Seguridad
P70: Capacitación/Entrenamiento | Q70: Contar con el curso de Inducción General OHS (2.04.P05.E20 Inducción Plan de Emergencia ) | R70: Planillas de vigencia de Certificaciones / Competencias/ Capacitaciones | S70: Seguimiento a la Planilla de vigencia de cursos, autorizaciones, competencias y/o certificaciones de personas y equipos | T70: A. Mayor 80% | U70: 2. Administrativo/ Procedimientos/ Capacitación | V70: =IFERROR(IF(AA70="SEGURIDAD",OFFSET('PARÁMETROS'!$K$2,MATCH(U70,JC_SE,0),MATCH(T70,CC_SE,0)), IF(OR(AA70="DSRC/Estratégico",AA70="DSRC/Operativo"),OFFSET('PARÁMETROS'!$K$11,MATCH(U70,JC_DS,0),MATCH(T70,CC_DS,0)), IF(AA70="SALUD",OFFSET('PARÁMETROS'!$K$29,MATCH(U70,JC_SA,0),MATCH(T70,CC_SA,0)), IF(AA70="MEDIO AMBIENTE",OFFSET('PARÁMETROS'!$K$20,MATCH(U70,JC_MA,0),MATCH(T70,CC_MA,0)), IF(AA70="Rel. Gubernamentales",OFFSET('PARÁMETROS'!$K$48,MATCH(U70,JC_G,0),MATCH(T70,CC_G,0)), IF(AA70="OPERACIONAL",OFFSET('PARÁMETROS'!$K$56,MATCH(U70,JC_OP,0),MATCH(T70,CC_OP,0)), IF(AA70="FINANCIERO",OFFSET('PARÁMETROS'!$K$56,MATCH(U70,JC_FI,0),MATCH(T70,CC_FI,0)), OFFSET('PARÁMETROS'!$K$38,MATCH(U70,JC_L,0),MATCH(T70,CC_L,0))))))))),"") -> Control/Acción Eficaz | Z70: OK | AA70: =E62 -> Seguridad
P71: Competencias | Q71: Contar con personal competente para realizar Trabajo en Caliente | R71: Planillas de vigencia de Certificaciones / Competencias/ Capacitaciones | S71: Seguimiento a la Planilla de vigencia de cursos, autorizaciones, competencias y/o certificaciones de personas y equipos | T71: A. Mayor 80% | U71: 2. Administrativo/ Procedimientos/ Capacitación | V71: =IFERROR(IF(AA71="SEGURIDAD",OFFSET('PARÁMETROS'!$K$2,MATCH(U71,JC_SE,0),MATCH(T71,CC_SE,0)), IF(OR(AA71="DSRC/Estratégico",AA71="DSRC/Operativo"),OFFSET('PARÁMETROS'!$K$11,MATCH(U71,JC_DS,0),MATCH(T71,CC_DS,0)), IF(AA71="SALUD",OFFSET('PARÁMETROS'!$K$29,MATCH(U71,JC_SA,0),MATCH(T71,CC_SA,0)), IF(AA71="MEDIO AMBIENTE",OFFSET('PARÁMETROS'!$K$20,MATCH(U71,JC_MA,0),MATCH(T71,CC_MA,0)), IF(AA71="Rel. Gubernamentales",OFFSET('PARÁMETROS'!$K$48,MATCH(U71,JC_G,0),MATCH(T71,CC_G,0)), IF(AA71="OPERACIONAL",OFFSET('PARÁMETROS'!$K$56,MATCH(U71,JC_OP,0),MATCH(T71,CC_OP,0)), IF(AA71="FINANCIERO",OFFSET('PARÁMETROS'!$K$56,MATCH(U71,JC_FI,0),MATCH(T71,CC_FI,0)), OFFSET('PARÁMETROS'!$K$38,MATCH(U71,JC_L,0),MATCH(T71,CC_L,0))))))))),"") -> Control/Acción Eficaz | Z71: OK | AA71: =E62 -> Seguridad
P72: Capacitación/Entrenamiento | Q72: Difundir hoja ZAP SI-037 "Seguridad en la soldadura al arco " | R72: Planillas de vigencia de Certificaciones / Competencias/ Capacitaciones | S72: Seguimiento al programa de reuniones y evaluaciones de compromiso con la seguridad | T72: B. 50% y 80% | U72: 2. Administrativo/ Procedimientos/ Capacitación | V72: =IFERROR(IF(AA72="SEGURIDAD",OFFSET('PARÁMETROS'!$K$2,MATCH(U72,JC_SE,0),MATCH(T72,CC_SE,0)), IF(OR(AA72="DSRC/Estratégico",AA72="DSRC/Operativo"),OFFSET('PARÁMETROS'!$K$11,MATCH(U72,JC_DS,0),MATCH(T72,CC_DS,0)), IF(AA72="SALUD",OFFSET('PARÁMETROS'!$K$29,MATCH(U72,JC_SA,0),MATCH(T72,CC_SA,0)), IF(AA72="MEDIO AMBIENTE",OFFSET('PARÁMETROS'!$K$20,MATCH(U72,JC_MA,0),MATCH(T72,CC_MA,0)), IF(AA72="Rel. Gubernamentales",OFFSET('PARÁMETROS'!$K$48,MATCH(U72,JC_G,0),MATCH(T72,CC_G,0)), IF(AA72="OPERACIONAL",OFFSET('PARÁMETROS'!$K$56,MATCH(U72,JC_OP,0),MATCH(T72,CC_OP,0)), IF(AA72="FINANCIERO",OFFSET('PARÁMETROS'!$K$56,MATCH(U72,JC_FI,0),MATCH(T72,CC_FI,0)), OFFSET('PARÁMETROS'!$K$38,MATCH(U72,JC_L,0),MATCH(T72,CC_L,0))))))))),"") -> Control/Acción Satisfactorio | Z72: OK | AA72: =E62 -> Seguridad
P73: Capacitación/Entrenamiento | Q73: Difundir hoja ZAP SI-035 "Uso de EPP en trabajos para amoladora" | R73: Planillas de vigencia de Certificaciones / Competencias/ Capacitaciones | S73: Seguimiento al programa de reuniones y evaluaciones de compromiso con la seguridad | T73: B. 50% y 80% | U73: 2. Administrativo/ Procedimientos/ Capacitación | V73: =IFERROR(IF(AA73="SEGURIDAD",OFFSET('PARÁMETROS'!$K$2,MATCH(U73,JC_SE,0),MATCH(T73,CC_SE,0)), IF(OR(AA73="DSRC/Estratégico",AA73="DSRC/Operativo"),OFFSET('PARÁMETROS'!$K$11,MATCH(U73,JC_DS,0),MATCH(T73,CC_DS,0)), IF(AA73="SALUD",OFFSET('PARÁMETROS'!$K$29,MATCH(U73,JC_SA,0),MATCH(T73,CC_SA,0)), IF(AA73="MEDIO AMBIENTE",OFFSET('PARÁMETROS'!$K$20,MATCH(U73,JC_MA,0),MATCH(T73,CC_MA,0)), IF(AA73="Rel. Gubernamentales",OFFSET('PARÁMETROS'!$K$48,MATCH(U73,JC_G,0),MATCH(T73,CC_G,0)), IF(AA73="OPERACIONAL",OFFSET('PARÁMETROS'!$K$56,MATCH(U73,JC_OP,0),MATCH(T73,CC_OP,0)), IF(AA73="FINANCIERO",OFFSET('PARÁMETROS'!$K$56,MATCH(U73,JC_FI,0),MATCH(T73,CC_FI,0)), OFFSET('PARÁMETROS'!$K$38,MATCH(U73,JC_L,0),MATCH(T73,CC_L,0))))))))),"") -> Control/Acción Satisfactorio | Z73: OK | AA73: =E62 -> Seguridad
P74: Capacitación/Entrenamiento | Q74: Difundir hoja ZAP SI-026 "Protección Respiratoria contra polvo y Humos" | R74: Planillas de vigencia de Certificaciones / Competencias/ Capacitaciones | S74: Seguimiento al programa de reuniones y evaluaciones de compromiso con la seguridad | T74: B. 50% y 80% | U74: 2. Administrativo/ Procedimientos/ Capacitación | V74: =IFERROR(IF(AA74="SEGURIDAD",OFFSET('PARÁMETROS'!$K$2,MATCH(U74,JC_SE,0),MATCH(T74,CC_SE,0)), IF(OR(AA74="DSRC/Estratégico",AA74="DSRC/Operativo"),OFFSET('PARÁMETROS'!$K$11,MATCH(U74,JC_DS,0),MATCH(T74,CC_DS,0)), IF(AA74="SALUD",OFFSET('PARÁMETROS'!$K$29,MATCH(U74,JC_SA,0),MATCH(T74,CC_SA,0)), IF(AA74="MEDIO AMBIENTE",OFFSET('PARÁMETROS'!$K$20,MATCH(U74,JC_MA,0),MATCH(T74,CC_MA,0)), IF(AA74="Rel. Gubernamentales",OFFSET('PARÁMETROS'!$K$48,MATCH(U74,JC_G,0),MATCH(T74,CC_G,0)), IF(AA74="OPERACIONAL",OFFSET('PARÁMETROS'!$K$56,MATCH(U74,JC_OP,0),MATCH(T74,CC_OP,0)), IF(AA74="FINANCIERO",OFFSET('PARÁMETROS'!$K$56,MATCH(U74,JC_FI,0),MATCH(T74,CC_FI,0)), OFFSET('PARÁMETROS'!$K$38,MATCH(U74,JC_L,0),MATCH(T74,CC_L,0))))))))),"") -> Control/Acción Satisfactorio | Z74: OK | AA74: =E62 -> Seguridad
P75: Capacitación/Entrenamiento | Q75: Capacitar al personal sobre los estándares del Instructivo de Trabajos en Caliente 1.02.P06.I32 | R75: Planes / Programas | S75: Seguimiento al programa de difusión de instructivos y capacitaciones internas | T75: B. 50% y 80% | U75: 2. Administrativo/ Procedimientos/ Capacitación | V75: =IFERROR(IF(AA75="SEGURIDAD",OFFSET('PARÁMETROS'!$K$2,MATCH(U75,JC_SE,0),MATCH(T75,CC_SE,0)), IF(OR(AA75="DSRC/Estratégico",AA75="DSRC/Operativo"),OFFSET('PARÁMETROS'!$K$11,MATCH(U75,JC_DS,0),MATCH(T75,CC_DS,0)), IF(AA75="SALUD",OFFSET('PARÁMETROS'!$K$29,MATCH(U75,JC_SA,0),MATCH(T75,CC_SA,0)), IF(AA75="MEDIO AMBIENTE",OFFSET('PARÁMETROS'!$K$20,MATCH(U75,JC_MA,0),MATCH(T75,CC_MA,0)), IF(AA75="Rel. Gubernamentales",OFFSET('PARÁMETROS'!$K$48,MATCH(U75,JC_G,0),MATCH(T75,CC_G,0)), IF(AA75="OPERACIONAL",OFFSET('PARÁMETROS'!$K$56,MATCH(U75,JC_OP,0),MATCH(T75,CC_OP,0)), IF(AA75="FINANCIERO",OFFSET('PARÁMETROS'!$K$56,MATCH(U75,JC_FI,0),MATCH(T75,CC_FI,0)), OFFSET('PARÁMETROS'!$K$38,MATCH(U75,JC_L,0),MATCH(T75,CC_L,0))))))))),"") -> Control/Acción Satisfactorio | Z75: OK | AA75: =E62 -> Seguridad
P76: Procedimientos / Instructivos / Reglamentos y otros. | Q76: Cumplir con los estándares del Instructivo de Trabajos en Caliente 1.02.P06.I32 | R76: Publicación de Indicadores | S76: Seguimiento y publicación de reporte STOP o Seguimiento y publicación de reporte de observaciones conductuales | T76: A. Mayor 80% | U76: 2. Administrativo/ Procedimientos/ Capacitación | V76: =IFERROR(IF(AA76="SEGURIDAD",OFFSET('PARÁMETROS'!$K$2,MATCH(U76,JC_SE,0),MATCH(T76,CC_SE,0)), IF(OR(AA76="DSRC/Estratégico",AA76="DSRC/Operativo"),OFFSET('PARÁMETROS'!$K$11,MATCH(U76,JC_DS,0),MATCH(T76,CC_DS,0)), IF(AA76="SALUD",OFFSET('PARÁMETROS'!$K$29,MATCH(U76,JC_SA,0),MATCH(T76,CC_SA,0)), IF(AA76="MEDIO AMBIENTE",OFFSET('PARÁMETROS'!$K$20,MATCH(U76,JC_MA,0),MATCH(T76,CC_MA,0)), IF(AA76="Rel. Gubernamentales",OFFSET('PARÁMETROS'!$K$48,MATCH(U76,JC_G,0),MATCH(T76,CC_G,0)), IF(AA76="OPERACIONAL",OFFSET('PARÁMETROS'!$K$56,MATCH(U76,JC_OP,0),MATCH(T76,CC_OP,0)), IF(AA76="FINANCIERO",OFFSET('PARÁMETROS'!$K$56,MATCH(U76,JC_FI,0),MATCH(T76,CC_FI,0)), OFFSET('PARÁMETROS'!$K$38,MATCH(U76,JC_L,0),MATCH(T76,CC_L,0))))))))),"") -> Control/Acción Eficaz | Z76: OK | AA76: =E62 -> Seguridad
P77: Controles de Ingeniería | Q77: Contar con mamparas, biombos en torno al área de trabajo y/o manta ignífuga para proteger los dispositivos. | R77: Planes / Programas | S77: Seguimiento al programa de inspecciones IRO´S: Trabajos en Caliente | T77: A. Mayor 80% | U77: 4. Ingeniería | V77: =IFERROR(IF(AA77="SEGURIDAD",OFFSET('PARÁMETROS'!$K$2,MATCH(U77,JC_SE,0),MATCH(T77,CC_SE,0)), IF(OR(AA77="DSRC/Estratégico",AA77="DSRC/Operativo"),OFFSET('PARÁMETROS'!$K$11,MATCH(U77,JC_DS,0),MATCH(T77,CC_DS,0)), IF(AA77="SALUD",OFFSET('PARÁMETROS'!$K$29,MATCH(U77,JC_SA,0),MATCH(T77,CC_SA,0)), IF(AA77="MEDIO AMBIENTE",OFFSET('PARÁMETROS'!$K$20,MATCH(U77,JC_MA,0),MATCH(T77,CC_MA,0)), IF(AA77="Rel. Gubernamentales",OFFSET('PARÁMETROS'!$K$48,MATCH(U77,JC_G,0),MATCH(T77,CC_G,0)), IF(AA77="OPERACIONAL",OFFSET('PARÁMETROS'!$K$56,MATCH(U77,JC_OP,0),MATCH(T77,CC_OP,0)), IF(AA77="FINANCIERO",OFFSET('PARÁMETROS'!$K$56,MATCH(U77,JC_FI,0),MATCH(T77,CC_FI,0)), OFFSET('PARÁMETROS'!$K$38,MATCH(U77,JC_L,0),MATCH(T77,CC_L,0))))))))),"") -> Control/Acción Eficaz | Z77: OK | AA77: =E62 -> Seguridad
P78: Capacitación/Entrenamiento | Q78: Difundir hoja ZAP SI-178 "Trabajos en Caliente con Equipo Oxiflama" | R78: Planes / Programas | S78: Seguimiento al programa de reuniones y evaluaciones de compromiso con la seguridad | T78: C. Menor a 50% | U78: 2. Administrativo/ Procedimientos/ Capacitación | V78: =IFERROR(IF(AA78="SEGURIDAD",OFFSET('PARÁMETROS'!$K$2,MATCH(U78,JC_SE,0),MATCH(T78,CC_SE,0)), IF(OR(AA78="DSRC/Estratégico",AA78="DSRC/Operativo"),OFFSET('PARÁMETROS'!$K$11,MATCH(U78,JC_DS,0),MATCH(T78,CC_DS,0)), IF(AA78="SALUD",OFFSET('PARÁMETROS'!$K$29,MATCH(U78,JC_SA,0),MATCH(T78,CC_SA,0)), IF(AA78="MEDIO AMBIENTE",OFFSET('PARÁMETROS'!$K$20,MATCH(U78,JC_MA,0),MATCH(T78,CC_MA,0)), IF(AA78="Rel. Gubernamentales",OFFSET('PARÁMETROS'!$K$48,MATCH(U78,JC_G,0),MATCH(T78,CC_G,0)), IF(AA78="OPERACIONAL",OFFSET('PARÁMETROS'!$K$56,MATCH(U78,JC_OP,0),MATCH(T78,CC_OP,0)), IF(AA78="FINANCIERO",OFFSET('PARÁMETROS'!$K$56,MATCH(U78,JC_FI,0),MATCH(T78,CC_FI,0)), OFFSET('PARÁMETROS'!$K$38,MATCH(U78,JC_L,0),MATCH(T78,CC_L,0))))))))),"") -> Control/Acción No Eficaz | Z78: OK | AA78: =E62 -> Seguridad
P79: Procedimientos / Instructivos / Reglamentos y otros. | Q79: Implementar formularios ART/VPT según Guía para la Identificación y Evaluación de Riesgos 1.02.P06.I01 para realizar trabajo de Desmontaje y montaje de componentes del Chancador Primario (araña, cóncavos, eje principal) | R79: Planes / Programas | S79: Seguimiento al programa de inspecciones IRO´S: Trabajos en Caliente | T79: A. Mayor 80% | U79: 2. Administrativo/ Procedimientos/ Capacitación | V79: =IFERROR(IF(AA79="SEGURIDAD",OFFSET('PARÁMETROS'!$K$2,MATCH(U79,JC_SE,0),MATCH(T79,CC_SE,0)), IF(OR(AA79="DSRC/Estratégico",AA79="DSRC/Operativo"),OFFSET('PARÁMETROS'!$K$11,MATCH(U79,JC_DS,0),MATCH(T79,CC_DS,0)), IF(AA79="SALUD",OFFSET('PARÁMETROS'!$K$29,MATCH(U79,JC_SA,0),MATCH(T79,CC_SA,0)), IF(AA79="MEDIO AMBIENTE",OFFSET('PARÁMETROS'!$K$20,MATCH(U79,JC_MA,0),MATCH(T79,CC_MA,0)), IF(AA79="Rel. Gubernamentales",OFFSET('PARÁMETROS'!$K$48,MATCH(U79,JC_G,0),MATCH(T79,CC_G,0)), IF(AA79="OPERACIONAL",OFFSET('PARÁMETROS'!$K$56,MATCH(U79,JC_OP,0),MATCH(T79,CC_OP,0)), IF(AA79="FINANCIERO",OFFSET('PARÁMETROS'!$K$56,MATCH(U79,JC_FI,0),MATCH(T79,CC_FI,0)), OFFSET('PARÁMETROS'!$K$38,MATCH(U79,JC_L,0),MATCH(T79,CC_L,0))))))))),"") -> Control/Acción Eficaz | Z79: OK | AA79: =E62 -> Seguridad
A80: 7 | B80: Mantenimiento Chancador | C80: Desmontaje y montaje de componentes del Chancador Primario (araña, cóncavos, eje principal) | D80: Normal | E80: Seguridad | F80: Trabajo en caliente (soldadura, corte, desbaste) torchado, arco eléctrico, amolado, esmerilado, oxicorte, oxiflama, etc. | G80: Trabajos de soldadura que generan calor y proyectan chispas incandescentes, o metal fundido y generan superficies caliente | H80: Contacto con superficies/partículas/objetos calientes | I80: Contacto con chispas incandescentes, metal fundido, quemaduras | J80: 2 | K80: 2 | L80: =IF(OR(J80<>"",K80<>""),OFFSET('PARÁMETROS'!$B$2,K80,J80),"") -> 5 | M80: 4 | N80: =IFERROR(L80*M80,"") -> 20 | O80: =IF(N80="","",IFERROR(IF(N80<=2,"ACEPTABLE",IF(N80<=6,"BAJA",IF(N80<=10,"ACEPTABLE CON REVISIÓN",IF(N80<=15,"SUSTANCIAL","INACEPTABLE")))),"")) -> INACEPTABLE | P80: E.P.P. | Q80: Usar EPP para trabajos en caliente (soldadura), chaqueta de cuero, pantalón de cuero, coleto, guantes de caña larga de soldador, protección respiratoria, polainas y botines de seguridad | R80: Publicación de Indicadores | S80: Seguimiento y publicación de reporte STOP o Seguimiento y publicación de reporte de observaciones conductuales | T80: A. Mayor 80% | U80: 1. EPP | V80: =IFERROR(IF(AA80="SEGURIDAD",OFFSET('PARÁMETROS'!$K$2,MATCH(U80,JC_SE,0),MATCH(T80,CC_SE,0)), IF(OR(AA80="DSRC/Estratégico",AA80="DSRC/Operativo"),OFFSET('PARÁMETROS'!$K$11,MATCH(U80,JC_DS,0),MATCH(T80,CC_DS,0)), IF(AA80="SALUD",OFFSET('PARÁMETROS'!$K$29,MATCH(U80,JC_SA,0),MATCH(T80,CC_SA,0)), IF(AA80="MEDIO AMBIENTE",OFFSET('PARÁMETROS'!$K$20,MATCH(U80,JC_MA,0),MATCH(T80,CC_MA,0)), IF(AA80="Rel. Gubernamentales",OFFSET('PARÁMETROS'!$K$48,MATCH(U80,JC_G,0),MATCH(T80,CC_G,0)), IF(AA80="OPERACIONAL",OFFSET('PARÁMETROS'!$K$56,MATCH(U80,JC_OP,0),MATCH(T80,CC_OP,0)), IF(AA80="FINANCIERO",OFFSET('PARÁMETROS'!$K$56,MATCH(U80,JC_FI,0),MATCH(T80,CC_FI,0)), OFFSET('PARÁMETROS'!$K$38,MATCH(U80,JC_L,0),MATCH(T80,CC_L,0))))))))),"") -> Control/Acción Satisfactorio | W80: =IF(E80="","", IF(COUNTA( V80:V82)-COUNTBLANK( V80:V82)=1, IF(O80="INACEPTABLE",IF(COUNTIF( V80:V82,"Control/Acción Eficaz")>=1,"SUSTANCIAL","INACEPTABLE"), IF(O80="SUSTANCIAL",IF(COUNTIF( V80:V82,"Control/Acción Eficaz")>=1,"ACEPTABLE CON REVISIÓN","SUSTANCIAL"), IF(O80="ACEPTABLE CON REVISIÓN",IF(COUNTIF( V80:V82,"Control/Acción Eficaz")>=1,"BAJA","ACEPTABLE CON REVISIÓN"), IF(O80="BAJA",IF(COUNTIF( V80:V82,"Control/Acción Eficaz")>=1,"ACEPTABLE","BAJA"),)))), IF(COUNTA( V80:V82)-COUNTBLANK( V80:V82)=2, IF(O80="INACEPTABLE",IF(COUNTIF( V80:V82,"Control/Acción Eficaz")=2,"ACEPTABLE CON REVISIÓN", IF(OR(AND(COUNTIF( V80:V82,"Control/Acción Eficaz")=1,COUNTIF( V80:V82,"Control/Acción Satisfactorio")=1), AND(COUNTIF( V80:V82,"Control/Acción Eficaz")=1,COUNTIF( V80:V82,"Control/Acción No Eficaz")=1)),"SUSTANCIAL","INACEPTABLE")), IF(O80="SUSTANCIAL",IF(COUNTIF( V80:V82,"Control/Acción Eficaz")=2,"BAJA", IF(OR(AND(COUNTIF( V80:V82,"Control/Acción Eficaz")=1,COUNTIF( V80:V82,"Control/Acción Satisfactorio")=1), AND(COUNTIF( V80:V82,"Control/Acción Eficaz")=1,COUNTIF( V80:V82,"Control/Acción No Eficaz")=1)),"ACEPTABLE CON REVISIÓN ","SUSTANCIAL")), IF(O80="ACEPTABLE CON REVISIÓN",IF(COUNTIF( V80:V82,"Control/Acción Eficaz")=2,"ACEPTABLE", IF(OR(AND(COUNTIF( V80:V82,"Control/Acción Eficaz")=1,COUNTIF( V80:V82,"Control/Acción Satisfactorio")=1), AND(COUNTIF( V80:V82,"Control/Acción Eficaz")=1,COUNTIF( V80:V82,"Control/Acción No Eficaz")=1)),"BAJA","ACEPTABLE CON REVISIÓN")), IF(O80="BAJA",IF(COUNTIF( V80:V82,"Control/Acción Eficaz")>=2,"ACEPTABLE","BAJA"),)))), IF(COUNTA( V80:V82)-COUNTBLANK( V80:V82)>=3, IF(O80="INACEPTABLE", IF(COUNTBLANK( V80:V82)=COUNTA( V80:V82),"", IF(COUNTIF( V80:V82,"Control/Acción No Eficaz")>=2,"INACEPTABLE", IF(AND(COUNTIF( V80:V82,"Control/Acción No Eficaz")=0,COUNTIF( V80:V82,"Control/Acción Eficaz")>=2),"ACEPTABLE CON REVISIÓN ","SUSTANCIAL"))), IF(O80="SUSTANCIAL", IF(COUNTBLANK( V80:V82)=COUNTA( V80:V82),"", IF(COUNTIF( V80:V82,"Control/Acción No Eficaz")>=2,"SUSTANCIAL", IF(AND(COUNTIF( V80:V82,"Control/Acción No Eficaz")=0,COUNTIF( V80:V82,"Control/Acción Eficaz")>=2),"BAJA","ACEPTABLE CON REVISIÓN"))), IF(O80="ACEPTABLE CON REVISIÓN", IF(COUNTBLANK( V80:V82)=COUNTA( V80:V82),"", IF(COUNTIF( V80:V82,"Control/Acción No Eficaz")>=2,"ACEPTABLE CON REVISIÓN", IF(AND(COUNTIF( V80:V82,"Control/Acción No Eficaz")=0,COUNTIF( V80:V82,"Control/Acción Eficaz")>=2),"ACEPTABLE","BAJA"))), IF(O80="BAJA", IF(COUNTBLANK( V80:V82)=COUNTA( V80:V82),"", IF(AND(COUNTBLANK( V80:V82)<1,COUNTA( V80:V82)=1), IF(COUNTIF( V80:V82,"Control/Acción No Eficaz")>=2,"BAJA", IF(AND(COUNTIF( V80:V82,"Control/Acción No Eficaz")=0,COUNTIF( V80:V82,"Control/Acción Eficaz")>=2),"ACEPTABLE","BAJA")), IF(COUNTIF( V80:V82,"Control/Acción No Eficaz")>=2,"BAJA", IF(AND(COUNTIF( V80:V82,"Control/Acción No Eficaz")=0,COUNTIF( V80:V82,"Control/Acción Eficaz")>=2),"ACEPTABLE","BAJA")))), IF(COUNTIF( V80:V82,"")>=5,"",O80))))), "")))) -> ACEPTABLE CON REVISIÓN | Z80: OK | AA80: =E80 -> Seguridad
P81: Controles de Ingeniería | Q81: Contar con mamparas, biombos en torno al área de trabajo y/o manta ignífuga para proteger los dispositivos. | R81: Planes / Programas | S81: Seguimiento al programa de inspecciones IRO´S: Trabajos en Caliente | T81: A. Mayor 80% | U81: 4. Ingeniería | V81: =IFERROR(IF(AA81="SEGURIDAD",OFFSET('PARÁMETROS'!$K$2,MATCH(U81,JC_SE,0),MATCH(T81,CC_SE,0)), IF(OR(AA81="DSRC/Estratégico",AA81="DSRC/Operativo"),OFFSET('PARÁMETROS'!$K$11,MATCH(U81,JC_DS,0),MATCH(T81,CC_DS,0)), IF(AA81="SALUD",OFFSET('PARÁMETROS'!$K$29,MATCH(U81,JC_SA,0),MATCH(T81,CC_SA,0)), IF(AA81="MEDIO AMBIENTE",OFFSET('PARÁMETROS'!$K$20,MATCH(U81,JC_MA,0),MATCH(T81,CC_MA,0)), IF(AA81="Rel. Gubernamentales",OFFSET('PARÁMETROS'!$K$48,MATCH(U81,JC_G,0),MATCH(T81,CC_G,0)), IF(AA81="OPERACIONAL",OFFSET('PARÁMETROS'!$K$56,MATCH(U81,JC_OP,0),MATCH(T81,CC_OP,0)), IF(AA81="FINANCIERO",OFFSET('PARÁMETROS'!$K$56,MATCH(U81,JC_FI,0),MATCH(T81,CC_FI,0)), OFFSET('PARÁMETROS'!$K$38,MATCH(U81,JC_L,0),MATCH(T81,CC_L,0))))))))),"") -> Control/Acción Eficaz | Z81: OK | AA81: =E80 -> Seguridad
P82: Procedimientos / Instructivos / Reglamentos y otros. | Q82: Implementar formularios ART/VPT según Guía para la Identificación y Evaluación de Riesgos 1.02.P06.I01 para realizar trabajo de Desmontaje y montaje de componentes del Chancador Primario (araña, cóncavos, eje principal) | R82: Planes / Programas | S82: Seguimiento al programa de inspecciones IRO´S: Trabajos en Caliente | T82: A. Mayor 80% | U82: 2. Administrativo/ Procedimientos/ Capacitación | V82: =IFERROR(IF(AA82="SEGURIDAD",OFFSET('PARÁMETROS'!$K$2,MATCH(U82,JC_SE,0),MATCH(T82,CC_SE,0)), IF(OR(AA82="DSRC/Estratégico",AA82="DSRC/Operativo"),OFFSET('PARÁMETROS'!$K$11,MATCH(U82,JC_DS,0),MATCH(T82,CC_DS,0)), IF(AA82="SALUD",OFFSET('PARÁMETROS'!$K$29,MATCH(U82,JC_SA,0),MATCH(T82,CC_SA,0)), IF(AA82="MEDIO AMBIENTE",OFFSET('PARÁMETROS'!$K$20,MATCH(U82,JC_MA,0),MATCH(T82,CC_MA,0)), IF(AA82="Rel. Gubernamentales",OFFSET('PARÁMETROS'!$K$48,MATCH(U82,JC_G,0),MATCH(T82,CC_G,0)), IF(AA82="OPERACIONAL",OFFSET('PARÁMETROS'!$K$56,MATCH(U82,JC_OP,0),MATCH(T82,CC_OP,0)), IF(AA82="FINANCIERO",OFFSET('PARÁMETROS'!$K$56,MATCH(U82,JC_FI,0),MATCH(T82,CC_FI,0)), OFFSET('PARÁMETROS'!$K$38,MATCH(U82,JC_L,0),MATCH(T82,CC_L,0))))))))),"") -> Control/Acción Eficaz | Z82: OK | AA82: =E80 -> Seguridad
A83: 8 | B83: Mantenimiento Chancador | C83: Desmontaje y montaje de componentes del Chancador Primario (araña, cóncavos, eje principal) | D83: Normal | E83: Seguridad | F83: Equipo o línea energizada | G83: Daños en conductores eléctricos o carcasa de equipo de soldar | H83: Choque eléctrico | I83: Contacto con energía eléctrica | J83: 4 | K83: 2 | L83: =IF(OR(J83<>"",K83<>""),OFFSET('PARÁMETROS'!$B$2,K83,J83),"") -> 3 | M83: 4 | N83: =IFERROR(L83*M83,"") -> 12 | O83: =IF(N83="","",IFERROR(IF(N83<=2,"ACEPTABLE",IF(N83<=6,"BAJA",IF(N83<=10,"ACEPTABLE CON REVISIÓN",IF(N83<=15,"SUSTANCIAL","INACEPTABLE")))),"")) -> SUSTANCIAL | P83: Capacitación/Entrenamiento | Q83: Capacitar al personal sobre los estándares del Instructivo de Soldadura con arco eléctrico 1.02.P06.I04 | R83: Planes / Programas | S83: Seguimiento al programa de difusión de instructivos y capacitaciones internas | T83: C. Menor a 50% | U83: 2. Administrativo/ Procedimientos/ Capacitación | V83: =IFERROR(IF(AA83="SEGURIDAD",OFFSET('PARÁMETROS'!$K$2,MATCH(U83,JC_SE,0),MATCH(T83,CC_SE,0)), IF(OR(AA83="DSRC/Estratégico",AA83="DSRC/Operativo"),OFFSET('PARÁMETROS'!$K$11,MATCH(U83,JC_DS,0),MATCH(T83,CC_DS,0)), IF(AA83="SALUD",OFFSET('PARÁMETROS'!$K$29,MATCH(U83,JC_SA,0),MATCH(T83,CC_SA,0)), IF(AA83="MEDIO AMBIENTE",OFFSET('PARÁMETROS'!$K$20,MATCH(U83,JC_MA,0),MATCH(T83,CC_MA,0)), IF(AA83="Rel. Gubernamentales",OFFSET('PARÁMETROS'!$K$48,MATCH(U83,JC_G,0),MATCH(T83,CC_G,0)), IF(AA83="OPERACIONAL",OFFSET('PARÁMETROS'!$K$56,MATCH(U83,JC_OP,0),MATCH(T83,CC_OP,0)), IF(AA83="FINANCIERO",OFFSET('PARÁMETROS'!$K$56,MATCH(U83,JC_FI,0),MATCH(T83,CC_FI,0)), OFFSET('PARÁMETROS'!$K$38,MATCH(U83,JC_L,0),MATCH(T83,CC_L,0))))))))),"") -> Control/Acción No Eficaz | W83: =IF(E83="","", IF(COUNTA( V83:V89)-COUNTBLANK( V83:V89)=1, IF(O83="INACEPTABLE",IF(COUNTIF( V83:V89,"Control/Acción Eficaz")>=1,"SUSTANCIAL","INACEPTABLE"), IF(O83="SUSTANCIAL",IF(COUNTIF( V83:V89,"Control/Acción Eficaz")>=1,"ACEPTABLE CON REVISIÓN","SUSTANCIAL"), IF(O83="ACEPTABLE CON REVISIÓN",IF(COUNTIF( V83:V89,"Control/Acción Eficaz")>=1,"BAJA","ACEPTABLE CON REVISIÓN"), IF(O83="BAJA",IF(COUNTIF( V83:V89,"Control/Acción Eficaz")>=1,"ACEPTABLE","BAJA"),)))), IF(COUNTA( V83:V89)-COUNTBLANK( V83:V89)=2, IF(O83="INACEPTABLE",IF(COUNTIF( V83:V89,"Control/Acción Eficaz")=2,"ACEPTABLE CON REVISIÓN", IF(OR(AND(COUNTIF( V83:V89,"Control/Acción Eficaz")=1,COUNTIF( V83:V89,"Control/Acción Satisfactorio")=1), AND(COUNTIF( V83:V89,"Control/Acción Eficaz")=1,COUNTIF( V83:V89,"Control/Acción No Eficaz")=1)),"SUSTANCIAL","INACEPTABLE")), IF(O83="SUSTANCIAL",IF(COUNTIF( V83:V89,"Control/Acción Eficaz")=2,"BAJA", IF(OR(AND(COUNTIF( V83:V89,"Control/Acción Eficaz")=1,COUNTIF( V83:V89,"Control/Acción Satisfactorio")=1), AND(COUNTIF( V83:V89,"Control/Acción Eficaz")=1,COUNTIF( V83:V89,"Control/Acción No Eficaz")=1)),"ACEPTABLE CON REVISIÓN ","SUSTANCIAL")), IF(O83="ACEPTABLE CON REVISIÓN",IF(COUNTIF( V83:V89,"Control/Acción Eficaz")=2,"ACEPTABLE", IF(OR(AND(COUNTIF( V83:V89,"Control/Acción Eficaz")=1,COUNTIF( V83:V89,"Control/Acción Satisfactorio")=1), AND(COUNTIF( V83:V89,"Control/Acción Eficaz")=1,COUNTIF( V83:V89,"Control/Acción No Eficaz")=1)),"BAJA","ACEPTABLE CON REVISIÓN")), IF(O83="BAJA",IF(COUNTIF( V83:V89,"Control/Acción Eficaz")>=2,"ACEPTABLE","BAJA"),)))), IF(COUNTA( V83:V89)-COUNTBLANK( V83:V89)>=3, IF(O83="INACEPTABLE", IF(COUNTBLANK( V83:V89)=COUNTA( V83:V89),"", IF(COUNTIF( V83:V89,"Control/Acción No Eficaz")>=2,"INACEPTABLE", IF(AND(COUNTIF( V83:V89,"Control/Acción No Eficaz")=0,COUNTIF( V83:V89,"Control/Acción Eficaz")>=2),"ACEPTABLE CON REVISIÓN ","SUSTANCIAL"))), IF(O83="SUSTANCIAL", IF(COUNTBLANK( V83:V89)=COUNTA( V83:V89),"", IF(COUNTIF( V83:V89,"Control/Acción No Eficaz")>=2,"SUSTANCIAL", IF(AND(COUNTIF( V83:V89,"Control/Acción No Eficaz")=0,COUNTIF( V83:V89,"Control/Acción Eficaz")>=2),"BAJA","ACEPTABLE CON REVISIÓN"))), IF(O83="ACEPTABLE CON REVISIÓN", IF(COUNTBLANK( V83:V89)=COUNTA( V83:V89),"", IF(COUNTIF( V83:V89,"Control/Acción No Eficaz")>=2,"ACEPTABLE CON REVISIÓN", IF(AND(COUNTIF( V83:V89,"Control/Acción No Eficaz")=0,COUNTIF( V83:V89,"Control/Acción Eficaz")>=2),"ACEPTABLE","BAJA"))), IF(O83="BAJA", IF(COUNTBLANK( V83:V89)=COUNTA( V83:V89),"", IF(AND(COUNTBLANK( V83:V89)<1,COUNTA( V83:V89)=1), IF(COUNTIF( V83:V89,"Control/Acción No Eficaz")>=2,"BAJA", IF(AND(COUNTIF( V83:V89,"Control/Acción No Eficaz")=0,COUNTIF( V83:V89,"Control/Acción Eficaz")>=2),"ACEPTABLE","BAJA")), IF(COUNTIF( V83:V89,"Control/Acción No Eficaz")>=2,"BAJA", IF(AND(COUNTIF( V83:V89,"Control/Acción No Eficaz")=0,COUNTIF( V83:V89,"Control/Acción Eficaz")>=2),"ACEPTABLE","BAJA")))), IF(COUNTIF( V83:V89,"")>=5,"",O83))))), "")))) -> ACEPTABLE CON REVISIÓN | Z83: OK | AA83: =E83 -> Seguridad
P84: Controles de Ingeniería | Q84: Tener la Toma de fuerza conectada a interruptor diferencial | R84: Publicación de Indicadores | S84: Seguimiento y publicación de reporte STOP o Seguimiento y publicación de reporte de observaciones conductuales | T84: A. Mayor 80% | U84: 2. Administrativo/ Procedimientos/ Capacitación | V84: =IFERROR(IF(AA84="SEGURIDAD",OFFSET('PARÁMETROS'!$K$2,MATCH(U84,JC_SE,0),MATCH(T84,CC_SE,0)), IF(OR(AA84="DSRC/Estratégico",AA84="DSRC/Operativo"),OFFSET('PARÁMETROS'!$K$11,MATCH(U84,JC_DS,0),MATCH(T84,CC_DS,0)), IF(AA84="SALUD",OFFSET('PARÁMETROS'!$K$29,MATCH(U84,JC_SA,0),MATCH(T84,CC_SA,0)), IF(AA84="MEDIO AMBIENTE",OFFSET('PARÁMETROS'!$K$20,MATCH(U84,JC_MA,0),MATCH(T84,CC_MA,0)), IF(AA84="Rel. Gubernamentales",OFFSET('PARÁMETROS'!$K$48,MATCH(U84,JC_G,0),MATCH(T84,CC_G,0)), IF(AA84="OPERACIONAL",OFFSET('PARÁMETROS'!$K$56,MATCH(U84,JC_OP,0),MATCH(T84,CC_OP,0)), IF(AA84="FINANCIERO",OFFSET('PARÁMETROS'!$K$56,MATCH(U84,JC_FI,0),MATCH(T84,CC_FI,0)), OFFSET('PARÁMETROS'!$K$38,MATCH(U84,JC_L,0),MATCH(T84,CC_L,0))))))))),"") -> Control/Acción Eficaz | AA84: =E83 -> Seguridad
P85: Inspecciones | Q85: Inspección de Equipos de Soldar según formulario 1.02.P06.F4 Inspeccion Equipos de Soldar | R85: Planes / Programas | S85: Seguimiento al programa de Inspecciones Interno | T85: A. Mayor 80% | U85: 2. Administrativo/ Procedimientos/ Capacitación | V85: =IFERROR(IF(AA85="SEGURIDAD",OFFSET('PARÁMETROS'!$K$2,MATCH(U85,JC_SE,0),MATCH(T85,CC_SE,0)), IF(OR(AA85="DSRC/Estratégico",AA85="DSRC/Operativo"),OFFSET('PARÁMETROS'!$K$11,MATCH(U85,JC_DS,0),MATCH(T85,CC_DS,0)), IF(AA85="SALUD",OFFSET('PARÁMETROS'!$K$29,MATCH(U85,JC_SA,0),MATCH(T85,CC_SA,0)), IF(AA85="MEDIO AMBIENTE",OFFSET('PARÁMETROS'!$K$20,MATCH(U85,JC_MA,0),MATCH(T85,CC_MA,0)), IF(AA85="Rel. Gubernamentales",OFFSET('PARÁMETROS'!$K$48,MATCH(U85,JC_G,0),MATCH(T85,CC_G,0)), IF(AA85="OPERACIONAL",OFFSET('PARÁMETROS'!$K$56,MATCH(U85,JC_OP,0),MATCH(T85,CC_OP,0)), IF(AA85="FINANCIERO",OFFSET('PARÁMETROS'!$K$56,MATCH(U85,JC_FI,0),MATCH(T85,CC_FI,0)), OFFSET('PARÁMETROS'!$K$38,MATCH(U85,JC_L,0),MATCH(T85,CC_L,0))))))))),"") -> Control/Acción Eficaz | Z85: El formulario de inspeccion de equipos de soldar es el 1.02.P06.F42 | AA85: =E83 -> Seguridad
P86: Controles de Ingeniería | Q86: Ejecutar plan de mantenimiento de equipos (equipos de soldar) | R86: Planes / Programas | S86: Seguimiento al programa de mantenimientos de equipos/ vehículos | T86: A. Mayor 80% | U86: 4. Ingeniería | V86: =IFERROR(IF(AA86="SEGURIDAD",OFFSET('PARÁMETROS'!$K$2,MATCH(U86,JC_SE,0),MATCH(T86,CC_SE,0)), IF(OR(AA86="DSRC/Estratégico",AA86="DSRC/Operativo"),OFFSET('PARÁMETROS'!$K$11,MATCH(U86,JC_DS,0),MATCH(T86,CC_DS,0)), IF(AA86="SALUD",OFFSET('PARÁMETROS'!$K$29,MATCH(U86,JC_SA,0),MATCH(T86,CC_SA,0)), IF(AA86="MEDIO AMBIENTE",OFFSET('PARÁMETROS'!$K$20,MATCH(U86,JC_MA,0),MATCH(T86,CC_MA,0)), IF(AA86="Rel. Gubernamentales",OFFSET('PARÁMETROS'!$K$48,MATCH(U86,JC_G,0),MATCH(T86,CC_G,0)), IF(AA86="OPERACIONAL",OFFSET('PARÁMETROS'!$K$56,MATCH(U86,JC_OP,0),MATCH(T86,CC_OP,0)), IF(AA86="FINANCIERO",OFFSET('PARÁMETROS'!$K$56,MATCH(U86,JC_FI,0),MATCH(T86,CC_FI,0)), OFFSET('PARÁMETROS'!$K$38,MATCH(U86,JC_L,0),MATCH(T86,CC_L,0))))))))),"") -> Control/Acción Eficaz | Z86: OK | AA86: =E83 -> Seguridad
P87: Capacitación/Entrenamiento | Q87: Difundir hoja ZAP SI-037 "Seguridad en la soldadura al arco " | R87: Planillas de vigencia de Certificaciones / Competencias/ Capacitaciones | S87: Seguimiento al programa de reuniones y evaluaciones de compromiso con la seguridad | T87: B. 50% y 80% | U87: 2. Administrativo/ Procedimientos/ Capacitación | V87: =IFERROR(IF(AA87="SEGURIDAD",OFFSET('PARÁMETROS'!$K$2,MATCH(U87,JC_SE,0),MATCH(T87,CC_SE,0)), IF(OR(AA87="DSRC/Estratégico",AA87="DSRC/Operativo"),OFFSET('PARÁMETROS'!$K$11,MATCH(U87,JC_DS,0),MATCH(T87,CC_DS,0)), IF(AA87="SALUD",OFFSET('PARÁMETROS'!$K$29,MATCH(U87,JC_SA,0),MATCH(T87,CC_SA,0)), IF(AA87="MEDIO AMBIENTE",OFFSET('PARÁMETROS'!$K$20,MATCH(U87,JC_MA,0),MATCH(T87,CC_MA,0)), IF(AA87="Rel. Gubernamentales",OFFSET('PARÁMETROS'!$K$48,MATCH(U87,JC_G,0),MATCH(T87,CC_G,0)), IF(AA87="OPERACIONAL",OFFSET('PARÁMETROS'!$K$56,MATCH(U87,JC_OP,0),MATCH(T87,CC_OP,0)), IF(AA87="FINANCIERO",OFFSET('PARÁMETROS'!$K$56,MATCH(U87,JC_FI,0),MATCH(T87,CC_FI,0)), OFFSET('PARÁMETROS'!$K$38,MATCH(U87,JC_L,0),MATCH(T87,CC_L,0))))))))),"") -> Control/Acción Satisfactorio | Z87: OK | AA87: =E83 -> Seguridad
P88: E.P.P. | Q88: Usar EPP para trabajos en caliente (soldadura), chaqueta de cuero, pantalón de cuero, coleto, guantes de caña larga de soldador, protección respiratoria, polainas y botines de seguridad | R88: Publicación de Indicadores | S88: Seguimiento y publicación de reporte STOP o Seguimiento y publicación de reporte de observaciones conductuales | T88: A. Mayor 80% | U88: 1. EPP | V88: =IFERROR(IF(AA88="SEGURIDAD",OFFSET('PARÁMETROS'!$K$2,MATCH(U88,JC_SE,0),MATCH(T88,CC_SE,0)), IF(OR(AA88="DSRC/Estratégico",AA88="DSRC/Operativo"),OFFSET('PARÁMETROS'!$K$11,MATCH(U88,JC_DS,0),MATCH(T88,CC_DS,0)), IF(AA88="SALUD",OFFSET('PARÁMETROS'!$K$29,MATCH(U88,JC_SA,0),MATCH(T88,CC_SA,0)), IF(AA88="MEDIO AMBIENTE",OFFSET('PARÁMETROS'!$K$20,MATCH(U88,JC_MA,0),MATCH(T88,CC_MA,0)), IF(AA88="Rel. Gubernamentales",OFFSET('PARÁMETROS'!$K$48,MATCH(U88,JC_G,0),MATCH(T88,CC_G,0)), IF(AA88="OPERACIONAL",OFFSET('PARÁMETROS'!$K$56,MATCH(U88,JC_OP,0),MATCH(T88,CC_OP,0)), IF(AA88="FINANCIERO",OFFSET('PARÁMETROS'!$K$56,MATCH(U88,JC_FI,0),MATCH(T88,CC_FI,0)), OFFSET('PARÁMETROS'!$K$38,MATCH(U88,JC_L,0),MATCH(T88,CC_L,0))))))))),"") -> Control/Acción Satisfactorio | Z88: OK | AA88: =E83 -> Seguridad
P89: Procedimientos / Instructivos / Reglamentos y otros. | Q89: Implementar formularios ART/VPT según Guía para la Identificación y Evaluación de Riesgos 1.02.P06.I01 para realizar trabajo de Desmontaje y montaje de componentes del Chancador Primario (araña, cóncavos, eje principal) | R89: Publicación de Indicadores | S89: Seguimiento y publicación de reporte STOP o Seguimiento y publicación de reporte de observaciones conductuales | T89: A. Mayor 80% | U89: 2. Administrativo/ Procedimientos/ Capacitación | V89: =IFERROR(IF(AA89="SEGURIDAD",OFFSET('PARÁMETROS'!$K$2,MATCH(U89,JC_SE,0),MATCH(T89,CC_SE,0)), IF(OR(AA89="DSRC/Estratégico",AA89="DSRC/Operativo"),OFFSET('PARÁMETROS'!$K$11,MATCH(U89,JC_DS,0),MATCH(T89,CC_DS,0)), IF(AA89="SALUD",OFFSET('PARÁMETROS'!$K$29,MATCH(U89,JC_SA,0),MATCH(T89,CC_SA,0)), IF(AA89="MEDIO AMBIENTE",OFFSET('PARÁMETROS'!$K$20,MATCH(U89,JC_MA,0),MATCH(T89,CC_MA,0)), IF(AA89="Rel. Gubernamentales",OFFSET('PARÁMETROS'!$K$48,MATCH(U89,JC_G,0),MATCH(T89,CC_G,0)), IF(AA89="OPERACIONAL",OFFSET('PARÁMETROS'!$K$56,MATCH(U89,JC_OP,0),MATCH(T89,CC_OP,0)), IF(AA89="FINANCIERO",OFFSET('PARÁMETROS'!$K$56,MATCH(U89,JC_FI,0),MATCH(T89,CC_FI,0)), OFFSET('PARÁMETROS'!$K$38,MATCH(U89,JC_L,0),MATCH(T89,CC_L,0))))))))),"") -> Control/Acción Eficaz | Z89: OK | AA89: =E83 -> Seguridad
A90: 9 | B90: Mantenimiento Chancador | C90: Desmontaje y montaje de componentes del Chancador Primario (araña, cóncavos, eje principal) | D90: Normal | E90: Seguridad | F90: Agentes Físicos (ruido) | G90: Generación de ruido durante uso arco eléctrico, oxiflama | H90: Exposición a Ruido | I90: Perdida auditiva inducida por el ruido | J90: 5 | K90: 3 | L90: =IF(OR(J90<>"",K90<>""),OFFSET('PARÁMETROS'!$B$2,K90,J90),"") -> 2 | M90: 4 | N90: =IFERROR(L90*M90,"") -> 8 | O90: =IF(N90="","",IFERROR(IF(N90<=2,"ACEPTABLE",IF(N90<=6,"BAJA",IF(N90<=10,"ACEPTABLE CON REVISIÓN",IF(N90<=15,"SUSTANCIAL","INACEPTABLE")))),"")) -> ACEPTABLE CON REVISIÓN | P90: E.P.P. | Q90: Usar EPP básico y adicional (Casco, botines de Seguridad, Lentes) y protección auditiva | R90: Publicación de Indicadores | S90: Seguimiento y publicación de reporte STOP o Seguimiento y publicación de reporte de observaciones conductuales | T90: A. Mayor 80% | U90: 1. EPP | V90: =IFERROR(IF(AA90="SEGURIDAD",OFFSET('PARÁMETROS'!$K$2,MATCH(U90,JC_SE,0),MATCH(T90,CC_SE,0)), IF(OR(AA90="DSRC/Estratégico",AA90="DSRC/Operativo"),OFFSET('PARÁMETROS'!$K$11,MATCH(U90,JC_DS,0),MATCH(T90,CC_DS,0)), IF(AA90="SALUD",OFFSET('PARÁMETROS'!$K$29,MATCH(U90,JC_SA,0),MATCH(T90,CC_SA,0)), IF(AA90="MEDIO AMBIENTE",OFFSET('PARÁMETROS'!$K$20,MATCH(U90,JC_MA,0),MATCH(T90,CC_MA,0)), IF(AA90="Rel. Gubernamentales",OFFSET('PARÁMETROS'!$K$48,MATCH(U90,JC_G,0),MATCH(T90,CC_G,0)), IF(AA90="OPERACIONAL",OFFSET('PARÁMETROS'!$K$56,MATCH(U90,JC_OP,0),MATCH(T90,CC_OP,0)), IF(AA90="FINANCIERO",OFFSET('PARÁMETROS'!$K$56,MATCH(U90,JC_FI,0),MATCH(T90,CC_FI,0)), OFFSET('PARÁMETROS'!$K$38,MATCH(U90,JC_L,0),MATCH(T90,CC_L,0))))))))),"") -> Control/Acción Satisfactorio | W90: =IF(E90="","", IF(COUNTA( V90:V93)-COUNTBLANK( V90:V93)=1, IF(O90="INACEPTABLE",IF(COUNTIF( V90:V93,"Control/Acción Eficaz")>=1,"SUSTANCIAL","INACEPTABLE"), IF(O90="SUSTANCIAL",IF(COUNTIF( V90:V93,"Control/Acción Eficaz")>=1,"ACEPTABLE CON REVISIÓN","SUSTANCIAL"), IF(O90="ACEPTABLE CON REVISIÓN",IF(COUNTIF( V90:V93,"Control/Acción Eficaz")>=1,"BAJA","ACEPTABLE CON REVISIÓN"), IF(O90="BAJA",IF(COUNTIF( V90:V93,"Control/Acción Eficaz")>=1,"ACEPTABLE","BAJA"),)))), IF(COUNTA( V90:V93)-COUNTBLANK( V90:V93)=2, IF(O90="INACEPTABLE",IF(COUNTIF( V90:V93,"Control/Acción Eficaz")=2,"ACEPTABLE CON REVISIÓN", IF(OR(AND(COUNTIF( V90:V93,"Control/Acción Eficaz")=1,COUNTIF( V90:V93,"Control/Acción Satisfactorio")=1), AND(COUNTIF( V90:V93,"Control/Acción Eficaz")=1,COUNTIF( V90:V93,"Control/Acción No Eficaz")=1)),"SUSTANCIAL","INACEPTABLE")), IF(O90="SUSTANCIAL",IF(COUNTIF( V90:V93,"Control/Acción Eficaz")=2,"BAJA", IF(OR(AND(COUNTIF( V90:V93,"Control/Acción Eficaz")=1,COUNTIF( V90:V93,"Control/Acción Satisfactorio")=1), AND(COUNTIF( V90:V93,"Control/Acción Eficaz")=1,COUNTIF( V90:V93,"Control/Acción No Eficaz")=1)),"ACEPTABLE CON REVISIÓN ","SUSTANCIAL")), IF(O90="ACEPTABLE CON REVISIÓN",IF(COUNTIF( V90:V93,"Control/Acción Eficaz")=2,"ACEPTABLE", IF(OR(AND(COUNTIF( V90:V93,"Control/Acción Eficaz")=1,COUNTIF( V90:V93,"Control/Acción Satisfactorio")=1), AND(COUNTIF( V90:V93,"Control/Acción Eficaz")=1,COUNTIF( V90:V93,"Control/Acción No Eficaz")=1)),"BAJA","ACEPTABLE CON REVISIÓN")), IF(O90="BAJA",IF(COUNTIF( V90:V93,"Control/Acción Eficaz")>=2,"ACEPTABLE","BAJA"),)))), IF(COUNTA( V90:V93)-COUNTBLANK( V90:V93)>=3, IF(O90="INACEPTABLE", IF(COUNTBLANK( V90:V93)=COUNTA( V90:V93),"", IF(COUNTIF( V90:V93,"Control/Acción No Eficaz")>=2,"INACEPTABLE", IF(AND(COUNTIF( V90:V93,"Control/Acción No Eficaz")=0,COUNTIF( V90:V93,"Control/Acción Eficaz")>=2),"ACEPTABLE CON REVISIÓN ","SUSTANCIAL"))), IF(O90="SUSTANCIAL", IF(COUNTBLANK( V90:V93)=COUNTA( V90:V93),"", IF(COUNTIF( V90:V93,"Control/Acción No Eficaz")>=2,"SUSTANCIAL", IF(AND(COUNTIF( V90:V93,"Control/Acción No Eficaz")=0,COUNTIF( V90:V93,"Control/Acción Eficaz")>=2),"BAJA","ACEPTABLE CON REVISIÓN"))), IF(O90="ACEPTABLE CON REVISIÓN", IF(COUNTBLANK( V90:V93)=COUNTA( V90:V93),"", IF(COUNTIF( V90:V93,"Control/Acción No Eficaz")>=2,"ACEPTABLE CON REVISIÓN", IF(AND(COUNTIF( V90:V93,"Control/Acción No Eficaz")=0,COUNTIF( V90:V93,"Control/Acción Eficaz")>=2),"ACEPTABLE","BAJA"))), IF(O90="BAJA", IF(COUNTBLANK( V90:V93)=COUNTA( V90:V93),"", IF(AND(COUNTBLANK( V90:V93)<1,COUNTA( V90:V93)=1), IF(COUNTIF( V90:V93,"Control/Acción No Eficaz")>=2,"BAJA", IF(AND(COUNTIF( V90:V93,"Control/Acción No Eficaz")=0,COUNTIF( V90:V93,"Control/Acción Eficaz")>=2),"ACEPTABLE","BAJA")), IF(COUNTIF( V90:V93,"Control/Acción No Eficaz")>=2,"BAJA", IF(AND(COUNTIF( V90:V93,"Control/Acción No Eficaz")=0,COUNTIF( V90:V93,"Control/Acción Eficaz")>=2),"ACEPTABLE","BAJA")))), IF(COUNTIF( V90:V93,"")>=5,"",O90))))), "")))) -> ACEPTABLE | Z90: OK | AA90: =E90 -> Seguridad
P91: Controles de Salud Ocupacional | Q91: Realizar la evaluación de Salud Ocupacional al personal. | R91: Planes / Programas | S91: Seguimiento a los programas preventivos y de control en salud | T91: A. Mayor 80% | U91: 2. Administrativo/ Procedimientos/ Capacitación | V91: =IFERROR(IF(AA91="SEGURIDAD",OFFSET('PARÁMETROS'!$K$2,MATCH(U91,JC_SE,0),MATCH(T91,CC_SE,0)), IF(OR(AA91="DSRC/Estratégico",AA91="DSRC/Operativo"),OFFSET('PARÁMETROS'!$K$11,MATCH(U91,JC_DS,0),MATCH(T91,CC_DS,0)), IF(AA91="SALUD",OFFSET('PARÁMETROS'!$K$29,MATCH(U91,JC_SA,0),MATCH(T91,CC_SA,0)), IF(AA91="MEDIO AMBIENTE",OFFSET('PARÁMETROS'!$K$20,MATCH(U91,JC_MA,0),MATCH(T91,CC_MA,0)), IF(AA91="Rel. Gubernamentales",OFFSET('PARÁMETROS'!$K$48,MATCH(U91,JC_G,0),MATCH(T91,CC_G,0)), IF(AA91="OPERACIONAL",OFFSET('PARÁMETROS'!$K$56,MATCH(U91,JC_OP,0),MATCH(T91,CC_OP,0)), IF(AA91="FINANCIERO",OFFSET('PARÁMETROS'!$K$56,MATCH(U91,JC_FI,0),MATCH(T91,CC_FI,0)), OFFSET('PARÁMETROS'!$K$38,MATCH(U91,JC_L,0),MATCH(T91,CC_L,0))))))))),"") -> Control/Acción Eficaz | Z91: OK | AA91: =E90 -> Seguridad
P92: Capacitación/Entrenamiento | Q92: Difundir hoja ZAP SI-057 "Protección de los oídos " | R92: Planillas de vigencia de Certificaciones / Competencias/ Capacitaciones | S92: Seguimiento al programa de reuniones y evaluaciones de compromiso con la seguridad | T92: B. 50% y 80% | U92: 2. Administrativo/ Procedimientos/ Capacitación | V92: =IFERROR(IF(AA92="SEGURIDAD",OFFSET('PARÁMETROS'!$K$2,MATCH(U92,JC_SE,0),MATCH(T92,CC_SE,0)), IF(OR(AA92="DSRC/Estratégico",AA92="DSRC/Operativo"),OFFSET('PARÁMETROS'!$K$11,MATCH(U92,JC_DS,0),MATCH(T92,CC_DS,0)), IF(AA92="SALUD",OFFSET('PARÁMETROS'!$K$29,MATCH(U92,JC_SA,0),MATCH(T92,CC_SA,0)), IF(AA92="MEDIO AMBIENTE",OFFSET('PARÁMETROS'!$K$20,MATCH(U92,JC_MA,0),MATCH(T92,CC_MA,0)), IF(AA92="Rel. Gubernamentales",OFFSET('PARÁMETROS'!$K$48,MATCH(U92,JC_G,0),MATCH(T92,CC_G,0)), IF(AA92="OPERACIONAL",OFFSET('PARÁMETROS'!$K$56,MATCH(U92,JC_OP,0),MATCH(T92,CC_OP,0)), IF(AA92="FINANCIERO",OFFSET('PARÁMETROS'!$K$56,MATCH(U92,JC_FI,0),MATCH(T92,CC_FI,0)), OFFSET('PARÁMETROS'!$K$38,MATCH(U92,JC_L,0),MATCH(T92,CC_L,0))))))))),"") -> Control/Acción Satisfactorio | Z92: OK
P93: Procedimientos / Instructivos / Reglamentos y otros. | Q93: Implementar formularios ART/VPT según Guía para la Identificación y Evaluación de Riesgos 1.02.P06.I01 para realizar trabajo de Desmontaje y montaje de componentes del Chancador Primario (araña, cóncavos, eje principal) | R93: Publicación de Indicadores | S93: Seguimiento y publicación de reporte STOP o Seguimiento y publicación de reporte de observaciones conductuales | T93: A. Mayor 80% | U93: 2. Administrativo/ Procedimientos/ Capacitación | V93: =IFERROR(IF(AA93="SEGURIDAD",OFFSET('PARÁMETROS'!$K$2,MATCH(U93,JC_SE,0),MATCH(T93,CC_SE,0)), IF(OR(AA93="DSRC/Estratégico",AA93="DSRC/Operativo"),OFFSET('PARÁMETROS'!$K$11,MATCH(U93,JC_DS,0),MATCH(T93,CC_DS,0)), IF(AA93="SALUD",OFFSET('PARÁMETROS'!$K$29,MATCH(U93,JC_SA,0),MATCH(T93,CC_SA,0)), IF(AA93="MEDIO AMBIENTE",OFFSET('PARÁMETROS'!$K$20,MATCH(U93,JC_MA,0),MATCH(T93,CC_MA,0)), IF(AA93="Rel. Gubernamentales",OFFSET('PARÁMETROS'!$K$48,MATCH(U93,JC_G,0),MATCH(T93,CC_G,0)), IF(AA93="OPERACIONAL",OFFSET('PARÁMETROS'!$K$56,MATCH(U93,JC_OP,0),MATCH(T93,CC_OP,0)), IF(AA93="FINANCIERO",OFFSET('PARÁMETROS'!$K$56,MATCH(U93,JC_FI,0),MATCH(T93,CC_FI,0)), OFFSET('PARÁMETROS'!$K$38,MATCH(U93,JC_L,0),MATCH(T93,CC_L,0))))))))),"") -> Control/Acción Eficaz | Z93: OK | AA93: =E90 -> Seguridad
A94: 10 | B94: Mantenimiento Chancador | C94: Desmontaje y montaje de componentes del Chancador Primario (araña, cóncavos, eje principal) | D94: Normal | E94: Seguridad | F94: Desorden y falta de limpieza | G94: Generación de polvo de epóxico durante retiro de material | H94: Exposición a Material Particulado | I94: Inhalación de epóxico, sensibilización , enfermedades respiratorias | J94: 4 | K94: 3 | L94: =IF(OR(J94<>"",K94<>""),OFFSET('PARÁMETROS'!$B$2,K94,J94),"") -> 3 | M94: 1 | N94: =IFERROR(L94*M94,"") -> 3 | O94: =IF(N94="","",IFERROR(IF(N94<=2,"ACEPTABLE",IF(N94<=6,"BAJA",IF(N94<=10,"ACEPTABLE CON REVISIÓN",IF(N94<=15,"SUSTANCIAL","INACEPTABLE")))),"")) -> BAJA | P94: E.P.P. | Q94: Usar EPP básico y adicional (Casco, botines de Seguridad, Lentes) y protector respiratorio (8210 polvo o 8515 gases, humos) | R94: Publicación de Indicadores | S94: Seguimiento y publicación de reporte STOP o Seguimiento y publicación de reporte de observaciones conductuales | T94: A. Mayor 80% | U94: 1. EPP | V94: =IFERROR(IF(AA94="SEGURIDAD",OFFSET('PARÁMETROS'!$K$2,MATCH(U94,JC_SE,0),MATCH(T94,CC_SE,0)), IF(OR(AA94="DSRC/Estratégico",AA94="DSRC/Operativo"),OFFSET('PARÁMETROS'!$K$11,MATCH(U94,JC_DS,0),MATCH(T94,CC_DS,0)), IF(AA94="SALUD",OFFSET('PARÁMETROS'!$K$29,MATCH(U94,JC_SA,0),MATCH(T94,CC_SA,0)), IF(AA94="MEDIO AMBIENTE",OFFSET('PARÁMETROS'!$K$20,MATCH(U94,JC_MA,0),MATCH(T94,CC_MA,0)), IF(AA94="Rel. Gubernamentales",OFFSET('PARÁMETROS'!$K$48,MATCH(U94,JC_G,0),MATCH(T94,CC_G,0)), IF(AA94="OPERACIONAL",OFFSET('PARÁMETROS'!$K$56,MATCH(U94,JC_OP,0),MATCH(T94,CC_OP,0)), IF(AA94="FINANCIERO",OFFSET('PARÁMETROS'!$K$56,MATCH(U94,JC_FI,0),MATCH(T94,CC_FI,0)), OFFSET('PARÁMETROS'!$K$38,MATCH(U94,JC_L,0),MATCH(T94,CC_L,0))))))))),"") -> Control/Acción Satisfactorio | W94: =IF(E94="","", IF(COUNTA( V94)-COUNTBLANK( V94)=1, IF(O94="INACEPTABLE",IF(COUNTIF( V94,"Control/Acción Eficaz")>=1,"SUSTANCIAL","INACEPTABLE"), IF(O94="SUSTANCIAL",IF(COUNTIF( V94,"Control/Acción Eficaz")>=1,"ACEPTABLE CON REVISIÓN","SUSTANCIAL"), IF(O94="ACEPTABLE CON REVISIÓN",IF(COUNTIF( V94,"Control/Acción Eficaz")>=1,"BAJA","ACEPTABLE CON REVISIÓN"), IF(O94="BAJA",IF(COUNTIF( V94,"Control/Acción Eficaz")>=1,"ACEPTABLE","BAJA"),)))), IF(COUNTA( V94)-COUNTBLANK( V94)=2, IF(O94="INACEPTABLE",IF(COUNTIF( V94,"Control/Acción Eficaz")=2,"ACEPTABLE CON REVISIÓN", IF(OR(AND(COUNTIF( V94,"Control/Acción Eficaz")=1,COUNTIF( V94,"Control/Acción Satisfactorio")=1), AND(COUNTIF( V94,"Control/Acción Eficaz")=1,COUNTIF( V94,"Control/Acción No Eficaz")=1)),"SUSTANCIAL","INACEPTABLE")), IF(O94="SUSTANCIAL",IF(COUNTIF( V94,"Control/Acción Eficaz")=2,"BAJA", IF(OR(AND(COUNTIF( V94,"Control/Acción Eficaz")=1,COUNTIF( V94,"Control/Acción Satisfactorio")=1), AND(COUNTIF( V94,"Control/Acción Eficaz")=1,COUNTIF( V94,"Control/Acción No Eficaz")=1)),"ACEPTABLE CON REVISIÓN ","SUSTANCIAL")), IF(O94="ACEPTABLE CON REVISIÓN",IF(COUNTIF( V94,"Control/Acción Eficaz")=2,"ACEPTABLE", IF(OR(AND(COUNTIF( V94,"Control/Acción Eficaz")=1,COUNTIF( V94,"Control/Acción Satisfactorio")=1), AND(COUNTIF( V94,"Control/Acción Eficaz")=1,COUNTIF( V94,"Control/Acción No Eficaz")=1)),"BAJA","ACEPTABLE CON REVISIÓN")), IF(O94="BAJA",IF(COUNTIF( V94,"Control/Acción Eficaz")>=2,"ACEPTABLE","BAJA"),)))), IF(COUNTA( V94)-COUNTBLANK( V94)>=3, IF(O94="INACEPTABLE", IF(COUNTBLANK( V94)=COUNTA( V94),"", IF(COUNTIF( V94,"Control/Acción No Eficaz")>=2,"INACEPTABLE", IF(AND(COUNTIF( V94,"Control/Acción No Eficaz")=0,COUNTIF( V94,"Control/Acción Eficaz")>=2),"ACEPTABLE CON REVISIÓN ","SUSTANCIAL"))), IF(O94="SUSTANCIAL", IF(COUNTBLANK( V94)=COUNTA( V94),"", IF(COUNTIF( V94,"Control/Acción No Eficaz")>=2,"SUSTANCIAL", IF(AND(COUNTIF( V94,"Control/Acción No Eficaz")=0,COUNTIF( V94,"Control/Acción Eficaz")>=2),"BAJA","ACEPTABLE CON REVISIÓN"))), IF(O94="ACEPTABLE CON REVISIÓN", IF(COUNTBLANK( V94)=COUNTA( V94),"", IF(COUNTIF( V94,"Control/Acción No Eficaz")>=2,"ACEPTABLE CON REVISIÓN", IF(AND(COUNTIF( V94,"Control/Acción No Eficaz")=0,COUNTIF( V94,"Control/Acción Eficaz")>=2),"ACEPTABLE","BAJA"))), IF(O94="BAJA", IF(COUNTBLANK( V94)=COUNTA( V94),"", IF(AND(COUNTBLANK( V94)<1,COUNTA( V94)=1), IF(COUNTIF( V94,"Control/Acción No Eficaz")>=2,"BAJA", IF(AND(COUNTIF( V94,"Control/Acción No Eficaz")=0,COUNTIF( V94,"Control/Acción Eficaz")>=2),"ACEPTABLE","BAJA")), IF(COUNTIF( V94,"Control/Acción No Eficaz")>=2,"BAJA", IF(AND(COUNTIF( V94,"Control/Acción No Eficaz")=0,COUNTIF( V94,"Control/Acción Eficaz")>=2),"ACEPTABLE","BAJA")))), IF(COUNTIF( V94,"")>=5,"",O94))))), "")))) -> BAJA | Z94: OK | AA94: =E94 -> Seguridad
A95: 11 | B95: Mantenimiento Chancador | C95: Desmontaje y montaje de componentes del Chancador Primario (araña, cóncavos, eje principal) | D95: Normal | E95: Seguridad | F95: Trabajo en caliente (soldadura, corte, desbaste) torchado, arco eléctrico, amolado, esmerilado, oxicorte, oxiflama, etc. | G95: Trabajos de soldadura que generan radiación no ionizante | H95: Exposición a Radiaciones Ionizantes / No ionizantes / UV | I95: Exposición a Rayos Ultra Violeta durante la operación, quemaduras de la piel, ojos, cáncer de piel | J95: 3 | K95: 2 | L95: =IF(OR(J95<>"",K95<>""),OFFSET('PARÁMETROS'!$B$2,K95,J95),"") -> 4 | M95: 4 | N95: =IFERROR(L95*M95,"") -> 16 | O95: =IF(N95="","",IFERROR(IF(N95<=2,"ACEPTABLE",IF(N95<=6,"BAJA",IF(N95<=10,"ACEPTABLE CON REVISIÓN",IF(N95<=15,"SUSTANCIAL","INACEPTABLE")))),"")) -> INACEPTABLE | P95: E.P.P. | Q95: Usar EPP para trabajos en caliente (soldadura), chaqueta de cuero, pantalón de cuero, coleto, guantes de caña larga de soldador, protección respiratoria, mascara de soldar, polainas y botines de seguridad | R95: Publicación de Indicadores | S95: Seguimiento y publicación de reporte STOP o Seguimiento y publicación de reporte de observaciones conductuales | T95: A. Mayor 80% | U95: 1. EPP | V95: =IFERROR(IF(AA95="SEGURIDAD",OFFSET('PARÁMETROS'!$K$2,MATCH(U95,JC_SE,0),MATCH(T95,CC_SE,0)), IF(OR(AA95="DSRC/Estratégico",AA95="DSRC/Operativo"),OFFSET('PARÁMETROS'!$K$11,MATCH(U95,JC_DS,0),MATCH(T95,CC_DS,0)), IF(AA95="SALUD",OFFSET('PARÁMETROS'!$K$29,MATCH(U95,JC_SA,0),MATCH(T95,CC_SA,0)), IF(AA95="MEDIO AMBIENTE",OFFSET('PARÁMETROS'!$K$20,MATCH(U95,JC_MA,0),MATCH(T95,CC_MA,0)), IF(AA95="Rel. Gubernamentales",OFFSET('PARÁMETROS'!$K$48,MATCH(U95,JC_G,0),MATCH(T95,CC_G,0)), IF(AA95="OPERACIONAL",OFFSET('PARÁMETROS'!$K$56,MATCH(U95,JC_OP,0),MATCH(T95,CC_OP,0)), IF(AA95="FINANCIERO",OFFSET('PARÁMETROS'!$K$56,MATCH(U95,JC_FI,0),MATCH(T95,CC_FI,0)), OFFSET('PARÁMETROS'!$K$38,MATCH(U95,JC_L,0),MATCH(T95,CC_L,0))))))))),"") -> Control/Acción Satisfactorio | W95: =IF(E95="","", IF(COUNTA( V95:V97)-COUNTBLANK( V95:V97)=1, IF(O95="INACEPTABLE",IF(COUNTIF( V95:V97,"Control/Acción Eficaz")>=1,"SUSTANCIAL","INACEPTABLE"), IF(O95="SUSTANCIAL",IF(COUNTIF( V95:V97,"Control/Acción Eficaz")>=1,"ACEPTABLE CON REVISIÓN","SUSTANCIAL"), IF(O95="ACEPTABLE CON REVISIÓN",IF(COUNTIF( V95:V97,"Control/Acción Eficaz")>=1,"BAJA","ACEPTABLE CON REVISIÓN"), IF(O95="BAJA",IF(COUNTIF( V95:V97,"Control/Acción Eficaz")>=1,"ACEPTABLE","BAJA"),)))), IF(COUNTA( V95:V97)-COUNTBLANK( V95:V97)=2, IF(O95="INACEPTABLE",IF(COUNTIF( V95:V97,"Control/Acción Eficaz")=2,"ACEPTABLE CON REVISIÓN", IF(OR(AND(COUNTIF( V95:V97,"Control/Acción Eficaz")=1,COUNTIF( V95:V97,"Control/Acción Satisfactorio")=1), AND(COUNTIF( V95:V97,"Control/Acción Eficaz")=1,COUNTIF( V95:V97,"Control/Acción No Eficaz")=1)),"SUSTANCIAL","INACEPTABLE")), IF(O95="SUSTANCIAL",IF(COUNTIF( V95:V97,"Control/Acción Eficaz")=2,"BAJA", IF(OR(AND(COUNTIF( V95:V97,"Control/Acción Eficaz")=1,COUNTIF( V95:V97,"Control/Acción Satisfactorio")=1), AND(COUNTIF( V95:V97,"Control/Acción Eficaz")=1,COUNTIF( V95:V97,"Control/Acción No Eficaz")=1)),"ACEPTABLE CON REVISIÓN ","SUSTANCIAL")), IF(O95="ACEPTABLE CON REVISIÓN",IF(COUNTIF( V95:V97,"Control/Acción Eficaz")=2,"ACEPTABLE", IF(OR(AND(COUNTIF( V95:V97,"Control/Acción Eficaz")=1,COUNTIF( V95:V97,"Control/Acción Satisfactorio")=1), AND(COUNTIF( V95:V97,"Control/Acción Eficaz")=1,COUNTIF( V95:V97,"Control/Acción No Eficaz")=1)),"BAJA","ACEPTABLE CON REVISIÓN")), IF(O95="BAJA",IF(COUNTIF( V95:V97,"Control/Acción Eficaz")>=2,"ACEPTABLE","BAJA"),)))), IF(COUNTA( V95:V97)-COUNTBLANK( V95:V97)>=3, IF(O95="INACEPTABLE", IF(COUNTBLANK( V95:V97)=COUNTA( V95:V97),"", IF(COUNTIF( V95:V97,"Control/Acción No Eficaz")>=2,"INACEPTABLE", IF(AND(COUNTIF( V95:V97,"Control/Acción No Eficaz")=0,COUNTIF( V95:V97,"Control/Acción Eficaz")>=2),"ACEPTABLE CON REVISIÓN ","SUSTANCIAL"))), IF(O95="SUSTANCIAL", IF(COUNTBLANK( V95:V97)=COUNTA( V95:V97),"", IF(COUNTIF( V95:V97,"Control/Acción No Eficaz")>=2,"SUSTANCIAL", IF(AND(COUNTIF( V95:V97,"Control/Acción No Eficaz")=0,COUNTIF( V95:V97,"Control/Acción Eficaz")>=2),"BAJA","ACEPTABLE CON REVISIÓN"))), IF(O95="ACEPTABLE CON REVISIÓN", IF(COUNTBLANK( V95:V97)=COUNTA( V95:V97),"", IF(COUNTIF( V95:V97,"Control/Acción No Eficaz")>=2,"ACEPTABLE CON REVISIÓN", IF(AND(COUNTIF( V95:V97,"Control/Acción No Eficaz")=0,COUNTIF( V95:V97,"Control/Acción Eficaz")>=2),"ACEPTABLE","BAJA"))), IF(O95="BAJA", IF(COUNTBLANK( V95:V97)=COUNTA( V95:V97),"", IF(AND(COUNTBLANK( V95:V97)<1,COUNTA( V95:V97)=1), IF(COUNTIF( V95:V97,"Control/Acción No Eficaz")>=2,"BAJA", IF(AND(COUNTIF( V95:V97,"Control/Acción No Eficaz")=0,COUNTIF( V95:V97,"Control/Acción Eficaz")>=2),"ACEPTABLE","BAJA")), IF(COUNTIF( V95:V97,"Control/Acción No Eficaz")>=2,"BAJA", IF(AND(COUNTIF( V95:V97,"Control/Acción No Eficaz")=0,COUNTIF( V95:V97,"Control/Acción Eficaz")>=2),"ACEPTABLE","BAJA")))), IF(COUNTIF( V95:V97,"")>=5,"",O95))))), "")))) -> SUSTANCIAL | Z95: OK | AA95: =E95 -> Seguridad
P96: Procedimientos / Instructivos / Reglamentos y otros. | Q96: Cumplir con los estandares del Instructivo de Trabajos en Caliente 1.02.P06.I32 | R96: Publicación de Indicadores | S96: Seguimiento y publicación de reporte STOP o Seguimiento y publicación de reporte de observaciones conductuales | T96: A. Mayor 80% | U96: 1. EPP | V96: =IFERROR(IF(AA96="SEGURIDAD",OFFSET('PARÁMETROS'!$K$2,MATCH(U96,JC_SE,0),MATCH(T96,CC_SE,0)), IF(OR(AA96="DSRC/Estratégico",AA96="DSRC/Operativo"),OFFSET('PARÁMETROS'!$K$11,MATCH(U96,JC_DS,0),MATCH(T96,CC_DS,0)), IF(AA96="SALUD",OFFSET('PARÁMETROS'!$K$29,MATCH(U96,JC_SA,0),MATCH(T96,CC_SA,0)), IF(AA96="MEDIO AMBIENTE",OFFSET('PARÁMETROS'!$K$20,MATCH(U96,JC_MA,0),MATCH(T96,CC_MA,0)), IF(AA96="Rel. Gubernamentales",OFFSET('PARÁMETROS'!$K$48,MATCH(U96,JC_G,0),MATCH(T96,CC_G,0)), IF(AA96="OPERACIONAL",OFFSET('PARÁMETROS'!$K$56,MATCH(U96,JC_OP,0),MATCH(T96,CC_OP,0)), IF(AA96="FINANCIERO",OFFSET('PARÁMETROS'!$K$56,MATCH(U96,JC_FI,0),MATCH(T96,CC_FI,0)), OFFSET('PARÁMETROS'!$K$38,MATCH(U96,JC_L,0),MATCH(T96,CC_L,0))))))))),"") -> Control/Acción Satisfactorio | AA96: =E95 -> Seguridad
P97: Procedimientos / Instructivos / Reglamentos y otros. | Q97: Implementar formularios ART/VPT según Guía para la Identificación y Evaluación de Riesgos 1.02.P06.I01 para realizar trabajo de Desmontaje y montaje de componentes del Chancador Primario (araña, cóncavos, eje principal) | R97: Publicación de Indicadores | S97: Seguimiento y publicación de reporte STOP o Seguimiento y publicación de reporte de observaciones conductuales | T97: A. Mayor 80% | U97: 2. Administrativo/ Procedimientos/ Capacitación | V97: =IFERROR(IF(AA97="SEGURIDAD",OFFSET('PARÁMETROS'!$K$2,MATCH(U97,JC_SE,0),MATCH(T97,CC_SE,0)), IF(OR(AA97="DSRC/Estratégico",AA97="DSRC/Operativo"),OFFSET('PARÁMETROS'!$K$11,MATCH(U97,JC_DS,0),MATCH(T97,CC_DS,0)), IF(AA97="SALUD",OFFSET('PARÁMETROS'!$K$29,MATCH(U97,JC_SA,0),MATCH(T97,CC_SA,0)), IF(AA97="MEDIO AMBIENTE",OFFSET('PARÁMETROS'!$K$20,MATCH(U97,JC_MA,0),MATCH(T97,CC_MA,0)), IF(AA97="Rel. Gubernamentales",OFFSET('PARÁMETROS'!$K$48,MATCH(U97,JC_G,0),MATCH(T97,CC_G,0)), IF(AA97="OPERACIONAL",OFFSET('PARÁMETROS'!$K$56,MATCH(U97,JC_OP,0),MATCH(T97,CC_OP,0)), IF(AA97="FINANCIERO",OFFSET('PARÁMETROS'!$K$56,MATCH(U97,JC_FI,0),MATCH(T97,CC_FI,0)), OFFSET('PARÁMETROS'!$K$38,MATCH(U97,JC_L,0),MATCH(T97,CC_L,0))))))))),"") -> Control/Acción Eficaz | Z97: Además de la documentación que se señala (ART/VPT), debe incluirse la obligatoriedad a contar con PT vigente | AA97: =E95 -> Seguridad | AB97: MEDIDA ANTERIOR HACE REFERENCIA AL PT
A98: 12 | B98: Mantenimiento Chancador | C98: Desmontaje y montaje de componentes del Chancador Primario (araña, cóncavos, eje principal) | D98: Normal | E98: Seguridad | F98: Presencia de polvo, material particulado, humo o gas | G98: Generación de humos por el proceso de Soldadura, corte con arco eléctrico, oxiflama | H98: Exposición a Humos Metálicos | I98: Enfermedades respiratorias | J98: 5 | K98: 2 | L98: =IF(OR(J98<>"",K98<>""),OFFSET('PARÁMETROS'!$B$2,K98,J98),"") -> 3 | M98: 4 | N98: =IFERROR(L98*M98,"") -> 12 | O98: =IF(N98="","",IFERROR(IF(N98<=2,"ACEPTABLE",IF(N98<=6,"BAJA",IF(N98<=10,"ACEPTABLE CON REVISIÓN",IF(N98<=15,"SUSTANCIAL","INACEPTABLE")))),"")) -> SUSTANCIAL | P98: E.P.P. | Q98: Usar EPP básico y adicional (Casco, botines de Seguridad, Lentes) y protector respiratorio (8210 polvo o 8515 gases, humos) | R98: Publicación de Indicadores | S98: Seguimiento y publicación de reporte STOP o Seguimiento y publicación de reporte de observaciones conductuales | T98: A. Mayor 80% | U98: 1. EPP | V98: =IFERROR(IF(AA98="SEGURIDAD",OFFSET('PARÁMETROS'!$K$2,MATCH(U98,JC_SE,0),MATCH(T98,CC_SE,0)), IF(OR(AA98="DSRC/Estratégico",AA98="DSRC/Operativo"),OFFSET('PARÁMETROS'!$K$11,MATCH(U98,JC_DS,0),MATCH(T98,CC_DS,0)), IF(AA98="SALUD",OFFSET('PARÁMETROS'!$K$29,MATCH(U98,JC_SA,0),MATCH(T98,CC_SA,0)), IF(AA98="MEDIO AMBIENTE",OFFSET('PARÁMETROS'!$K$20,MATCH(U98,JC_MA,0),MATCH(T98,CC_MA,0)), IF(AA98="Rel. Gubernamentales",OFFSET('PARÁMETROS'!$K$48,MATCH(U98,JC_G,0),MATCH(T98,CC_G,0)), IF(AA98="OPERACIONAL",OFFSET('PARÁMETROS'!$K$56,MATCH(U98,JC_OP,0),MATCH(T98,CC_OP,0)), IF(AA98="FINANCIERO",OFFSET('PARÁMETROS'!$K$56,MATCH(U98,JC_FI,0),MATCH(T98,CC_FI,0)), OFFSET('PARÁMETROS'!$K$38,MATCH(U98,JC_L,0),MATCH(T98,CC_L,0))))))))),"") -> Control/Acción Satisfactorio | W98: =IF(E98="","", IF(COUNTA( V98:V102)-COUNTBLANK( V98:V102)=1, IF(O98="INACEPTABLE",IF(COUNTIF( V98:V102,"Control/Acción Eficaz")>=1,"SUSTANCIAL","INACEPTABLE"), IF(O98="SUSTANCIAL",IF(COUNTIF( V98:V102,"Control/Acción Eficaz")>=1,"ACEPTABLE CON REVISIÓN","SUSTANCIAL"), IF(O98="ACEPTABLE CON REVISIÓN",IF(COUNTIF( V98:V102,"Control/Acción Eficaz")>=1,"BAJA","ACEPTABLE CON REVISIÓN"), IF(O98="BAJA",IF(COUNTIF( V98:V102,"Control/Acción Eficaz")>=1,"ACEPTABLE","BAJA"),)))), IF(COUNTA( V98:V102)-COUNTBLANK( V98:V102)=2, IF(O98="INACEPTABLE",IF(COUNTIF( V98:V102,"Control/Acción Eficaz")=2,"ACEPTABLE CON REVISIÓN", IF(OR(AND(COUNTIF( V98:V102,"Control/Acción Eficaz")=1,COUNTIF( V98:V102,"Control/Acción Satisfactorio")=1), AND(COUNTIF( V98:V102,"Control/Acción Eficaz")=1,COUNTIF( V98:V102,"Control/Acción No Eficaz")=1)),"SUSTANCIAL","INACEPTABLE")), IF(O98="SUSTANCIAL",IF(COUNTIF( V98:V102,"Control/Acción Eficaz")=2,"BAJA", IF(OR(AND(COUNTIF( V98:V102,"Control/Acción Eficaz")=1,COUNTIF( V98:V102,"Control/Acción Satisfactorio")=1), AND(COUNTIF( V98:V102,"Control/Acción Eficaz")=1,COUNTIF( V98:V102,"Control/Acción No Eficaz")=1)),"ACEPTABLE CON REVISIÓN ","SUSTANCIAL")), IF(O98="ACEPTABLE CON REVISIÓN",IF(COUNTIF( V98:V102,"Control/Acción Eficaz")=2,"ACEPTABLE", IF(OR(AND(COUNTIF( V98:V102,"Control/Acción Eficaz")=1,COUNTIF( V98:V102,"Control/Acción Satisfactorio")=1), AND(COUNTIF( V98:V102,"Control/Acción Eficaz")=1,COUNTIF( V98:V102,"Control/Acción No Eficaz")=1)),"BAJA","ACEPTABLE CON REVISIÓN")), IF(O98="BAJA",IF(COUNTIF( V98:V102,"Control/Acción Eficaz")>=2,"ACEPTABLE","BAJA"),)))), IF(COUNTA( V98:V102)-COUNTBLANK( V98:V102)>=3, IF(O98="INACEPTABLE", IF(COUNTBLANK( V98:V102)=COUNTA( V98:V102),"", IF(COUNTIF( V98:V102,"Control/Acción No Eficaz")>=2,"INACEPTABLE", IF(AND(COUNTIF( V98:V102,"Control/Acción No Eficaz")=0,COUNTIF( V98:V102,"Control/Acción Eficaz")>=2),"ACEPTABLE CON REVISIÓN ","SUSTANCIAL"))), IF(O98="SUSTANCIAL", IF(COUNTBLANK( V98:V102)=COUNTA( V98:V102),"", IF(COUNTIF( V98:V102,"Control/Acción No Eficaz")>=2,"SUSTANCIAL", IF(AND(COUNTIF( V98:V102,"Control/Acción No Eficaz")=0,COUNTIF( V98:V102,"Control/Acción Eficaz")>=2),"BAJA","ACEPTABLE CON REVISIÓN"))), IF(O98="ACEPTABLE CON REVISIÓN", IF(COUNTBLANK( V98:V102)=COUNTA( V98:V102),"", IF(COUNTIF( V98:V102,"Control/Acción No Eficaz")>=2,"ACEPTABLE CON REVISIÓN", IF(AND(COUNTIF( V98:V102,"Control/Acción No Eficaz")=0,COUNTIF( V98:V102,"Control/Acción Eficaz")>=2),"ACEPTABLE","BAJA"))), IF(O98="BAJA", IF(COUNTBLANK( V98:V102)=COUNTA( V98:V102),"", IF(AND(COUNTBLANK( V98:V102)<1,COUNTA( V98:V102)=1), IF(COUNTIF( V98:V102,"Control/Acción No Eficaz")>=2,"BAJA", IF(AND(COUNTIF( V98:V102,"Control/Acción No Eficaz")=0,COUNTIF( V98:V102,"Control/Acción Eficaz")>=2),"ACEPTABLE","BAJA")), IF(COUNTIF( V98:V102,"Control/Acción No Eficaz")>=2,"BAJA", IF(AND(COUNTIF( V98:V102,"Control/Acción No Eficaz")=0,COUNTIF( V98:V102,"Control/Acción Eficaz")>=2),"ACEPTABLE","BAJA")))), IF(COUNTIF( V98:V102,"")>=5,"",O98))))), "")))) -> BAJA | Z98: OK | AA98: =E98 -> Seguridad
P99: Controles de Salud Ocupacional | Q99: Realizar la evaluación de Salud Ocupacional al personal. | R99: Planes / Programas | S99: Seguimiento a los programas preventivos y de control en salud | T99: A. Mayor 80% | U99: 2. Administrativo/ Procedimientos/ Capacitación | V99: =IFERROR(IF(AA99="SEGURIDAD",OFFSET('PARÁMETROS'!$K$2,MATCH(U99,JC_SE,0),MATCH(T99,CC_SE,0)), IF(OR(AA99="DSRC/Estratégico",AA99="DSRC/Operativo"),OFFSET('PARÁMETROS'!$K$11,MATCH(U99,JC_DS,0),MATCH(T99,CC_DS,0)), IF(AA99="SALUD",OFFSET('PARÁMETROS'!$K$29,MATCH(U99,JC_SA,0),MATCH(T99,CC_SA,0)), IF(AA99="MEDIO AMBIENTE",OFFSET('PARÁMETROS'!$K$20,MATCH(U99,JC_MA,0),MATCH(T99,CC_MA,0)), IF(AA99="Rel. Gubernamentales",OFFSET('PARÁMETROS'!$K$48,MATCH(U99,JC_G,0),MATCH(T99,CC_G,0)), IF(AA99="OPERACIONAL",OFFSET('PARÁMETROS'!$K$56,MATCH(U99,JC_OP,0),MATCH(T99,CC_OP,0)), IF(AA99="FINANCIERO",OFFSET('PARÁMETROS'!$K$56,MATCH(U99,JC_FI,0),MATCH(T99,CC_FI,0)), OFFSET('PARÁMETROS'!$K$38,MATCH(U99,JC_L,0),MATCH(T99,CC_L,0))))))))),"") -> Control/Acción Eficaz | Z99: OK | AA99: =E98 -> Seguridad
P100: Controles de Ingeniería | Q100: Contar con mamparas, biombos en torno al área de trabajo y/o manta ignífuga para proteger los dispositivos. | R100: Planes / Programas | S100: Seguimiento al programa de inspecciones IRO´S: Trabajos en Caliente | T100: A. Mayor 80% | U100: 4. Ingeniería | V100: =IFERROR(IF(AA100="SEGURIDAD",OFFSET('PARÁMETROS'!$K$2,MATCH(U100,JC_SE,0),MATCH(T100,CC_SE,0)), IF(OR(AA100="DSRC/Estratégico",AA100="DSRC/Operativo"),OFFSET('PARÁMETROS'!$K$11,MATCH(U100,JC_DS,0),MATCH(T100,CC_DS,0)), IF(AA100="SALUD",OFFSET('PARÁMETROS'!$K$29,MATCH(U100,JC_SA,0),MATCH(T100,CC_SA,0)), IF(AA100="MEDIO AMBIENTE",OFFSET('PARÁMETROS'!$K$20,MATCH(U100,JC_MA,0),MATCH(T100,CC_MA,0)), IF(AA100="Rel. Gubernamentales",OFFSET('PARÁMETROS'!$K$48,MATCH(U100,JC_G,0),MATCH(T100,CC_G,0)), IF(AA100="OPERACIONAL",OFFSET('PARÁMETROS'!$K$56,MATCH(U100,JC_OP,0),MATCH(T100,CC_OP,0)), IF(AA100="FINANCIERO",OFFSET('PARÁMETROS'!$K$56,MATCH(U100,JC_FI,0),MATCH(T100,CC_FI,0)), OFFSET('PARÁMETROS'!$K$38,MATCH(U100,JC_L,0),MATCH(T100,CC_L,0))))))))),"") -> Control/Acción Eficaz | Z100: OK | AA100: =E98 -> Seguridad
...

Sheet PARÁMETROS
A1: C. Probabilidad (A x B) | J1: Jerarquía del Control | K1: Calidad del Control
B2: A. Exposición | C2: 1 | D2: 2 | E2: 3 | F2: 4 | G2: 5 | H2: 6 | K2: Efectividad del Control | L2: C. Menor a 50% | M2: B. 50% y 80% | N2: A. Mayor 80% | P2: FAMILIA DE PELIGROS - SEGURIDAD | R2: FAMILIA DE RIESGOS - SEGURIDAD | T2: FAMILIA DE CONTROLES/ACCIONES - SEGURIDAD | V2: FAMILIA DE VERIFICADORES - SEGURIDAD | X2: Verificadores | Z2: FAMILIA DE ASPECTOS - MEDIO AMBIENTE | AB2: FAMILIA DE IMPACTOS - MEDIO AMBIENTE | AD2: FAMILIA DE CONTROLES - MEDIO AMBIENTE | AF2: FAMILIA DE VERIFICADORES - MEDIO AMBIENTE | AH2: FAMILIA PELIGROS - SALUD | AJ2: FAMILIA RIESGOS - SALUD | AL2: FAMILIA CONTROLES - SALUD | AN2: FAMILIA DE VERIFICADORES - SALUD | AP2: FAMILIA PELIGROS - LEGAL | AR2: FAMILIA RIESGOS - LEGAL | AT2: FAMILIA CONTROLES - LEGAL | AV2: FAMILIA VERIFICADORES - LEGAL | AX2: FAMILIA DE PELIGROS DSRC | AZ2: FAMILIA RIESGOS - DSRC | BB2: FAMILIA CONTROLES - DSRC | BD2: FAMILIA VERIFICADORES - DSRC | BF2: FAMILIA DE PELIGROS RG | BH2: FAMILIA RIESGOS - RG | BJ2: FAMILIA CONTROLES - RG | BL2: FAMILIA VERIFICADORES - RG | BN2: FAMILIA DE PELIGROS OPERACIONAL | BP2: FAMILIA RIESGOS OPERACIONAL | BR2: FAMILIA CONTROLES OPERACIONALES | BT2: FAMILIA VERIFICADORES OPERACIONALES | BV2: FAMILIA DE PELIGROS - FINANCIEROS | BX2: FAMILIA RIESGOS FINANCIEROS | BZ2: FAMILIA CONTROLES FINANCIEROS | CB2: FAMILIA VERIFICADORES FINANCIEROS
A3: B. Posibilidad | B3: 1 | C3: 5 | D3: 5 | E3: 4 | F3: 4 | G3: 3 | H3: 3 | K3: 6. Eliminación | L3: Control/Acción Satisfactorio | M3: Control/Acción Satisfactorio | N3: Control/Acción Eficaz | P3: Agentes Biológicos (animales, insectos, bacterias, virus, etc.) | R3: Aplastamiento | T3: Eliminación | V3: Planilla de vigencia de Autorizaciones, Permisos y Licencias (Gubernamentales, legales, normativos) | X3: Seguimiento a la Planilla de vigencia de cursos, autorizaciones, competencias y/o certificaciones de personas y equipos | Z3: Cambio de uso de suelo natural por actividad industrial, cultivos u otros | AB3: Agotamiento del recurso mineral/ reservas y recursos geológicos | AD3: Eliminación del proceso | AF3: Acreditaciones | AH3: A | AJ3: AA | AP3: LEGAL | AR3: LEGAL | AT3: LEGAL | AV3: LEGAL | AX3: Agotamiento de agua de pozos | AZ3: Bloqueos/Marchas/Amenazas/Demandas Sociales | BB3: RC.3.1.1. Fortalecer la cadena productiva de Quinua en comunidades del área de intervención en coordinación con el Consejo Consultivo mediante alianzas estratégicas | BD3: Publicación de indicadores | BF3: RELACIONALES GUBERNAMENTALES | BH3: RELACIONALES GUBERNAMENTALES | BJ3: RELACIONALES GUBERNAMENTALES | BN3: Conflictos sociales | BP3: Daño a la propiedad pública o privada | BR3: Alarmas / señales / advertencias | BT3: Verificadores Operacionales | BV3: financiero | BX3: financiero | BZ3: financiero | CB3: financiero
B4: 2 | C4: 5 | D4: 5 | E4: 4 | F4: 3 | G4: 3 | H4: 3 | K4: 5. Sustitución/ Minimización | L4: Control/Acción Satisfactorio | M4: Control/Acción Satisfactorio | N4: Control/Acción Eficaz | P4: Agentes Físicos (iluminación excesiva/baja/inadecuada o sin iluminación) | R4: Arco eléctrico | T4: Sustitución | V4: Planillas de vigencia de Certificaciones / Competencias/ Capacitaciones | X4: Seguimiento al programa de reuniones y evaluaciones de compromiso con la seguridad | Z4: Consumo de agua de vertientes para fines humanos y pecuarios/ agua potable, abrevaderos y riego | AB4: Alteración del clima por cambios climáticos/ efecto invernadero | AD4: Eliminación sustancia peligrosa del proceso | AF4: Certificaciones | AH4: salud | AJ4: SALUD | AL4: SALUD | AN4: SALUD | AP4: LEGAL | AR4: LEGAL | AT4: LEGAL | AV4: LEGAL | AX4: Agua para ganado | AZ4: Cierre de Proyectos de Desarrollo | BB4: RC.3.1.2. Fortalecer la cadena productiva de Camélidos en comunidades del área de intervención en coordinación con el Consejo Consultivo y las alianzas estratégicas | BD4: Planes y/o Programas | BF4: RELACIONALES GUBERNAMENTALES | BH4: RELACIONALES GUBERNAMENTALES | BJ4: RELACIONALES GUBERNAMENTALES | BL4: RELACIONALES GUBERNAMENTALES | BN4: Condiciones climatológicas | BP4: Fallas en sistema mecanizado de embarque / Infraestructura de atraque | BR4: Inspecciones | BT4: Publicación de Indicadores | BV4: financiero | BX4: financiero | BZ4: financiero | CB4: financiero
B5: 3 | C5: 4 | D5: 4 | E5: 4 | F5: 3 | G5: 2 | H5: 2 | K5: 4. Ingeniería | L5: Control/Acción No Eficaz | M5: Control/Acción Satisfactorio | N5: Control/Acción Eficaz | P5: Agentes Físicos (radiación) | R5: Asfixia / Ahogamiento | T5: Controles de Ingeniería | V5: Matriz de Requisitos Legales | X5: Seguimiento al programa de difusión de instructivos y capacitaciones internas | Z5: Consumo de agua subterránea para procesos industriales/ campo de pozos | AB5: Contaminación de aguas por derrame de sustancias peligrosas | AD5: Cambio de disposición de residuos peligrosos | AF5: Confiabilidad de mediciones de factores ambientales/equipos certificados | AH5: salud | AJ5: SALUD | AL5: SALUD | AN5: SALUD | AP5: LEGAL | AR5: LEGAL | AT5: LEGAL | AV5: LEGAL | AX5: Agua por gravedad | AZ5: Confrontaciones Sociales | BB5: RC.3.1.3. Fortalecer la cadena productiva de Turismo en comunidades del área de intervención en coordinación con el Consejo Consultivo mediante alianzas estratégicas. | BF5: RELACIONALES GUBERNAMENTALES | BH5: RELACIONALES GUBERNAMENTALES | BJ5: RELACIONALES GUBERNAMENTALES | BL5: RELACIONALES GUBERNAMENTALES | BN5: Transferencia de concentrados en PdM | BP5: Efecto negativo sobre la estabilidad física de taludes | BR5: Control de emergencias | BT5: Planes y/o Programas | BV5: financiero | BX5: financiero | BZ5: financiero | CB5: financiero
B6: 4 | C6: 4 | D6: 3 | E6: 3 | F6: 2 | G6: 2 | H6: 1 | K6: 3. Señalización/ Advertencias/ Alarma | L6: Control/Acción No Eficaz | M6: Control/Acción Satisfactorio | N6: Control/Acción Eficaz | P6: Agentes Físicos (ruido) | R6: Atrapamiento (entre objetos, por deslizamientos) | T6: Controles Ergonómicos | V6: Planes / Programas | X6: Seguimiento al programa de Inspecciones Interno | Z6: Consumo de aguas superficiales para fines agropecuarios/ abrevaderos y riego | AB6: Contaminación de suelo por derrame de sustancias peligrosas | AD6: Reemplazo de reactivos químicos de menor impacto | AF6: Informes con indicadores y verificadores ambientales | AH6: salud | AJ6: SALUD | AL6: SALUD | AN6: SALUD | AP6: LEGAL | AR6: LEGAL | AT6: LEGAL | AV6: LEGAL | AX6: Cantidad y calidad de agua | AZ6: Denuncias | BB6: RC.3.1.4. Fortalecer la Educación regular, alternativa y superior en el área de intervención en coordinación con el Consejo Consultivo y las alianzas estratégicas | BF6: RELACIONALES GUBERNAMENTALES | BH6: RELACIONALES GUBERNAMENTALES | BJ6: RELACIONALES GUBERNAMENTALES | BL6: RELACIONALES GUBERNAMENTALES | BN6: Extracción de recursos naturales renovables/ agregados para construcciones | BP6: Pérdida del patrimonio cultural/ arqueología | BR6: Instrucción operacional | BT6: Acreditaciones, Certificaciones, Permisos normativos | BV6: financiero | BX6: financiero | BZ6: financiero | CB6: financiero
B7: 5 | C7: 3 | D7: 3 | E7: 2 | F7: 2 | G7: 1 | H7: 1 | K7: 2. Administrativo/ Procedimientos/ Capacitación | L7: Control/Acción No Eficaz | M7: Control/Acción Satisfactorio | N7: Control/Acción Eficaz | P7: Agentes Físicos (ventilación) | R7: Atropello | T7: Controles de Salud Ocupacional | V7: Publicación de Indicadores | X7: Seguimiento al programa de inspecciones ISOP | Z7: Consumo de energía eléctrica | AB7: Contaminación del aire por gases orgánicos persistentes | AD7: Tecnología para disminuir consumo de agua natural/ recirculación | AF7: Matriz de Requisitos Legales ambientales en áreas operativas/soporte | AH7: salud | AJ7: SALUD | AL7: SALUD | AN7: SALUD | AP7: LEGAL | AR7: LEGAL | AT7: LEGAL | AV7: LEGAL | AX7: Cierre de la mina | AZ7: Perdida de Licencia Social para Operar de MSC | BB7: RC.3.1.5. Fortalecer el funcionamiento de centro Integral de salud de San Cristóbal y la red de salud Municipal, en coordinación con el Consejo consultivo y alianzas estratégicas. | BF7: RELACIONALES GUBERNAMENTALES | BH7: RELACIONALES GUBERNAMENTALES | BJ7: RELACIONALES GUBERNAMENTALES | BL7: RELACIONALES GUBERNAMENTALES | BN7: Remoción de lugares de patrimonio social de la comunidad | BP7: Baja en el movimiento de mineral en los frentes de carguío | BR7: Control de ingeniería | BV7: financiero | BX7: financiero | BZ7: financiero | CB7: financiero
B8: 6 | C8: 3 | D8: 3 | E8: 2 | F8: 1 | G8: 1 | H8: 1 | K8: 1. EPP | L8: Control/Acción No Eficaz | M8: Control/Acción No Eficaz | N8: Control/Acción Satisfactorio | P8: Agentes Físicos (vibración) | R8: Caída a distinto nivel (Menor a 1,80) | T8: Controles Sanitarios | V8: Verificadores Operacionales | X8: Seguimiento al programa de inspecciones IRO´S: Aislamiento | Z8: Consumo de recursos naturales no renovables/ hidrocarburos fósiles: petróleo y gas natural | AB8: Daño a la propiedad pública o privada | AD8: Mejora en la eficiencia del proceso/ optimización en uso de recursos naturales no renovables | AF8: Permisos normativos | AH8: salud | AJ8: SALUD | AL8: SALUD | AN8: SALUD | AP8: LEGAL | AR8: LEGAL | AT8: LEGAL | AV8: LEGAL | AX8: Conflicto políticas sociales externas a MSC | AZ8: Perdidas económicas para Comunidades | BB8: RC.4.1.2. Realizar el manejo de quejas / preocupaciones y riesgos sociales de los grupos de interés del área de influencia de MSC | BF8: RELACIONALES GUBERNAMENTALES | BH8: RELACIONALES GUBERNAMENTALES | BJ8: RELACIONALES GUBERNAMENTALES | BL8: RELACIONALES GUBERNAMENTALES | BN8: Disponibilidad, utilización | BP8: Falta de continuidad en el movimiento de camiones | BR8: Procedimientos / Instructivos / Reglamentos y otros. | BV8: financiero | BX8: financiero | BZ8: financiero | CB8: financiero
P9: Agentes Químicos (gases, vapores, aerosoles, etc.) | R9: Caída al mismo nivel | T9: Autorizaciones, Permisos y Licencias (Gubernamentales, legales, normativos) | X9: Seguimiento al programa de inspecciones IRO´S: Izaje | Z9: Derrame de residuos peligrosos/ empetrolados, relaves de colas, lodos sépticos, otros | AB9: Degradación de la calidad de agua subterránea por aguas de proceso | AD9: Revegetación y rehabilitación de áreas perturbadas | AF9: Planes y programas | AH9: salud | AJ9: SALUD | AL9: SALUD | AN9: SALUD | AP9: LEGAL | AR9: LEGAL | AT9: LEGAL | AV9: LEGAL | AX9: Hospital 2do Nivel | AZ9: Perdidas económicas para MSC | BB9: RC.4.1.3. Desarrollar estudios socio económicos en las comunidades de influencia directa para la gestión social | BF9: RELACIONALES GUBERNAMENTALES | BH9: RELACIONALES GUBERNAMENTALES | BJ9: RELACIONALES GUBERNAMENTALES | BL9: RELACIONALES GUBERNAMENTALES | BN9: Operación Planta | BP9: Falta de movimiento de mineral en frentes de carguío planificados | BR9: Sustitución | BV9: financiero | BX9: financiero | BZ9: financiero | CB9: financiero
B10: oportunidad | J10: Jerarquía del Control - DSRC | K10: Calidad del Control-DSRC | P10: Almacenamiento inadecuado de materiales, herramientas, etc. (en depósitos, estantes, etc.) | R10: Caída de altura (Igual o Mayor a 1,80) | T10: Certificaciones | X10: Seguimiento al programa de inspecciones IRO´S: Sustancias Peligrosas | Z10: Derrame de aguas de proceso/ aguas de colas, aguas de piscina de emergencia | AB10: Degradación de la calidad de cuerpos de agua superficial por descargas | AD10: Uso de geomembrana como aislante para prevención | AF10: Planillas de vigencia | AH10: salud | AJ10: SALUD | AL10: SALUD | AN10: SALUD | AP10: LEGAL | AR10: LEGAL | AT10: LEGAL | AV10: LEGAL | AX10: Inapropiación del Desarrollo Económico Local por parte de las comunidades | AZ10: Preocupaciones/Quejas/Determinación de las Comunidades/Inspecciones/Fiscalizaciones | BB10: RC.4.2.1. Monitorear el cumplimiento de los acuerdos y convenios entre empresa, comunidades y otras organizaciones. | BF10: RELACIONALES GUBERNAMENTALES | BH10: RELACIONALES GUBERNAMENTALES | BJ10: RELACIONALES GUBERNAMENTALES | BL10: RELACIONALES GUBERNAMENTALES | BN10: Disponibilidad | BP10: Baja en la alimentación de mineral | BR10: Certificaciones | BV10: financiero | BX10: financiero | BZ10: financiero | CB10: financiero
B11: prob | D11: 5 | E11: 4 | F11: 3 | G11: 2 | H11: 1 | K11: Efectividad del Control | L11: C. Menor a 50% | M11: B. 50% y 80% | N11: A. Mayor 80% | P11: Área de trabajo reducida, congestionada, acceso difícil o inadecuado | R11: Caída de objetos / materiales/roca | T11: Competencias | X11: Seguimiento al programa de inspecciones IRO´S: Taludes Frentes de Carguío Banquinas | Z11: Derrame de concentrados de minerales | AB11: Degradación de la flora natural | AD11: Riego de caminos para reducir emisión de polvo | AF11: Publicación de indicadores | AH11: salud | AJ11: SALUD | AL11: SALUD | AN11: SALUD | AP11: LEGAL | AR11: LEGAL | AT11: LEGAL | AV11: LEGAL | AX11: Operación Wila Khara Deposito de Colas | BB11: RC.4.2.2. Mitigar los impactos socio económicos ocasionados por las operaciones de MSC en las comunidades de San Cristóbal, Culpina K | BF11: RELACIONALES GUBERNAMENTALES | BH11: RELACIONALES GUBERNAMENTALES | BJ11: RELACIONALES GUBERNAMENTALES | BL11: RELACIONALES GUBERNAMENTALES | BP11: Baja en el tratamiento de mineral | BV11: financiero | BX11: financiero | BZ11: financiero | CB11: financiero
B12: Severidad | C12: 5 | D12: Altamente Implementable | E12: Altamente Implementable | F12: Implementable | G12: Implementable con Revisión | H12: No Recomendable su Implementación | K12: 6. Acuerdos estratégicos/Convenios estratégicos | L12: Control/Acción Satisfactorio | M12: Control/Acción Satisfactorio | N12: Control/Acción Eficaz | P12: Áreas de trabajo con desniveles o gradas | R12: Choque eléctrico | T12: Controles/Acciones de Emergencias | X12: Seguimiento al programa de inspecciones IRO´S: Trabajo Eléctrico - Actos | Z12: Derrame de hidrocarburos/ lubricantes y combustibles | AB12: Degradación del paisaje natural | AD12: Uso de cobertor para reducir emisión de polvo | AF12: Verificadores operacionales | AH12: salud | AJ12: SALUD | AL12: SALUD | AN12: SALUD | AP12: LEGAL | AR12: LEGAL | AT12: LEGAL | AV12: LEGAL | AX12: Pasivos ambientales generados por MSC | BB12: RC.4.2.3. Fortalecer la administración y operaciones de los servicios básicos en las comunidades San Cristóbal y Culpina K | BF12: RELACIONALES GUBERNAMENTALES | BH12: RELACIONALES GUBERNAMENTALES | BJ12: RELACIONALES GUBERNAMENTALES | BL12: RELACIONALES GUBERNAMENTALES | BV12: financiero | BX12: financiero | BZ12: financiero | CB12: financiero
C13: 4 | D13: Altamente Implementable | E13: Altamente Implementable | F13: Implementable | G13: Implementable con Revisión | H13: No Recomendable su Implementación | K13: 5. Acuerdos específicos/Convenios específicos | L13: Control/Acción Satisfactorio | M13: Control/Acción Satisfactorio | N13: Control/Acción Eficaz | P13: Condiciones climatológicas adversas (tormenta eléctrica, viento, nieve, lluvia, rayos UV, etc.) | R13: Colisión / Choque | T13: Capacitación/Entrenamiento | X13: Seguimiento al programa de inspecciones IRO´S: Trabajo Eléctrico - Condiciones | Z13: Derrame de sustancias peligrosas/ reactivos químicos y otros insumos industriales | AB13: Degradación o alteración de la fauna silvestre | AD13: Uso de barreras - diques para aguas de contacto | AH13: salud | AJ13: SALUD | AL13: SALUD | AN13: SALUD | AP13: LEGAL | AR13: LEGAL | AT13: LEGAL | AV13: LEGAL | AX13: Reducción de nivel freático en Campo de Pozos | BB13: RC.4.2.4.Apoyar en la atención a los diferente grupos sociales de las comunidades del área de influencia directa de MSC. | BF13: RELACIONALES GUBERNAMENTALES | BH13: RELACIONALES GUBERNAMENTALES | BJ13: RELACIONALES GUBERNAMENTALES | BL13: RELACIONALES GUBERNAMENTALES | BV13: financiero | BX13: financiero | BZ13: financiero | CB13: financiero
C14: 3 | D14: Implementable | E14: Implementable | F14: Implementable con Revisión | G14: No Recomendable su Implementación | H14: No Recomendable su Implementación | K14: 4. Planes estratégicos | L14: Control/Acción No Eficaz | M14: Control/Acción Satisfactorio | N14: Control/Acción Eficaz | P14: Desorden y falta de limpieza | R14: Contacto con herramientas, objetos cortantes y/o punzantes (corte o incrustación) | T14: Instrucción Operacional | X14: Seguimiento al programa de inspecciones IRO´S: Trabajo en Altura | Z14: Descarga de aguas pluviales de área de mina, planta, campamento y otros | AB14: Disminución de agua subterránea/descenso del nivel freático | AD14: Mejora tecnológica - diseños de ingeniería | AH14: salud | AJ14: SALUD | AL14: SALUD | AN14: SALUD | AP14: LEGAL | AR14: LEGAL | AT14: LEGAL | AV14: LEGAL | BB14: RC.4.3.2.Apoyar la gestión del Uso Racional del agua en comunidades del área de influencia de MSC | BF14: RELACIONALES GUBERNAMENTALES | BH14: RELACIONALES GUBERNAMENTALES | BJ14: RELACIONALES GUBERNAMENTALES | BL14: RELACIONALES GUBERNAMENTALES
C15: 2 | D15: Implementable con Revisión | E15: Implementable con Revisión | F15: No Recomendable su Implementación | G15: No Recomendable su Implementación | H15: No Implementable | K15: 3. Intervenciones directas | L15: Control/Acción No Eficaz | M15: Control/Acción Satisfactorio | N15: Control/Acción Eficaz | P15: Energía almacenada que puede liberarse repentinamente | R15: Contacto con superficies/partículas/objetos calientes | T15: Procedimientos / Instructivos / Reglamentos y otros. | X15: Seguimiento al programa de inspecciones IRO´S: Trabajo en Espacios Confinados | Z15: Descarga de aguas residuales de lavado de vehículos (Truck shop, Toldos) | AB15: Disminución de nutrientes del suelo/ pérdida de calidad del suelo | AD15: Tratamiento de aguas residuales/ físico, químico, biológico | AH15: salud | AJ15: SALUD | AL15: SALUD | AN15: SALUD | AP15: LEGAL | AR15: LEGAL | AT15: LEGAL | AV15: LEGAL | BB15: RC.4.4.1. Mantener contactos permanentes con los grupos de interés del área de influencia directa | BF15: RELACIONALES GUBERNAMENTALES | BH15: RELACIONALES GUBERNAMENTALES | BJ15: RELACIONALES GUBERNAMENTALES | BL15: RELACIONALES GUBERNAMENTALES
C16: 1 | D16: No Recomendable su Implementación | E16: No Recomendable su Implementación | F16: No Recomendable su Implementación | G16: No Implementable | H16: No Implementable | K16: 2. Reuniones formales | L16: Control/Acción No Eficaz | M16: Control/Acción Satisfactorio | N16: Control/Acción Eficaz | P16: Equipo con partes / elementos en movimiento | R16: Contacto por proyección de materiales, partículas, objetos, etc. | T16: Inspecciones | X16: Seguimiento al programa de inspecciones IRO´S: Trabajo en Excavaciones | Z16: Descarga de aguas residuales de tratamiento de aguas servidas/ campamento, cocina | AB16: Disminución de recursos naturales no renovables / hidrocarburos fósiles | AD16: Mantenimiento preventivo de equipos- vehículos | AH16: salud | AJ16: SALUD | AL16: SALUD | AN16: SALUD | AP16: LEGAL | AR16: LEGAL | AT16: LEGAL | AV16: LEGAL | BB16: RC.4.4.3. Mantener contactos permanentes con los grupos de interés de Desarrollo Socio Económico. | BF16: RELACIONALES GUBERNAMENTALES | BH16: RELACIONALES GUBERNAMENTALES | BJ16: RELACIONALES GUBERNAMENTALES | BL16: RELACIONALES GUBERNAMENTALES
K17: 1. Relacionamientos | L17: Control/Acción No Eficaz | M17: Control/Acción No Eficaz | N17: Control/Acción Satisfactorio | P17: Equipo o línea energizada | R17: Contacto por proyección de rocas o fragmentos de rocas volantes | T17: Señales/ Advertencias/ Alarmas | X17: Seguimiento al programa de inspecciones IRO´S: Trabajos en Caliente | Z17: Descarga de colas de la planta | AB17: Efecto de degradación de la calidad del aire | AD17: Inspecciones planificadas y no planificadas | AH17: salud | AJ17: SALUD | AL17: SALUD | AN17: SALUD | AP17: LEGAL | AR17: LEGAL | AT17: LEGAL | AV17: LEGAL | BB17: RC.4.4.5. Atender oportunamente las solicitudes provenientes de las comunidades, la región y Potosí.
C18: 1 | P18: Estructuras a baja altura o con partes salientes | R18: Deslizamiento / Desprendimiento | T18: E.P.P. | X18: Seguimiento al programa de mantenimientos de equipos/ vehículos | Z18: Descarga de efluentes de área de mina | AB18: Efecto negativo sobre la estabilidad física de taludes | AD18: Verificación de velocidad de vehículos | AH18: salud | AJ18: SALUD | AL18: SALUD | AN18: SALUD | AP18: LEGAL | AR18: LEGAL | AT18: LEGAL | AV18: LEGAL
C19: 2 | J19: Jerarquía del Control - M.A. | K19: Calidad del Control-Medio Ambiente | P19: Gases comprimidos (transporte, uso, manipulación botellones) | R19: Desmoronamiento | X19: Seguimiento y publicación de reportes de velocidades | Z19: Emanación de olores | AB19: Efecto negativo sobre la salud humana | AD19: Simulacros de emergencia (Derrame) | AH19: salud | AJ19: SALUD | AL19: SALUD | AN19: SALUD | AP19: LEGAL | AR19: LEGAL | AT19: LEGAL | AV19: LEGAL
C20: 3 | K20: Efectividad del Control | L20: C. Menor a 50% | M20: B. 50% y 80% | N20: A. Mayor 80% | P20: Inestabilidad de taludes / terrenos | R20: Encandilamiento | X20: Seguimiento y publicación de reporte STOP o Seguimiento y publicación de reporte de observaciones conductuales | Z20: Emisión de gases de fuentes fijas/ incinerador, laboratorios, talleres y otros | AB20: Efectos fisiológicos sobre la salud humana | AD20: Hojas de seguridad de sustancias peligrosas | AH20: salud | AJ20: SALUD | AL20: SALUD | AN20: SALUD | AP20: LEGAL | AR20: LEGAL | AT20: LEGAL | AV20: LEGAL
C21: 4 | K21: 6. Eliminación | L21: Control/Acción Satisfactorio | M21: Control/Acción Satisfactorio | N21: Control/Acción Eficaz | P21: Izaje mecanizado de materiales / cargas suspendidas | R21: Estrés térmico, Exposición a ambientes fríos o calurosos | X21: Seguimiento a los programas preventivos y de control en salud | Z21: Emisión de gases de fuentes móviles/ vehículos | AB21: Pérdida de biodiversidad en áreas protegidas o restringidas | AD21: Autorización por instancia competente - sustancias peligrosas | AH21: salud
C22: 5 | K22: 5. Sustitución/ Minimización | L22: Control/Acción Satisfactorio | M22: Control/Acción Satisfactorio | N22: Control/Acción Eficaz | P22: Manejo Manual de Carga / materiales | R22: Explosión | X22: Seguimiento y publicación de reportes/informes e indicadores internos | Z22: Emisión de sustancias agotadores de la capa de ozono/ sistemas de refrigeración | AB22: Pérdida de la cobertura vegetal | AD22: Señalización de sustancias y residuos peligrosos | AH22: salud
K23: 4. Ingeniería | L23: Control/Acción No Eficaz | M23: Control/Acción Satisfactorio | N23: Control/Acción Eficaz | P23: Manejo Mecanizado de Materiales | R23: Exposición a Agentes biológicos | Z23: Extracción de recursos naturales no renovables/ minerales | AB23: Pérdida del patrimonio cultural/ arqueología | AD23: Higienización | AH23: salud
K24: 3. Señalización/ Advertencias/ Alarma | L24: Control/Acción No Eficaz | M24: Control/Acción Satisfactorio | N24: Control/Acción Eficaz | P24: Manipulación/uso de herramientas, instrumentos, objetos (cortantes, punzantes, calientes, pesados, sin Verificación / Calibración, etc.) | R24: Exposición a Ambiente con Deficiencia de Oxígeno (Sofocación) | Z24: Extracción de recursos naturales renovables/ agregados para construcciones | AB24: Efecto invernadero cambio climático | AD24: Involucramiento del supervisor a través de inspecciones internas y otros | AH24: salud
K25: 2. Administrativo/ Procedimientos/ Capacitación | L25: Control/Acción No Eficaz | M25: Control/Acción Satisfactorio | N25: Control/Acción Eficaz | P25: Piscinas, tazones, tanques o estanques sin protección | R25: Exposición a Ambiente/Atmósfera Peligrosa/Contaminada | Z25: Generación de polvo | AB25: Efectos a la biota | AD25: Certificaciones | AH25: salud
K26: 1. EPP | L26: Control/Acción No Eficaz | M26: Control/Acción No Eficaz | N26: Control/Acción Satisfactorio | P26: Presencia de polvo, material particulado, humo o gas | R26: Exposición a Atmósfera Explosiva | Z26: Generación de residuos sólidos convencionales, orgánicos e industriales | AB26: Efectos a la biota de suelo y fauna | AD26: Control de emergencias ambientales | AH26: salud
P27: Proyección de fragmentos de roca, materiales, partículas | R27: Exposición a Atmósfera Inflamable | Z27: Generación de ruido | AB27: Erosión al suelo, efecto a la calidad del suelo natural | AD27: Instructivos, procedimientos operacionales | AH27: salud
J28: Jerarquía del Control - Salud | K28: Calidad del Control-Salud | P28: Psicosociales (Acoso, Intimidación, Victimización, Bullying, mobbing, Disturbios Civiles) | R28: Exposición a Condiciones Ergonómicas Ambientales / de Diseño del Puesto de Trabajo | Z28: Generación y disposición de residuos hospitalarios | AB28: Pérdida de recursos culturales | AD28: Instructivos generales y específicos | AH28: salud
K29: Efectividad del Control | L29: C. Menor a 50% | M29: B. 50% y 80% | N29: A. Mayor 80% | P29: Remoción y limpieza de materiales acumulados | R29: Exposición a Humos Metálicos | Z29: Generación y disposición de residuos minero-metalúrgicos | AB29: Riesgos de derrames y efecto al suelo y aguas | AD29: Capacitación en manejo del proceso, sustancias, residuos y otros
K30: 6. Eliminación | L30: Control/Acción Satisfactorio | M30: Control/Acción Satisfactorio | N30: Control/Acción Eficaz | P30: Superficie Irregular, con obstrucciones, desnivelada, resbaladiza, congelada y/o blanda | R30: Exposición a Material Particulado | Z30: Generación y disposición de residuos peligrosos | AD30: Competencia para ejercer cargo
K31: 5. Sustitución/ Minimización | L31: Control/Acción Satisfactorio | M31: Control/Acción Satisfactorio | N31: Control/Acción Eficaz | P31: Superficies / partículas calientes | R31: Exposición a Ondas Expansivas | Z31: Incineración de residuos hospitalarios | AD31: Instructivos generales y específicos
K32: 4. Ingeniería | L32: Control/Acción No Eficaz | M32: Control/Acción Satisfactorio | N32: Control/Acción Eficaz | P32: Sustancias peligrosas (transporte, uso, manipulación) | R32: Exposición a Radiaciones Ionizantes / No ionizantes / UV | Z32: Manejo y consumo de sustancias peligrosas | AD32: Capacitación manejo del proceso, sustancias, residuos y otros
K33: 3. Señalización/ Advertencias/ Alarma | L33: Control/Acción No Eficaz | M33: Control/Acción Satisfactorio | N33: Control/Acción Eficaz | P33: Trabajo / circulación de equipo/vehículo (pesado / liviano) | R33: Exposición a Ruido | Z33: Remoción y manejo de top soil | AD33: Competencia para ejercer cargo
K34: 2. Administrativo/ Procedimientos/ Capacitación | L34: Control/Acción No Eficaz | M34: Control/Acción Satisfactorio | N34: Control/Acción Eficaz | P34: Trabajo en altura, sobre plataformas elevadas, escaleras, andamios, rampas o pisos sin barreras de protección (barandas o barreras rígidas). | R34: Exposición a Sustancias Peligrosas | Z34: Revegetación con especies introducidas | AD34: Planes de manejo de recursos naturales, riego, polvo, revegetación
K35: 1. EPP | L35: Control/Acción No Eficaz | M35: Control/Acción No Eficaz | N35: Control/Acción Satisfactorio | P35: Trabajo en caliente (soldadura, corte, desbaste) torchado, arco eléctrico, amolado, esmerilado, oxicorte, oxiflama, etc. | R35: Exposición a Vibración | Z35: Topografía y paisaje natural | AD35: Competencias
P36: Trabajo en Espacios Confinados (Clase I o II) | R36: Exposición a factores Psicosociales / Tensiones Mentales, Físicas o Fisiológicas | Z36: Uso de áreas protegidas o de recursos arqueológicos
J37: Jerarquía del Control - Legal | K37: Calidad del Control-Legal | P37: Trabajo en excavación (zanjas, aperturas, perforaciones, todo trabajo dentro una excavación) | R37: Golpeado contra | Z37: Gestión de lubricantes
K38: Efectividad del Control | L38: C. Menor a 50% | M38: B. 50% y 80% | N38: A. Mayor 80% | P38: Trabajos en cercanía de líneas eléctricas energizadas, tableros eléctricos, etc. | R38: Golpeado por | Z38: Gestión de sustancias peligrosas
K39: 6. Eliminación | L39: Control/Acción Satisfactorio | M39: Control/Acción Satisfactorio | N39: Control/Acción Eficaz | P39: Trabajos en cercanías de taludes o botaderos | R39: Incendio | Z39: Incineración de residuos hospitalarios
K40: 5. Sustitución/ Minimización | L40: Control/Acción Satisfactorio | M40: Control/Acción Satisfactorio | N40: Control/Acción Eficaz | P40: Tránsito de peatones en áreas de circulación vehicular o de equipos | R40: Inmersión | Z40: Incineración de residuos sólidos
K41: 4. Ingeniería | L41: Control/Acción No Eficaz | M41: Control/Acción Satisfactorio | N41: Control/Acción Eficaz | P41: Transporte de carga en movilidad o equipo móvil | R41: Liberación de energía peligrosa (hidráulica, neumática, eléctrica, radioactiva, etc.) | Z41: Intervención a lugares arqueológicos
K42: 3. Señalización/ Advertencias/ Alarma | L42: Control/Acción No Eficaz | M42: Control/Acción Satisfactorio | N42: Control/Acción Eficaz | P42: Transporte, manipulación o uso de explosivos | R42: Sobre esfuerzo | Z42: Lixiviación de residuos sólidos
K43: 2. Administrativo/ Procedimientos/ Capacitación | L43: Control/Acción No Eficaz | M43: Control/Acción Satisfactorio | N43: Control/Acción Eficaz | P43: Variables ergonómicas (movimientos repetitivos, posiciones incómodas, fatiga, estrés, sobre carga de trabajo, etc.) | R43: Tropezón | Z43: Manejo y consumo de sustancias peligrosas
K44: 1. EPP | L44: Control/Acción No Eficaz | M44: Control/Acción No Eficaz | N44: Control/Acción Satisfactorio | P44: Otros | R44: Vuelco | Z44: Remoción de la capa vegetal del suelo-top soil
P45: N/A | R45: Otros | Z45: Remoción de lugares de patrimonio social de la comunidad
J46: Jerarquía del Control - Rel. G | K46: Calidad del Control-Relaciones Gubernamentales | R46: N/A | Z46: Remoción de lugares propios de la fauna silvestre
K47: Efectividad del Control | L47: C. Menor a 50% | M47: B. 50% y 80% | N47: A. Mayor 80%
K48: 6. Eliminación | L48: Control/Acción Satisfactorio | M48: Control/Acción Satisfactorio | N48: Control/Acción Eficaz
K49: 5. Sustitución/ Minimización | L49: Control/Acción Satisfactorio | M49: Control/Acción Satisfactorio | N49: Control/Acción Eficaz
K50: 4. Ingeniería | L50: Control/Acción No Eficaz | M50: Control/Acción Satisfactorio | N50: Control/Acción Eficaz
K51: 3. Señalización/ Advertencias/ Alarma | L51: Control/Acción No Eficaz | M51: Control/Acción Satisfactorio | N51: Control/Acción Eficaz
K52: 2. Administrativo/ Procedimientos/ Capacitación | L52: Control/Acción No Eficaz | M52: Control/Acción Satisfactorio | N52: Control/Acción Eficaz
K53: 1. EPP | L53: Control/Acción No Eficaz | M53: Control/Acción No Eficaz | N53: Control/Acción Satisfactorio
J55: Jerarquía del Control - OPERACIONALES | K55: Calidad del Control-OPERACIONALES
K56: Efectividad del Control | L56: C. Menor a 50% | M56: B. 50% y 80% | N56: A. Mayor 80%
K57: 6. Eliminación | L57: Control/Acción Satisfactorio | M57: Control/Acción Satisfactorio | N57: Control/Acción Eficaz
K58: 5. Sustitución/ Minimización | L58: Control/Acción Satisfactorio | M58: Control/Acción Satisfactorio | N58: Control/Acción Eficaz
K59: 4. Ingeniería | L59: Control/Acción No Eficaz | M59: Control/Acción Satisfactorio | N59: Control/Acción Eficaz
K60: 3. Señalización/ Advertencias/ Alarma | L60: Control/Acción No Eficaz | M60: Control/Acción Satisfactorio | N60: Control/Acción Eficaz
K61: 2. Administrativo/ Procedimientos/ Capacitación | L61: Control/Acción No Eficaz | M61: Control/Acción Satisfactorio | N61: Control/Acción Eficaz
K62: 1. EPP | L62: Control/Acción No Eficaz | M62: Control/Acción No Eficaz | N62: Control/Acción Satisfactorio
J64: Jerarquía del Control - FINANCIEROS | K64: Calidad del Control-FINANCIEROS
K65: Efectividad del Control | L65: C. Menor a 50% | M65: B. 50% y 80% | N65: A. Mayor 80%
K66: 6. Eliminación | L66: Control/Acción Satisfactorio | M66: Control/Acción Satisfactorio | N66: Control/Acción Eficaz
K67: 5. Sustitución/ Minimización | L67: Control/Acción Satisfactorio | M67: Control/Acción Satisfactorio | N67: Control/Acción Eficaz
K68: 4. Ingeniería | L68: Control/Acción No Eficaz | M68: Control/Acción Satisfactorio | N68: Control/Acción Eficaz
K69: 3. Señalización/ Advertencias/ Alarma | L69: Control/Acción No Eficaz | M69: Control/Acción Satisfactorio | N69: Control/Acción Eficaz
K70: 2. Administrativo/ Procedimientos/ Capacitación | L70: Control/Acción No Eficaz | M70: Control/Acción Satisfactorio | N70: Control/Acción Eficaz
K71: 1. EPP | L71: Control/Acción No Eficaz | M71: Control/Acción No Eficaz | N71: Control/Acción Satisfactorio
AV92: PLANIFICACIÓN E INFORME DE INDICADORES GESTIÓN 2020 RRCC | AZ92: PLANIFICACIÓN E INFORME DE INDICADORES GESTIÓN 2020 RRCC
AV93: PLANIFICACIÓN E INFORME DE INDICADORES GESTIÓN 2020 RRCC | AZ93: PLANIFICACIÓN E INFORME DE INDICADORES GESTIÓN 2020 RRCC
AV94: PLANIFICACIÓN E INFORME DE INDICADORES GESTIÓN 2020 RRCC | AZ94: PLANIFICACIÓN E INFORME DE INDICADORES GESTIÓN 2020 RRCC
AV95: PLANIFICACIÓN E INFORME DE INDICADORES GESTIÓN 2020 RRCC | AZ95: PLANIFICACIÓN E INFORME DE INDICADORES GESTIÓN 2020 RRCC
AV96: PLANIFICACIÓN E INFORME DE INDICADORES GESTIÓN 2020 RRCC | AZ96: PLANIFICACIÓN E INFORME DE INDICADORES GESTIÓN 2020 RRCC
AV97: PLANIFICACIÓN E INFORME DE INDICADORES GESTIÓN 2020 RRCC | AZ97: PLANIFICACIÓN E INFORME DE INDICADORES GESTIÓN 2020 RRCC
AV98: PLANIFICACIÓN E INFORME DE INDICADORES GESTIÓN 2020 RRCC | AZ98: PLANIFICACIÓN E INFORME DE INDICADORES GESTIÓN 2020 RRCC
AV99: PLANIFICACIÓN E INFORME DE INDICADORES GESTIÓN 2020 RRCC | AZ99: PLANIFICACIÓN E INFORME DE INDICADORES GESTIÓN 2020 RRCC
AV100: PLANIFICACIÓN E INFORME DE INDICADORES GESTIÓN 2020 RRCC | AZ100: PLANIFICACIÓN E INFORME DE INDICADORES GESTIÓN 2020 RRCC
AV101: PLANIFICACIÓN E INFORME DE INDICADORES GESTIÓN 2020 RRCC | AZ101: PLANIFICACIÓN E INFORME DE INDICADORES GESTIÓN 2020 RRCC
AV102: PLANIFICACIÓN E INFORME DE INDICADORES GESTIÓN 2020 RRCC | AZ102: PLANIFICACIÓN E INFORME DE INDICADORES GESTIÓN 2020 RRCC
AV103: PLANIFICACIÓN E INFORME DE INDICADORES GESTIÓN 2020 RRCC | AZ103: PLANIFICACIÓN E INFORME DE INDICADORES GESTIÓN 2020 RRCC
... AV123: PLANIFICACIÓN E INFORME DE INDICADORES GESTIÓN 2020 DS | AZ123: PLANIFICACIÓN E INFORME DE INDICADORES GESTIÓN 2020 DS
AZ124: PLANIFICACIÓN E INFORME DE INDICADORES GESTIÓN 2020 RRCC
AV172: PLANIFICACIÓN E INFORME DE INDICADORES GESTIÓN 2020 RRCC
BC390: Recibir información constante de medios de comunicación y del grupo de enlaces comunitarios
